{
  "type": "Feature",
  "properties": {
    "gn:admin1_code":"07",
    "gn:asciiname":"Mbadi",
    "gn:country_code":"CG",
    "gn:dem":140,
    "gn:feature_class":"P",
    "gn:feature_code":"PPL",
    "gn:name":"Mbadi",
    "gn:population":0,
    "gn:timezone":"Africa/Brazzaville",
    "iso:country":"CG",
    "wof:name":"Mbadi",
    "wof:placetype":"locality"
},
  "geometry": {"coordinates":[12.08222,-3.24028],"type":"Point"}
}