{
  "type": "Feature",
  "properties": {
    "gn:admin1_code":"10",
    "gn:asciiname":"Mekam",
    "gn:country_code":"CG",
    "gn:dem":518,
    "gn:feature_class":"P",
    "gn:feature_code":"PPL",
    "gn:name":"M\u00e9kam",
    "gn:population":0,
    "gn:timezone":"Africa/Brazzaville",
    "iso:country":"CG",
    "wof:name":"Mekam",
    "wof:placetype":"locality"
},
  "geometry": {"coordinates":[14.16861,1.45333],"type":"Point"}
}