{
  "type": "Feature",
  "properties": {
    "gn:admin1_code":"11",
    "gn:asciiname":"Kindanba",
    "gn:cc2":"CG",
    "gn:country_code":"CG",
    "gn:dem":429,
    "gn:feature_class":"P",
    "gn:feature_code":"PPL",
    "gn:name":"Kindanba",
    "gn:population":0,
    "gn:timezone":"Africa/Brazzaville",
    "iso:country":"CG",
    "name:und_x_variant":[
        "Kindamba",
        "Kindanba"
    ],
    "wof:name":"Kindanba",
    "wof:placetype":"locality"
},
  "geometry": {"coordinates":[14.96694,-3.98611],"type":"Point"}
}