{
  "type": "Feature",
  "properties": {
    "gn:admin1_code":"05",
    "gn:asciiname":"Kani Bakota",
    "gn:country_code":"CG",
    "gn:dem":683,
    "gn:feature_class":"P",
    "gn:feature_code":"PPL",
    "gn:name":"Kani Bakota",
    "gn:population":0,
    "gn:timezone":"Africa/Brazzaville",
    "iso:country":"CG",
    "wof:name":"Kani Bakota",
    "wof:placetype":"locality"
},
  "geometry": {"coordinates":[13.61083,-2.94972],"type":"Point"}
}