{
  "type": "Feature",
  "properties": {
    "gn:admin1_code":"08",
    "gn:asciiname":"Omeinkouere",
    "gn:country_code":"CG",
    "gn:dem":513,
    "gn:feature_class":"P",
    "gn:feature_code":"PPL",
    "gn:name":"Om\u00e9inkou\u00e9r\u00e9",
    "gn:population":0,
    "gn:timezone":"Africa/Brazzaville",
    "iso:country":"CG",
    "wof:name":"Omeinkouere",
    "wof:placetype":"locality"
},
  "geometry": {"coordinates":[15.80139,-2.36667],"type":"Point"}
}