{
  "type": "Feature",
  "properties": {
    "gn:admin1_code":"01",
    "gn:asciiname":"Minga",
    "gn:country_code":"CG",
    "gn:dem":618,
    "gn:feature_class":"P",
    "gn:feature_code":"PPL",
    "gn:name":"Minga",
    "gn:population":0,
    "gn:timezone":"Africa/Brazzaville",
    "iso:country":"CG",
    "name:cat_x_preferred":[
        "Minga"
    ],
    "name:ceb_x_preferred":[
        "Minga"
    ],
    "name:deu_x_preferred":[
        "Minga"
    ],
    "name:fra_x_preferred":[
        "Minga"
    ],
    "name:pol_x_preferred":[
        "Minga"
    ],
    "name:spa_x_preferred":[
        "Minga"
    ],
    "name:swe_x_preferred":[
        "Minga"
    ],
    "wof:name":"Minga",
    "wof:placetype":"locality"
},
  "geometry": {"coordinates":[13.67667,-4.5225],"type":"Point"}
}