{
  "type": "Feature",
  "properties": {
    "gn:admin1_code":"05",
    "gn:asciiname":"Mibami",
    "gn:country_code":"CG",
    "gn:dem":678,
    "gn:feature_class":"P",
    "gn:feature_code":"PPL",
    "gn:name":"Mibami",
    "gn:population":0,
    "gn:timezone":"Africa/Brazzaville",
    "iso:country":"CG",
    "wof:name":"Mibami",
    "wof:placetype":"locality"
},
  "geometry": {"coordinates":[13.60611,-2.95694],"type":"Point"}
}