{
  "type": "Feature",
  "properties": {
    "gn:admin1_code":"12",
    "gn:asciiname":"Mikatou",
    "gn:country_code":"CG",
    "gn:dem":345,
    "gn:feature_class":"P",
    "gn:feature_code":"PPL",
    "gn:name":"Mikatou",
    "gn:population":0,
    "gn:timezone":"Africa/Brazzaville",
    "iso:country":"CG",
    "wof:name":"Mikatou",
    "wof:placetype":"locality"
},
  "geometry": {"coordinates":[15.13528,-4.27806],"type":"Point"}
}