{
  "type": "Feature",
  "properties": {
    "gn:admin1_code":"06",
    "gn:asciiname":"Maounda",
    "gn:cc2":"CG",
    "gn:country_code":"CG",
    "gn:dem":311,
    "gn:feature_class":"P",
    "gn:feature_code":"PPL",
    "gn:name":"Maounda",
    "gn:population":0,
    "gn:timezone":"Africa/Brazzaville",
    "iso:country":"CG",
    "name:und_x_variant":[
        "Mahounda",
        "Maounda"
    ],
    "wof:name":"Maounda",
    "wof:placetype":"locality"
},
  "geometry": {"coordinates":[17.35833,1.16194],"type":"Point"}
}