{
  "type": "Feature",
  "properties": {
    "gn:admin1_code":"13",
    "gn:asciiname":"Empoura",
    "gn:country_code":"CG",
    "gn:dem":400,
    "gn:feature_class":"P",
    "gn:feature_code":"PPL",
    "gn:name":"Empoura",
    "gn:population":0,
    "gn:timezone":"Africa/Brazzaville",
    "iso:country":"CG",
    "wof:name":"Empoura",
    "wof:placetype":"locality"
},
  "geometry": {"coordinates":[14.61667,-1.61528],"type":"Point"}
}