{
  "type": "Feature",
  "properties": {
    "gn:admin1_code":"08",
    "gn:asciiname":"Osao",
    "gn:cc2":"CG",
    "gn:country_code":"CG",
    "gn:dem":383,
    "gn:feature_class":"P",
    "gn:feature_code":"PPL",
    "gn:name":"Osao",
    "gn:population":0,
    "gn:timezone":"Africa/Brazzaville",
    "iso:country":"CG",
    "name:und_x_variant":[
        "Ossao",
        "Osao"
    ],
    "wof:name":"Osao",
    "wof:placetype":"locality"
},
  "geometry": {"coordinates":[15.88667,-1.57028],"type":"Point"}
}