{
  "type": "Feature",
  "properties": {
    "gn:admin1_code":"08",
    "gn:asciiname":"Nganba",
    "gn:cc2":"CG",
    "gn:country_code":"CG",
    "gn:dem":444,
    "gn:feature_class":"P",
    "gn:feature_code":"PPL",
    "gn:name":"Nganba",
    "gn:population":0,
    "gn:timezone":"Africa/Brazzaville",
    "iso:country":"CG",
    "name:und_x_variant":[
        "Gambo",
        "Nganba"
    ],
    "wof:name":"Nganba",
    "wof:placetype":"locality"
},
  "geometry": {"coordinates":[15.54361,-1.47306],"type":"Point"}
}