{
  "type": "Feature",
  "properties": {
    "gn:admin1_code":"08",
    "gn:asciiname":"Bodouango II",
    "gn:country_code":"CG",
    "gn:dem":290,
    "gn:feature_class":"P",
    "gn:feature_code":"PPL",
    "gn:name":"Bodouango II",
    "gn:population":0,
    "gn:timezone":"Africa/Brazzaville",
    "iso:country":"CG",
    "wof:name":"Bodouango II",
    "wof:placetype":"locality"
},
  "geometry": {"coordinates":[16.45361,-1.75028],"type":"Point"}
}