{
  "type": "Feature",
  "properties": {
    "gn:admin1_code":"11",
    "gn:asciiname":"Kiani",
    "gn:country_code":"CG",
    "gn:dem":679,
    "gn:feature_class":"P",
    "gn:feature_code":"PPL",
    "gn:name":"Kiani",
    "gn:population":0,
    "gn:timezone":"Africa/Brazzaville",
    "iso:country":"CG",
    "wof:name":"Kiani",
    "wof:placetype":"locality"
},
  "geometry": {"coordinates":[15.63306,-3.08861],"type":"Point"}
}