{
  "type": "Feature",
  "properties": {
    "gn:admin1_code":"13",
    "gn:asciiname":"Oudzima",
    "gn:cc2":"CG",
    "gn:country_code":"CG",
    "gn:dem":335,
    "gn:feature_class":"P",
    "gn:feature_code":"PPL",
    "gn:name":"Oudzima",
    "gn:population":0,
    "gn:timezone":"Africa/Brazzaville",
    "iso:country":"CG",
    "name:und_x_variant":[
        "Oz\u00e9ma",
        "Oudzima"
    ],
    "wof:name":"Oudzima",
    "wof:placetype":"locality"
},
  "geometry": {"coordinates":[16.04194,-0.13778],"type":"Point"}
}