{
  "type": "Feature",
  "properties": {
    "gn:admin1_code":"08",
    "gn:asciiname":"Village Babinga",
    "gn:country_code":"CG",
    "gn:dem":662,
    "gn:feature_class":"P",
    "gn:feature_code":"PPL",
    "gn:name":"Village Babinga",
    "gn:population":0,
    "gn:timezone":"Africa/Brazzaville",
    "iso:country":"CG",
    "wof:name":"Village Babinga",
    "wof:placetype":"locality"
},
  "geometry": {"coordinates":[14.49722,-2.57083],"type":"Point"}
}