{
  "type": "Feature",
  "properties": {
    "gn:admin1_code":"01",
    "gn:asciiname":"Kinsaka",
    "gn:country_code":"CG",
    "gn:dem":312,
    "gn:feature_class":"P",
    "gn:feature_code":"PPL",
    "gn:name":"Kinsaka",
    "gn:population":0,
    "gn:timezone":"Africa/Brazzaville",
    "iso:country":"CG",
    "wof:name":"Kinsaka",
    "wof:placetype":"locality"
},
  "geometry": {"coordinates":[13.60861,-4.32417],"type":"Point"}
}