{
  "type": "Feature",
  "properties": {
    "gn:admin1_code":"07",
    "gn:asciiname":"Lekana",
    "gn:country_code":"CG",
    "gn:dem":467,
    "gn:feature_class":"P",
    "gn:feature_code":"PPL",
    "gn:name":"Lekana",
    "gn:population":0,
    "gn:timezone":"Africa/Brazzaville",
    "iso:country":"CG",
    "name:fra_x_preferred":[
        "L\u00e9kana"
    ],
    "name:nld_x_preferred":[
        "L\u00e9kana"
    ],
    "name:por_x_preferred":[
        "L\u00e9kana"
    ],
    "name:urd_x_preferred":[
        "\u0644\u06cc\u06a9\u0627\u0646\u0627"
    ],
    "wof:name":"Lekana",
    "wof:placetype":"locality"
},
  "geometry": {"coordinates":[13.08833,-3.17667],"type":"Point"}
}