{
  "type": "Feature",
  "properties": {
    "gn:admin1_code":"07",
    "gn:asciiname":"Boudinga",
    "gn:country_code":"CG",
    "gn:dem":656,
    "gn:feature_class":"P",
    "gn:feature_code":"PPL",
    "gn:name":"Boudinga",
    "gn:population":0,
    "gn:timezone":"Africa/Brazzaville",
    "iso:country":"CG",
    "wof:name":"Boudinga",
    "wof:placetype":"locality"
},
  "geometry": {"coordinates":[12.78722,-2.20639],"type":"Point"}
}