{
  "type": "Feature",
  "properties": {
    "gn:admin1_code":"13",
    "gn:asciiname":"Obomba",
    "gn:country_code":"CG",
    "gn:dem":337,
    "gn:feature_class":"P",
    "gn:feature_code":"PPL",
    "gn:name":"Obomba",
    "gn:population":0,
    "gn:timezone":"Africa/Brazzaville",
    "iso:country":"CG",
    "wof:name":"Obomba",
    "wof:placetype":"locality"
},
  "geometry": {"coordinates":[15.61028,-0.02028],"type":"Point"}
}