{
  "type": "Feature",
  "properties": {
    "gn:admin1_code":"08",
    "gn:asciiname":"Okoubi",
    "gn:country_code":"CG",
    "gn:dem":388,
    "gn:feature_class":"P",
    "gn:feature_code":"PPL",
    "gn:name":"Okoubi",
    "gn:population":0,
    "gn:timezone":"Africa/Brazzaville",
    "iso:country":"CG",
    "wof:name":"Okoubi",
    "wof:placetype":"locality"
},
  "geometry": {"coordinates":[15.62444,-1.39389],"type":"Point"}
}