{
  "type": "Feature",
  "properties": {
    "gn:admin1_code":"08",
    "gn:asciiname":"Odzion",
    "gn:country_code":"CG",
    "gn:dem":794,
    "gn:feature_class":"P",
    "gn:feature_code":"PPL",
    "gn:name":"Odzion",
    "gn:population":0,
    "gn:timezone":"Africa/Brazzaville",
    "iso:country":"CG",
    "wof:name":"Odzion",
    "wof:placetype":"locality"
},
  "geometry": {"coordinates":[14.70889,-2.46667],"type":"Point"}
}