{
  "type": "Feature",
  "properties": {
    "gn:admin1_code":"13",
    "gn:asciiname":"Moindje",
    "gn:cc2":"CG",
    "gn:country_code":"CG",
    "gn:dem":379,
    "gn:feature_class":"P",
    "gn:feature_code":"PPL",
    "gn:name":"Moindj\u00e9",
    "gn:population":0,
    "gn:timezone":"Africa/Brazzaville",
    "iso:country":"CG",
    "name:und_x_variant":[
        "Mouandjou",
        "Mourandjok",
        "Moindj\u00e9"
    ],
    "wof:name":"Moindje",
    "wof:placetype":"locality"
},
  "geometry": {"coordinates":[15.67389,0.09667],"type":"Point"}
}