{
  "type": "Feature",
  "properties": {
    "gn:admin1_code":"13",
    "gn:asciiname":"Ambimi",
    "gn:country_code":"CG",
    "gn:dem":526,
    "gn:feature_class":"P",
    "gn:feature_code":"PPL",
    "gn:name":"Ambimi",
    "gn:population":0,
    "gn:timezone":"Africa/Brazzaville",
    "iso:country":"CG",
    "wof:name":"Ambimi",
    "wof:placetype":"locality"
},
  "geometry": {"coordinates":[14.60028,-1.35278],"type":"Point"}
}