{
  "type": "Feature",
  "properties": {
    "gn:admin1_code":"07",
    "gn:asciiname":"Kimongo",
    "gn:country_code":"CG",
    "gn:dem":393,
    "gn:feature_class":"P",
    "gn:feature_code":"PPL",
    "gn:name":"Kimongo",
    "gn:population":0,
    "gn:timezone":"Africa/Brazzaville",
    "iso:country":"CG",
    "wof:name":"Kimongo",
    "wof:placetype":"locality"
},
  "geometry": {"coordinates":[12.9425,-4.475],"type":"Point"}
}