{
  "type": "Feature",
  "properties": {
    "gn:admin1_code":"14",
    "gn:asciiname":"Alieni I",
    "gn:country_code":"CG",
    "gn:dem":457,
    "gn:feature_class":"P",
    "gn:feature_code":"PPL",
    "gn:name":"Ali\u00e9ni I",
    "gn:population":0,
    "gn:timezone":"Africa/Brazzaville",
    "iso:country":"CG",
    "wof:name":"Alieni I",
    "wof:placetype":"locality"
},
  "geometry": {"coordinates":[14.70417,-0.02389],"type":"Point"}
}