{
  "type": "Feature",
  "properties": {
    "gn:admin1_code":"04",
    "gn:asciiname":"Cotivindou",
    "gn:country_code":"CG",
    "gn:dem":142,
    "gn:feature_class":"P",
    "gn:feature_code":"PPL",
    "gn:name":"Cotivindou",
    "gn:population":0,
    "gn:timezone":"Africa/Brazzaville",
    "iso:country":"CG",
    "wof:name":"Cotivindou",
    "wof:placetype":"locality"
},
  "geometry": {"coordinates":[11.54972,-3.7625],"type":"Point"}
}