{
  "type": "Feature",
  "properties": {
    "gn:admin1_code":"14",
    "gn:asciiname":"Lebili",
    "gn:country_code":"CG",
    "gn:dem":508,
    "gn:feature_class":"P",
    "gn:feature_code":"PPL",
    "gn:name":"L\u00e9bili",
    "gn:population":0,
    "gn:timezone":"Africa/Brazzaville",
    "iso:country":"CG",
    "wof:name":"Lebili",
    "wof:placetype":"locality"
},
  "geometry": {"coordinates":[14.55222,-1.12278],"type":"Point"}
}