{
  "type": "Feature",
  "properties": {
    "gn:admin1_code":"10",
    "gn:asciiname":"Golo",
    "gn:country_code":"CG",
    "gn:dem":406,
    "gn:feature_class":"P",
    "gn:feature_code":"PPL",
    "gn:name":"Golo",
    "gn:population":0,
    "gn:timezone":"Africa/Brazzaville",
    "iso:country":"CG",
    "wof:name":"Golo",
    "wof:placetype":"locality"
},
  "geometry": {"coordinates":[15.09222,1.58611],"type":"Point"}
}