{
  "type": "Feature",
  "properties": {
    "gn:admin1_code":"11",
    "gn:asciiname":"Kimbedi",
    "gn:country_code":"CG",
    "gn:dem":212,
    "gn:feature_class":"P",
    "gn:feature_code":"PPL",
    "gn:name":"Kimbedi",
    "gn:population":0,
    "gn:timezone":"Africa/Brazzaville",
    "iso:country":"CG",
    "wof:name":"Kimbedi",
    "wof:placetype":"locality"
},
  "geometry": {"coordinates":[13.96722,-4.29444],"type":"Point"}
}