{
  "type": "Feature",
  "properties": {
    "gn:admin1_code":"11",
    "gn:asciiname":"Ampo",
    "gn:country_code":"CG",
    "gn:dem":591,
    "gn:feature_class":"P",
    "gn:feature_code":"PPL",
    "gn:name":"Ampo",
    "gn:population":0,
    "gn:timezone":"Africa/Brazzaville",
    "iso:country":"CG",
    "wof:name":"Ampo",
    "wof:placetype":"locality"
},
  "geometry": {"coordinates":[15.95,-3.23333],"type":"Point"}
}