{
  "type": "Feature",
  "properties": {
    "gn:admin1_code":"13",
    "gn:asciiname":"Tongo",
    "gn:country_code":"CG",
    "gn:dem":303,
    "gn:feature_class":"P",
    "gn:feature_code":"PPL",
    "gn:name":"Tongo",
    "gn:population":0,
    "gn:timezone":"Africa/Brazzaville",
    "iso:country":"CG",
    "name:ceb_x_preferred":[
        "Tongo"
    ],
    "name:fra_x_preferred":[
        "Tongo"
    ],
    "name:ind_x_preferred":[
        "Tongo"
    ],
    "name:pol_x_preferred":[
        "Tongo"
    ],
    "name:swe_x_preferred":[
        "Tongo"
    ],
    "wof:name":"Tongo",
    "wof:placetype":"locality"
},
  "geometry": {"coordinates":[16.30833,-1.38861],"type":"Point"}
}