{
  "type": "Feature",
  "properties": {
    "gn:admin1_code":"07",
    "gn:asciiname":"Bikabisende I",
    "gn:cc2":"CG",
    "gn:country_code":"CG",
    "gn:dem":129,
    "gn:feature_class":"P",
    "gn:feature_code":"PPL",
    "gn:name":"Bikabisend\u00e9 I",
    "gn:population":0,
    "gn:timezone":"Africa/Brazzaville",
    "iso:country":"CG",
    "name:und_x_variant":[
        "Bikabissend\u00e9",
        "Bikabissend\u00e9 I",
        "Bikabisend\u00e9 I"
    ],
    "wof:name":"Bikabisende I",
    "wof:placetype":"locality"
},
  "geometry": {"coordinates":[12.17889,-3.78083],"type":"Point"}
}