{
  "type": "Feature",
  "properties": {
    "gn:admin1_code":"10",
    "gn:asciiname":"Gangasa",
    "gn:cc2":"CG",
    "gn:country_code":"CG",
    "gn:dem":325,
    "gn:feature_class":"P",
    "gn:feature_code":"PPL",
    "gn:name":"Gangasa",
    "gn:population":0,
    "gn:timezone":"Africa/Brazzaville",
    "iso:country":"CG",
    "name:und_x_variant":[
        "Gangassa",
        "Gangasa"
    ],
    "wof:name":"Gangasa",
    "wof:placetype":"locality"
},
  "geometry": {"coordinates":[16.59194,0.83944],"type":"Point"}
}