{
  "type": "Feature",
  "properties": {
    "gn:admin1_code":"08",
    "gn:asciiname":"Boubou",
    "gn:country_code":"CG",
    "gn:dem":355,
    "gn:feature_class":"P",
    "gn:feature_code":"PPL",
    "gn:name":"Boubou",
    "gn:population":0,
    "gn:timezone":"Africa/Brazzaville",
    "iso:country":"CG",
    "name:ceb_x_preferred":[
        "Boubou"
    ],
    "name:fra_x_preferred":[
        "Boubou"
    ],
    "name:swe_x_preferred":[
        "Boubou"
    ],
    "wof:name":"Boubou",
    "wof:placetype":"locality"
},
  "geometry": {"coordinates":[15.81806,-1.42694],"type":"Point"}
}