{
  "type": "Feature",
  "properties": {
    "gn:admin1_code":"11",
    "gn:asciiname":"Yalavounga",
    "gn:cc2":"CG",
    "gn:country_code":"CG",
    "gn:dem":453,
    "gn:feature_class":"P",
    "gn:feature_code":"PPL",
    "gn:name":"Yalavounga",
    "gn:population":0,
    "gn:timezone":"Africa/Brazzaville",
    "iso:country":"CG",
    "name:und_x_variant":[
        "Yala Vounga",
        "Yalavounga"
    ],
    "wof:name":"Yalavounga",
    "wof:placetype":"locality"
},
  "geometry": {"coordinates":[14.75722,-4.41694],"type":"Point"}
}