{
  "type": "Feature",
  "properties": {
    "gn:admin1_code":"10",
    "gn:asciiname":"Poumba-Ekoum II",
    "gn:country_code":"CG",
    "gn:dem":498,
    "gn:feature_class":"P",
    "gn:feature_code":"PPL",
    "gn:name":"Poumba-Ekoum II",
    "gn:population":0,
    "gn:timezone":"Africa/Brazzaville",
    "iso:country":"CG",
    "wof:name":"Poumba-Ekoum II",
    "wof:placetype":"locality"
},
  "geometry": {"coordinates":[13.49944,1.62083],"type":"Point"}
}