{
  "type": "Feature",
  "properties": {
    "gn:admin1_code":"06",
    "gn:asciiname":"Youmbe",
    "gn:country_code":"CG",
    "gn:dem":310,
    "gn:feature_class":"P",
    "gn:feature_code":"PPL",
    "gn:name":"Youmb\u00e9",
    "gn:population":0,
    "gn:timezone":"Africa/Brazzaville",
    "iso:country":"CG",
    "wof:name":"Youmbe",
    "wof:placetype":"locality"
},
  "geometry": {"coordinates":[17.94083,1.27083],"type":"Point"}
}