{
  "type": "Feature",
  "properties": {
    "gn:admin1_code":"11",
    "gn:asciiname":"Kinngoma",
    "gn:cc2":"CG",
    "gn:country_code":"CG",
    "gn:dem":533,
    "gn:feature_class":"P",
    "gn:feature_code":"PPL",
    "gn:name":"Kinngoma",
    "gn:population":0,
    "gn:timezone":"Africa/Brazzaville",
    "iso:country":"CG",
    "name:und_x_variant":[
        "Kingoma",
        "Kinngoma"
    ],
    "wof:name":"Kinngoma",
    "wof:placetype":"locality"
},
  "geometry": {"coordinates":[14.63417,-4.88167],"type":"Point"}
}