{
  "type": "Feature",
  "properties": {
    "gn:admin1_code":"13",
    "gn:asciiname":"Okia",
    "gn:country_code":"CG",
    "gn:dem":376,
    "gn:feature_class":"P",
    "gn:feature_code":"PPL",
    "gn:name":"Okia",
    "gn:population":0,
    "gn:timezone":"Africa/Brazzaville",
    "iso:country":"CG",
    "wof:name":"Okia",
    "wof:placetype":"locality"
},
  "geometry": {"coordinates":[15.22972,-0.80278],"type":"Point"}
}