{
  "type": "Feature",
  "properties": {
    "gn:admin1_code":"11",
    "gn:asciiname":"Kikouimba",
    "gn:country_code":"CG",
    "gn:dem":539,
    "gn:feature_class":"P",
    "gn:feature_code":"PPL",
    "gn:name":"Kikouimba",
    "gn:population":0,
    "gn:timezone":"Africa/Brazzaville",
    "iso:country":"CG",
    "wof:name":"Kikouimba",
    "wof:placetype":"locality"
},
  "geometry": {"coordinates":[14.25222,-3.4825],"type":"Point"}
}