{
  "type": "Feature",
  "properties": {
    "gn:admin1_code":"07",
    "gn:asciiname":"Louboulou",
    "gn:country_code":"CG",
    "gn:dem":245,
    "gn:feature_class":"P",
    "gn:feature_code":"PPL",
    "gn:name":"Louboulou",
    "gn:population":0,
    "gn:timezone":"Africa/Brazzaville",
    "iso:country":"CG",
    "wof:name":"Louboulou",
    "wof:placetype":"locality"
},
  "geometry": {"coordinates":[12.50306,-3.335],"type":"Point"}
}