{
  "type": "Feature",
  "properties": {
    "gn:admin1_code":"08",
    "gn:asciiname":"Elonga II",
    "gn:cc2":"CG",
    "gn:country_code":"CG",
    "gn:dem":343,
    "gn:feature_class":"P",
    "gn:feature_code":"PPL",
    "gn:name":"Elonga II",
    "gn:population":0,
    "gn:timezone":"Africa/Brazzaville",
    "iso:country":"CG",
    "name:und_x_variant":[
        "Elonga",
        "Elonga II"
    ],
    "wof:name":"Elonga II",
    "wof:placetype":"locality"
},
  "geometry": {"coordinates":[15.96278,-1.44222],"type":"Point"}
}