{
  "type": "Feature",
  "properties": {
    "gn:admin1_code":"01",
    "gn:asciiname":"Youloukoye",
    "gn:country_code":"CG",
    "gn:dem":225,
    "gn:feature_class":"P",
    "gn:feature_code":"PPL",
    "gn:name":"Youloukoy\u00e9",
    "gn:population":0,
    "gn:timezone":"Africa/Brazzaville",
    "iso:country":"CG",
    "wof:name":"Youloukoye",
    "wof:placetype":"locality"
},
  "geometry": {"coordinates":[13.08806,-4.05972],"type":"Point"}
}