{
  "type": "Feature",
  "properties": {
    "gn:admin1_code":"10",
    "gn:asciiname":"Gola",
    "gn:cc2":"CG",
    "gn:country_code":"CG",
    "gn:dem":541,
    "gn:feature_class":"P",
    "gn:feature_code":"PPL",
    "gn:name":"Gola",
    "gn:population":0,
    "gn:timezone":"Africa/Brazzaville",
    "iso:country":"CG",
    "name:und_x_variant":[
        "Gola I",
        "Gola"
    ],
    "wof:name":"Gola",
    "wof:placetype":"locality"
},
  "geometry": {"coordinates":[14.19194,1.9275],"type":"Point"}
}