{
  "type": "Feature",
  "properties": {
    "gn:admin1_code":"05",
    "gn:asciiname":"Laga",
    "gn:country_code":"CG",
    "gn:dem":600,
    "gn:feature_class":"P",
    "gn:feature_code":"PPL",
    "gn:name":"Laga",
    "gn:population":0,
    "gn:timezone":"Africa/Brazzaville",
    "iso:country":"CG",
    "name:ceb_x_preferred":[
        "Laga"
    ],
    "name:deu_x_preferred":[
        "Laga"
    ],
    "name:nld_x_preferred":[
        "Laga"
    ],
    "name:swe_x_preferred":[
        "Laga"
    ],
    "wof:name":"Laga",
    "wof:placetype":"locality"
},
  "geometry": {"coordinates":[13.60306,-2.73722],"type":"Point"}
}