{
  "type": "Feature",
  "properties": {
    "gn:admin1_code":"11",
    "gn:asciiname":"Gambari",
    "gn:country_code":"CG",
    "gn:dem":451,
    "gn:feature_class":"P",
    "gn:feature_code":"PPL",
    "gn:name":"Gambari",
    "gn:population":0,
    "gn:timezone":"Africa/Brazzaville",
    "iso:country":"CG",
    "wof:name":"Gambari",
    "wof:placetype":"locality"
},
  "geometry": {"coordinates":[14.745,-4.32389],"type":"Point"}
}