{
  "type": "Feature",
  "properties": {
    "gn:admin1_code":"08",
    "gn:asciiname":"Aleki",
    "gn:country_code":"CG",
    "gn:dem":403,
    "gn:feature_class":"P",
    "gn:feature_code":"PPL",
    "gn:name":"Al\u00e9ki",
    "gn:population":0,
    "gn:timezone":"Africa/Brazzaville",
    "iso:country":"CG",
    "wof:name":"Aleki",
    "wof:placetype":"locality"
},
  "geometry": {"coordinates":[14.99194,-1.71306],"type":"Point"}
}