{
  "type": "Feature",
  "properties": {
    "gn:admin1_code":"07",
    "gn:asciiname":"Mallembe",
    "gn:cc2":"CG",
    "gn:country_code":"CG",
    "gn:dem":184,
    "gn:feature_class":"P",
    "gn:feature_code":"PPL",
    "gn:name":"Mallemb\u00e9",
    "gn:population":0,
    "gn:timezone":"Africa/Brazzaville",
    "iso:country":"CG",
    "name:und_x_variant":[
        "Malemb\u00e9",
        "Mallemb\u00e9"
    ],
    "wof:name":"Mallembe",
    "wof:placetype":"locality"
},
  "geometry": {"coordinates":[12.06667,-3.08333],"type":"Point"}
}