{
  "type": "Feature",
  "properties": {
    "gn:admin1_code":"10",
    "gn:asciiname":"Madjondo",
    "gn:country_code":"CG",
    "gn:dem":347,
    "gn:feature_class":"P",
    "gn:feature_code":"PPL",
    "gn:name":"Madjondo",
    "gn:population":0,
    "gn:timezone":"Africa/Brazzaville",
    "iso:country":"CG",
    "wof:name":"Madjondo",
    "wof:placetype":"locality"
},
  "geometry": {"coordinates":[16.1125,1.56194],"type":"Point"}
}