{
  "type": "Feature",
  "properties": {
    "gn:admin1_code":"13",
    "gn:asciiname":"Baya",
    "gn:cc2":"CG",
    "gn:country_code":"CG",
    "gn:dem":336,
    "gn:feature_class":"P",
    "gn:feature_code":"PPL",
    "gn:name":"Baya",
    "gn:population":0,
    "gn:timezone":"Africa/Brazzaville",
    "iso:country":"CG",
    "name:ara_x_preferred":[
        "\u0628\u0627\u064a\u0629"
    ],
    "name:ceb_x_preferred":[
        "Baya"
    ],
    "name:deu_x_preferred":[
        "Baya"
    ],
    "name:fra_x_preferred":[
        "Baya"
    ],
    "name:spa_x_preferred":[
        "Baya"
    ],
    "name:swe_x_preferred":[
        "Baya"
    ],
    "name:und_x_variant":[
        "Bouya"
    ],
    "wof:name":"Baya",
    "wof:placetype":"locality"
},
  "geometry": {"coordinates":[16.09333,-0.48861],"type":"Point"}
}