{
  "type": "Feature",
  "properties": {
    "gn:admin1_code":"14",
    "gn:asciiname":"Lembo",
    "gn:country_code":"CG",
    "gn:dem":592,
    "gn:feature_class":"P",
    "gn:feature_code":"PPL",
    "gn:name":"Lembo",
    "gn:population":0,
    "gn:timezone":"Africa/Brazzaville",
    "iso:country":"CG",
    "wof:name":"Lembo",
    "wof:placetype":"locality"
},
  "geometry": {"coordinates":[14.6875,0.39528],"type":"Point"}
}