{
  "type": "Feature",
  "properties": {
    "gn:admin1_code":"08",
    "gn:asciiname":"Onianva",
    "gn:country_code":"CG",
    "gn:dem":502,
    "gn:feature_class":"P",
    "gn:feature_code":"PPL",
    "gn:name":"Onianva",
    "gn:population":0,
    "gn:timezone":"Africa/Brazzaville",
    "iso:country":"CG",
    "name:urd_x_preferred":[
        "\u0627\u0648\u0646\u06cc\u0627\u0646\u0648\u0627"
    ],
    "wof:name":"Onianva",
    "wof:placetype":"locality"
},
  "geometry": {"coordinates":[15.81389,-2.34722],"type":"Point"}
}