{
  "type": "Feature",
  "properties": {
    "gn:admin1_code":"05",
    "gn:asciiname":"Moetche",
    "gn:country_code":"CG",
    "gn:dem":447,
    "gn:feature_class":"P",
    "gn:feature_code":"PPL",
    "gn:name":"Moetche",
    "gn:population":0,
    "gn:timezone":"Africa/Brazzaville",
    "iso:country":"CG",
    "wof:name":"Moetche",
    "wof:placetype":"locality"
},
  "geometry": {"coordinates":[13.28639,-3.00444],"type":"Point"}
}