{
  "type": "Feature",
  "properties": {
    "gn:admin1_code":"11",
    "gn:asciiname":"Kingoma",
    "gn:country_code":"CG",
    "gn:dem":446,
    "gn:feature_class":"P",
    "gn:feature_code":"PPL",
    "gn:name":"Kingoma",
    "gn:population":0,
    "gn:timezone":"Africa/Brazzaville",
    "iso:country":"CG",
    "wof:name":"Kingoma",
    "wof:placetype":"locality"
},
  "geometry": {"coordinates":[14.58472,-4.24944],"type":"Point"}
}