{
  "type": "Feature",
  "properties": {
    "gn:admin1_code":"13",
    "gn:asciiname":"Mokonda",
    "gn:cc2":"CG",
    "gn:country_code":"CG",
    "gn:dem":343,
    "gn:feature_class":"P",
    "gn:feature_code":"PPL",
    "gn:name":"Mokonda",
    "gn:population":0,
    "gn:timezone":"Africa/Brazzaville",
    "iso:country":"CG",
    "name:und_x_variant":[
        "Mokounda",
        "Mokonda"
    ],
    "wof:name":"Mokonda",
    "wof:placetype":"locality"
},
  "geometry": {"coordinates":[15.89306,-0.33417],"type":"Point"}
}