{
  "type": "Feature",
  "properties": {
    "gn:admin1_code":"07",
    "gn:asciiname":"Tsanga",
    "gn:cc2":"CG",
    "gn:country_code":"CG",
    "gn:dem":329,
    "gn:feature_class":"P",
    "gn:feature_code":"PPL",
    "gn:name":"Tsanga",
    "gn:population":0,
    "gn:timezone":"Africa/Brazzaville",
    "iso:country":"CG",
    "name:und_x_variant":[
        "Sanga",
        "Tsenga",
        "Tsanga-Mbouma",
        "Tsanga"
    ],
    "wof:name":"Tsanga",
    "wof:placetype":"locality"
},
  "geometry": {"coordinates":[12.87417,-4.17222],"type":"Point"}
}