{
  "type": "Feature",
  "properties": {
    "gn:admin1_code":"11",
    "gn:asciiname":"Yanga Dzala",
    "gn:country_code":"CG",
    "gn:dem":591,
    "gn:feature_class":"P",
    "gn:feature_code":"PPL",
    "gn:name":"Yanga Dzala",
    "gn:population":0,
    "gn:timezone":"Africa/Brazzaville",
    "iso:country":"CG",
    "wof:name":"Yanga Dzala",
    "wof:placetype":"locality"
},
  "geometry": {"coordinates":[14.64444,-4.745],"type":"Point"}
}