{
  "type": "Feature",
  "properties": {
    "gn:admin1_code":"11",
    "gn:asciiname":"Kinnsele",
    "gn:cc2":"CG",
    "gn:country_code":"CG",
    "gn:dem":508,
    "gn:feature_class":"P",
    "gn:feature_code":"PPL",
    "gn:name":"Kinns\u00e9l\u00e9",
    "gn:population":0,
    "gn:timezone":"Africa/Brazzaville",
    "iso:country":"CG",
    "name:und_x_variant":[
        "Kins\u00e9l\u00e9",
        "Kinns\u00e9l\u00e9"
    ],
    "wof:name":"Kinnsele",
    "wof:placetype":"locality"
},
  "geometry": {"coordinates":[14.68083,-4.48111],"type":"Point"}
}