{
  "type": "Feature",
  "properties": {
    "gn:admin1_code":"08",
    "gn:asciiname":"Babinga",
    "gn:country_code":"CG",
    "gn:dem":639,
    "gn:feature_class":"P",
    "gn:feature_code":"PPL",
    "gn:name":"Babinga",
    "gn:population":0,
    "gn:timezone":"Africa/Brazzaville",
    "iso:country":"CG",
    "wof:name":"Babinga",
    "wof:placetype":"locality"
},
  "geometry": {"coordinates":[15.49528,-2.17167],"type":"Point"}
}