{
  "type": "Feature",
  "properties": {
    "gn:admin1_code":"06",
    "gn:asciiname":"Goubangoye",
    "gn:country_code":"CG",
    "gn:dem":320,
    "gn:feature_class":"P",
    "gn:feature_code":"PPL",
    "gn:name":"Goubangoy\u00e9",
    "gn:population":0,
    "gn:timezone":"Africa/Brazzaville",
    "iso:country":"CG",
    "wof:name":"Goubangoye",
    "wof:placetype":"locality"
},
  "geometry": {"coordinates":[18.12611,2.39139],"type":"Point"}
}