{
  "type": "Feature",
  "properties": {
    "gn:admin1_code":"06",
    "gn:asciiname":"Soukissa-Balloys",
    "gn:country_code":"CG",
    "gn:dem":317,
    "gn:feature_class":"P",
    "gn:feature_code":"PPL",
    "gn:name":"Soukissa-Balloys",
    "gn:population":0,
    "gn:timezone":"Africa/Brazzaville",
    "iso:country":"CG",
    "wof:name":"Soukissa-Balloys",
    "wof:placetype":"locality"
},
  "geometry": {"coordinates":[17.93889,0.38278],"type":"Point"}
}