{
  "type": "Feature",
  "properties": {
    "gn:admin1_code":"10",
    "gn:asciiname":"Mboko",
    "gn:cc2":"CG",
    "gn:country_code":"CG",
    "gn:dem":353,
    "gn:feature_class":"P",
    "gn:feature_code":"PPL",
    "gn:name":"Mboko",
    "gn:population":0,
    "gn:timezone":"Africa/Brazzaville",
    "iso:country":"CG",
    "name:ceb_x_preferred":[
        "Mboko"
    ],
    "name:swe_x_preferred":[
        "Mboko"
    ],
    "name:und_x_variant":[
        "M\u2019Bako"
    ],
    "wof:name":"Mboko",
    "wof:placetype":"locality"
},
  "geometry": {"coordinates":[16.3725,1.26917],"type":"Point"}
}