{
  "type": "Feature",
  "properties": {
    "gn:admin1_code":"07",
    "gn:asciiname":"Kouedika",
    "gn:cc2":"CG",
    "gn:country_code":"CG",
    "gn:dem":255,
    "gn:feature_class":"P",
    "gn:feature_code":"PPL",
    "gn:name":"Kou\u00e9dika",
    "gn:population":0,
    "gn:timezone":"Africa/Brazzaville",
    "iso:country":"CG",
    "name:und_x_variant":[
        "Kou\u00e9dik\u00e9",
        "Kou\u00e9dika"
    ],
    "wof:name":"Kouedika",
    "wof:placetype":"locality"
},
  "geometry": {"coordinates":[12.15694,-3.64583],"type":"Point"}
}