{
  "type": "Feature",
  "properties": {
    "gn:admin1_code":"01",
    "gn:asciiname":"Nzasi",
    "gn:cc2":"CG",
    "gn:country_code":"CG",
    "gn:dem":332,
    "gn:feature_class":"P",
    "gn:feature_code":"PPL",
    "gn:name":"Nzasi",
    "gn:population":0,
    "gn:timezone":"Africa/Brazzaville",
    "iso:country":"CG",
    "name:und_x_variant":[
        "Dzassi",
        "Nzasi"
    ],
    "wof:name":"Nzasi",
    "wof:placetype":"locality"
},
  "geometry": {"coordinates":[13.67389,-4.0775],"type":"Point"}
}