{
  "type": "Feature",
  "properties": {
    "gn:admin1_code":"13",
    "gn:asciiname":"Yengo Monenn",
    "gn:country_code":"CG",
    "gn:dem":297,
    "gn:feature_class":"P",
    "gn:feature_code":"PPL",
    "gn:name":"Y\u00e8ngo Monenn",
    "gn:population":0,
    "gn:timezone":"Africa/Brazzaville",
    "iso:country":"CG",
    "wof:name":"Yengo Monenn",
    "wof:placetype":"locality"
},
  "geometry": {"coordinates":[16.67194,-0.7775],"type":"Point"}
}