{
  "type": "Feature",
  "properties": {
    "gn:admin1_code":"13",
    "gn:asciiname":"Angomon",
    "gn:country_code":"CG",
    "gn:dem":389,
    "gn:feature_class":"P",
    "gn:feature_code":"PPL",
    "gn:name":"Angomon",
    "gn:population":0,
    "gn:timezone":"Africa/Brazzaville",
    "iso:country":"CG",
    "wof:name":"Angomon",
    "wof:placetype":"locality"
},
  "geometry": {"coordinates":[15.00444,0.04417],"type":"Point"}
}