{
  "type": "Feature",
  "properties": {
    "gn:admin1_code":"06",
    "gn:asciiname":"Bondoki",
    "gn:country_code":"CG",
    "gn:dem":333,
    "gn:feature_class":"P",
    "gn:feature_code":"PPL",
    "gn:name":"Bondoki",
    "gn:population":0,
    "gn:timezone":"Africa/Brazzaville",
    "iso:country":"CG",
    "wof:name":"Bondoki",
    "wof:placetype":"locality"
},
  "geometry": {"coordinates":[17.10861,0.78583],"type":"Point"}
}