{
  "type": "Feature",
  "properties": {
    "gn:admin1_code":"04",
    "gn:asciiname":"Bimba",
    "gn:country_code":"CG",
    "gn:dem":110,
    "gn:feature_class":"P",
    "gn:feature_code":"PPL",
    "gn:name":"Bimba",
    "gn:population":0,
    "gn:timezone":"Africa/Brazzaville",
    "iso:country":"CG",
    "name:ceb_x_preferred":[
        "Bimba"
    ],
    "name:deu_x_preferred":[
        "Bimba"
    ],
    "name:ita_x_preferred":[
        "Bimba"
    ],
    "name:swe_x_preferred":[
        "Bimba"
    ],
    "wof:name":"Bimba",
    "wof:placetype":"locality"
},
  "geometry": {"coordinates":[11.74417,-3.965],"type":"Point"}
}