{
  "type": "Feature",
  "properties": {
    "gn:admin1_code":"11",
    "gn:asciiname":"Bouyala I",
    "gn:country_code":"CG",
    "gn:dem":552,
    "gn:feature_class":"P",
    "gn:feature_code":"PPL",
    "gn:name":"Bouyala I",
    "gn:population":0,
    "gn:timezone":"Africa/Brazzaville",
    "iso:country":"CG",
    "wof:name":"Bouyala I",
    "wof:placetype":"locality"
},
  "geometry": {"coordinates":[14.72083,-4.72972],"type":"Point"}
}