{
  "type": "Feature",
  "properties": {
    "gn:admin1_code":"06",
    "gn:asciiname":"Tala-Ngai",
    "gn:country_code":"CG",
    "gn:dem":318,
    "gn:feature_class":"P",
    "gn:feature_code":"PPL",
    "gn:name":"Tala-Ngai",
    "gn:population":0,
    "gn:timezone":"Africa/Brazzaville",
    "iso:country":"CG",
    "wof:name":"Tala-Ngai",
    "wof:placetype":"locality"
},
  "geometry": {"coordinates":[18.08528,2.18083],"type":"Point"}
}