{
  "type": "Feature",
  "properties": {
    "gn:admin1_code":"01",
    "gn:asciiname":"Bibondo",
    "gn:country_code":"CG",
    "gn:dem":288,
    "gn:feature_class":"P",
    "gn:feature_code":"PPL",
    "gn:name":"Bibondo",
    "gn:population":0,
    "gn:timezone":"Africa/Brazzaville",
    "iso:country":"CG",
    "wof:name":"Bibondo",
    "wof:placetype":"locality"
},
  "geometry": {"coordinates":[13.78889,-4.30556],"type":"Point"}
}