{
  "type": "Feature",
  "properties": {
    "gn:admin1_code":"08",
    "gn:asciiname":"Ankan",
    "gn:country_code":"CG",
    "gn:dem":710,
    "gn:feature_class":"P",
    "gn:feature_code":"PPL",
    "gn:name":"Ankan",
    "gn:population":0,
    "gn:timezone":"Africa/Brazzaville",
    "iso:country":"CG",
    "wof:name":"Ankan",
    "wof:placetype":"locality"
},
  "geometry": {"coordinates":[15.05528,-2.17111],"type":"Point"}
}