{
  "type": "Feature",
  "properties": {
    "gn:admin1_code":"04",
    "gn:asciiname":"Tchingoli",
    "gn:country_code":"CG",
    "gn:dem":52,
    "gn:feature_class":"P",
    "gn:feature_code":"PPL",
    "gn:name":"Tchingoli",
    "gn:population":0,
    "gn:timezone":"Africa/Brazzaville",
    "iso:country":"CG",
    "wof:name":"Tchingoli",
    "wof:placetype":"locality"
},
  "geometry": {"coordinates":[11.96472,-4.49083],"type":"Point"}
}