{
  "type": "Feature",
  "properties": {
    "gn:admin1_code":"14",
    "gn:asciiname":"Mpagui",
    "gn:country_code":"CG",
    "gn:dem":426,
    "gn:feature_class":"P",
    "gn:feature_code":"PPL",
    "gn:name":"Mpagui",
    "gn:population":0,
    "gn:timezone":"Africa/Brazzaville",
    "iso:country":"CG",
    "wof:name":"Mpagui",
    "wof:placetype":"locality"
},
  "geometry": {"coordinates":[15.01667,-0.87361],"type":"Point"}
}