{
  "type": "Feature",
  "properties": {
    "gn:admin1_code":"07",
    "gn:asciiname":"Ditendolo",
    "gn:country_code":"CG",
    "gn:dem":213,
    "gn:feature_class":"P",
    "gn:feature_code":"PPL",
    "gn:name":"Ditendolo",
    "gn:population":0,
    "gn:timezone":"Africa/Brazzaville",
    "iso:country":"CG",
    "wof:name":"Ditendolo",
    "wof:placetype":"locality"
},
  "geometry": {"coordinates":[12.58333,-3.95],"type":"Point"}
}