{
  "type": "Feature",
  "properties": {
    "gn:admin1_code":"05",
    "gn:asciiname":"Badoungou",
    "gn:country_code":"CG",
    "gn:dem":441,
    "gn:feature_class":"P",
    "gn:feature_code":"PPL",
    "gn:name":"Badoungou",
    "gn:population":0,
    "gn:timezone":"Africa/Brazzaville",
    "iso:country":"CG",
    "wof:name":"Badoungou",
    "wof:placetype":"locality"
},
  "geometry": {"coordinates":[13.33333,-3.04389],"type":"Point"}
}