{
  "type": "Feature",
  "properties": {
    "gn:admin1_code":"04",
    "gn:asciiname":"Kakamoeka",
    "gn:country_code":"CG",
    "gn:dem":146,
    "gn:feature_class":"P",
    "gn:feature_code":"PPL",
    "gn:name":"Kakamo\u00e9ka",
    "gn:population":0,
    "gn:timezone":"Africa/Brazzaville",
    "iso:country":"CG",
    "wof:name":"Kakamoeka",
    "wof:placetype":"locality"
},
  "geometry": {"coordinates":[12.0675,-4.13083],"type":"Point"}
}