{
  "type": "Feature",
  "properties": {
    "gn:admin1_code":"06",
    "gn:asciiname":"Makasa",
    "gn:country_code":"CG",
    "gn:dem":338,
    "gn:feature_class":"P",
    "gn:feature_code":"PPL",
    "gn:name":"Makasa",
    "gn:population":0,
    "gn:timezone":"Africa/Brazzaville",
    "iso:country":"CG",
    "wof:name":"Makasa",
    "wof:placetype":"locality"
},
  "geometry": {"coordinates":[18.21417000000001,2.50444],"type":"Point"}
}