{
  "type": "Feature",
  "properties": {
    "gn:admin1_code":"11",
    "gn:asciiname":"Sakala",
    "gn:country_code":"CG",
    "gn:dem":606,
    "gn:feature_class":"P",
    "gn:feature_code":"PPL",
    "gn:name":"Sakala",
    "gn:population":0,
    "gn:timezone":"Africa/Brazzaville",
    "iso:country":"CG",
    "name:ceb_x_preferred":[
        "Sakala"
    ],
    "name:deu_x_preferred":[
        "Sakala"
    ],
    "name:est_x_preferred":[
        "Sakala"
    ],
    "name:glg_x_preferred":[
        "Sakala"
    ],
    "name:new_x_preferred":[
        "\u0938\u0915\u0932\u093e"
    ],
    "name:swe_x_preferred":[
        "Sakala"
    ],
    "wof:name":"Sakala",
    "wof:placetype":"locality"
},
  "geometry": {"coordinates":[13.98417,-4.3725],"type":"Point"}
}