{
  "type": "Feature",
  "properties": {
    "gn:admin1_code":"01",
    "gn:asciiname":"Kimbedi",
    "gn:country_code":"CG",
    "gn:dem":174,
    "gn:feature_class":"P",
    "gn:feature_code":"PPL",
    "gn:name":"Kimb\u00e9di",
    "gn:population":0,
    "gn:timezone":"Africa/Brazzaville",
    "iso:country":"CG",
    "wof:name":"Kimbedi",
    "wof:placetype":"locality"
},
  "geometry": {"coordinates":[13.33639,-4.27167],"type":"Point"}
}