{
  "type": "Feature",
  "properties": {
    "gn:admin1_code":"08",
    "gn:asciiname":"Ngakoma",
    "gn:cc2":"CG",
    "gn:country_code":"CG",
    "gn:dem":387,
    "gn:feature_class":"P",
    "gn:feature_code":"PPL",
    "gn:name":"Ngakoma",
    "gn:population":0,
    "gn:timezone":"Africa/Brazzaville",
    "iso:country":"CG",
    "name:und_x_variant":[
        "Gankoma",
        "Ngakoma"
    ],
    "wof:name":"Ngakoma",
    "wof:placetype":"locality"
},
  "geometry": {"coordinates":[15.1225,-1.47583],"type":"Point"}
}