{
  "type": "Feature",
  "properties": {
    "gn:admin1_code":"11",
    "gn:asciiname":"Gabanoue",
    "gn:country_code":"CG",
    "gn:dem":446,
    "gn:feature_class":"P",
    "gn:feature_code":"PPL",
    "gn:name":"Gabanou\u00e9",
    "gn:population":0,
    "gn:timezone":"Africa/Brazzaville",
    "iso:country":"CG",
    "wof:name":"Gabanoue",
    "wof:placetype":"locality"
},
  "geometry": {"coordinates":[14.74833,-4.33833],"type":"Point"}
}