{
  "type": "Feature",
  "properties": {
    "gn:admin1_code":"07",
    "gn:asciiname":"Nyali",
    "gn:country_code":"CG",
    "gn:dem":172,
    "gn:feature_class":"P",
    "gn:feature_code":"PPL",
    "gn:name":"Nyali",
    "gn:population":0,
    "gn:timezone":"Africa/Brazzaville",
    "iso:country":"CG",
    "name:fra_x_preferred":[
        "Nyali"
    ],
    "wof:name":"Nyali",
    "wof:placetype":"locality"
},
  "geometry": {"coordinates":[11.99111,-2.855],"type":"Point"}
}