{
  "type": "Feature",
  "properties": {
    "gn:admin1_code":"14",
    "gn:asciiname":"Ekouya",
    "gn:country_code":"CG",
    "gn:dem":433,
    "gn:feature_class":"P",
    "gn:feature_code":"PPL",
    "gn:name":"Ekouya",
    "gn:population":0,
    "gn:timezone":"Africa/Brazzaville",
    "iso:country":"CG",
    "wof:name":"Ekouya",
    "wof:placetype":"locality"
},
  "geometry": {"coordinates":[14.78667,-0.06361],"type":"Point"}
}