{
  "type": "Feature",
  "properties": {
    "gn:admin1_code":"13",
    "gn:asciiname":"Pori",
    "gn:country_code":"CG",
    "gn:dem":579,
    "gn:feature_class":"P",
    "gn:feature_code":"PPL",
    "gn:name":"Pori",
    "gn:population":0,
    "gn:timezone":"Africa/Brazzaville",
    "iso:country":"CG",
    "name:und_x_variant":[
        "Nkori",
        "Pori"
    ],
    "wof:name":"Pori",
    "wof:placetype":"locality"
},
  "geometry": {"coordinates":[14.60972,-1.27167],"type":"Point"}
}