{
  "type": "Feature",
  "properties": {
    "gn:admin1_code":"13",
    "gn:asciiname":"Okondo",
    "gn:cc2":"CG",
    "gn:country_code":"CG",
    "gn:dem":335,
    "gn:feature_class":"P",
    "gn:feature_code":"PPL",
    "gn:name":"Okondo",
    "gn:population":0,
    "gn:timezone":"Africa/Brazzaville",
    "iso:country":"CG",
    "name:ara_x_preferred":[
        "\u0623\u0648\u0643\u064a\u0646\u062f\u0648"
    ],
    "name:arg_x_preferred":[
        "Okondo"
    ],
    "name:ast_x_preferred":[
        "Oquendo"
    ],
    "name:azb_x_preferred":[
        "\u0627\u06a9\u0646\u062f\u0648"
    ],
    "name:bre_x_preferred":[
        "Okondo"
    ],
    "name:cat_x_preferred":[
        "Okondo"
    ],
    "name:ceb_x_preferred":[
        "Okondo"
    ],
    "name:eus_x_preferred":[
        "Okondo"
    ],
    "name:fas_x_preferred":[
        "\u0627\u06a9\u0646\u062f\u0648"
    ],
    "name:fra_x_preferred":[
        "Okondo"
    ],
    "name:glg_x_preferred":[
        "Okondo"
    ],
    "name:hun_x_preferred":[
        "Okondo"
    ],
    "name:ita_x_preferred":[
        "Okondo"
    ],
    "name:mkd_x_preferred":[
        "\u041e\u043a\u043e\u043d\u0434\u043e"
    ],
    "name:msa_x_preferred":[
        "Okondo"
    ],
    "name:nld_x_preferred":[
        "Okondo"
    ],
    "name:oci_x_preferred":[
        "Okondo"
    ],
    "name:pol_x_preferred":[
        "Okondo"
    ],
    "name:por_x_preferred":[
        "Okondo"
    ],
    "name:rus_x_preferred":[
        "\u041e\u043a\u0435\u043d\u0434\u043e"
    ],
    "name:sco_x_preferred":[
        "Okondo"
    ],
    "name:spa_x_preferred":[
        "Oquendo"
    ],
    "name:swe_x_preferred":[
        "Okondo"
    ],
    "name:tur_x_preferred":[
        "Oquendo"
    ],
    "name:ukr_x_preferred":[
        "\u041e\u043a\u043e\u043d\u0434\u043e"
    ],
    "name:und_x_variant":[
        "Okando",
        "Okondo"
    ],
    "name:uzb_x_preferred":[
        "Oquendo"
    ],
    "name:vie_x_preferred":[
        "Okondo"
    ],
    "name:war_x_preferred":[
        "Okondo"
    ],
    "name:zho_x_preferred":[
        "\u5965\u57fa\u7fc1\u591a"
    ],
    "wof:name":"Okondo",
    "wof:placetype":"locality"
},
  "geometry": {"coordinates":[15.84389,0.115],"type":"Point"}
}