{
  "type": "Feature",
  "properties": {
    "gn:admin1_code":"13",
    "gn:asciiname":"Okondo",
    "gn:cc2":"CG",
    "gn:country_code":"CG",
    "gn:dem":335,
    "gn:feature_class":"P",
    "gn:feature_code":"PPL",
    "gn:name":"Okondo",
    "gn:population":0,
    "gn:timezone":"Africa/Brazzaville",
    "iso:country":"CG",
    "name:und_x_variant":[
        "Okando",
        "Okondo"
    ],
    "wof:name":"Okondo",
    "wof:placetype":"locality"
},
  "geometry": {"coordinates":[15.84389,0.115],"type":"Point"}
}