{
  "type": "Feature",
  "properties": {
    "gn:admin1_code":"13",
    "gn:asciiname":"Ntokou-Fago",
    "gn:cc2":"CG",
    "gn:country_code":"CG",
    "gn:dem":332,
    "gn:feature_class":"P",
    "gn:feature_code":"PPL",
    "gn:name":"Ntokou-Fago",
    "gn:population":0,
    "gn:timezone":"Africa/Brazzaville",
    "iso:country":"CG",
    "name:und_x_variant":[
        "Ntokou",
        "Remondville",
        "Ntokou-Fago"
    ],
    "wof:name":"Ntokou-Fago",
    "wof:placetype":"locality"
},
  "geometry": {"coordinates":[16.39528,0.01667],"type":"Point"}
}