{
  "type": "Feature",
  "properties": {
    "gn:admin1_code":"07",
    "gn:asciiname":"Oubouesse",
    "gn:cc2":"CG",
    "gn:country_code":"CG",
    "gn:dem":468,
    "gn:feature_class":"P",
    "gn:feature_code":"PPL",
    "gn:name":"Oubou\u00e9ss\u00e9",
    "gn:population":0,
    "gn:timezone":"Africa/Brazzaville",
    "iso:country":"CG",
    "name:und_x_variant":[
        "Boues\u00e9",
        "Oubou\u00e9ss\u00e9"
    ],
    "wof:name":"Oubouesse",
    "wof:placetype":"locality"
},
  "geometry": {"coordinates":[12.66028,-2.85583],"type":"Point"}
}