{
  "type": "Feature",
  "properties": {
    "gn:admin1_code":"08",
    "gn:asciiname":"Mbe",
    "gn:country_code":"CG",
    "gn:dem":627,
    "gn:feature_class":"P",
    "gn:feature_code":"PPL",
    "gn:name":"Mbe",
    "gn:population":0,
    "gn:timezone":"Africa/Brazzaville",
    "iso:country":"CG",
    "wof:name":"Mbe",
    "wof:placetype":"locality"
},
  "geometry": {"coordinates":[15.52889,-2.80583],"type":"Point"}
}