{
  "type": "Feature",
  "properties": {
    "gn:admin1_code":"13",
    "gn:asciiname":"Katsoko",
    "gn:country_code":"CG",
    "gn:dem":348,
    "gn:feature_class":"P",
    "gn:feature_code":"PPL",
    "gn:name":"Katsoko",
    "gn:population":0,
    "gn:timezone":"Africa/Brazzaville",
    "iso:country":"CG",
    "wof:name":"Katsoko",
    "wof:placetype":"locality"
},
  "geometry": {"coordinates":[15.62472,-0.81583],"type":"Point"}
}