{
  "type": "Feature",
  "properties": {
    "gn:admin1_code":"11",
    "gn:asciiname":"Bebezi",
    "gn:country_code":"CG",
    "gn:dem":458,
    "gn:feature_class":"P",
    "gn:feature_code":"PPL",
    "gn:name":"B\u00e9b\u00e9zi",
    "gn:population":0,
    "gn:timezone":"Africa/Brazzaville",
    "iso:country":"CG",
    "wof:name":"Bebezi",
    "wof:placetype":"locality"
},
  "geometry": {"coordinates":[14.74222,-4.51056],"type":"Point"}
}