{
  "type": "Feature",
  "properties": {
    "gn:admin1_code":"04",
    "gn:asciiname":"Tchibangou",
    "gn:country_code":"CG",
    "gn:dem":34,
    "gn:feature_class":"P",
    "gn:feature_code":"PPL",
    "gn:name":"Tchibangou",
    "gn:population":0,
    "gn:timezone":"Africa/Brazzaville",
    "iso:country":"CG",
    "wof:name":"Tchibangou",
    "wof:placetype":"locality"
},
  "geometry": {"coordinates":[11.71667,-4.33333],"type":"Point"}
}