{
  "type": "Feature",
  "properties": {
    "gn:admin1_code":"13",
    "gn:asciiname":"Ekondzo",
    "gn:cc2":"CG",
    "gn:country_code":"CG",
    "gn:dem":375,
    "gn:feature_class":"P",
    "gn:feature_code":"PPL",
    "gn:name":"Ekondzo",
    "gn:population":0,
    "gn:timezone":"Africa/Brazzaville",
    "iso:country":"CG",
    "name:und_x_variant":[
        "Ekondjo",
        "Ekondzo"
    ],
    "wof:name":"Ekondzo",
    "wof:placetype":"locality"
},
  "geometry": {"coordinates":[15.9225,-0.22806],"type":"Point"}
}