{
  "type": "Feature",
  "properties": {
    "gn:admin1_code":"12",
    "gn:asciiname":"Kindamba",
    "gn:country_code":"CG",
    "gn:dem":345,
    "gn:feature_class":"P",
    "gn:feature_code":"PPL",
    "gn:name":"Kindamba",
    "gn:population":0,
    "gn:timezone":"Africa/Brazzaville",
    "iso:country":"CG",
    "wof:name":"Kindamba",
    "wof:placetype":"locality"
},
  "geometry": {"coordinates":[15.04889,-4.30472],"type":"Point"}
}