{
  "type": "Feature",
  "properties": {
    "gn:admin1_code":"01",
    "gn:asciiname":"Kisende",
    "gn:country_code":"CG",
    "gn:dem":171,
    "gn:feature_class":"P",
    "gn:feature_code":"PPL",
    "gn:name":"Kisend\u00e9",
    "gn:population":0,
    "gn:timezone":"Africa/Brazzaville",
    "iso:country":"CG",
    "wof:name":"Kisende",
    "wof:placetype":"locality"
},
  "geometry": {"coordinates":[13.50861,-4.17639],"type":"Point"}
}