{
  "type": "Feature",
  "properties": {
    "gn:admin1_code":"11",
    "gn:asciiname":"Mpoumako",
    "gn:cc2":"CG",
    "gn:country_code":"CG",
    "gn:dem":686,
    "gn:feature_class":"P",
    "gn:feature_code":"PPL",
    "gn:name":"Mpoumako",
    "gn:population":0,
    "gn:timezone":"Africa/Brazzaville",
    "iso:country":"CG",
    "name:und_x_variant":[
        "Poumako",
        "Mpoumako"
    ],
    "wof:name":"Mpoumako",
    "wof:placetype":"locality"
},
  "geometry": {"coordinates":[15.61222,-3.11111],"type":"Point"}
}