{
  "type": "Feature",
  "properties": {
    "gn:admin1_code":"12",
    "gn:asciiname":"Le Ferik",
    "gn:country_code":"CG",
    "gn:dem":354,
    "gn:feature_class":"P",
    "gn:feature_code":"PPL",
    "gn:name":"Le F\u00e9rik",
    "gn:population":0,
    "gn:timezone":"Africa/Brazzaville",
    "iso:country":"CG",
    "wof:name":"Le Ferik",
    "wof:placetype":"locality"
},
  "geometry": {"coordinates":[15.11667,-4.26667],"type":"Point"}
}