{
  "type": "Feature",
  "properties": {
    "gn:admin1_code":"11",
    "gn:asciiname":"Mbemba",
    "gn:country_code":"CG",
    "gn:dem":469,
    "gn:feature_class":"P",
    "gn:feature_code":"PPL",
    "gn:name":"Mbemba",
    "gn:population":0,
    "gn:timezone":"Africa/Brazzaville",
    "iso:country":"CG",
    "name:ceb_x_preferred":[
        "Mbemba"
    ],
    "name:deu_x_preferred":[
        "Mbemba"
    ],
    "name:fra_x_preferred":[
        "Mbemba"
    ],
    "name:swe_x_preferred":[
        "Mbemba"
    ],
    "wof:name":"Mbemba",
    "wof:placetype":"locality"
},
  "geometry": {"coordinates":[14.50667,-3.50167],"type":"Point"}
}