{
  "type": "Feature",
  "properties": {
    "gn:admin1_code":"07",
    "gn:asciiname":"Idoumi",
    "gn:country_code":"CG",
    "gn:dem":281,
    "gn:feature_class":"P",
    "gn:feature_code":"PPL",
    "gn:name":"Idoumi",
    "gn:population":0,
    "gn:timezone":"Africa/Brazzaville",
    "iso:country":"CG",
    "wof:name":"Idoumi",
    "wof:placetype":"locality"
},
  "geometry": {"coordinates":[11.80889,-2.77944],"type":"Point"}
}