{
  "type": "Feature",
  "properties": {
    "gn:admin1_code":"11",
    "gn:asciiname":"Kololo",
    "gn:country_code":"CG",
    "gn:dem":505,
    "gn:feature_class":"P",
    "gn:feature_code":"PPL",
    "gn:name":"Kololo",
    "gn:population":0,
    "gn:timezone":"Africa/Brazzaville",
    "iso:country":"CG",
    "wof:name":"Kololo",
    "wof:placetype":"locality"
},
  "geometry": {"coordinates":[14.44417,-3.455],"type":"Point"}
}