{
  "type": "Feature",
  "properties": {
    "gn:admin1_code":"08",
    "gn:asciiname":"Makotipoko",
    "gn:cc2":"CG",
    "gn:country_code":"CG",
    "gn:dem":287,
    "gn:feature_class":"P",
    "gn:feature_code":"PPL",
    "gn:name":"Makotipoko",
    "gn:population":0,
    "gn:timezone":"Africa/Brazzaville",
    "iso:country":"CG",
    "name:und_x_variant":[
        "Makotimpoko",
        "Makotipoko"
    ],
    "wof:name":"Makotipoko",
    "wof:placetype":"locality"
},
  "geometry": {"coordinates":[16.31528,-1.99528],"type":"Point"}
}