{
  "type": "Feature",
  "properties": {
    "gn:admin1_code":"11",
    "gn:asciiname":"Yakou",
    "gn:country_code":"CG",
    "gn:dem":524,
    "gn:feature_class":"P",
    "gn:feature_code":"PPL",
    "gn:name":"Yakou",
    "gn:population":0,
    "gn:timezone":"Africa/Brazzaville",
    "iso:country":"CG",
    "wof:name":"Yakou",
    "wof:placetype":"locality"
},
  "geometry": {"coordinates":[14.19583,-3.36667],"type":"Point"}
}