{
  "type": "Feature",
  "properties": {
    "gn:admin1_code":"07",
    "gn:asciiname":"Ngono",
    "gn:country_code":"CG",
    "gn:dem":460,
    "gn:feature_class":"P",
    "gn:feature_code":"PPL",
    "gn:name":"Ngono",
    "gn:population":0,
    "gn:timezone":"Africa/Brazzaville",
    "iso:country":"CG",
    "wof:name":"Ngono",
    "wof:placetype":"locality"
},
  "geometry": {"coordinates":[12.64528,-2.93111],"type":"Point"}
}