{
  "type": "Feature",
  "properties": {
    "gn:admin1_code":"13",
    "gn:asciiname":"Assala",
    "gn:cc2":"CG",
    "gn:country_code":"CG",
    "gn:dem":318,
    "gn:feature_class":"P",
    "gn:feature_code":"PPL",
    "gn:name":"Assala",
    "gn:population":0,
    "gn:timezone":"Africa/Brazzaville",
    "iso:country":"CG",
    "name:und_x_variant":[
        "Assali",
        "Assala"
    ],
    "wof:name":"Assala",
    "wof:placetype":"locality"
},
  "geometry": {"coordinates":[15.96222,-0.54194],"type":"Point"}
}