{
  "type": "Feature",
  "properties": {
    "gn:admin1_code":"13",
    "gn:asciiname":"Bokwele",
    "gn:country_code":"CG",
    "gn:dem":307,
    "gn:feature_class":"P",
    "gn:feature_code":"PPL",
    "gn:name":"Bokw\u00e9l\u00e9",
    "gn:population":0,
    "gn:timezone":"Africa/Brazzaville",
    "iso:country":"CG",
    "wof:name":"Bokwele",
    "wof:placetype":"locality"
},
  "geometry": {"coordinates":[16.3175,-1.03667],"type":"Point"}
}