{
  "type": "Feature",
  "properties": {
    "gn:admin1_code":"05",
    "gn:asciiname":"Mafoula",
    "gn:country_code":"CG",
    "gn:dem":609,
    "gn:feature_class":"P",
    "gn:feature_code":"PPL",
    "gn:name":"Mafoula",
    "gn:population":0,
    "gn:timezone":"Africa/Brazzaville",
    "iso:country":"CG",
    "wof:name":"Mafoula",
    "wof:placetype":"locality"
},
  "geometry": {"coordinates":[13.60722,-2.905],"type":"Point"}
}