{
  "type": "Feature",
  "properties": {
    "gn:admin1_code":"10",
    "gn:asciiname":"Kabo",
    "gn:country_code":"CG",
    "gn:dem":365,
    "gn:feature_class":"P",
    "gn:feature_code":"PPL",
    "gn:name":"Kabo",
    "gn:population":0,
    "gn:timezone":"Africa/Brazzaville",
    "iso:country":"CG",
    "name:azb_x_preferred":[
        "\u06a9\u0627\u0628\u0648"
    ],
    "name:ceb_x_preferred":[
        "Kabo"
    ],
    "name:fas_x_preferred":[
        "\u06a9\u0627\u0628\u0648"
    ],
    "name:fra_x_preferred":[
        "Kabo"
    ],
    "name:ita_x_preferred":[
        "Kabo"
    ],
    "name:pol_x_preferred":[
        "Kabo"
    ],
    "name:ron_x_preferred":[
        "Kabo"
    ],
    "name:rus_x_preferred":[
        "\u041a\u0430\u0431\u043e"
    ],
    "name:sag_x_preferred":[
        "Kabo"
    ],
    "name:swe_x_preferred":[
        "Kabo"
    ],
    "name:tur_x_preferred":[
        "Kabo"
    ],
    "wof:name":"Kabo",
    "wof:placetype":"locality"
},
  "geometry": {"coordinates":[16.08194,2.03056],"type":"Point"}
}