{
  "type": "Feature",
  "properties": {
    "gn:admin1_code":"10",
    "gn:asciiname":"Kabo",
    "gn:country_code":"CG",
    "gn:dem":365,
    "gn:feature_class":"P",
    "gn:feature_code":"PPL",
    "gn:name":"Kabo",
    "gn:population":0,
    "gn:timezone":"Africa/Brazzaville",
    "iso:country":"CG",
    "wof:name":"Kabo",
    "wof:placetype":"locality"
},
  "geometry": {"coordinates":[16.08194,2.03056],"type":"Point"}
}