{
  "type": "Feature",
  "properties": {
    "gn:admin1_code":"14",
    "gn:asciiname":"Okelataka",
    "gn:country_code":"CG",
    "gn:dem":427,
    "gn:feature_class":"P",
    "gn:feature_code":"PPL",
    "gn:name":"Ok\u00e9lataka",
    "gn:population":0,
    "gn:timezone":"Africa/Brazzaville",
    "iso:country":"CG",
    "name:und_x_variant":[
        "Okalataka",
        "Ok\u00e9lataka"
    ],
    "wof:name":"Okelataka",
    "wof:placetype":"locality"
},
  "geometry": {"coordinates":[14.915,-0.30611],"type":"Point"}
}