{
  "type": "Feature",
  "properties": {
    "gn:admin1_code":"12",
    "gn:asciiname":"Tingoy",
    "gn:country_code":"CG",
    "gn:dem":421,
    "gn:feature_class":"P",
    "gn:feature_code":"PPL",
    "gn:name":"Tingoy",
    "gn:population":0,
    "gn:timezone":"Africa/Brazzaville",
    "iso:country":"CG",
    "name:und_x_variant":[
        "Kingoy\u00e9",
        "Tingoy"
    ],
    "wof:name":"Tingoy",
    "wof:placetype":"locality"
},
  "geometry": {"coordinates":[15.03333,-4.36556],"type":"Point"}
}