{
  "type": "Feature",
  "properties": {
    "gn:admin1_code":"11",
    "gn:asciiname":"Gombe",
    "gn:country_code":"CG",
    "gn:dem":587,
    "gn:feature_class":"P",
    "gn:feature_code":"PPL",
    "gn:name":"Gomb\u00e9",
    "gn:population":0,
    "gn:timezone":"Africa/Brazzaville",
    "iso:country":"CG",
    "name:cat_x_preferred":[
        "Gombe"
    ],
    "name:ceb_x_preferred":[
        "Gombe"
    ],
    "name:dan_x_preferred":[
        "Gombe"
    ],
    "name:deu_x_preferred":[
        "Gombe"
    ],
    "name:fra_x_preferred":[
        "Gombe"
    ],
    "name:glg_x_preferred":[
        "Gombe"
    ],
    "name:hau_x_preferred":[
        "Gombe"
    ],
    "name:ita_x_preferred":[
        "Gombe"
    ],
    "name:lug_x_preferred":[
        "Gombe"
    ],
    "name:mlg_x_preferred":[
        "Gombe"
    ],
    "name:nld_x_preferred":[
        "Gombe"
    ],
    "name:pol_x_preferred":[
        "Gombe"
    ],
    "name:por_x_preferred":[
        "Gombe"
    ],
    "name:spa_x_preferred":[
        "Gombe"
    ],
    "name:swe_x_preferred":[
        "Gombe"
    ],
    "wof:name":"Gombe",
    "wof:placetype":"locality"
},
  "geometry": {"coordinates":[14.64972,-4.78028],"type":"Point"}
}