{
  "type": "Feature",
  "properties": {
    "gn:admin1_code":"05",
    "gn:asciiname":"Ketouna",
    "gn:cc2":"CG",
    "gn:country_code":"CG",
    "gn:dem":589,
    "gn:feature_class":"P",
    "gn:feature_code":"PPL",
    "gn:name":"K\u00e9touna",
    "gn:population":0,
    "gn:timezone":"Africa/Brazzaville",
    "iso:country":"CG",
    "name:und_x_variant":[
        "K\u00e9touno",
        "K\u00e9touna"
    ],
    "wof:name":"Ketouna",
    "wof:placetype":"locality"
},
  "geometry": {"coordinates":[13.96,-2.93639],"type":"Point"}
}