{
  "type": "Feature",
  "properties": {
    "gn:country":"CG",
    "gn:fcode":"PPL",
    "gn:population":23204,
    "iso:country":"CG",
    "name:eng_x_preferred":[
        "Loandjili district"
    ],
    "name:fra_x_preferred":[
        "Loandjili"
    ],
    "name:und_x_variant":[
        "Louantili"
    ],
    "qs:name":"Loandjili",
    "qs:photos_9r":0,
    "qs:photos_sr":0,
    "qs:pop_sr":"7",
    "wd:wordcount":66,
    "wof:name":"Loandjili",
    "wof:placetype":"locality",
    "wof:population":23204
},
  "geometry": {"coordinates":[11.85778,-4.75611],"type":"Point"}
}