{
  "type": "Feature",
  "properties": {
    "gn:admin1_code":"11",
    "gn:asciiname":"Nsomo",
    "gn:country_code":"CG",
    "gn:dem":381,
    "gn:feature_class":"P",
    "gn:feature_code":"PPL",
    "gn:name":"Nsomo",
    "gn:population":0,
    "gn:timezone":"Africa/Brazzaville",
    "iso:country":"CG",
    "wof:name":"Nsomo",
    "wof:placetype":"locality"
},
  "geometry": {"coordinates":[14.95722,-4.41972],"type":"Point"}
}