{
  "type": "Feature",
  "properties": {
    "gn:admin1_code":"10",
    "gn:asciiname":"Tembe",
    "gn:country_code":"CG",
    "gn:dem":365,
    "gn:feature_class":"P",
    "gn:feature_code":"PPL",
    "gn:name":"Tembe",
    "gn:population":0,
    "gn:timezone":"Africa/Brazzaville",
    "iso:country":"CG",
    "wof:name":"Tembe",
    "wof:placetype":"locality"
},
  "geometry": {"coordinates":[15.08,1.985],"type":"Point"}
}