{
  "type": "Feature",
  "properties": {
    "gn:admin1_code":"12",
    "gn:asciiname":"Kaganbanzi",
    "gn:country_code":"CG",
    "gn:dem":272,
    "gn:feature_class":"P",
    "gn:feature_code":"PPL",
    "gn:name":"Kaganbanzi",
    "gn:population":0,
    "gn:timezone":"Africa/Brazzaville",
    "iso:country":"CG",
    "wof:name":"Kaganbanzi",
    "wof:placetype":"locality"
},
  "geometry": {"coordinates":[15.91333,-3.89833],"type":"Point"}
}