{
  "type": "Feature",
  "properties": {
    "gn:admin1_code":"10",
    "gn:asciiname":"Indouma I",
    "gn:country_code":"CG",
    "gn:dem":417,
    "gn:feature_class":"P",
    "gn:feature_code":"PPL",
    "gn:name":"Indouma I",
    "gn:population":0,
    "gn:timezone":"Africa/Brazzaville",
    "iso:country":"CG",
    "wof:name":"Indouma I",
    "wof:placetype":"locality"
},
  "geometry": {"coordinates":[15.91667,1.43333],"type":"Point"}
}