{
  "type": "Feature",
  "properties": {
    "gn:admin1_code":"05",
    "gn:asciiname":"Antangi",
    "gn:cc2":"CG",
    "gn:country_code":"CG",
    "gn:dem":571,
    "gn:feature_class":"P",
    "gn:feature_code":"PPL",
    "gn:name":"Antangi",
    "gn:population":0,
    "gn:timezone":"Africa/Brazzaville",
    "iso:country":"CG",
    "name:und_x_variant":[
        "Antangui",
        "Antangi"
    ],
    "wof:name":"Antangi",
    "wof:placetype":"locality"
},
  "geometry": {"coordinates":[13.61278,-2.75417],"type":"Point"}
}