{
  "type": "Feature",
  "properties": {
    "gn:admin1_code":"10",
    "gn:asciiname":"Goulmenen",
    "gn:country_code":"CG",
    "gn:dem":531,
    "gn:feature_class":"P",
    "gn:feature_code":"PPL",
    "gn:name":"Goulm\u00e9n\u00e8n",
    "gn:population":0,
    "gn:timezone":"Africa/Brazzaville",
    "iso:country":"CG",
    "wof:name":"Goulmenen",
    "wof:placetype":"locality"
},
  "geometry": {"coordinates":[13.805,1.74833],"type":"Point"}
}