{
  "type": "Feature",
  "properties": {
    "gn:admin1_code":"01",
    "gn:asciiname":"Matchi-Koye",
    "gn:country_code":"CG",
    "gn:dem":162,
    "gn:feature_class":"P",
    "gn:feature_code":"PPL",
    "gn:name":"Matchi-Koy\u00e9",
    "gn:population":0,
    "gn:timezone":"Africa/Brazzaville",
    "iso:country":"CG",
    "wof:name":"Matchi-Koye",
    "wof:placetype":"locality"
},
  "geometry": {"coordinates":[13.06444,-4.12528],"type":"Point"}
}