{
  "type": "Feature",
  "properties": {
    "gn:admin1_code":"01",
    "gn:asciiname":"Kingondala-Tsanga",
    "gn:country_code":"CG",
    "gn:dem":788,
    "gn:feature_class":"P",
    "gn:feature_code":"PPL",
    "gn:name":"Kingondala-Tsanga",
    "gn:population":0,
    "gn:timezone":"Africa/Brazzaville",
    "iso:country":"CG",
    "wof:name":"Kingondala-Tsanga",
    "wof:placetype":"locality"
},
  "geometry": {"coordinates":[13.70639,-4.47583],"type":"Point"}
}