{
  "type": "Feature",
  "properties": {
    "gn:admin1_code":"06",
    "gn:asciiname":"Mambangue",
    "gn:country_code":"CG",
    "gn:dem":301,
    "gn:feature_class":"P",
    "gn:feature_code":"PPL",
    "gn:name":"Mambangu\u00e9",
    "gn:population":0,
    "gn:timezone":"Africa/Brazzaville",
    "iso:country":"CG",
    "wof:name":"Mambangue",
    "wof:placetype":"locality"
},
  "geometry": {"coordinates":[17.46611,-0.73667],"type":"Point"}
}