{
  "type": "Feature",
  "properties": {
    "gn:admin1_code":"11",
    "gn:asciiname":"Fia",
    "gn:cc2":"CG",
    "gn:country_code":"CG",
    "gn:dem":438,
    "gn:feature_class":"P",
    "gn:feature_code":"PPL",
    "gn:name":"Fia",
    "gn:population":0,
    "gn:timezone":"Africa/Brazzaville",
    "iso:country":"CG",
    "name:und_x_variant":[
        "M\u2019Fia",
        "Fia"
    ],
    "wof:name":"Fia",
    "wof:placetype":"locality"
},
  "geometry": {"coordinates":[14.8325,-3.43083],"type":"Point"}
}