{
  "type": "Feature",
  "properties": {
    "gn:admin1_code":"12",
    "gn:asciiname":"Boulankio",
    "gn:country_code":"CG",
    "gn:dem":744,
    "gn:feature_class":"P",
    "gn:feature_code":"PPL",
    "gn:name":"Boulankio",
    "gn:population":0,
    "gn:timezone":"Africa/Brazzaville",
    "iso:country":"CG",
    "wof:name":"Boulankio",
    "wof:placetype":"locality"
},
  "geometry": {"coordinates":[15.255,-3.81944],"type":"Point"}
}