{
  "type": "Feature",
  "properties": {
    "gn:admin1_code":"12",
    "gn:asciiname":"Kibouende II",
    "gn:country_code":"CG",
    "gn:dem":397,
    "gn:feature_class":"P",
    "gn:feature_code":"PPL",
    "gn:name":"Kibouend\u00e9 II",
    "gn:population":0,
    "gn:timezone":"Africa/Brazzaville",
    "iso:country":"CG",
    "wof:name":"Kibouende II",
    "wof:placetype":"locality"
},
  "geometry": {"coordinates":[15.25139,-4.18583],"type":"Point"}
}