{
  "type": "Feature",
  "properties": {
    "gn:admin1_code":"01",
    "gn:asciiname":"Kintouari",
    "gn:country_code":"CG",
    "gn:dem":433,
    "gn:feature_class":"P",
    "gn:feature_code":"PPL",
    "gn:name":"Kintouari",
    "gn:population":0,
    "gn:timezone":"Africa/Brazzaville",
    "iso:country":"CG",
    "wof:name":"Kintouari",
    "wof:placetype":"locality"
},
  "geometry": {"coordinates":[14.17278,-3.85917],"type":"Point"}
}