{
  "type": "Feature",
  "properties": {
    "gn:admin1_code":"11",
    "gn:asciiname":"Kaounga",
    "gn:country_code":"CG",
    "gn:dem":617,
    "gn:feature_class":"P",
    "gn:feature_code":"PPL",
    "gn:name":"Kaounga",
    "gn:population":0,
    "gn:timezone":"Africa/Brazzaville",
    "iso:country":"CG",
    "wof:name":"Kaounga",
    "wof:placetype":"locality"
},
  "geometry": {"coordinates":[14.60833,-3.05278],"type":"Point"}
}