{
  "type": "Feature",
  "properties": {
    "gn:admin1_code":"11",
    "gn:asciiname":"Makou",
    "gn:country_code":"CG",
    "gn:dem":551,
    "gn:feature_class":"P",
    "gn:feature_code":"PPL",
    "gn:name":"Makou",
    "gn:population":0,
    "gn:timezone":"Africa/Brazzaville",
    "iso:country":"CG",
    "wof:name":"Makou",
    "wof:placetype":"locality"
},
  "geometry": {"coordinates":[14.225,-3.13083],"type":"Point"}
}