{
  "type": "Feature",
  "properties": {
    "gn:admin1_code":"06",
    "gn:asciiname":"Gounda",
    "gn:cc2":"CG",
    "gn:country_code":"CG",
    "gn:dem":329,
    "gn:feature_class":"P",
    "gn:feature_code":"PPL",
    "gn:name":"Gounda",
    "gn:population":0,
    "gn:timezone":"Africa/Brazzaville",
    "iso:country":"CG",
    "name:und_x_variant":[
        "Ngounda",
        "Gounda"
    ],
    "wof:name":"Gounda",
    "wof:placetype":"locality"
},
  "geometry": {"coordinates":[17.88417,1.46139],"type":"Point"}
}