{
  "type": "Feature",
  "properties": {
    "gn:admin1_code":"11",
    "gn:asciiname":"Yana",
    "gn:country_code":"CG",
    "gn:dem":594,
    "gn:feature_class":"P",
    "gn:feature_code":"PPL",
    "gn:name":"Yana",
    "gn:population":0,
    "gn:timezone":"Africa/Brazzaville",
    "iso:country":"CG",
    "wof:name":"Yana",
    "wof:placetype":"locality"
},
  "geometry": {"coordinates":[14.64306,-4.77083],"type":"Point"}
}