{
  "type": "Feature",
  "properties": {
    "gn:admin1_code":"11",
    "gn:asciiname":"Yana",
    "gn:country_code":"CG",
    "gn:dem":594,
    "gn:feature_class":"P",
    "gn:feature_code":"PPL",
    "gn:name":"Yana",
    "gn:population":0,
    "gn:timezone":"Africa/Brazzaville",
    "iso:country":"CG",
    "name:aze_x_preferred":[
        "Yana"
    ],
    "name:bul_x_preferred":[
        "\u042f\u043d\u0430"
    ],
    "name:ceb_x_preferred":[
        "Yana"
    ],
    "name:chv_x_preferred":[
        "\u042f\u043d\u0430"
    ],
    "name:deu_x_preferred":[
        "Yana"
    ],
    "name:fra_x_preferred":[
        "Yana"
    ],
    "name:nld_x_preferred":[
        "Yana"
    ],
    "name:rus_x_preferred":[
        "\u042f\u043d\u0430"
    ],
    "name:sah_x_preferred":[
        "\u0414\u044c\u0430\u0430\u04a5\u044b"
    ],
    "name:spa_x_preferred":[
        "Yana"
    ],
    "name:swe_x_preferred":[
        "Yana"
    ],
    "name:tur_x_preferred":[
        "Yana"
    ],
    "name:ukr_x_preferred":[
        "\u042f\u043d\u0430"
    ],
    "wof:name":"Yana",
    "wof:placetype":"locality"
},
  "geometry": {"coordinates":[14.64306,-4.77083],"type":"Point"}
}