{
  "type": "Feature",
  "properties": {
    "gn:admin1_code":"01",
    "gn:asciiname":"Nitoumbi",
    "gn:country_code":"CG",
    "gn:dem":148,
    "gn:feature_class":"P",
    "gn:feature_code":"PPL",
    "gn:name":"Nitoumbi",
    "gn:population":0,
    "gn:timezone":"Africa/Brazzaville",
    "iso:country":"CG",
    "wof:name":"Nitoumbi",
    "wof:placetype":"locality"
},
  "geometry": {"coordinates":[12.74333,-3.80917],"type":"Point"}
}