{
  "type": "Feature",
  "properties": {
    "gn:admin1_code":"08",
    "gn:asciiname":"Mboube",
    "gn:cc2":"CG",
    "gn:country_code":"CG",
    "gn:dem":520,
    "gn:feature_class":"P",
    "gn:feature_code":"PPL",
    "gn:name":"Mboub\u00e9",
    "gn:population":0,
    "gn:timezone":"Africa/Brazzaville",
    "iso:country":"CG",
    "name:und_x_variant":[
        "Boub\u00e9",
        "M\u2019Boubou",
        "Mboub\u00e9"
    ],
    "wof:name":"Mboube",
    "wof:placetype":"locality"
},
  "geometry": {"coordinates":[15.23917,-1.73083],"type":"Point"}
}