{
  "type": "Feature",
  "properties": {
    "gn:admin1_code":"13",
    "gn:asciiname":"Djadaka",
    "gn:cc2":"CG",
    "gn:country_code":"CG",
    "gn:dem":337,
    "gn:feature_class":"P",
    "gn:feature_code":"PPL",
    "gn:name":"Djadaka",
    "gn:population":0,
    "gn:timezone":"Africa/Brazzaville",
    "iso:country":"CG",
    "name:und_x_variant":[
        "Djabaka",
        "Djadaka"
    ],
    "wof:name":"Djadaka",
    "wof:placetype":"locality"
},
  "geometry": {"coordinates":[15.64111,-0.74722],"type":"Point"}
}