{
  "type": "Feature",
  "properties": {
    "gn:admin1_code":"13",
    "gn:asciiname":"Mbali",
    "gn:country_code":"CG",
    "gn:dem":351,
    "gn:feature_class":"P",
    "gn:feature_code":"PPL",
    "gn:name":"Mbali",
    "gn:population":0,
    "gn:timezone":"Africa/Brazzaville",
    "iso:country":"CG",
    "name:ceb_x_preferred":[
        "Mbali"
    ],
    "name:deu_x_preferred":[
        "Mbali"
    ],
    "name:swe_x_preferred":[
        "Mbali"
    ],
    "wof:name":"Mbali",
    "wof:placetype":"locality"
},
  "geometry": {"coordinates":[15.78139,-0.35944],"type":"Point"}
}