{
  "type": "Feature",
  "properties": {
    "gn:admin1_code":"11",
    "gn:asciiname":"Kinimbi",
    "gn:country_code":"CG",
    "gn:dem":443,
    "gn:feature_class":"P",
    "gn:feature_code":"PPL",
    "gn:name":"Kinimbi",
    "gn:population":0,
    "gn:timezone":"Africa/Brazzaville",
    "iso:country":"CG",
    "wof:name":"Kinimbi",
    "wof:placetype":"locality"
},
  "geometry": {"coordinates":[14.755,-4.50389],"type":"Point"}
}