{
  "type": "Feature",
  "properties": {
    "gn:admin1_code":"05",
    "gn:asciiname":"Tsiemayo",
    "gn:country_code":"CG",
    "gn:dem":463,
    "gn:feature_class":"P",
    "gn:feature_code":"PPL",
    "gn:name":"Tsi\u00e9mayo",
    "gn:population":0,
    "gn:timezone":"Africa/Brazzaville",
    "iso:country":"CG",
    "wof:name":"Tsiemayo",
    "wof:placetype":"locality"
},
  "geometry": {"coordinates":[13.35444,-3.52528],"type":"Point"}
}