{
  "type": "Feature",
  "properties": {
    "gn:admin1_code":"05",
    "gn:asciiname":"Tsitsa",
    "gn:country_code":"CG",
    "gn:dem":330,
    "gn:feature_class":"P",
    "gn:feature_code":"PPL",
    "gn:name":"Tsitsa",
    "gn:population":0,
    "gn:timezone":"Africa/Brazzaville",
    "iso:country":"CG",
    "wof:name":"Tsitsa",
    "wof:placetype":"locality"
},
  "geometry": {"coordinates":[13.31583,-3.85333],"type":"Point"}
}