{
  "type": "Feature",
  "properties": {
    "gn:admin1_code":"08",
    "gn:asciiname":"Okamamoue",
    "gn:country_code":"CG",
    "gn:dem":393,
    "gn:feature_class":"P",
    "gn:feature_code":"PPL",
    "gn:name":"Okamamou\u00e9",
    "gn:population":0,
    "gn:timezone":"Africa/Brazzaville",
    "iso:country":"CG",
    "wof:name":"Okamamoue",
    "wof:placetype":"locality"
},
  "geometry": {"coordinates":[15.805,-1.46778],"type":"Point"}
}