{
  "type": "Feature",
  "properties": {
    "gn:admin1_code":"11",
    "gn:asciiname":"Meleze",
    "gn:country_code":"CG",
    "gn:dem":272,
    "gn:feature_class":"P",
    "gn:feature_code":"PPL",
    "gn:name":"M\u00e9l\u00e9z\u00e9",
    "gn:population":0,
    "gn:timezone":"Africa/Brazzaville",
    "iso:country":"CG",
    "wof:name":"Meleze",
    "wof:placetype":"locality"
},
  "geometry": {"coordinates":[16.08333,-3.56667],"type":"Point"}
}