{
  "type": "Feature",
  "properties": {
    "gn:admin1_code":"13",
    "gn:asciiname":"Otogo Ollibi",
    "gn:country_code":"CG",
    "gn:dem":407,
    "gn:feature_class":"P",
    "gn:feature_code":"PPL",
    "gn:name":"Otogo Ollibi",
    "gn:population":0,
    "gn:timezone":"Africa/Brazzaville",
    "iso:country":"CG",
    "wof:name":"Otogo Ollibi",
    "wof:placetype":"locality"
},
  "geometry": {"coordinates":[15.18333,-0.63333],"type":"Point"}
}