{
  "type": "Feature",
  "properties": {
    "gn:admin1_code":"07",
    "gn:asciiname":"Moudounga",
    "gn:country_code":"CG",
    "gn:dem":512,
    "gn:feature_class":"P",
    "gn:feature_code":"PPL",
    "gn:name":"Moudounga",
    "gn:population":0,
    "gn:timezone":"Africa/Brazzaville",
    "iso:country":"CG",
    "wof:name":"Moudounga",
    "wof:placetype":"locality"
},
  "geometry": {"coordinates":[12.305,-2.50028],"type":"Point"}
}