{
  "type": "Feature",
  "properties": {
    "gn:admin1_code":"08",
    "gn:asciiname":"Oban",
    "gn:country_code":"CG",
    "gn:dem":648,
    "gn:feature_class":"P",
    "gn:feature_code":"PPL",
    "gn:name":"Oban",
    "gn:population":0,
    "gn:timezone":"Africa/Brazzaville",
    "iso:country":"CG",
    "wof:name":"Oban",
    "wof:placetype":"locality"
},
  "geometry": {"coordinates":[15.65806,-2.59111],"type":"Point"}
}