{
  "type": "Feature",
  "properties": {
    "gn:admin1_code":"11",
    "gn:asciiname":"Mayenani",
    "gn:country_code":"CG",
    "gn:dem":453,
    "gn:feature_class":"P",
    "gn:feature_code":"PPL",
    "gn:name":"May\u00e9nani",
    "gn:population":0,
    "gn:timezone":"Africa/Brazzaville",
    "iso:country":"CG",
    "wof:name":"Mayenani",
    "wof:placetype":"locality"
},
  "geometry": {"coordinates":[14.33389,-3.60611],"type":"Point"}
}