{
  "type": "Feature",
  "properties": {
    "gn:admin1_code":"01",
    "gn:asciiname":"Kimbaoka",
    "gn:country_code":"CG",
    "gn:dem":342,
    "gn:feature_class":"P",
    "gn:feature_code":"PPL",
    "gn:name":"Kimbaoka",
    "gn:population":0,
    "gn:timezone":"Africa/Brazzaville",
    "iso:country":"CG",
    "wof:name":"Kimbaoka",
    "wof:placetype":"locality"
},
  "geometry": {"coordinates":[13.60611,-4.43833],"type":"Point"}
}