{
  "type": "Feature",
  "properties": {
    "gn:admin1_code":"10",
    "gn:asciiname":"Mokeko",
    "gn:cc2":"CG",
    "gn:country_code":"CG",
    "gn:dem":435,
    "gn:feature_class":"P",
    "gn:feature_code":"PPL",
    "gn:name":"Mok\u00e9ko",
    "gn:population":0,
    "gn:timezone":"Africa/Brazzaville",
    "iso:country":"CG",
    "name:und_x_variant":[
        "Mok\u00e9lo",
        "Mok\u00e9ko"
    ],
    "wof:name":"Mokeko",
    "wof:placetype":"locality"
},
  "geometry": {"coordinates":[15.94111,1.56333],"type":"Point"}
}