{
  "type": "Feature",
  "properties": {
    "gn:admin1_code":"08",
    "gn:asciiname":"Goulanpika",
    "gn:cc2":"CG",
    "gn:country_code":"CG",
    "gn:dem":851,
    "gn:feature_class":"P",
    "gn:feature_code":"PPL",
    "gn:name":"Goulanpika",
    "gn:population":0,
    "gn:timezone":"Africa/Brazzaville",
    "iso:country":"CG",
    "name:und_x_variant":[
        "Goutanpika",
        "Goulanpika"
    ],
    "wof:name":"Goulanpika",
    "wof:placetype":"locality"
},
  "geometry": {"coordinates":[14.41278,-2.45111],"type":"Point"}
}