{
  "type": "Feature",
  "properties": {
    "gn:admin1_code":"11",
    "gn:asciiname":"Lemba",
    "gn:country_code":"CG",
    "gn:dem":296,
    "gn:feature_class":"P",
    "gn:feature_code":"PPL",
    "gn:name":"Lemba",
    "gn:population":0,
    "gn:timezone":"Africa/Brazzaville",
    "iso:country":"CG",
    "wof:name":"Lemba",
    "wof:placetype":"locality"
},
  "geometry": {"coordinates":[14.45833,-4.84],"type":"Point"}
}