{
  "type": "Feature",
  "properties": {
    "gn:admin1_code":"04",
    "gn:asciiname":"Lenzi",
    "gn:country_code":"CG",
    "gn:dem":98,
    "gn:feature_class":"P",
    "gn:feature_code":"PPL",
    "gn:name":"Lenzi",
    "gn:population":0,
    "gn:timezone":"Africa/Brazzaville",
    "iso:country":"CG",
    "name:ceb_x_preferred":[
        "Lenz\u012b"
    ],
    "name:fas_x_preferred":[
        "\u0644\u0646\u0632\u06cc"
    ],
    "name:msa_x_preferred":[
        "Lenzi"
    ],
    "name:swe_x_preferred":[
        "Lenz\u012b"
    ],
    "name:ukr_x_preferred":[
        "\u041b\u0435\u043d\u0437\u0456"
    ],
    "wof:name":"Lenzi",
    "wof:placetype":"locality"
},
  "geometry": {"coordinates":[12.11639,-4.62917],"type":"Point"}
}