{
  "type": "Feature",
  "properties": {
    "gn:admin1_code":"05",
    "gn:asciiname":"Kiaba",
    "gn:country_code":"CG",
    "gn:dem":456,
    "gn:feature_class":"P",
    "gn:feature_code":"PPL",
    "gn:name":"Kiaba",
    "gn:population":0,
    "gn:timezone":"Africa/Brazzaville",
    "iso:country":"CG",
    "wof:name":"Kiaba",
    "wof:placetype":"locality"
},
  "geometry": {"coordinates":[13.13222,-3.23],"type":"Point"}
}