{
  "type": "Feature",
  "properties": {
    "gn:admin1_code":"01",
    "gn:asciiname":"Kimboukou",
    "gn:country_code":"CG",
    "gn:dem":536,
    "gn:feature_class":"P",
    "gn:feature_code":"PPL",
    "gn:name":"Kimboukou",
    "gn:population":0,
    "gn:timezone":"Africa/Brazzaville",
    "iso:country":"CG",
    "wof:name":"Kimboukou",
    "wof:placetype":"locality"
},
  "geometry": {"coordinates":[13.72278,-4.02333],"type":"Point"}
}