{
  "type": "Feature",
  "properties": {
    "gn:admin1_code":"07",
    "gn:asciiname":"Kifimba",
    "gn:country_code":"CG",
    "gn:dem":138,
    "gn:feature_class":"P",
    "gn:feature_code":"PPL",
    "gn:name":"Kifimba",
    "gn:population":0,
    "gn:timezone":"Africa/Brazzaville",
    "iso:country":"CG",
    "wof:name":"Kifimba",
    "wof:placetype":"locality"
},
  "geometry": {"coordinates":[12.52167,-3.7225],"type":"Point"}
}