{
  "type": "Feature",
  "properties": {
    "gn:admin1_code":"11",
    "gn:asciiname":"Kimpanza",
    "gn:country_code":"CG",
    "gn:dem":548,
    "gn:feature_class":"P",
    "gn:feature_code":"PPL",
    "gn:name":"Kimpanza",
    "gn:population":0,
    "gn:timezone":"Africa/Brazzaville",
    "iso:country":"CG",
    "wof:name":"Kimpanza",
    "wof:placetype":"locality"
},
  "geometry": {"coordinates":[14.66861,-4.62694],"type":"Point"}
}