{
  "type": "Feature",
  "properties": {
    "gn:admin1_code":"12",
    "gn:asciiname":"Manyanga",
    "gn:country_code":"CG",
    "gn:dem":281,
    "gn:feature_class":"P",
    "gn:feature_code":"PPL",
    "gn:name":"Many\u00e1nga",
    "gn:population":0,
    "gn:timezone":"Africa/Brazzaville",
    "iso:country":"CG",
    "name:und_x_variant":[
        "Mouyanga",
        "Manianga",
        "Many\u00e1nga"
    ],
    "wof:name":"Manyanga",
    "wof:placetype":"locality"
},
  "geometry": {"coordinates":[15.3125,-4.16417],"type":"Point"}
}