{
  "type": "Feature",
  "properties": {
    "gn:admin1_code":"13",
    "gn:asciiname":"Tchambitcho",
    "gn:country_code":"CG",
    "gn:dem":314,
    "gn:feature_class":"P",
    "gn:feature_code":"PPL",
    "gn:name":"Tchambitcho",
    "gn:population":0,
    "gn:timezone":"Africa/Brazzaville",
    "iso:country":"CG",
    "wof:name":"Tchambitcho",
    "wof:placetype":"locality"
},
  "geometry": {"coordinates":[16.00722,-1.17694],"type":"Point"}
}