{
  "type": "Feature",
  "properties": {
    "gn:admin1_code":"13",
    "gn:asciiname":"Mboko",
    "gn:country_code":"CG",
    "gn:dem":339,
    "gn:feature_class":"P",
    "gn:feature_code":"PPL",
    "gn:name":"Mboko",
    "gn:population":0,
    "gn:timezone":"Africa/Brazzaville",
    "iso:country":"CG",
    "name:ceb_x_preferred":[
        "Mboko"
    ],
    "name:swe_x_preferred":[
        "Mboko"
    ],
    "wof:name":"Mboko",
    "wof:placetype":"locality"
},
  "geometry": {"coordinates":[15.6975,0.055],"type":"Point"}
}