{
  "type": "Feature",
  "properties": {
    "gn:admin1_code":"07",
    "gn:asciiname":"Malou",
    "gn:country_code":"CG",
    "gn:dem":464,
    "gn:feature_class":"P",
    "gn:feature_code":"PPL",
    "gn:name":"Malou",
    "gn:population":0,
    "gn:timezone":"Africa/Brazzaville",
    "iso:country":"CG",
    "wof:name":"Malou",
    "wof:placetype":"locality"
},
  "geometry": {"coordinates":[12.38056,-2.77],"type":"Point"}
}