{
  "type": "Feature",
  "properties": {
    "gn:admin1_code":"08",
    "gn:asciiname":"Kongalikou",
    "gn:country_code":"CG",
    "gn:dem":329,
    "gn:feature_class":"P",
    "gn:feature_code":"PPL",
    "gn:name":"Kongalikou",
    "gn:population":0,
    "gn:timezone":"Africa/Brazzaville",
    "iso:country":"CG",
    "wof:name":"Kongalikou",
    "wof:placetype":"locality"
},
  "geometry": {"coordinates":[15.7425,-1.07639],"type":"Point"}
}