{
  "type": "Feature",
  "properties": {
    "gn:admin1_code":"06",
    "gn:asciiname":"Boubangui",
    "gn:cc2":"CG",
    "gn:country_code":"CG",
    "gn:dem":302,
    "gn:feature_class":"P",
    "gn:feature_code":"PPL",
    "gn:name":"Boubangui",
    "gn:population":0,
    "gn:timezone":"Africa/Brazzaville",
    "iso:country":"CG",
    "name:und_x_variant":[
        "Bobangui",
        "Boubangui"
    ],
    "wof:name":"Boubangui",
    "wof:placetype":"locality"
},
  "geometry": {"coordinates":[17.70028,-0.0925],"type":"Point"}
}