{
  "type": "Feature",
  "properties": {
    "gn:admin1_code":"08",
    "gn:asciiname":"Ongouli",
    "gn:country_code":"CG",
    "gn:dem":329,
    "gn:feature_class":"P",
    "gn:feature_code":"PPL",
    "gn:name":"Ongouli",
    "gn:population":0,
    "gn:timezone":"Africa/Brazzaville",
    "iso:country":"CG",
    "wof:name":"Ongouli",
    "wof:placetype":"locality"
},
  "geometry": {"coordinates":[15.89639,-1.20944],"type":"Point"}
}