{
  "type": "Feature",
  "properties": {
    "gn:admin1_code":"06",
    "gn:asciiname":"Bongandzi",
    "gn:cc2":"CG",
    "gn:country_code":"CG",
    "gn:dem":320,
    "gn:feature_class":"P",
    "gn:feature_code":"PPL",
    "gn:name":"Bongandzi",
    "gn:population":0,
    "gn:timezone":"Africa/Brazzaville",
    "iso:country":"CG",
    "name:und_x_variant":[
        "Boganda",
        "Bongandzi"
    ],
    "wof:name":"Bongandzi",
    "wof:placetype":"locality"
},
  "geometry": {"coordinates":[17.64027999999999,1.46806],"type":"Point"}
}