{
  "type": "Feature",
  "properties": {
    "gn:admin1_code":"11",
    "gn:asciiname":"Kimpanzou",
    "gn:cc2":"CG",
    "gn:country_code":"CG",
    "gn:dem":377,
    "gn:feature_class":"P",
    "gn:feature_code":"PPL",
    "gn:name":"Kimpanzou",
    "gn:population":0,
    "gn:timezone":"Africa/Brazzaville",
    "iso:country":"CG",
    "name:und_x_variant":[
        "Quimpanza",
        "Kimpanzon",
        "Kimpanzou"
    ],
    "wof:name":"Kimpanzou",
    "wof:placetype":"locality"
},
  "geometry": {"coordinates":[14.95111,-4.57],"type":"Point"}
}