{
  "type": "Feature",
  "properties": {
    "gn:admin1_code":"07",
    "gn:asciiname":"Makanga",
    "gn:country_code":"CG",
    "gn:dem":189,
    "gn:feature_class":"P",
    "gn:feature_code":"PPL",
    "gn:name":"Makanga",
    "gn:population":0,
    "gn:timezone":"Africa/Brazzaville",
    "iso:country":"CG",
    "wof:name":"Makanga",
    "wof:placetype":"locality"
},
  "geometry": {"coordinates":[11.69639,-2.68778],"type":"Point"}
}