{
  "type": "Feature",
  "properties": {
    "gn:admin1_code":"11",
    "gn:asciiname":"Vinnza",
    "gn:cc2":"CG",
    "gn:country_code":"CG",
    "gn:dem":441,
    "gn:feature_class":"P",
    "gn:feature_code":"PPL",
    "gn:name":"Vinnza",
    "gn:population":0,
    "gn:timezone":"Africa/Brazzaville",
    "iso:country":"CG",
    "name:und_x_variant":[
        "Vinza",
        "Vinnza"
    ],
    "wof:name":"Vinnza",
    "wof:placetype":"locality"
},
  "geometry": {"coordinates":[14.76528,-4.34056],"type":"Point"}
}