{
  "type": "Feature",
  "properties": {
    "gn:admin1_code":"13",
    "gn:asciiname":"Obanga",
    "gn:country_code":"CG",
    "gn:dem":325,
    "gn:feature_class":"P",
    "gn:feature_code":"PPL",
    "gn:name":"Obanga",
    "gn:population":0,
    "gn:timezone":"Africa/Brazzaville",
    "iso:country":"CG",
    "wof:name":"Obanga",
    "wof:placetype":"locality"
},
  "geometry": {"coordinates":[15.92528,-0.42639],"type":"Point"}
}