{
  "type": "Feature",
  "properties": {
    "gn:admin1_code":"07",
    "gn:asciiname":"Makaga",
    "gn:country_code":"CG",
    "gn:dem":428,
    "gn:feature_class":"P",
    "gn:feature_code":"PPL",
    "gn:name":"Makaga",
    "gn:population":0,
    "gn:timezone":"Africa/Brazzaville",
    "iso:country":"CG",
    "wof:name":"Makaga",
    "wof:placetype":"locality"
},
  "geometry": {"coordinates":[12.88861,-3.13722],"type":"Point"}
}