{
  "type": "Feature",
  "properties": {
    "gn:admin1_code":"11",
    "gn:asciiname":"Loubitoukou",
    "gn:country_code":"CG",
    "gn:dem":465,
    "gn:feature_class":"P",
    "gn:feature_code":"PPL",
    "gn:name":"Loubitoukou",
    "gn:population":0,
    "gn:timezone":"Africa/Brazzaville",
    "iso:country":"CG",
    "wof:name":"Loubitoukou",
    "wof:placetype":"locality"
},
  "geometry": {"coordinates":[14.82222,-4.58583],"type":"Point"}
}