{
  "type": "Feature",
  "properties": {
    "gn:admin1_code":"13",
    "gn:asciiname":"Dzaka",
    "gn:cc2":"CG",
    "gn:country_code":"CG",
    "gn:dem":363,
    "gn:feature_class":"P",
    "gn:feature_code":"PPL",
    "gn:name":"Dzaka",
    "gn:population":0,
    "gn:timezone":"Africa/Brazzaville",
    "iso:country":"CG",
    "name:und_x_variant":[
        "Ndzakou",
        "Dzaka"
    ],
    "wof:name":"Dzaka",
    "wof:placetype":"locality"
},
  "geometry": {"coordinates":[15.74,-0.18806],"type":"Point"}
}