{
  "type": "Feature",
  "properties": {
    "gn:admin1_code":"01",
    "gn:asciiname":"Moukambou",
    "gn:country_code":"CG",
    "gn:dem":688,
    "gn:feature_class":"P",
    "gn:feature_code":"PPL",
    "gn:name":"Moukambou",
    "gn:population":0,
    "gn:timezone":"Africa/Brazzaville",
    "iso:country":"CG",
    "wof:name":"Moukambou",
    "wof:placetype":"locality"
},
  "geometry": {"coordinates":[13.77694,-4.32639],"type":"Point"}
}