{
  "type": "Feature",
  "properties": {
    "gn:admin1_code":"11",
    "gn:asciiname":"Guenzie",
    "gn:cc2":"CG",
    "gn:country_code":"CG",
    "gn:dem":412,
    "gn:feature_class":"P",
    "gn:feature_code":"PPL",
    "gn:name":"Guenzi\u00e9",
    "gn:population":0,
    "gn:timezone":"Africa/Brazzaville",
    "iso:country":"CG",
    "name:und_x_variant":[
        "Genzi\u00e9",
        "Guenzi\u00e9"
    ],
    "wof:name":"Guenzie",
    "wof:placetype":"locality"
},
  "geometry": {"coordinates":[14.795,-4.42778],"type":"Point"}
}