{
  "type": "Feature",
  "properties": {
    "gn:admin1_code":"05",
    "gn:asciiname":"Zanaga Bakota",
    "gn:country_code":"CG",
    "gn:dem":477,
    "gn:feature_class":"P",
    "gn:feature_code":"PPL",
    "gn:name":"Zanaga Bakota",
    "gn:population":0,
    "gn:timezone":"Africa/Brazzaville",
    "iso:country":"CG",
    "wof:name":"Zanaga Bakota",
    "wof:placetype":"locality"
},
  "geometry": {"coordinates":[13.55667,-3.07],"type":"Point"}
}