{
  "type": "Feature",
  "properties": {
    "gn:admin1_code":"08",
    "gn:asciiname":"Eko",
    "gn:country_code":"CG",
    "gn:dem":421,
    "gn:feature_class":"P",
    "gn:feature_code":"PPL",
    "gn:name":"Eko",
    "gn:population":0,
    "gn:timezone":"Africa/Brazzaville",
    "iso:country":"CG",
    "wof:name":"Eko",
    "wof:placetype":"locality"
},
  "geometry": {"coordinates":[15.2775,-1.69889],"type":"Point"}
}