{
  "type": "Feature",
  "properties": {
    "gn:admin1_code":"04",
    "gn:asciiname":"Bondi",
    "gn:country_code":"CG",
    "gn:dem":97,
    "gn:feature_class":"P",
    "gn:feature_code":"PPL",
    "gn:name":"Bondi",
    "gn:population":0,
    "gn:timezone":"Africa/Brazzaville",
    "iso:country":"CG",
    "name:ceb_x_preferred":[
        "Bondi"
    ],
    "name:ces_x_preferred":[
        "Bondi"
    ],
    "name:deu_x_preferred":[
        "Bondi"
    ],
    "name:fin_x_preferred":[
        "Bondi"
    ],
    "name:fra_x_preferred":[
        "Bondi"
    ],
    "name:heb_x_preferred":[
        "\u05d1\u05d5\u05e0\u05d3\u05d9"
    ],
    "name:ita_x_preferred":[
        "Bondi"
    ],
    "name:mlg_x_preferred":[
        "Bondi"
    ],
    "name:swe_x_preferred":[
        "Bondi"
    ],
    "wof:name":"Bondi",
    "wof:placetype":"locality"
},
  "geometry": {"coordinates":[12.07722,-4.53028],"type":"Point"}
}