{
  "type": "Feature",
  "properties": {
    "gn:admin1_code":"07",
    "gn:asciiname":"Masangou II",
    "gn:country_code":"CG",
    "gn:dem":545,
    "gn:feature_class":"P",
    "gn:feature_code":"PPL",
    "gn:name":"Masangou II",
    "gn:population":0,
    "gn:timezone":"Africa/Brazzaville",
    "iso:country":"CG",
    "wof:name":"Masangou II",
    "wof:placetype":"locality"
},
  "geometry": {"coordinates":[12.66778,-2.81722],"type":"Point"}
}