{
  "type": "Feature",
  "properties": {
    "gn:admin1_code":"08",
    "gn:asciiname":"Okassa",
    "gn:cc2":"CG",
    "gn:country_code":"CG",
    "gn:dem":325,
    "gn:feature_class":"P",
    "gn:feature_code":"PPL",
    "gn:name":"Okassa",
    "gn:population":0,
    "gn:timezone":"Africa/Brazzaville",
    "iso:country":"CG",
    "name:und_x_variant":[
        "Okasa",
        "Okassa"
    ],
    "wof:name":"Okassa",
    "wof:placetype":"locality"
},
  "geometry": {"coordinates":[16.07222,-1.45889],"type":"Point"}
}