{
  "type": "Feature",
  "properties": {
    "gn:admin1_code":"07",
    "gn:asciiname":"Mouyamba",
    "gn:country_code":"CG",
    "gn:dem":226,
    "gn:feature_class":"P",
    "gn:feature_code":"PPL",
    "gn:name":"Mouyamba",
    "gn:population":0,
    "gn:timezone":"Africa/Brazzaville",
    "iso:country":"CG",
    "wof:name":"Mouyamba",
    "wof:placetype":"locality"
},
  "geometry": {"coordinates":[11.93417,-2.84639],"type":"Point"}
}