{
  "type": "Feature",
  "properties": {
    "gn:admin1_code":"11",
    "gn:asciiname":"Mpeoula",
    "gn:country_code":"CG",
    "gn:dem":459,
    "gn:feature_class":"P",
    "gn:feature_code":"PPL",
    "gn:name":"Mp\u00e9oula",
    "gn:population":0,
    "gn:timezone":"Africa/Brazzaville",
    "iso:country":"CG",
    "wof:name":"Mpeoula",
    "wof:placetype":"locality"
},
  "geometry": {"coordinates":[14.6825,-4.22306],"type":"Point"}
}