{
  "type": "Feature",
  "properties": {
    "gn:admin1_code":"11",
    "gn:asciiname":"Louenga",
    "gn:country_code":"CG",
    "gn:dem":364,
    "gn:feature_class":"P",
    "gn:feature_code":"PPL",
    "gn:name":"Louenga",
    "gn:population":0,
    "gn:timezone":"Africa/Brazzaville",
    "iso:country":"CG",
    "wof:name":"Louenga",
    "wof:placetype":"locality"
},
  "geometry": {"coordinates":[14.54583,-4.75611],"type":"Point"}
}