{
  "type": "Feature",
  "properties": {
    "gn:admin1_code":"13",
    "gn:asciiname":"Andjala",
    "gn:country_code":"CG",
    "gn:dem":332,
    "gn:feature_class":"P",
    "gn:feature_code":"PPL",
    "gn:name":"Andjala",
    "gn:population":0,
    "gn:timezone":"Africa/Brazzaville",
    "iso:country":"CG",
    "wof:name":"Andjala",
    "wof:placetype":"locality"
},
  "geometry": {"coordinates":[15.59833,-0.03889],"type":"Point"}
}