{
  "type": "Feature",
  "properties": {
    "gn:admin1_code":"13",
    "gn:asciiname":"Oliemi",
    "gn:country_code":"CG",
    "gn:dem":377,
    "gn:feature_class":"P",
    "gn:feature_code":"PPL",
    "gn:name":"Oli\u00e9mi",
    "gn:population":0,
    "gn:timezone":"Africa/Brazzaville",
    "iso:country":"CG",
    "name:und_x_variant":[
        "Oli\u00e9me",
        "Oli\u00e9mi"
    ],
    "wof:name":"Oliemi",
    "wof:placetype":"locality"
},
  "geometry": {"coordinates":[15.07167,-1.43139],"type":"Point"}
}