{
  "type": "Feature",
  "properties": {
    "gn:admin1_code":"11",
    "gn:asciiname":"Nkenzo",
    "gn:country_code":"CG",
    "gn:dem":487,
    "gn:feature_class":"P",
    "gn:feature_code":"PPL",
    "gn:name":"Nkenzo",
    "gn:population":0,
    "gn:timezone":"Africa/Brazzaville",
    "iso:country":"CG",
    "wof:name":"Nkenzo",
    "wof:placetype":"locality"
},
  "geometry": {"coordinates":[14.54583,-3.64583],"type":"Point"}
}