{
  "type": "Feature",
  "properties": {
    "gn:admin1_code":"04",
    "gn:asciiname":"Kivoula",
    "gn:cc2":"CG",
    "gn:country_code":"CG",
    "gn:dem":72,
    "gn:feature_class":"P",
    "gn:feature_code":"PPL",
    "gn:name":"Kivoula",
    "gn:population":0,
    "gn:timezone":"Africa/Brazzaville",
    "iso:country":"CG",
    "name:und_x_variant":[
        "Tchivoula",
        "Kivoula"
    ],
    "wof:name":"Kivoula",
    "wof:placetype":"locality"
},
  "geometry": {"coordinates":[12.14417,-4.65472],"type":"Point"}
}