{
  "type": "Feature",
  "properties": {
    "gn:admin1_code":"13",
    "gn:asciiname":"Okoyo",
    "gn:cc2":"CG",
    "gn:country_code":"CG",
    "gn:dem":383,
    "gn:feature_class":"P",
    "gn:feature_code":"PPL",
    "gn:name":"Okoyo",
    "gn:population":0,
    "gn:timezone":"Africa/Brazzaville",
    "iso:country":"CG",
    "name:und_x_variant":[
        "Koyo",
        "Okoyo"
    ],
    "wof:name":"Okoyo",
    "wof:placetype":"locality"
},
  "geometry": {"coordinates":[15.07616,-1.46008],"type":"Point"}
}