{
  "type": "Feature",
  "properties": {
    "gn:admin1_code":"11",
    "gn:asciiname":"Kingouala",
    "gn:cc2":"CG",
    "gn:country_code":"CG",
    "gn:dem":326,
    "gn:feature_class":"P",
    "gn:feature_code":"PPL",
    "gn:name":"Kingouala",
    "gn:population":0,
    "gn:timezone":"Africa/Brazzaville",
    "iso:country":"CG",
    "name:und_x_variant":[
        "Kinngouala",
        "Kingouala"
    ],
    "wof:name":"Kingouala",
    "wof:placetype":"locality"
},
  "geometry": {"coordinates":[14.35056,-4.11861],"type":"Point"}
}