{
  "type": "Feature",
  "properties": {
    "gn:admin1_code":"04",
    "gn:asciiname":"Tandou Bivenze",
    "gn:country_code":"CG",
    "gn:dem":36,
    "gn:feature_class":"P",
    "gn:feature_code":"PPL",
    "gn:name":"Tandou Bivenz\u00e9",
    "gn:population":0,
    "gn:timezone":"Africa/Brazzaville",
    "iso:country":"CG",
    "wof:name":"Tandou Bivenze",
    "wof:placetype":"locality"
},
  "geometry": {"coordinates":[12.06917,-4.54917],"type":"Point"}
}