{
  "type": "Feature",
  "properties": {
    "gn:admin1_code":"11",
    "gn:asciiname":"Movimba",
    "gn:country_code":"CG",
    "gn:dem":562,
    "gn:feature_class":"P",
    "gn:feature_code":"PPL",
    "gn:name":"Movimba",
    "gn:population":0,
    "gn:timezone":"Africa/Brazzaville",
    "iso:country":"CG",
    "wof:name":"Movimba",
    "wof:placetype":"locality"
},
  "geometry": {"coordinates":[14.21028,-3.16278],"type":"Point"}
}