{
  "type": "Feature",
  "properties": {
    "gn:admin1_code":"06",
    "gn:asciiname":"Bolomo",
    "gn:country_code":"CG",
    "gn:dem":327,
    "gn:feature_class":"P",
    "gn:feature_code":"PPL",
    "gn:name":"Bolomo",
    "gn:population":0,
    "gn:timezone":"Africa/Brazzaville",
    "iso:country":"CG",
    "wof:name":"Bolomo",
    "wof:placetype":"locality"
},
  "geometry": {"coordinates":[18.14889,2.44667],"type":"Point"}
}