{
  "type": "Feature",
  "properties": {
    "gn:admin1_code":"07",
    "gn:asciiname":"Moukourounzenne",
    "gn:country_code":"CG",
    "gn:dem":393,
    "gn:feature_class":"P",
    "gn:feature_code":"PPL",
    "gn:name":"Moukourounzenn\u00e9",
    "gn:population":0,
    "gn:timezone":"Africa/Brazzaville",
    "iso:country":"CG",
    "wof:name":"Moukourounzenne",
    "wof:placetype":"locality"
},
  "geometry": {"coordinates":[11.93194,-2.46778],"type":"Point"}
}