{
  "type": "Feature",
  "properties": {
    "gn:admin1_code":"07",
    "gn:asciiname":"Moulandou Maambou",
    "gn:country_code":"CG",
    "gn:dem":135,
    "gn:feature_class":"P",
    "gn:feature_code":"PPL",
    "gn:name":"Moulandou Maambou",
    "gn:population":0,
    "gn:timezone":"Africa/Brazzaville",
    "iso:country":"CG",
    "wof:name":"Moulandou Maambou",
    "wof:placetype":"locality"
},
  "geometry": {"coordinates":[12.30528,-3.47944],"type":"Point"}
}