{
  "type": "Feature",
  "properties": {
    "gn:admin1_code":"05",
    "gn:asciiname":"Loukana",
    "gn:country_code":"CG",
    "gn:dem":524,
    "gn:feature_class":"P",
    "gn:feature_code":"PPL",
    "gn:name":"Loukana",
    "gn:population":0,
    "gn:timezone":"Africa/Brazzaville",
    "iso:country":"CG",
    "wof:name":"Loukana",
    "wof:placetype":"locality"
},
  "geometry": {"coordinates":[13.32944,-3.70972],"type":"Point"}
}