{
  "type": "Feature",
  "properties": {
    "gn:admin1_code":"11",
    "gn:asciiname":"Bandzibikie",
    "gn:country_code":"CG",
    "gn:dem":566,
    "gn:feature_class":"P",
    "gn:feature_code":"PPL",
    "gn:name":"Bandzibiki\u00e9",
    "gn:population":0,
    "gn:timezone":"Africa/Brazzaville",
    "iso:country":"CG",
    "wof:name":"Bandzibikie",
    "wof:placetype":"locality"
},
  "geometry": {"coordinates":[14.12222,-3.31361],"type":"Point"}
}