{
  "type": "Feature",
  "properties": {
    "gn:admin1_code":"10",
    "gn:asciiname":"Ngobe",
    "gn:country_code":"CG",
    "gn:dem":349,
    "gn:feature_class":"P",
    "gn:feature_code":"PPL",
    "gn:name":"Ngob\u00e9",
    "gn:population":0,
    "gn:timezone":"Africa/Brazzaville",
    "iso:country":"CG",
    "wof:name":"Ngobe",
    "wof:placetype":"locality"
},
  "geometry": {"coordinates":[16.08778,1.90278],"type":"Point"}
}