{
  "type": "Feature",
  "properties": {
    "gn:admin1_code":"05",
    "gn:asciiname":"Nzouala",
    "gn:country_code":"CG",
    "gn:dem":699,
    "gn:feature_class":"P",
    "gn:feature_code":"PPL",
    "gn:name":"Nzouala",
    "gn:population":0,
    "gn:timezone":"Africa/Brazzaville",
    "iso:country":"CG",
    "wof:name":"Nzouala",
    "wof:placetype":"locality"
},
  "geometry": {"coordinates":[13.71139,-3.27833],"type":"Point"}
}