{
  "type": "Feature",
  "properties": {
    "gn:admin1_code":"08",
    "gn:asciiname":"Ofounou",
    "gn:cc2":"CG",
    "gn:country_code":"CG",
    "gn:dem":310,
    "gn:feature_class":"P",
    "gn:feature_code":"PPL",
    "gn:name":"Ofounou",
    "gn:population":0,
    "gn:timezone":"Africa/Brazzaville",
    "iso:country":"CG",
    "name:und_x_variant":[
        "Omphounou",
        "Ofounou"
    ],
    "wof:name":"Ofounou",
    "wof:placetype":"locality"
},
  "geometry": {"coordinates":[16.07361,-1.84361],"type":"Point"}
}