{
  "type": "Feature",
  "properties": {
    "gn:admin1_code":"14",
    "gn:asciiname":"Ndiba",
    "gn:country_code":"CG",
    "gn:dem":596,
    "gn:feature_class":"P",
    "gn:feature_code":"PPL",
    "gn:name":"Ndiba",
    "gn:population":0,
    "gn:timezone":"Africa/Brazzaville",
    "iso:country":"CG",
    "wof:name":"Ndiba",
    "wof:placetype":"locality"
},
  "geometry": {"coordinates":[14.54139,0.44111],"type":"Point"}
}