{
  "type": "Feature",
  "properties": {
    "gn:admin1_code":"14",
    "gn:asciiname":"Yembelangoy",
    "gn:country_code":"CG",
    "gn:dem":448,
    "gn:feature_class":"P",
    "gn:feature_code":"PPL",
    "gn:name":"Yemb\u00e9langoy",
    "gn:population":0,
    "gn:timezone":"Africa/Brazzaville",
    "iso:country":"CG",
    "name:und_x_variant":[
        "Yembelangoye",
        "Yemb\u00e9langoy"
    ],
    "wof:name":"Yembelangoy",
    "wof:placetype":"locality"
},
  "geometry": {"coordinates":[14.19833,0.18194],"type":"Point"}
}