{
  "type": "Feature",
  "properties": {
    "gn:admin1_code":"06",
    "gn:asciiname":"Faraka",
    "gn:country_code":"CG",
    "gn:dem":310,
    "gn:feature_class":"P",
    "gn:feature_code":"PPL",
    "gn:name":"Faraka",
    "gn:population":0,
    "gn:timezone":"Africa/Brazzaville",
    "iso:country":"CG",
    "wof:name":"Faraka",
    "wof:placetype":"locality"
},
  "geometry": {"coordinates":[17.91306,1.15528],"type":"Point"}
}