{
  "type": "Feature",
  "properties": {
    "gn:admin1_code":"07",
    "gn:asciiname":"Dchitou Bouala",
    "gn:country_code":"CG",
    "gn:dem":263,
    "gn:feature_class":"P",
    "gn:feature_code":"PPL",
    "gn:name":"Dchitou Bouala",
    "gn:population":0,
    "gn:timezone":"Africa/Brazzaville",
    "iso:country":"CG",
    "wof:name":"Dchitou Bouala",
    "wof:placetype":"locality"
},
  "geometry": {"coordinates":[12.55,-3.81667],"type":"Point"}
}