{
  "type": "Feature",
  "properties": {
    "gn:admin1_code":"11",
    "gn:asciiname":"Kimbanza",
    "gn:country_code":"CG",
    "gn:dem":423,
    "gn:feature_class":"P",
    "gn:feature_code":"PPL",
    "gn:name":"Kimbanza",
    "gn:population":0,
    "gn:timezone":"Africa/Brazzaville",
    "iso:country":"CG",
    "wof:name":"Kimbanza",
    "wof:placetype":"locality"
},
  "geometry": {"coordinates":[14.82833,-4.79222],"type":"Point"}
}