{
  "type": "Feature",
  "properties": {
    "gn:admin1_code":"14",
    "gn:asciiname":"Eti",
    "gn:country_code":"CG",
    "gn:dem":483,
    "gn:feature_class":"P",
    "gn:feature_code":"PPL",
    "gn:name":"Eti",
    "gn:population":0,
    "gn:timezone":"Africa/Brazzaville",
    "iso:country":"CG",
    "wof:name":"Eti",
    "wof:placetype":"locality"
},
  "geometry": {"coordinates":[14.66361,-1.00417],"type":"Point"}
}