{
  "type": "Feature",
  "properties": {
    "gn:admin1_code":"13",
    "gn:asciiname":"Ndole",
    "gn:country_code":"CG",
    "gn:dem":294,
    "gn:feature_class":"P",
    "gn:feature_code":"PPL",
    "gn:name":"Ndol\u00e9",
    "gn:population":0,
    "gn:timezone":"Africa/Brazzaville",
    "iso:country":"CG",
    "wof:name":"Ndole",
    "wof:placetype":"locality"
},
  "geometry": {"coordinates":[16.72361,-0.93472],"type":"Point"}
}