{
  "type": "Feature",
  "properties": {
    "gn:admin1_code":"11",
    "gn:asciiname":"Moutete",
    "gn:country_code":"CG",
    "gn:dem":453,
    "gn:feature_class":"P",
    "gn:feature_code":"PPL",
    "gn:name":"Mout\u00e9t\u00e9",
    "gn:population":0,
    "gn:timezone":"Africa/Brazzaville",
    "iso:country":"CG",
    "wof:name":"Moutete",
    "wof:placetype":"locality"
},
  "geometry": {"coordinates":[14.52444,-4.2925],"type":"Point"}
}