{
  "type": "Feature",
  "properties": {
    "gn:admin1_code":"13",
    "gn:asciiname":"Oyo",
    "gn:country_code":"CG",
    "gn:dem":320,
    "gn:feature_class":"P",
    "gn:feature_code":"PPL",
    "gn:name":"Oyo",
    "gn:population":0,
    "gn:timezone":"Africa/Brazzaville",
    "iso:country":"CG",
    "name:bul_x_preferred":[
        "\u041e\u0439\u043e"
    ],
    "name:fra_x_preferred":[
        "Oyo"
    ],
    "name:ita_x_preferred":[
        "Oyo"
    ],
    "name:pol_x_preferred":[
        "Oyo"
    ],
    "name:por_x_preferred":[
        "Oyo"
    ],
    "name:ron_x_preferred":[
        "Oyo"
    ],
    "name:urd_x_preferred":[
        "\u0627\u0648\u06cc\u0648"
    ],
    "name:zho_x_preferred":[
        "\u5967\u7d04"
    ],
    "wof:name":"Oyo",
    "wof:placetype":"locality"
},
  "geometry": {"coordinates":[15.97,-1.165],"type":"Point"}
}