{
  "type": "Feature",
  "properties": {
    "gn:admin1_code":"13",
    "gn:asciiname":"Oyo",
    "gn:country_code":"CG",
    "gn:dem":320,
    "gn:feature_class":"P",
    "gn:feature_code":"PPL",
    "gn:name":"Oyo",
    "gn:population":0,
    "gn:timezone":"Africa/Brazzaville",
    "iso:country":"CG",
    "wof:name":"Oyo",
    "wof:placetype":"locality"
},
  "geometry": {"coordinates":[15.97,-1.165],"type":"Point"}
}