{
  "type": "Feature",
  "properties": {
    "gn:admin1_code":"08",
    "gn:asciiname":"Bvi",
    "gn:cc2":"CG",
    "gn:country_code":"CG",
    "gn:dem":368,
    "gn:feature_class":"P",
    "gn:feature_code":"PPL",
    "gn:name":"Bvi",
    "gn:population":0,
    "gn:timezone":"Africa/Brazzaville",
    "iso:country":"CG",
    "name:deu_x_preferred":[
        "Bvi"
    ],
    "name:ukr_x_preferred":[
        "Bvi"
    ],
    "name:und_x_variant":[
        "Bvie",
        "Bvi"
    ],
    "wof:name":"Bvi",
    "wof:placetype":"locality"
},
  "geometry": {"coordinates":[15.28361,-1.65944],"type":"Point"}
}