{
  "type": "Feature",
  "properties": {
    "gn:admin1_code":"14",
    "gn:asciiname":"Ndoumbi",
    "gn:country_code":"CG",
    "gn:dem":451,
    "gn:feature_class":"P",
    "gn:feature_code":"PPL",
    "gn:name":"Ndoumbi",
    "gn:population":0,
    "gn:timezone":"Africa/Brazzaville",
    "iso:country":"CG",
    "name:und_x_variant":[
        "Oss\u00e9l\u00e9",
        "Ndoumbi"
    ],
    "wof:name":"Ndoumbi",
    "wof:placetype":"locality"
},
  "geometry": {"coordinates":[14.92278,-0.89583],"type":"Point"}
}