{
  "type": "Feature",
  "properties": {
    "gn:admin1_code":"12",
    "gn:asciiname":"Landamambou",
    "gn:country_code":"CG",
    "gn:dem":337,
    "gn:feature_class":"P",
    "gn:feature_code":"PPL",
    "gn:name":"Landamambou",
    "gn:population":0,
    "gn:timezone":"Africa/Brazzaville",
    "iso:country":"CG",
    "wof:name":"Landamambou",
    "wof:placetype":"locality"
},
  "geometry": {"coordinates":[15.08111,-4.46833],"type":"Point"}
}