{
  "type": "Feature",
  "properties": {
    "gn:admin1_code":"08",
    "gn:asciiname":"Oleme",
    "gn:country_code":"CG",
    "gn:dem":322,
    "gn:feature_class":"P",
    "gn:feature_code":"PPL",
    "gn:name":"Ol\u00e9m\u00e9",
    "gn:population":0,
    "gn:timezone":"Africa/Brazzaville",
    "iso:country":"CG",
    "wof:name":"Oleme",
    "wof:placetype":"locality"
},
  "geometry": {"coordinates":[15.90917,-1.23417],"type":"Point"}
}