{
  "type": "Feature",
  "properties": {
    "gn:admin1_code":"11",
    "gn:asciiname":"Koulou",
    "gn:country_code":"CG",
    "gn:dem":414,
    "gn:feature_class":"P",
    "gn:feature_code":"PPL",
    "gn:name":"Koulou",
    "gn:population":0,
    "gn:timezone":"Africa/Brazzaville",
    "iso:country":"CG",
    "name:fin_x_preferred":[
        "Koulou"
    ],
    "name:fra_x_preferred":[
        "Koulou"
    ],
    "name:ita_x_preferred":[
        "Koulou"
    ],
    "name:nld_x_preferred":[
        "Koulou"
    ],
    "name:spa_x_preferred":[
        "Koulou"
    ],
    "wof:name":"Koulou",
    "wof:placetype":"locality"
},
  "geometry": {"coordinates":[14.81111,-4.15306],"type":"Point"}
}