{
  "type": "Feature",
  "properties": {
    "gn:admin1_code":"12",
    "gn:asciiname":"Kinkala",
    "gn:country_code":"CG",
    "gn:dem":381,
    "gn:feature_class":"P",
    "gn:feature_code":"PPL",
    "gn:name":"Kinkala",
    "gn:population":0,
    "gn:timezone":"Africa/Brazzaville",
    "iso:country":"CG",
    "name:und_x_variant":[
        "Kinkala Sud",
        "Kinkala"
    ],
    "wof:name":"Kinkala",
    "wof:placetype":"locality"
},
  "geometry": {"coordinates":[15.06167,-4.45],"type":"Point"}
}