{
  "type": "Feature",
  "properties": {
    "gn:admin1_code":"12",
    "gn:asciiname":"Kinkala",
    "gn:country_code":"CG",
    "gn:dem":381,
    "gn:feature_class":"P",
    "gn:feature_code":"PPL",
    "gn:name":"Kinkala",
    "gn:population":0,
    "gn:timezone":"Africa/Brazzaville",
    "iso:country":"CG",
    "name:ceb_x_preferred":[
        "Kinkala"
    ],
    "name:deu_x_preferred":[
        "Kinkala"
    ],
    "name:epo_x_preferred":[
        "Kinkala"
    ],
    "name:fra_x_preferred":[
        "Kinkala"
    ],
    "name:frr_x_preferred":[
        "Kinkala"
    ],
    "name:ita_x_preferred":[
        "Kinkala"
    ],
    "name:kon_x_preferred":[
        "Kinkala"
    ],
    "name:lat_x_preferred":[
        "Kinkala"
    ],
    "name:lit_x_preferred":[
        "Kinkala"
    ],
    "name:nld_x_preferred":[
        "Kinkala"
    ],
    "name:pol_x_preferred":[
        "Kinkala"
    ],
    "name:por_x_preferred":[
        "Kinkala"
    ],
    "name:ron_x_preferred":[
        "Kinkala"
    ],
    "name:rus_x_preferred":[
        "\u041a\u0438\u043d\u043a\u0430\u043b\u0430"
    ],
    "name:spa_x_preferred":[
        "Kinkala"
    ],
    "name:swe_x_preferred":[
        "Kinkala"
    ],
    "name:ukr_x_preferred":[
        "\u041a\u0456\u043d\u043a\u0430\u043b\u0430"
    ],
    "name:und_x_variant":[
        "Kinkala Sud"
    ],
    "name:urd_x_preferred":[
        "\u06a9\u0646\u06a9\u0627\u0644\u0627"
    ],
    "name:zho_x_preferred":[
        "\u91d1\u5361\u62c9"
    ],
    "wof:name":"Kinkala",
    "wof:placetype":"locality"
},
  "geometry": {"coordinates":[15.06167,-4.45],"type":"Point"}
}