{
  "type": "Feature",
  "properties": {
    "gn:admin1_code":"08",
    "gn:asciiname":"Ebou",
    "gn:country_code":"CG",
    "gn:dem":404,
    "gn:feature_class":"P",
    "gn:feature_code":"PPL",
    "gn:name":"Ebou",
    "gn:population":0,
    "gn:timezone":"Africa/Brazzaville",
    "iso:country":"CG",
    "wof:name":"Ebou",
    "wof:placetype":"locality"
},
  "geometry": {"coordinates":[15.58694,-1.28333],"type":"Point"}
}