{
  "type": "Feature",
  "properties": {
    "gn:admin1_code":"07",
    "gn:asciiname":"Mouyantse",
    "gn:country_code":"CG",
    "gn:dem":126,
    "gn:feature_class":"P",
    "gn:feature_code":"PPL",
    "gn:name":"Mouyants\u00e9",
    "gn:population":0,
    "gn:timezone":"Africa/Brazzaville",
    "iso:country":"CG",
    "wof:name":"Mouyantse",
    "wof:placetype":"locality"
},
  "geometry": {"coordinates":[12.28222,-3.45139],"type":"Point"}
}