{
  "type": "Feature",
  "properties": {
    "gn:admin1_code":"04",
    "gn:asciiname":"Kimpesse",
    "gn:country_code":"CG",
    "gn:dem":244,
    "gn:feature_class":"P",
    "gn:feature_code":"PPL",
    "gn:name":"Kimpesse",
    "gn:population":0,
    "gn:timezone":"Africa/Brazzaville",
    "iso:country":"CG",
    "wof:name":"Kimpesse",
    "wof:placetype":"locality"
},
  "geometry": {"coordinates":[12.57444,-4.54167],"type":"Point"}
}