{
  "type": "Feature",
  "properties": {
    "gn:admin1_code":"08",
    "gn:asciiname":"Ponbo",
    "gn:cc2":"CG",
    "gn:country_code":"CG",
    "gn:dem":305,
    "gn:feature_class":"P",
    "gn:feature_code":"PPL",
    "gn:name":"Ponbo",
    "gn:population":0,
    "gn:timezone":"Africa/Brazzaville",
    "iso:country":"CG",
    "name:und_x_variant":[
        "Pombo-Bouendza",
        "Pombo",
        "Ponbo"
    ],
    "wof:name":"Ponbo",
    "wof:placetype":"locality"
},
  "geometry": {"coordinates":[16.27611,-1.35861],"type":"Point"}
}