{
  "type": "Feature",
  "properties": {
    "gn:admin1_code":"11",
    "gn:asciiname":"Kimpala",
    "gn:country_code":"CG",
    "gn:dem":269,
    "gn:feature_class":"P",
    "gn:feature_code":"PPL",
    "gn:name":"Kimpala",
    "gn:population":0,
    "gn:timezone":"Africa/Brazzaville",
    "iso:country":"CG",
    "wof:name":"Kimpala",
    "wof:placetype":"locality"
},
  "geometry": {"coordinates":[13.99889,-4.32806],"type":"Point"}
}