{
  "type": "Feature",
  "properties": {
    "gn:admin1_code":"05",
    "gn:asciiname":"Okilandzouli",
    "gn:country_code":"CG",
    "gn:dem":552,
    "gn:feature_class":"P",
    "gn:feature_code":"PPL",
    "gn:name":"Okilandzouli",
    "gn:population":0,
    "gn:timezone":"Africa/Brazzaville",
    "iso:country":"CG",
    "wof:name":"Okilandzouli",
    "wof:placetype":"locality"
},
  "geometry": {"coordinates":[13.56667,-2.43333],"type":"Point"}
}