{
  "type": "Feature",
  "properties": {
    "gn:admin1_code":"08",
    "gn:asciiname":"Bodouango",
    "gn:cc2":"CG",
    "gn:country_code":"CG",
    "gn:dem":286,
    "gn:feature_class":"P",
    "gn:feature_code":"PPL",
    "gn:name":"Bodouango",
    "gn:population":0,
    "gn:timezone":"Africa/Brazzaville",
    "iso:country":"CG",
    "name:und_x_variant":[
        "Bodouongo",
        "Bodouango"
    ],
    "wof:name":"Bodouango",
    "wof:placetype":"locality"
},
  "geometry": {"coordinates":[16.44972000000001,-1.77306],"type":"Point"}
}