{
  "type": "Feature",
  "properties": {
    "gn:admin1_code":"04",
    "gn:asciiname":"Ntoupou",
    "gn:cc2":"CG",
    "gn:country_code":"CG",
    "gn:dem":60,
    "gn:feature_class":"P",
    "gn:feature_code":"PPL",
    "gn:name":"Ntoupou",
    "gn:population":0,
    "gn:timezone":"Africa/Brazzaville",
    "iso:country":"CG",
    "name:und_x_variant":[
        "Toumbou",
        "Ntoupou"
    ],
    "wof:name":"Ntoupou",
    "wof:placetype":"locality"
},
  "geometry": {"coordinates":[11.81472,-4.555],"type":"Point"}
}