{
  "type": "Feature",
  "properties": {
    "gn:admin1_code":"11",
    "gn:asciiname":"Kinnsoundi",
    "gn:cc2":"CG",
    "gn:country_code":"CG",
    "gn:dem":555,
    "gn:feature_class":"P",
    "gn:feature_code":"PPL",
    "gn:name":"Kinnsoundi",
    "gn:population":0,
    "gn:timezone":"Africa/Brazzaville",
    "iso:country":"CG",
    "name:und_x_variant":[
        "Kinsoundi",
        "Kinnsoundi"
    ],
    "wof:name":"Kinnsoundi",
    "wof:placetype":"locality"
},
  "geometry": {"coordinates":[14.47917,-4.05528],"type":"Point"}
}