{
  "type": "Feature",
  "properties": {
    "gn:admin1_code":"01",
    "gn:asciiname":"Nsiaki",
    "gn:country_code":"CG",
    "gn:dem":460,
    "gn:feature_class":"P",
    "gn:feature_code":"PPL",
    "gn:name":"Nsiaki",
    "gn:population":0,
    "gn:timezone":"Africa/Brazzaville",
    "iso:country":"CG",
    "wof:name":"Nsiaki",
    "wof:placetype":"locality"
},
  "geometry": {"coordinates":[14.1775,-3.69194],"type":"Point"}
}