{
  "type": "Feature",
  "properties": {
    "gn:admin1_code":"07",
    "gn:asciiname":"Koutina",
    "gn:country_code":"CG",
    "gn:dem":152,
    "gn:feature_class":"P",
    "gn:feature_code":"PPL",
    "gn:name":"Koutina",
    "gn:population":0,
    "gn:timezone":"Africa/Brazzaville",
    "iso:country":"CG",
    "wof:name":"Koutina",
    "wof:placetype":"locality"
},
  "geometry": {"coordinates":[12.51,-3.67694],"type":"Point"}
}