{
  "type": "Feature",
  "properties": {
    "gn:admin1_code":"13",
    "gn:asciiname":"Niete Boumba",
    "gn:country_code":"CG",
    "gn:dem":345,
    "gn:feature_class":"P",
    "gn:feature_code":"PPL",
    "gn:name":"Ni\u00e9t\u00e9 Boumba",
    "gn:population":0,
    "gn:timezone":"Africa/Brazzaville",
    "iso:country":"CG",
    "wof:name":"Niete Boumba",
    "wof:placetype":"locality"
},
  "geometry": {"coordinates":[15.76472,-0.23944],"type":"Point"}
}