{
  "type": "Feature",
  "properties": {
    "gn:admin1_code":"14",
    "gn:asciiname":"Douka",
    "gn:country_code":"CG",
    "gn:dem":418,
    "gn:feature_class":"P",
    "gn:feature_code":"PPL",
    "gn:name":"Douka",
    "gn:population":0,
    "gn:timezone":"Africa/Brazzaville",
    "iso:country":"CG",
    "wof:name":"Douka",
    "wof:placetype":"locality"
},
  "geometry": {"coordinates":[14.86778,-0.00861],"type":"Point"}
}