{
  "type": "Feature",
  "properties": {
    "gn:admin1_code":"08",
    "gn:asciiname":"Nkono",
    "gn:cc2":"CG",
    "gn:country_code":"CG",
    "gn:dem":403,
    "gn:feature_class":"P",
    "gn:feature_code":"PPL",
    "gn:name":"Nkono",
    "gn:population":0,
    "gn:timezone":"Africa/Brazzaville",
    "iso:country":"CG",
    "name:und_x_variant":[
        "N\u2019Kono",
        "Nkono"
    ],
    "wof:name":"Nkono",
    "wof:placetype":"locality"
},
  "geometry": {"coordinates":[15.68667,-1.66139],"type":"Point"}
}