{
  "type": "Feature",
  "properties": {
    "gn:admin1_code":"05",
    "gn:asciiname":"Tongo",
    "gn:cc2":"CG",
    "gn:country_code":"CG",
    "gn:dem":635,
    "gn:feature_class":"P",
    "gn:feature_code":"PPL",
    "gn:name":"Tongo",
    "gn:population":0,
    "gn:timezone":"Africa/Brazzaville",
    "iso:country":"CG",
    "name:ceb_x_preferred":[
        "Tongo"
    ],
    "name:fra_x_preferred":[
        "Tongo"
    ],
    "name:ind_x_preferred":[
        "Tongo"
    ],
    "name:pol_x_preferred":[
        "Tongo"
    ],
    "name:swe_x_preferred":[
        "Tongo"
    ],
    "name:und_x_variant":[
        "Mawat\u00e9na"
    ],
    "wof:name":"Tongo",
    "wof:placetype":"locality"
},
  "geometry": {"coordinates":[13.82528,-3.18139],"type":"Point"}
}