{
  "type": "Feature",
  "properties": {
    "gn:admin1_code":"11",
    "gn:asciiname":"Loumo",
    "gn:country_code":"CG",
    "gn:dem":536,
    "gn:feature_class":"P",
    "gn:feature_code":"PPL",
    "gn:name":"Loumo",
    "gn:population":0,
    "gn:timezone":"Africa/Brazzaville",
    "iso:country":"CG",
    "wof:name":"Loumo",
    "wof:placetype":"locality"
},
  "geometry": {"coordinates":[14.47917,-4.64667],"type":"Point"}
}