{
  "type": "Feature",
  "properties": {
    "gn:admin1_code":"07",
    "gn:asciiname":"Songho",
    "gn:country_code":"CG",
    "gn:dem":285,
    "gn:feature_class":"P",
    "gn:feature_code":"PPL",
    "gn:name":"Songho",
    "gn:population":0,
    "gn:timezone":"Africa/Brazzaville",
    "iso:country":"CG",
    "wof:name":"Songho",
    "wof:placetype":"locality"
},
  "geometry": {"coordinates":[11.88611,-2.43222],"type":"Point"}
}