{
  "type": "Feature",
  "properties": {
    "gn:admin1_code":"10",
    "gn:asciiname":"Babali",
    "gn:cc2":"CG",
    "gn:country_code":"CG",
    "gn:dem":368,
    "gn:feature_class":"P",
    "gn:feature_code":"PPL",
    "gn:name":"Babali",
    "gn:population":0,
    "gn:timezone":"Africa/Brazzaville",
    "iso:country":"CG",
    "name:und_x_variant":[
        "Bacbali",
        "Babali"
    ],
    "wof:name":"Babali",
    "wof:placetype":"locality"
},
  "geometry": {"coordinates":[16.09222,2.08472],"type":"Point"}
}