{
  "type": "Feature",
  "properties": {
    "gn:admin1_code":"08",
    "gn:asciiname":"Epinge",
    "gn:country_code":"CG",
    "gn:dem":327,
    "gn:feature_class":"P",
    "gn:feature_code":"PPL",
    "gn:name":"Eping\u00e9",
    "gn:population":0,
    "gn:timezone":"Africa/Brazzaville",
    "iso:country":"CG",
    "wof:name":"Epinge",
    "wof:placetype":"locality"
},
  "geometry": {"coordinates":[16.02472,-1.37417],"type":"Point"}
}