{
  "type": "Feature",
  "properties": {
    "gn:admin1_code":"07",
    "gn:asciiname":"Bayombe",
    "gn:country_code":"CG",
    "gn:dem":326,
    "gn:feature_class":"P",
    "gn:feature_code":"PPL",
    "gn:name":"Bayomb\u00e9",
    "gn:population":0,
    "gn:timezone":"Africa/Brazzaville",
    "iso:country":"CG",
    "wof:name":"Bayombe",
    "wof:placetype":"locality"
},
  "geometry": {"coordinates":[12.65722,-4.18472],"type":"Point"}
}