{
  "type": "Feature",
  "properties": {
    "gn:admin1_code":"08",
    "gn:asciiname":"Bouambe",
    "gn:country_code":"CG",
    "gn:dem":410,
    "gn:feature_class":"P",
    "gn:feature_code":"PPL",
    "gn:name":"Bouamb\u00e9",
    "gn:population":0,
    "gn:timezone":"Africa/Brazzaville",
    "iso:country":"CG",
    "wof:name":"Bouambe",
    "wof:placetype":"locality"
},
  "geometry": {"coordinates":[15.58333,-2.91667],"type":"Point"}
}