{
  "type": "Feature",
  "properties": {
    "gn:admin1_code":"10",
    "gn:asciiname":"Boniola-Boundja",
    "gn:country_code":"CG",
    "gn:dem":358,
    "gn:feature_class":"P",
    "gn:feature_code":"PPL",
    "gn:name":"Boniola-Boundja",
    "gn:population":0,
    "gn:timezone":"Africa/Brazzaville",
    "iso:country":"CG",
    "wof:name":"Boniola-Boundja",
    "wof:placetype":"locality"
},
  "geometry": {"coordinates":[16.58861,0.52667],"type":"Point"}
}