{
  "type": "Feature",
  "properties": {
    "gn:admin1_code":"13",
    "gn:asciiname":"Ongali",
    "gn:country_code":"CG",
    "gn:dem":517,
    "gn:feature_class":"P",
    "gn:feature_code":"PPL",
    "gn:name":"Ongali",
    "gn:population":0,
    "gn:timezone":"Africa/Brazzaville",
    "iso:country":"CG",
    "wof:name":"Ongali",
    "wof:placetype":"locality"
},
  "geometry": {"coordinates":[14.79472,-1.58556],"type":"Point"}
}