{
  "type": "Feature",
  "properties": {
    "gn:admin1_code":"08",
    "gn:asciiname":"Okari",
    "gn:country_code":"CG",
    "gn:dem":589,
    "gn:feature_class":"P",
    "gn:feature_code":"PPL",
    "gn:name":"Okari",
    "gn:population":0,
    "gn:timezone":"Africa/Brazzaville",
    "iso:country":"CG",
    "wof:name":"Okari",
    "wof:placetype":"locality"
},
  "geometry": {"coordinates":[15.86667,-2.46667],"type":"Point"}
}