{
  "type": "Feature",
  "properties": {
    "gn:admin1_code":"01",
    "gn:asciiname":"Kimpeni",
    "gn:cc2":"CG",
    "gn:country_code":"CG",
    "gn:dem":509,
    "gn:feature_class":"P",
    "gn:feature_code":"PPL",
    "gn:name":"Kimp\u00e9ni",
    "gn:population":0,
    "gn:timezone":"Africa/Brazzaville",
    "iso:country":"CG",
    "name:und_x_variant":[
        "Kimp\u00e9ri",
        "Kimp\u00e9ni"
    ],
    "wof:name":"Kimpeni",
    "wof:placetype":"locality"
},
  "geometry": {"coordinates":[13.89,-3.95278],"type":"Point"}
}