{
  "type": "Feature",
  "properties": {
    "gn:admin1_code":"08",
    "gn:asciiname":"Npoumou",
    "gn:country_code":"CG",
    "gn:dem":332,
    "gn:feature_class":"P",
    "gn:feature_code":"PPL",
    "gn:name":"Npoumou",
    "gn:population":0,
    "gn:timezone":"Africa/Brazzaville",
    "iso:country":"CG",
    "wof:name":"Npoumou",
    "wof:placetype":"locality"
},
  "geometry": {"coordinates":[16.03083,-1.32667],"type":"Point"}
}