{
  "type": "Feature",
  "properties": {
    "gn:admin1_code":"10",
    "gn:asciiname":"Doumakenia",
    "gn:country_code":"CG",
    "gn:dem":455,
    "gn:feature_class":"P",
    "gn:feature_code":"PPL",
    "gn:name":"Doumak\u00e9nia",
    "gn:population":0,
    "gn:timezone":"Africa/Brazzaville",
    "iso:country":"CG",
    "wof:name":"Doumakenia",
    "wof:placetype":"locality"
},
  "geometry": {"coordinates":[15.83333,1.25],"type":"Point"}
}