{
  "type": "Feature",
  "properties": {
    "gn:admin1_code":"07",
    "gn:asciiname":"Tadimosi",
    "gn:country_code":"CG",
    "gn:dem":133,
    "gn:feature_class":"P",
    "gn:feature_code":"PPL",
    "gn:name":"Tadimosi",
    "gn:population":0,
    "gn:timezone":"Africa/Brazzaville",
    "iso:country":"CG",
    "wof:name":"Tadimosi",
    "wof:placetype":"locality"
},
  "geometry": {"coordinates":[12.54083,-3.27778],"type":"Point"}
}