{
  "type": "Feature",
  "properties": {
    "gn:admin1_code":"11",
    "gn:asciiname":"Kingimi",
    "gn:country_code":"CG",
    "gn:dem":455,
    "gn:feature_class":"P",
    "gn:feature_code":"PPL",
    "gn:name":"Kingimi",
    "gn:population":0,
    "gn:timezone":"Africa/Brazzaville",
    "iso:country":"CG",
    "wof:name":"Kingimi",
    "wof:placetype":"locality"
},
  "geometry": {"coordinates":[14.73,-4.01667],"type":"Point"}
}