{
  "type": "Feature",
  "properties": {
    "gn:admin1_code":"10",
    "gn:asciiname":"Elen",
    "gn:country_code":"CG",
    "gn:dem":552,
    "gn:feature_class":"P",
    "gn:feature_code":"PPL",
    "gn:name":"Elen",
    "gn:population":0,
    "gn:timezone":"Africa/Brazzaville",
    "iso:country":"CG",
    "name:bre_x_preferred":[
        "Elen"
    ],
    "name:cym_x_preferred":[
        "Elen"
    ],
    "name:deu_x_preferred":[
        "Elen"
    ],
    "wof:name":"Elen",
    "wof:placetype":"locality"
},
  "geometry": {"coordinates":[13.96083,2.11417],"type":"Point"}
}