{
  "type": "Feature",
  "properties": {
    "gn:admin1_code":"01",
    "gn:asciiname":"Kimbimi",
    "gn:country_code":"CG",
    "gn:dem":608,
    "gn:feature_class":"P",
    "gn:feature_code":"PPL",
    "gn:name":"Kimbimi",
    "gn:population":0,
    "gn:timezone":"Africa/Brazzaville",
    "iso:country":"CG",
    "wof:name":"Kimbimi",
    "wof:placetype":"locality"
},
  "geometry": {"coordinates":[13.91389,-3.70833],"type":"Point"}
}