{
  "type": "Feature",
  "properties": {
    "gn:admin1_code":"11",
    "gn:asciiname":"Moulengo",
    "gn:country_code":"CG",
    "gn:dem":458,
    "gn:feature_class":"P",
    "gn:feature_code":"PPL",
    "gn:name":"Moulengo",
    "gn:population":0,
    "gn:timezone":"Africa/Brazzaville",
    "iso:country":"CG",
    "wof:name":"Moulengo",
    "wof:placetype":"locality"
},
  "geometry": {"coordinates":[14.33139,-3.60722],"type":"Point"}
}