{
  "type": "Feature",
  "properties": {
    "gn:admin1_code":"08",
    "gn:asciiname":"Oko",
    "gn:country_code":"CG",
    "gn:dem":542,
    "gn:feature_class":"P",
    "gn:feature_code":"PPL",
    "gn:name":"Oko",
    "gn:population":0,
    "gn:timezone":"Africa/Brazzaville",
    "iso:country":"CG",
    "wof:name":"Oko",
    "wof:placetype":"locality"
},
  "geometry": {"coordinates":[15.62083,-2.06889],"type":"Point"}
}