{
  "type": "Feature",
  "properties": {
    "gn:admin1_code":"08",
    "gn:asciiname":"Oko",
    "gn:country_code":"CG",
    "gn:dem":542,
    "gn:feature_class":"P",
    "gn:feature_code":"PPL",
    "gn:name":"Oko",
    "gn:population":0,
    "gn:timezone":"Africa/Brazzaville",
    "iso:country":"CG",
    "name:bul_x_preferred":[
        "\u041e\u043a\u043e"
    ],
    "name:deu_x_preferred":[
        "Oko"
    ],
    "name:fin_x_preferred":[
        "Oko"
    ],
    "name:fra_x_preferred":[
        "Oko"
    ],
    "name:pol_x_preferred":[
        "Oko"
    ],
    "name:por_x_preferred":[
        "Oko"
    ],
    "name:rus_x_preferred":[
        "\u041e\u043a\u043e"
    ],
    "wof:name":"Oko",
    "wof:placetype":"locality"
},
  "geometry": {"coordinates":[15.62083,-2.06889],"type":"Point"}
}