{
  "type": "Feature",
  "properties": {
    "gn:admin1_code":"01",
    "gn:asciiname":"Makoungou",
    "gn:country_code":"CG",
    "gn:dem":424,
    "gn:feature_class":"P",
    "gn:feature_code":"PPL",
    "gn:name":"Makoungou",
    "gn:population":0,
    "gn:timezone":"Africa/Brazzaville",
    "iso:country":"CG",
    "wof:name":"Makoungou",
    "wof:placetype":"locality"
},
  "geometry": {"coordinates":[13.73444,-3.8625],"type":"Point"}
}