{
  "type": "Feature",
  "properties": {
    "gn:admin1_code":"05",
    "gn:asciiname":"Mouyali",
    "gn:cc2":"CG",
    "gn:country_code":"CG",
    "gn:dem":641,
    "gn:feature_class":"P",
    "gn:feature_code":"PPL",
    "gn:name":"Mouyali",
    "gn:population":0,
    "gn:timezone":"Africa/Brazzaville",
    "iso:country":"CG",
    "name:und_x_variant":[
        "Mouyabi",
        "Mouyali"
    ],
    "wof:name":"Mouyali",
    "wof:placetype":"locality"
},
  "geometry": {"coordinates":[13.60444,-2.91],"type":"Point"}
}