{
  "type": "Feature",
  "properties": {
    "gn:admin1_code":"10",
    "gn:asciiname":"Banda",
    "gn:country_code":"CG",
    "gn:dem":446,
    "gn:feature_class":"P",
    "gn:feature_code":"PPL",
    "gn:name":"Banda",
    "gn:population":0,
    "gn:timezone":"Africa/Brazzaville",
    "iso:country":"CG",
    "wof:name":"Banda",
    "wof:placetype":"locality"
},
  "geometry": {"coordinates":[15.8725,1.43389],"type":"Point"}
}