{
  "type": "Feature",
  "properties": {
    "gn:admin1_code":"06",
    "gn:asciiname":"Ilanga",
    "gn:cc2":"CG",
    "gn:country_code":"CG",
    "gn:dem":311,
    "gn:feature_class":"P",
    "gn:feature_code":"PPL",
    "gn:name":"Ilanga",
    "gn:population":0,
    "gn:timezone":"Africa/Brazzaville",
    "iso:country":"CG",
    "name:und_x_variant":[
        "Itanga",
        "Ilanga"
    ],
    "wof:name":"Ilanga",
    "wof:placetype":"locality"
},
  "geometry": {"coordinates":[17.41611,1.21583],"type":"Point"}
}