{
  "type": "Feature",
  "properties": {
    "gn:admin1_code":"05",
    "gn:asciiname":"Mocaboula",
    "gn:country_code":"CG",
    "gn:dem":357,
    "gn:feature_class":"P",
    "gn:feature_code":"PPL",
    "gn:name":"Mocaboula",
    "gn:population":0,
    "gn:timezone":"Africa/Brazzaville",
    "iso:country":"CG",
    "wof:name":"Mocaboula",
    "wof:placetype":"locality"
},
  "geometry": {"coordinates":[17.46667,2.36667],"type":"Point"}
}