{
  "type": "Feature",
  "properties": {
    "gn:admin1_code":"13",
    "gn:asciiname":"Tsama",
    "gn:country_code":"CG",
    "gn:dem":361,
    "gn:feature_class":"P",
    "gn:feature_code":"PPL",
    "gn:name":"Tsama",
    "gn:population":0,
    "gn:timezone":"Africa/Brazzaville",
    "iso:country":"CG",
    "wof:name":"Tsama",
    "wof:placetype":"locality"
},
  "geometry": {"coordinates":[15.30611,-0.68583],"type":"Point"}
}