{
  "type": "Feature",
  "properties": {
    "gn:admin1_code":"07",
    "gn:asciiname":"Ngonogo",
    "gn:country_code":"CG",
    "gn:dem":475,
    "gn:feature_class":"P",
    "gn:feature_code":"PPL",
    "gn:name":"Ngonogo",
    "gn:population":0,
    "gn:timezone":"Africa/Brazzaville",
    "iso:country":"CG",
    "wof:name":"Ngonogo",
    "wof:placetype":"locality"
},
  "geometry": {"coordinates":[12.88333,-3.06667],"type":"Point"}
}