{
  "type": "Feature",
  "properties": {
    "gn:admin1_code":"04",
    "gn:asciiname":"Fouta",
    "gn:country_code":"CG",
    "gn:dem":18,
    "gn:feature_class":"P",
    "gn:feature_code":"PPL",
    "gn:name":"Fouta",
    "gn:population":0,
    "gn:timezone":"Africa/Brazzaville",
    "iso:country":"CG",
    "name:fra_x_preferred":[
        "Fouta"
    ],
    "name:swe_x_preferred":[
        "Fouta"
    ],
    "wof:name":"Fouta",
    "wof:placetype":"locality"
},
  "geometry": {"coordinates":[11.97306,-4.95306],"type":"Point"}
}