{
  "type": "Feature",
  "properties": {
    "gn:admin1_code":"06",
    "gn:asciiname":"Niangi",
    "gn:country_code":"CG",
    "gn:dem":317,
    "gn:feature_class":"P",
    "gn:feature_code":"PPL",
    "gn:name":"Niangi",
    "gn:population":0,
    "gn:timezone":"Africa/Brazzaville",
    "iso:country":"CG",
    "wof:name":"Niangi",
    "wof:placetype":"locality"
},
  "geometry": {"coordinates":[18.05472,1.81861],"type":"Point"}
}