{
  "type": "Feature",
  "properties": {
    "gn:admin1_code":"04",
    "gn:asciiname":"Konde",
    "gn:country_code":"CG",
    "gn:dem":160,
    "gn:feature_class":"P",
    "gn:feature_code":"PPL",
    "gn:name":"Kond\u00e9",
    "gn:population":0,
    "gn:timezone":"Africa/Brazzaville",
    "iso:country":"CG",
    "name:ceb_x_preferred":[
        "Konde"
    ],
    "name:deu_x_preferred":[
        "Konde"
    ],
    "name:ita_x_preferred":[
        "Konde"
    ],
    "name:swa_x_preferred":[
        "Konde"
    ],
    "name:swe_x_preferred":[
        "Konde"
    ],
    "wof:name":"Konde",
    "wof:placetype":"locality"
},
  "geometry": {"coordinates":[12.31667,-4.34667],"type":"Point"}
}