{
  "type": "Feature",
  "properties": {
    "gn:admin1_code":"11",
    "gn:asciiname":"Mountoko",
    "gn:country_code":"CG",
    "gn:dem":503,
    "gn:feature_class":"P",
    "gn:feature_code":"PPL",
    "gn:name":"Mountoko",
    "gn:population":0,
    "gn:timezone":"Africa/Brazzaville",
    "iso:country":"CG",
    "wof:name":"Mountoko",
    "wof:placetype":"locality"
},
  "geometry": {"coordinates":[14.58056,-3.71111],"type":"Point"}
}