{
  "type": "Feature",
  "properties": {
    "gn:admin1_code":"13",
    "gn:asciiname":"Kouya",
    "gn:country_code":"CG",
    "gn:dem":416,
    "gn:feature_class":"P",
    "gn:feature_code":"PPL",
    "gn:name":"Kouya",
    "gn:population":0,
    "gn:timezone":"Africa/Brazzaville",
    "iso:country":"CG",
    "wof:name":"Kouya",
    "wof:placetype":"locality"
},
  "geometry": {"coordinates":[14.95306,-1.16917],"type":"Point"}
}