{
  "type": "Feature",
  "properties": {
    "gn:admin1_code":"11",
    "gn:asciiname":"Vouloumamba",
    "gn:country_code":"CG",
    "gn:dem":440,
    "gn:feature_class":"P",
    "gn:feature_code":"PPL",
    "gn:name":"Vouloumamba",
    "gn:population":0,
    "gn:timezone":"Africa/Brazzaville",
    "iso:country":"CG",
    "wof:name":"Vouloumamba",
    "wof:placetype":"locality"
},
  "geometry": {"coordinates":[14.67083,-4.19694],"type":"Point"}
}