{
  "type": "Feature",
  "properties": {
    "gn:admin1_code":"08",
    "gn:asciiname":"Adzi",
    "gn:cc2":"CG",
    "gn:country_code":"CG",
    "gn:dem":709,
    "gn:feature_class":"P",
    "gn:feature_code":"PPL",
    "gn:name":"Adzi",
    "gn:population":0,
    "gn:timezone":"Africa/Brazzaville",
    "iso:country":"CG",
    "name:und_x_variant":[
        "Onki\u00e9l\u00e9",
        "Adzi"
    ],
    "wof:name":"Adzi",
    "wof:placetype":"locality"
},
  "geometry": {"coordinates":[15.305,-2.66917],"type":"Point"}
}