{
  "type": "Feature",
  "properties": {
    "gn:admin1_code":"08",
    "gn:asciiname":"Obo",
    "gn:country_code":"CG",
    "gn:dem":345,
    "gn:feature_class":"P",
    "gn:feature_code":"PPL",
    "gn:name":"Obo",
    "gn:population":0,
    "gn:timezone":"Africa/Brazzaville",
    "iso:country":"CG",
    "wof:name":"Obo",
    "wof:placetype":"locality"
},
  "geometry": {"coordinates":[15.91944,-1.37028],"type":"Point"}
}