{
  "type": "Feature",
  "properties": {
    "gn:admin1_code":"08",
    "gn:asciiname":"Obo",
    "gn:country_code":"CG",
    "gn:dem":345,
    "gn:feature_class":"P",
    "gn:feature_code":"PPL",
    "gn:name":"Obo",
    "gn:population":0,
    "gn:timezone":"Africa/Brazzaville",
    "iso:country":"CG",
    "name:azb_x_preferred":[
        "\u0627\u0648\u0628\u0648"
    ],
    "name:ceb_x_preferred":[
        "Obo"
    ],
    "name:deu_x_preferred":[
        "Obo"
    ],
    "name:est_x_preferred":[
        "Obo"
    ],
    "name:fas_x_preferred":[
        "\u0627\u0648\u0628\u0648"
    ],
    "name:fra_x_preferred":[
        "Obo"
    ],
    "name:frr_x_preferred":[
        "Obo"
    ],
    "name:ita_x_preferred":[
        "Obo"
    ],
    "name:jpn_x_preferred":[
        "\u30aa\u30dc"
    ],
    "name:lit_x_preferred":[
        "Obo"
    ],
    "name:nld_x_preferred":[
        "Obo"
    ],
    "name:pol_x_preferred":[
        "Obo"
    ],
    "name:ron_x_preferred":[
        "Obo"
    ],
    "name:rus_x_preferred":[
        "\u041e\u0431\u043e"
    ],
    "name:sag_x_preferred":[
        "Obo"
    ],
    "name:sqi_x_preferred":[
        "Obo"
    ],
    "name:swe_x_preferred":[
        "Obo"
    ],
    "name:tur_x_preferred":[
        "Obo"
    ],
    "name:urd_x_preferred":[
        "\u0627\u0648\u0628\u0648"
    ],
    "name:xmf_x_preferred":[
        "\u10dd\u10d1\u10dd"
    ],
    "wof:name":"Obo",
    "wof:placetype":"locality"
},
  "geometry": {"coordinates":[15.91944,-1.37028],"type":"Point"}
}