{
  "type": "Feature",
  "properties": {
    "gn:admin1_code":"13",
    "gn:asciiname":"Bokonko",
    "gn:country_code":"CG",
    "gn:dem":313,
    "gn:feature_class":"P",
    "gn:feature_code":"PPL",
    "gn:name":"Bokonko",
    "gn:population":0,
    "gn:timezone":"Africa/Brazzaville",
    "iso:country":"CG",
    "wof:name":"Bokonko",
    "wof:placetype":"locality"
},
  "geometry": {"coordinates":[16.46583,-1.245],"type":"Point"}
}