{
  "type": "Feature",
  "properties": {
    "gn:admin1_code":"10",
    "gn:asciiname":"Touakama",
    "gn:cc2":"CG",
    "gn:country_code":"CG",
    "gn:dem":558,
    "gn:feature_class":"P",
    "gn:feature_code":"PPL",
    "gn:name":"Touakama",
    "gn:population":0,
    "gn:timezone":"Africa/Brazzaville",
    "iso:country":"CG",
    "name:und_x_variant":[
        "Touamaka",
        "Touakama"
    ],
    "wof:name":"Touakama",
    "wof:placetype":"locality"
},
  "geometry": {"coordinates":[14.19583,1.96083],"type":"Point"}
}