{
  "type": "Feature",
  "properties": {
    "gn:admin1_code":"00",
    "gn:asciiname":"Lekondji",
    "gn:country_code":"CG",
    "gn:dem":283,
    "gn:feature_class":"P",
    "gn:feature_code":"PPL",
    "gn:name":"Lekondji",
    "gn:population":0,
    "gn:timezone":"Africa/Brazzaville",
    "iso:country":"CG",
    "wof:name":"Lekondji",
    "wof:placetype":"locality"
},
  "geometry": {"coordinates":[16.28333,-1.93333],"type":"Point"}
}