{
  "type": "Feature",
  "properties": {
    "gn:admin1_code":"07",
    "gn:asciiname":"Tsangi",
    "gn:country_code":"CG",
    "gn:dem":422,
    "gn:feature_class":"P",
    "gn:feature_code":"PPL",
    "gn:name":"Tsangi",
    "gn:population":0,
    "gn:timezone":"Africa/Brazzaville",
    "iso:country":"CG",
    "wof:name":"Tsangi",
    "wof:placetype":"locality"
},
  "geometry": {"coordinates":[13.40333,-4.72972],"type":"Point"}
}