{
  "type": "Feature",
  "properties": {
    "gn:admin1_code":"01",
    "gn:asciiname":"Boungou",
    "gn:country_code":"CG",
    "gn:dem":159,
    "gn:feature_class":"P",
    "gn:feature_code":"PPL",
    "gn:name":"Boungou",
    "gn:population":0,
    "gn:timezone":"Africa/Brazzaville",
    "iso:country":"CG",
    "name:fra_x_preferred":[
        "Boungou"
    ],
    "wof:name":"Boungou",
    "wof:placetype":"locality"
},
  "geometry": {"coordinates":[12.76778,-3.93639],"type":"Point"}
}