{
  "type": "Feature",
  "properties": {
    "gn:admin1_code":"11",
    "gn:asciiname":"Karikari",
    "gn:country_code":"CG",
    "gn:dem":367,
    "gn:feature_class":"P",
    "gn:feature_code":"PPL",
    "gn:name":"Karikari",
    "gn:population":0,
    "gn:timezone":"Africa/Brazzaville",
    "iso:country":"CG",
    "wof:name":"Karikari",
    "wof:placetype":"locality"
},
  "geometry": {"coordinates":[14.94861,-4.21833],"type":"Point"}
}