{
  "type": "Feature",
  "properties": {
    "gn:admin1_code":"11",
    "gn:asciiname":"Nganba",
    "gn:country_code":"CG",
    "gn:dem":411,
    "gn:feature_class":"P",
    "gn:feature_code":"PPL",
    "gn:name":"Nganba",
    "gn:population":0,
    "gn:timezone":"Africa/Brazzaville",
    "iso:country":"CG",
    "wof:name":"Nganba",
    "wof:placetype":"locality"
},
  "geometry": {"coordinates":[14.4075,-3.81444],"type":"Point"}
}