{
  "type": "Feature",
  "properties": {
    "gn:admin1_code":"06",
    "gn:asciiname":"Pakende",
    "gn:country_code":"CG",
    "gn:dem":395,
    "gn:feature_class":"P",
    "gn:feature_code":"PPL",
    "gn:name":"Pakend\u00e9",
    "gn:population":0,
    "gn:timezone":"Africa/Brazzaville",
    "iso:country":"CG",
    "wof:name":"Pakende",
    "wof:placetype":"locality"
},
  "geometry": {"coordinates":[17.26667,2.75],"type":"Point"}
}