{
  "type": "Feature",
  "properties": {
    "gn:admin1_code":"14",
    "gn:asciiname":"Tsama II",
    "gn:country_code":"CG",
    "gn:dem":474,
    "gn:feature_class":"P",
    "gn:feature_code":"PPL",
    "gn:name":"Tsama II",
    "gn:population":0,
    "gn:timezone":"Africa/Brazzaville",
    "iso:country":"CG",
    "name:und_x_variant":[
        "Ntsama",
        "Tsama",
        "Tsama II"
    ],
    "wof:name":"Tsama II",
    "wof:placetype":"locality"
},
  "geometry": {"coordinates":[14.57972,-0.51389],"type":"Point"}
}