{
  "type": "Feature",
  "properties": {
    "gn:admin1_code":"11",
    "gn:asciiname":"Mpe",
    "gn:country_code":"CG",
    "gn:dem":452,
    "gn:feature_class":"P",
    "gn:feature_code":"PPL",
    "gn:name":"Mp\u00e9",
    "gn:population":0,
    "gn:timezone":"Africa/Brazzaville",
    "iso:country":"CG",
    "wof:name":"Mpe",
    "wof:placetype":"locality"
},
  "geometry": {"coordinates":[14.7175,-2.90389],"type":"Point"}
}