{
  "type": "Feature",
  "properties": {
    "gn:admin1_code":"04",
    "gn:asciiname":"Toumbi",
    "gn:country_code":"CG",
    "gn:dem":160,
    "gn:feature_class":"P",
    "gn:feature_code":"PPL",
    "gn:name":"Toumbi",
    "gn:population":0,
    "gn:timezone":"Africa/Brazzaville",
    "iso:country":"CG",
    "wof:name":"Toumbi",
    "wof:placetype":"locality"
},
  "geometry": {"coordinates":[11.92444,-4.60472],"type":"Point"}
}