{
  "type": "Feature",
  "properties": {
    "gn:admin1_code":"11",
    "gn:asciiname":"Moungali",
    "gn:country_code":"CG",
    "gn:dem":308,
    "gn:feature_class":"P",
    "gn:feature_code":"PPL",
    "gn:name":"Moungali",
    "gn:population":0,
    "gn:timezone":"Africa/Brazzaville",
    "iso:country":"CG",
    "wof:name":"Moungali",
    "wof:placetype":"locality"
},
  "geometry": {"coordinates":[15.25916,-4.25333],"type":"Point"}
}