{
  "type": "Feature",
  "properties": {
    "gn:admin1_code":"08",
    "gn:asciiname":"Mbantse",
    "gn:cc2":"CG",
    "gn:country_code":"CG",
    "gn:dem":284,
    "gn:feature_class":"P",
    "gn:feature_code":"PPL",
    "gn:name":"Mbants\u00e9",
    "gn:population":0,
    "gn:timezone":"Africa/Brazzaville",
    "iso:country":"CG",
    "name:und_x_variant":[
        "Bentz\u00e9",
        "Bants\u00e9",
        "Mbants\u00e9"
    ],
    "wof:name":"Mbantse",
    "wof:placetype":"locality"
},
  "geometry": {"coordinates":[16.39917,-1.8125],"type":"Point"}
}