{
  "type": "Feature",
  "properties": {
    "gn:admin1_code":"13",
    "gn:asciiname":"Omvoula",
    "gn:country_code":"CG",
    "gn:dem":391,
    "gn:feature_class":"P",
    "gn:feature_code":"PPL",
    "gn:name":"Omvoula",
    "gn:population":0,
    "gn:timezone":"Africa/Brazzaville",
    "iso:country":"CG",
    "wof:name":"Omvoula",
    "wof:placetype":"locality"
},
  "geometry": {"coordinates":[15.0575,-1.37889],"type":"Point"}
}