{
  "type": "Feature",
  "properties": {
    "gn:admin1_code":"10",
    "gn:asciiname":"Poumba Ekoum",
    "gn:country_code":"CG",
    "gn:dem":527,
    "gn:feature_class":"P",
    "gn:feature_code":"PPL",
    "gn:name":"Poumba Ekoum",
    "gn:population":0,
    "gn:timezone":"Africa/Brazzaville",
    "iso:country":"CG",
    "wof:name":"Poumba Ekoum",
    "wof:placetype":"locality"
},
  "geometry": {"coordinates":[13.70667,1.66194],"type":"Point"}
}