{
  "type": "Feature",
  "properties": {
    "gn:admin1_code":"14",
    "gn:asciiname":"Akamou",
    "gn:country_code":"CG",
    "gn:dem":468,
    "gn:feature_class":"P",
    "gn:feature_code":"PPL",
    "gn:name":"Akamou",
    "gn:population":0,
    "gn:timezone":"Africa/Brazzaville",
    "iso:country":"CG",
    "name:und_x_variant":[
        "Akamo",
        "Akamou"
    ],
    "wof:name":"Akamou",
    "wof:placetype":"locality"
},
  "geometry": {"coordinates":[14.32028,0.02583],"type":"Point"}
}