{
  "type": "Feature",
  "properties": {
    "gn:admin1_code":"06",
    "gn:asciiname":"Lipendja",
    "gn:country_code":"CG",
    "gn:dem":369,
    "gn:feature_class":"P",
    "gn:feature_code":"PPL",
    "gn:name":"Lipendja",
    "gn:population":0,
    "gn:timezone":"Africa/Brazzaville",
    "iso:country":"CG",
    "wof:name":"Lipendja",
    "wof:placetype":"locality"
},
  "geometry": {"coordinates":[17.05,2.66667],"type":"Point"}
}