{
  "type": "Feature",
  "properties": {
    "gn:admin1_code":"14",
    "gn:asciiname":"Onienga",
    "gn:country_code":"CG",
    "gn:dem":541,
    "gn:feature_class":"P",
    "gn:feature_code":"PPL",
    "gn:name":"Onienga",
    "gn:population":0,
    "gn:timezone":"Africa/Brazzaville",
    "iso:country":"CG",
    "name:und_x_variant":[
        "Orienga",
        "Onienga"
    ],
    "wof:name":"Onienga",
    "wof:placetype":"locality"
},
  "geometry": {"coordinates":[13.98333,-0.06667],"type":"Point"}
}