{
  "type": "Feature",
  "properties": {
    "gn:admin1_code":"13",
    "gn:asciiname":"Sengolo",
    "gn:country_code":"CG",
    "gn:dem":310,
    "gn:feature_class":"P",
    "gn:feature_code":"PPL",
    "gn:name":"Sengolo",
    "gn:population":0,
    "gn:timezone":"Africa/Brazzaville",
    "iso:country":"CG",
    "wof:name":"Sengolo",
    "wof:placetype":"locality"
},
  "geometry": {"coordinates":[16.6825,-1.24389],"type":"Point"}
}