{
  "type": "Feature",
  "properties": {
    "gn:admin1_code":"08",
    "gn:asciiname":"Oboti",
    "gn:country_code":"CG",
    "gn:dem":544,
    "gn:feature_class":"P",
    "gn:feature_code":"PPL",
    "gn:name":"Oboti",
    "gn:population":0,
    "gn:timezone":"Africa/Brazzaville",
    "iso:country":"CG",
    "wof:name":"Oboti",
    "wof:placetype":"locality"
},
  "geometry": {"coordinates":[14.79972,-1.93361],"type":"Point"}
}