{
  "type": "Feature",
  "properties": {
    "gn:admin1_code":"11",
    "gn:asciiname":"Tenta",
    "gn:country_code":"CG",
    "gn:dem":438,
    "gn:feature_class":"P",
    "gn:feature_code":"PPL",
    "gn:name":"Tenta",
    "gn:population":0,
    "gn:timezone":"Africa/Brazzaville",
    "iso:country":"CG",
    "name:fra_x_preferred":[
        "Tenta"
    ],
    "wof:name":"Tenta",
    "wof:placetype":"locality"
},
  "geometry": {"coordinates":[14.78972,-4.81861],"type":"Point"}
}