{
  "type": "Feature",
  "properties": {
    "gn:admin1_code":"07",
    "gn:asciiname":"Passi-Passi",
    "gn:cc2":"CG",
    "gn:country_code":"CG",
    "gn:dem":279,
    "gn:feature_class":"P",
    "gn:feature_code":"PPL",
    "gn:name":"Passi-Passi",
    "gn:population":0,
    "gn:timezone":"Africa/Brazzaville",
    "iso:country":"CG",
    "name:und_x_variant":[
        "Dib\u00e9ni",
        "Passi-Passi"
    ],
    "wof:name":"Passi-Passi",
    "wof:placetype":"locality"
},
  "geometry": {"coordinates":[12.54639,-4.04778],"type":"Point"}
}