{
  "type": "Feature",
  "properties": {
    "gn:admin1_code":"07",
    "gn:asciiname":"Mabimba",
    "gn:country_code":"CG",
    "gn:dem":607,
    "gn:feature_class":"P",
    "gn:feature_code":"PPL",
    "gn:name":"Mabimba",
    "gn:population":0,
    "gn:timezone":"Africa/Brazzaville",
    "iso:country":"CG",
    "wof:name":"Mabimba",
    "wof:placetype":"locality"
},
  "geometry": {"coordinates":[12.73611,-2.59278],"type":"Point"}
}