{
  "type": "Feature",
  "properties": {
    "gn:admin1_code":"14",
    "gn:asciiname":"Anbela",
    "gn:country_code":"CG",
    "gn:dem":432,
    "gn:feature_class":"P",
    "gn:feature_code":"PPL",
    "gn:name":"Anb\u00e9la",
    "gn:population":0,
    "gn:timezone":"Africa/Brazzaville",
    "iso:country":"CG",
    "name:und_x_variant":[
        "Amb\u00e9la",
        "Anb\u00e9la"
    ],
    "wof:name":"Anbela",
    "wof:placetype":"locality"
},
  "geometry": {"coordinates":[14.85722,-0.60361],"type":"Point"}
}