{
  "type": "Feature",
  "properties": {
    "gn:admin1_code":"13",
    "gn:asciiname":"Makolondanbo",
    "gn:country_code":"CG",
    "gn:dem":289,
    "gn:feature_class":"P",
    "gn:feature_code":"PPL",
    "gn:name":"Makolondanbo",
    "gn:population":0,
    "gn:timezone":"Africa/Brazzaville",
    "iso:country":"CG",
    "wof:name":"Makolondanbo",
    "wof:placetype":"locality"
},
  "geometry": {"coordinates":[16.87556,-1.16889],"type":"Point"}
}