{
  "type": "Feature",
  "properties": {
    "gn:admin1_code":"07",
    "gn:asciiname":"Moungoundi",
    "gn:cc2":"CG",
    "gn:country_code":"CG",
    "gn:dem":243,
    "gn:feature_class":"P",
    "gn:feature_code":"PPL",
    "gn:name":"Moungoundi",
    "gn:population":0,
    "gn:timezone":"Africa/Brazzaville",
    "iso:country":"CG",
    "name:und_x_variant":[
        "Moungoudi",
        "Mougoudi",
        "Moungoundi"
    ],
    "wof:name":"Moungoundi",
    "wof:placetype":"locality"
},
  "geometry": {"coordinates":[11.76,-2.7525],"type":"Point"}
}