{
  "type": "Feature",
  "properties": {
    "gn:admin1_code":"08",
    "gn:asciiname":"Ongali",
    "gn:country_code":"CG",
    "gn:dem":378,
    "gn:feature_class":"P",
    "gn:feature_code":"PPL",
    "gn:name":"Ongali",
    "gn:population":0,
    "gn:timezone":"Africa/Brazzaville",
    "iso:country":"CG",
    "wof:name":"Ongali",
    "wof:placetype":"locality"
},
  "geometry": {"coordinates":[15.80333,-1.50361],"type":"Point"}
}