{
  "type": "Feature",
  "properties": {
    "gn:admin1_code":"10",
    "gn:asciiname":"Djampono",
    "gn:country_code":"CG",
    "gn:dem":620,
    "gn:feature_class":"P",
    "gn:feature_code":"PPL",
    "gn:name":"Djampono",
    "gn:population":0,
    "gn:timezone":"Africa/Brazzaville",
    "iso:country":"CG",
    "wof:name":"Djampono",
    "wof:placetype":"locality"
},
  "geometry": {"coordinates":[14.06667,2.15],"type":"Point"}
}