{
  "type": "Feature",
  "properties": {
    "gn:admin1_code":"07",
    "gn:asciiname":"Bihongo",
    "gn:country_code":"CG",
    "gn:dem":302,
    "gn:feature_class":"P",
    "gn:feature_code":"PPL",
    "gn:name":"Bihongo",
    "gn:population":0,
    "gn:timezone":"Africa/Brazzaville",
    "iso:country":"CG",
    "wof:name":"Bihongo",
    "wof:placetype":"locality"
},
  "geometry": {"coordinates":[11.83194,-2.78222],"type":"Point"}
}