{
  "type": "Feature",
  "properties": {
    "gn:admin1_code":"08",
    "gn:asciiname":"Elouo",
    "gn:country_code":"CG",
    "gn:dem":381,
    "gn:feature_class":"P",
    "gn:feature_code":"PPL",
    "gn:name":"Elouo",
    "gn:population":0,
    "gn:timezone":"Africa/Brazzaville",
    "iso:country":"CG",
    "wof:name":"Elouo",
    "wof:placetype":"locality"
},
  "geometry": {"coordinates":[15.99389,-1.75972],"type":"Point"}
}