{
  "type": "Feature",
  "properties": {
    "gn:admin1_code":"04",
    "gn:asciiname":"Bouvandji",
    "gn:country_code":"CG",
    "gn:dem":99,
    "gn:feature_class":"P",
    "gn:feature_code":"PPL",
    "gn:name":"Bouvandji",
    "gn:population":0,
    "gn:timezone":"Africa/Brazzaville",
    "iso:country":"CG",
    "wof:name":"Bouvandji",
    "wof:placetype":"locality"
},
  "geometry": {"coordinates":[11.98333,-4.76667],"type":"Point"}
}