{
  "type": "Feature",
  "properties": {
    "gn:admin1_code":"05",
    "gn:asciiname":"Mankesi",
    "gn:country_code":"CG",
    "gn:dem":666,
    "gn:feature_class":"P",
    "gn:feature_code":"PPL",
    "gn:name":"Mank\u00e9si",
    "gn:population":0,
    "gn:timezone":"Africa/Brazzaville",
    "iso:country":"CG",
    "wof:name":"Mankesi",
    "wof:placetype":"locality"
},
  "geometry": {"coordinates":[13.80611,-3.2125],"type":"Point"}
}