{
  "type": "Feature",
  "properties": {
    "gn:admin1_code":"05",
    "gn:asciiname":"Moule",
    "gn:country_code":"CG",
    "gn:dem":483,
    "gn:feature_class":"P",
    "gn:feature_code":"PPL",
    "gn:name":"Moul\u00e9",
    "gn:population":0,
    "gn:timezone":"Africa/Brazzaville",
    "iso:country":"CG",
    "name:ceb_x_preferred":[
        "Moule"
    ],
    "name:deu_x_preferred":[
        "Moule"
    ],
    "name:fra_x_preferred":[
        "Moule"
    ],
    "name:jpn_x_preferred":[
        "\u30e0\u30fc\u30eb"
    ],
    "name:swe_x_preferred":[
        "Moule"
    ],
    "wof:name":"Moule",
    "wof:placetype":"locality"
},
  "geometry": {"coordinates":[13.37278,-3.6275],"type":"Point"}
}