{
  "type": "Feature",
  "properties": {
    "gn:admin1_code":"11",
    "gn:asciiname":"Bandi",
    "gn:country_code":"CG",
    "gn:dem":439,
    "gn:feature_class":"P",
    "gn:feature_code":"PPL",
    "gn:name":"Bandi",
    "gn:population":0,
    "gn:timezone":"Africa/Brazzaville",
    "iso:country":"CG",
    "name:ceb_x_preferred":[
        "Bandi"
    ],
    "name:deu_x_preferred":[
        "Bandi"
    ],
    "name:fra_x_preferred":[
        "Bandi"
    ],
    "name:ita_x_preferred":[
        "Bandi"
    ],
    "name:slv_x_preferred":[
        "Bandi"
    ],
    "name:swe_x_preferred":[
        "Bandi"
    ],
    "name:vie_x_preferred":[
        "Bandi"
    ],
    "wof:name":"Bandi",
    "wof:placetype":"locality"
},
  "geometry": {"coordinates":[14.77194,-4.355],"type":"Point"}
}