{
  "type": "Feature",
  "properties": {
    "gn:admin1_code":"14",
    "gn:asciiname":"Kessala",
    "gn:country_code":"CG",
    "gn:dem":444,
    "gn:feature_class":"P",
    "gn:feature_code":"PPL",
    "gn:name":"Kessala",
    "gn:population":0,
    "gn:timezone":"Africa/Brazzaville",
    "iso:country":"CG",
    "wof:name":"Kessala",
    "wof:placetype":"locality"
},
  "geometry": {"coordinates":[14.61278,-0.7125],"type":"Point"}
}