{
  "type": "Feature",
  "properties": {
    "gn:admin1_code":"06",
    "gn:asciiname":"Bangi",
    "gn:country_code":"CG",
    "gn:dem":335,
    "gn:feature_class":"P",
    "gn:feature_code":"PPL",
    "gn:name":"Bangi",
    "gn:population":0,
    "gn:timezone":"Africa/Brazzaville",
    "iso:country":"CG",
    "name:ceb_x_preferred":[
        "Bangi"
    ],
    "name:deu_x_preferred":[
        "Bangi"
    ],
    "name:fra_x_preferred":[
        "Bangi"
    ],
    "name:por_x_preferred":[
        "Bangi"
    ],
    "name:swe_x_preferred":[
        "Bangi"
    ],
    "wof:name":"Bangi",
    "wof:placetype":"locality"
},
  "geometry": {"coordinates":[17.99861,2.32583],"type":"Point"}
}