{
  "type": "Feature",
  "properties": {
    "gn:admin1_code":"12",
    "gn:asciiname":"Touboula",
    "gn:country_code":"CG",
    "gn:dem":322,
    "gn:feature_class":"P",
    "gn:feature_code":"PPL",
    "gn:name":"Touboula",
    "gn:population":0,
    "gn:timezone":"Africa/Brazzaville",
    "iso:country":"CG",
    "wof:name":"Touboula",
    "wof:placetype":"locality"
},
  "geometry": {"coordinates":[15.13972,-4.36944],"type":"Point"}
}