{
  "type": "Feature",
  "properties": {
    "gn:admin1_code":"04",
    "gn:asciiname":"Loussala",
    "gn:cc2":"CG",
    "gn:country_code":"CG",
    "gn:dem":72,
    "gn:feature_class":"P",
    "gn:feature_code":"PPL",
    "gn:name":"Loussala",
    "gn:population":0,
    "gn:timezone":"Africa/Brazzaville",
    "iso:country":"CG",
    "name:und_x_variant":[
        "Pastorale",
        "Lousala",
        "Loussala"
    ],
    "wof:name":"Loussala",
    "wof:placetype":"locality"
},
  "geometry": {"coordinates":[11.92889,-4.78333],"type":"Point"}
}