{
  "type": "Feature",
  "properties": {
    "gn:admin1_code":"01",
    "gn:asciiname":"Moussoubou",
    "gn:country_code":"CG",
    "gn:dem":295,
    "gn:feature_class":"P",
    "gn:feature_code":"PPL",
    "gn:name":"Moussoubou",
    "gn:population":0,
    "gn:timezone":"Africa/Brazzaville",
    "iso:country":"CG",
    "wof:name":"Moussoubou",
    "wof:placetype":"locality"
},
  "geometry": {"coordinates":[14.11278,-4.12],"type":"Point"}
}