{
  "type": "Feature",
  "properties": {
    "gn:admin1_code":"10",
    "gn:asciiname":"Minguila",
    "gn:country_code":"CG",
    "gn:dem":363,
    "gn:feature_class":"P",
    "gn:feature_code":"PPL",
    "gn:name":"Minguila",
    "gn:population":0,
    "gn:timezone":"Africa/Brazzaville",
    "iso:country":"CG",
    "wof:name":"Minguila",
    "wof:placetype":"locality"
},
  "geometry": {"coordinates":[15.03861,1.97333],"type":"Point"}
}