{
  "type": "Feature",
  "properties": {
    "gn:admin1_code":"01",
    "gn:asciiname":"Moutombo",
    "gn:country_code":"CG",
    "gn:dem":363,
    "gn:feature_class":"P",
    "gn:feature_code":"PPL",
    "gn:name":"Moutombo",
    "gn:population":0,
    "gn:timezone":"Africa/Brazzaville",
    "iso:country":"CG",
    "wof:name":"Moutombo",
    "wof:placetype":"locality"
},
  "geometry": {"coordinates":[13.55333,-3.91111],"type":"Point"}
}