{
  "type": "Feature",
  "properties": {
    "gn:admin1_code":"10",
    "gn:asciiname":"Douma",
    "gn:country_code":"CG",
    "gn:dem":534,
    "gn:feature_class":"P",
    "gn:feature_code":"PPL",
    "gn:name":"Douma",
    "gn:population":0,
    "gn:timezone":"Africa/Brazzaville",
    "iso:country":"CG",
    "wof:name":"Douma",
    "wof:placetype":"locality"
},
  "geometry": {"coordinates":[15.23056,1.57611],"type":"Point"}
}