{
  "type": "Feature",
  "properties": {
    "gn:admin1_code":"10",
    "gn:asciiname":"Douma",
    "gn:country_code":"CG",
    "gn:dem":534,
    "gn:feature_class":"P",
    "gn:feature_code":"PPL",
    "gn:name":"Douma",
    "gn:population":0,
    "gn:timezone":"Africa/Brazzaville",
    "iso:country":"CG",
    "name:ara_x_preferred":[
        "\u062f\u0648\u0645\u0627"
    ],
    "name:ben_x_preferred":[
        "\u09a6\u09cc\u09ae\u09be"
    ],
    "name:ceb_x_preferred":[
        "Douma"
    ],
    "name:deu_x_preferred":[
        "Douma"
    ],
    "name:fra_x_preferred":[
        "Douma"
    ],
    "name:fry_x_preferred":[
        "Douma"
    ],
    "name:heb_x_preferred":[
        "\u05d3\u05d5\u05de\u05d0"
    ],
    "name:hin_x_preferred":[
        "\u0926\u093e\u090a\u092e\u093e"
    ],
    "name:hun_x_preferred":[
        "Douma"
    ],
    "name:kor_x_preferred":[
        "\ub450\ub9c8"
    ],
    "name:nld_x_preferred":[
        "Douma"
    ],
    "name:nno_x_preferred":[
        "Douma"
    ],
    "name:sco_x_preferred":[
        "Douma"
    ],
    "name:swe_x_preferred":[
        "Douma"
    ],
    "wof:name":"Douma",
    "wof:placetype":"locality"
},
  "geometry": {"coordinates":[15.23056,1.57611],"type":"Point"}
}