{
  "type": "Feature",
  "properties": {
    "gn:admin1_code":"14",
    "gn:asciiname":"Letoumbou",
    "gn:country_code":"CG",
    "gn:dem":421,
    "gn:feature_class":"P",
    "gn:feature_code":"PPL",
    "gn:name":"Letoumbou",
    "gn:population":0,
    "gn:timezone":"Africa/Brazzaville",
    "iso:country":"CG",
    "wof:name":"Letoumbou",
    "wof:placetype":"locality"
},
  "geometry": {"coordinates":[14.83694,-0.80417],"type":"Point"}
}