{
  "type": "Feature",
  "properties": {
    "gn:admin1_code":"13",
    "gn:asciiname":"Inguena-Oyako",
    "gn:country_code":"CG",
    "gn:dem":330,
    "gn:feature_class":"P",
    "gn:feature_code":"PPL",
    "gn:name":"Ingu\u00e9na-Oyako",
    "gn:population":0,
    "gn:timezone":"Africa/Brazzaville",
    "iso:country":"CG",
    "wof:name":"Inguena-Oyako",
    "wof:placetype":"locality"
},
  "geometry": {"coordinates":[15.94889,-0.83889],"type":"Point"}
}