{
  "type": "Feature",
  "properties": {
    "gn:admin1_code":"08",
    "gn:asciiname":"Intsiele",
    "gn:country_code":"CG",
    "gn:dem":461,
    "gn:feature_class":"P",
    "gn:feature_code":"PPL",
    "gn:name":"Intsi\u00e9l\u00e9",
    "gn:population":0,
    "gn:timezone":"Africa/Brazzaville",
    "iso:country":"CG",
    "wof:name":"Intsiele",
    "wof:placetype":"locality"
},
  "geometry": {"coordinates":[15.89389,-2.065],"type":"Point"}
}