{
  "type": "Feature",
  "properties": {
    "gn:admin1_code":"11",
    "gn:asciiname":"Makeninga",
    "gn:country_code":"CG",
    "gn:dem":465,
    "gn:feature_class":"P",
    "gn:feature_code":"PPL",
    "gn:name":"Mak\u00e9ninga",
    "gn:population":0,
    "gn:timezone":"Africa/Brazzaville",
    "iso:country":"CG",
    "wof:name":"Makeninga",
    "wof:placetype":"locality"
},
  "geometry": {"coordinates":[14.51222,-3.58083],"type":"Point"}
}