{
  "type": "Feature",
  "properties": {
    "gn:admin1_code":"08",
    "gn:asciiname":"Komo",
    "gn:cc2":"CG",
    "gn:country_code":"CG",
    "gn:dem":372,
    "gn:feature_class":"P",
    "gn:feature_code":"PPL",
    "gn:name":"Komo",
    "gn:population":0,
    "gn:timezone":"Africa/Brazzaville",
    "iso:country":"CG",
    "name:bul_x_preferred":[
        "\u041a\u043e\u043c\u043e"
    ],
    "name:deu_x_preferred":[
        "Komo"
    ],
    "name:fra_x_preferred":[
        "Komo"
    ],
    "name:lav_x_preferred":[
        "Komo"
    ],
    "name:mkd_x_preferred":[
        "\u041a\u043e\u043c\u043e"
    ],
    "name:oss_x_preferred":[
        "\u041a\u043e\u043c\u043e"
    ],
    "name:rus_x_preferred":[
        "\u041a\u043e\u043c\u043e"
    ],
    "name:srp_x_preferred":[
        "\u041a\u043e\u043c\u043e"
    ],
    "name:swe_x_preferred":[
        "Komo"
    ],
    "name:ukr_x_preferred":[
        "\u041a\u043e\u043c\u043e"
    ],
    "name:und_x_variant":[
        "Como"
    ],
    "wof:name":"Komo",
    "wof:placetype":"locality"
},
  "geometry": {"coordinates":[15.64389,-1.38417],"type":"Point"}
}