{
  "type": "Feature",
  "properties": {
    "gn:admin1_code":"10",
    "gn:asciiname":"Mopouma",
    "gn:country_code":"CG",
    "gn:dem":351,
    "gn:feature_class":"P",
    "gn:feature_code":"PPL",
    "gn:name":"Mopouma",
    "gn:population":0,
    "gn:timezone":"Africa/Brazzaville",
    "iso:country":"CG",
    "wof:name":"Mopouma",
    "wof:placetype":"locality"
},
  "geometry": {"coordinates":[16.15667,1.71583],"type":"Point"}
}