{
  "type": "Feature",
  "properties": {
    "gn:admin1_code":"01",
    "gn:asciiname":"Kimbinda",
    "gn:country_code":"CG",
    "gn:dem":652,
    "gn:feature_class":"P",
    "gn:feature_code":"PPL",
    "gn:name":"Kimbinda",
    "gn:population":0,
    "gn:timezone":"Africa/Brazzaville",
    "iso:country":"CG",
    "wof:name":"Kimbinda",
    "wof:placetype":"locality"
},
  "geometry": {"coordinates":[13.71389,-4.52667],"type":"Point"}
}