{
  "type": "Feature",
  "properties": {
    "gn:admin1_code":"13",
    "gn:asciiname":"Boundji",
    "gn:country_code":"CG",
    "gn:dem":311,
    "gn:feature_class":"P",
    "gn:feature_code":"PPL",
    "gn:name":"Boundji",
    "gn:population":0,
    "gn:timezone":"Africa/Brazzaville",
    "iso:country":"CG",
    "name:fra_x_preferred":[
        "Boundji"
    ],
    "name:pol_x_preferred":[
        "Boundji"
    ],
    "name:urd_x_preferred":[
        "\u0628\u0624\u0646\u062c\u06cc"
    ],
    "wof:name":"Boundji",
    "wof:placetype":"locality"
},
  "geometry": {"coordinates":[16.26556,-1.28472],"type":"Point"}
}