{
  "type": "Feature",
  "properties": {
    "gn:admin1_code":"04",
    "gn:asciiname":"Patra",
    "gn:country_code":"CG",
    "gn:dem":90,
    "gn:feature_class":"P",
    "gn:feature_code":"PPL",
    "gn:name":"Patra",
    "gn:population":0,
    "gn:timezone":"Africa/Brazzaville",
    "iso:country":"CG",
    "name:ceb_x_preferred":[
        "Patra"
    ],
    "name:fra_x_preferred":[
        "Patra"
    ],
    "name:nld_x_preferred":[
        "Patra"
    ],
    "wof:name":"Patra",
    "wof:placetype":"locality"
},
  "geometry": {"coordinates":[11.9525,-4.73306],"type":"Point"}
}