{
  "type": "Feature",
  "properties": {
    "gn:admin1_code":"08",
    "gn:asciiname":"Bandzounou",
    "gn:country_code":"CG",
    "gn:dem":839,
    "gn:feature_class":"P",
    "gn:feature_code":"PPL",
    "gn:name":"Bandzounou",
    "gn:population":0,
    "gn:timezone":"Africa/Brazzaville",
    "iso:country":"CG",
    "wof:name":"Bandzounou",
    "wof:placetype":"locality"
},
  "geometry": {"coordinates":[14.49167,-2.43861],"type":"Point"}
}