{
  "type": "Feature",
  "properties": {
    "gn:admin1_code":"12",
    "gn:asciiname":"Ikouri",
    "gn:country_code":"CG",
    "gn:dem":660,
    "gn:feature_class":"P",
    "gn:feature_code":"PPL",
    "gn:name":"Ikouri",
    "gn:population":0,
    "gn:timezone":"Africa/Brazzaville",
    "iso:country":"CG",
    "wof:name":"Ikouri",
    "wof:placetype":"locality"
},
  "geometry": {"coordinates":[15.68306,-3.90611],"type":"Point"}
}