{
  "type": "Feature",
  "properties": {
    "gn:admin1_code":"13",
    "gn:asciiname":"Kantse",
    "gn:country_code":"CG",
    "gn:dem":428,
    "gn:feature_class":"P",
    "gn:feature_code":"PPL",
    "gn:name":"Kants\u00e9",
    "gn:population":0,
    "gn:timezone":"Africa/Brazzaville",
    "iso:country":"CG",
    "wof:name":"Kantse",
    "wof:placetype":"locality"
},
  "geometry": {"coordinates":[15.04417,-1.49056],"type":"Point"}
}