{
  "type": "Feature",
  "properties": {
    "gn:admin1_code":"14",
    "gn:asciiname":"Olonga",
    "gn:country_code":"CG",
    "gn:dem":413,
    "gn:feature_class":"P",
    "gn:feature_code":"PPL",
    "gn:name":"Olonga",
    "gn:population":0,
    "gn:timezone":"Africa/Brazzaville",
    "iso:country":"CG",
    "name:und_x_variant":[
        "Elounga",
        "Olonga"
    ],
    "wof:name":"Olonga",
    "wof:placetype":"locality"
},
  "geometry": {"coordinates":[14.71778,-0.72639],"type":"Point"}
}