{
  "type": "Feature",
  "properties": {
    "gn:admin1_code":"07",
    "gn:asciiname":"Mousaou",
    "gn:country_code":"CG",
    "gn:dem":572,
    "gn:feature_class":"P",
    "gn:feature_code":"PPL",
    "gn:name":"Mousaou",
    "gn:population":0,
    "gn:timezone":"Africa/Brazzaville",
    "iso:country":"CG",
    "wof:name":"Mousaou",
    "wof:placetype":"locality"
},
  "geometry": {"coordinates":[12.59583,-2.70472],"type":"Point"}
}