{
  "type": "Feature",
  "properties": {
    "gn:admin1_code":"13",
    "gn:asciiname":"Bobongo",
    "gn:country_code":"CG",
    "gn:dem":298,
    "gn:feature_class":"P",
    "gn:feature_code":"PPL",
    "gn:name":"Bobongo",
    "gn:population":0,
    "gn:timezone":"Africa/Brazzaville",
    "iso:country":"CG",
    "wof:name":"Bobongo",
    "wof:placetype":"locality"
},
  "geometry": {"coordinates":[16.57667,-1.17806],"type":"Point"}
}