{
  "type": "Feature",
  "properties": {
    "gn:admin1_code":"05",
    "gn:asciiname":"Osiba",
    "gn:country_code":"CG",
    "gn:dem":454,
    "gn:feature_class":"P",
    "gn:feature_code":"PPL",
    "gn:name":"Osiba",
    "gn:population":0,
    "gn:timezone":"Africa/Brazzaville",
    "iso:country":"CG",
    "wof:name":"Osiba",
    "wof:placetype":"locality"
},
  "geometry": {"coordinates":[13.24389,-3.31222],"type":"Point"}
}