{
  "type": "Feature",
  "properties": {
    "gn:admin1_code":"08",
    "gn:asciiname":"Etiene",
    "gn:cc2":"CG",
    "gn:country_code":"CG",
    "gn:dem":626,
    "gn:feature_class":"P",
    "gn:feature_code":"PPL",
    "gn:name":"Eti\u00e9n\u00e9",
    "gn:population":0,
    "gn:timezone":"Africa/Brazzaville",
    "iso:country":"CG",
    "name:und_x_variant":[
        "Eti\u00e9me",
        "Eti\u00e9n\u00e9"
    ],
    "wof:name":"Etiene",
    "wof:placetype":"locality"
},
  "geometry": {"coordinates":[15.79222,-2.47444],"type":"Point"}
}