{
  "type": "Feature",
  "properties": {
    "gn:admin1_code":"08",
    "gn:asciiname":"Leketi",
    "gn:cc2":"CG",
    "gn:country_code":"CG",
    "gn:dem":367,
    "gn:feature_class":"P",
    "gn:feature_code":"PPL",
    "gn:name":"L\u00e9k\u00e9ti",
    "gn:population":0,
    "gn:timezone":"Africa/Brazzaville",
    "iso:country":"CG",
    "name:und_x_variant":[
        "Lekety",
        "L\u00e9kita",
        "L\u00e9k\u00e9ti"
    ],
    "wof:name":"Leketi",
    "wof:placetype":"locality"
},
  "geometry": {"coordinates":[14.95556,-1.59333],"type":"Point"}
}