{
  "type": "Feature",
  "properties": {
    "gn:admin1_code":"11",
    "gn:asciiname":"Mbanba I",
    "gn:country_code":"CG",
    "gn:dem":513,
    "gn:feature_class":"P",
    "gn:feature_code":"PPL",
    "gn:name":"Mbanba I",
    "gn:population":0,
    "gn:timezone":"Africa/Brazzaville",
    "iso:country":"CG",
    "wof:name":"Mbanba I",
    "wof:placetype":"locality"
},
  "geometry": {"coordinates":[14.41472,-3.45417],"type":"Point"}
}