{
  "type": "Feature",
  "properties": {
    "gn:admin1_code":"11",
    "gn:asciiname":"Ohoue",
    "gn:country_code":"CG",
    "gn:dem":675,
    "gn:feature_class":"P",
    "gn:feature_code":"PPL",
    "gn:name":"Ohou\u00e9",
    "gn:population":0,
    "gn:timezone":"Africa/Brazzaville",
    "iso:country":"CG",
    "wof:name":"Ohoue",
    "wof:placetype":"locality"
},
  "geometry": {"coordinates":[15.57,-3.32556],"type":"Point"}
}