{
  "type": "Feature",
  "properties": {
    "gn:admin1_code":"07",
    "gn:asciiname":"Mouyabi",
    "gn:country_code":"CG",
    "gn:dem":462,
    "gn:feature_class":"P",
    "gn:feature_code":"PPL",
    "gn:name":"Mouyabi",
    "gn:population":0,
    "gn:timezone":"Africa/Brazzaville",
    "iso:country":"CG",
    "wof:name":"Mouyabi",
    "wof:placetype":"locality"
},
  "geometry": {"coordinates":[12.87528,-3.09139],"type":"Point"}
}