{
  "type": "Feature",
  "properties": {
    "gn:admin1_code":"08",
    "gn:asciiname":"Emonpibi",
    "gn:country_code":"CG",
    "gn:dem":841,
    "gn:feature_class":"P",
    "gn:feature_code":"PPL",
    "gn:name":"Emonpibi",
    "gn:population":0,
    "gn:timezone":"Africa/Brazzaville",
    "iso:country":"CG",
    "wof:name":"Emonpibi",
    "wof:placetype":"locality"
},
  "geometry": {"coordinates":[14.46889,-2.42361],"type":"Point"}
}