{
  "type": "Feature",
  "properties": {
    "gn:admin1_code":"11",
    "gn:asciiname":"Mikoudi",
    "gn:country_code":"CG",
    "gn:dem":377,
    "gn:feature_class":"P",
    "gn:feature_code":"PPL",
    "gn:name":"Mikoudi",
    "gn:population":0,
    "gn:timezone":"Africa/Brazzaville",
    "iso:country":"CG",
    "wof:name":"Mikoudi",
    "wof:placetype":"locality"
},
  "geometry": {"coordinates":[14.89639,-4.29222],"type":"Point"}
}