{
  "type": "Feature",
  "properties": {
    "gn:admin1_code":"05",
    "gn:asciiname":"Kongoulou",
    "gn:country_code":"CG",
    "gn:dem":535,
    "gn:feature_class":"P",
    "gn:feature_code":"PPL",
    "gn:name":"Kongoulou",
    "gn:population":0,
    "gn:timezone":"Africa/Brazzaville",
    "iso:country":"CG",
    "wof:name":"Kongoulou",
    "wof:placetype":"locality"
},
  "geometry": {"coordinates":[13.31806,-3.72583],"type":"Point"}
}