{
  "type": "Feature",
  "properties": {
    "gn:admin1_code":"11",
    "gn:asciiname":"Nzomo",
    "gn:country_code":"CG",
    "gn:dem":550,
    "gn:feature_class":"P",
    "gn:feature_code":"PPL",
    "gn:name":"Nzomo",
    "gn:population":0,
    "gn:timezone":"Africa/Brazzaville",
    "iso:country":"CG",
    "wof:name":"Nzomo",
    "wof:placetype":"locality"
},
  "geometry": {"coordinates":[14.20667,-3.3075],"type":"Point"}
}