{
  "type": "Feature",
  "properties": {
    "gn:admin1_code":"14",
    "gn:asciiname":"Sembe",
    "gn:country_code":"CG",
    "gn:dem":426,
    "gn:feature_class":"P",
    "gn:feature_code":"PPL",
    "gn:name":"Semb\u00e9",
    "gn:population":0,
    "gn:timezone":"Africa/Brazzaville",
    "iso:country":"CG",
    "wof:name":"Sembe",
    "wof:placetype":"locality"
},
  "geometry": {"coordinates":[14.63861,0.60083],"type":"Point"}
}