{
  "type": "Feature",
  "properties": {
    "gn:admin1_code":"08",
    "gn:asciiname":"Eyoulou",
    "gn:country_code":"CG",
    "gn:dem":439,
    "gn:feature_class":"P",
    "gn:feature_code":"PPL",
    "gn:name":"Eyoulou",
    "gn:population":0,
    "gn:timezone":"Africa/Brazzaville",
    "iso:country":"CG",
    "wof:name":"Eyoulou",
    "wof:placetype":"locality"
},
  "geometry": {"coordinates":[15.56417,-1.44528],"type":"Point"}
}