{
  "type": "Feature",
  "properties": {
    "gn:admin1_code":"08",
    "gn:asciiname":"Yaba",
    "gn:cc2":"CG",
    "gn:country_code":"CG",
    "gn:dem":402,
    "gn:feature_class":"P",
    "gn:feature_code":"PPL",
    "gn:name":"Yaba",
    "gn:population":0,
    "gn:timezone":"Africa/Brazzaville",
    "iso:country":"CG",
    "name:und_x_variant":[
        "Yaba I",
        "Yaba"
    ],
    "wof:name":"Yaba",
    "wof:placetype":"locality"
},
  "geometry": {"coordinates":[15.7925,-1.70694],"type":"Point"}
}