{
  "type": "Feature",
  "properties": {
    "gn:admin1_code":"13",
    "gn:asciiname":"Obana",
    "gn:country_code":"CG",
    "gn:dem":479,
    "gn:feature_class":"P",
    "gn:feature_code":"PPL",
    "gn:name":"Obana",
    "gn:population":0,
    "gn:timezone":"Africa/Brazzaville",
    "iso:country":"CG",
    "wof:name":"Obana",
    "wof:placetype":"locality"
},
  "geometry": {"coordinates":[14.74694,-1.19222],"type":"Point"}
}