{
  "type": "Feature",
  "properties": {
    "gn:admin1_code":"04",
    "gn:asciiname":"Kakatielo",
    "gn:country_code":"CG",
    "gn:dem":36,
    "gn:feature_class":"P",
    "gn:feature_code":"PPL",
    "gn:name":"Kakati\u00e9lo",
    "gn:population":0,
    "gn:timezone":"Africa/Brazzaville",
    "iso:country":"CG",
    "wof:name":"Kakatielo",
    "wof:placetype":"locality"
},
  "geometry": {"coordinates":[11.82333,-4.28083],"type":"Point"}
}