{
  "type": "Feature",
  "properties": {
    "gn:admin1_code":"07",
    "gn:asciiname":"Nzima",
    "gn:cc2":"CG",
    "gn:country_code":"CG",
    "gn:dem":578,
    "gn:feature_class":"P",
    "gn:feature_code":"PPL",
    "gn:name":"Nzima",
    "gn:population":0,
    "gn:timezone":"Africa/Brazzaville",
    "iso:country":"CG",
    "name:und_x_variant":[
        "Zima",
        "Nzima"
    ],
    "wof:name":"Nzima",
    "wof:placetype":"locality"
},
  "geometry": {"coordinates":[12.70028,-2.61694],"type":"Point"}
}