{
  "type": "Feature",
  "properties": {
    "gn:admin1_code":"07",
    "gn:asciiname":"Loussouogou",
    "gn:country_code":"CG",
    "gn:dem":267,
    "gn:feature_class":"P",
    "gn:feature_code":"PPL",
    "gn:name":"Loussouogou",
    "gn:population":0,
    "gn:timezone":"Africa/Brazzaville",
    "iso:country":"CG",
    "wof:name":"Loussouogou",
    "wof:placetype":"locality"
},
  "geometry": {"coordinates":[12.55,-3.31667],"type":"Point"}
}