{
  "type": "Feature",
  "properties": {
    "gn:admin1_code":"01",
    "gn:asciiname":"Kimpolo I",
    "gn:country_code":"CG",
    "gn:dem":563,
    "gn:feature_class":"P",
    "gn:feature_code":"PPL",
    "gn:name":"Kimpolo I",
    "gn:population":0,
    "gn:timezone":"Africa/Brazzaville",
    "iso:country":"CG",
    "wof:name":"Kimpolo I",
    "wof:placetype":"locality"
},
  "geometry": {"coordinates":[14.09028,-3.5975],"type":"Point"}
}