{
  "type": "Feature",
  "properties": {
    "gn:admin1_code":"14",
    "gn:asciiname":"Bomo",
    "gn:country_code":"CG",
    "gn:dem":532,
    "gn:feature_class":"P",
    "gn:feature_code":"PPL",
    "gn:name":"Bomo",
    "gn:population":0,
    "gn:timezone":"Africa/Brazzaville",
    "iso:country":"CG",
    "wof:name":"Bomo",
    "wof:placetype":"locality"
},
  "geometry": {"coordinates":[14.39194,0.55778],"type":"Point"}
}