{
  "type": "Feature",
  "properties": {
    "gn:admin1_code":"01",
    "gn:asciiname":"Nsanga",
    "gn:country_code":"CG",
    "gn:dem":213,
    "gn:feature_class":"P",
    "gn:feature_code":"PPL",
    "gn:name":"Nsanga",
    "gn:population":0,
    "gn:timezone":"Africa/Brazzaville",
    "iso:country":"CG",
    "wof:name":"Nsanga",
    "wof:placetype":"locality"
},
  "geometry": {"coordinates":[13.62639,-4.23389],"type":"Point"}
}