{
  "type": "Feature",
  "properties": {
    "gn:admin1_code":"13",
    "gn:asciiname":"Boyenngue",
    "gn:cc2":"CG",
    "gn:country_code":"CG",
    "gn:dem":313,
    "gn:feature_class":"P",
    "gn:feature_code":"PPL",
    "gn:name":"Boyenngu\u00e9",
    "gn:population":0,
    "gn:timezone":"Africa/Brazzaville",
    "iso:country":"CG",
    "name:und_x_variant":[
        "Boyengh\u00e9",
        "Bayengu\u00e9",
        "Boyengu\u00e9",
        "Boyenngu\u00e9"
    ],
    "wof:name":"Boyenngue",
    "wof:placetype":"locality"
},
  "geometry": {"coordinates":[17.20333,-0.83167],"type":"Point"}
}