{
  "type": "Feature",
  "properties": {
    "gn:admin1_code":"10",
    "gn:asciiname":"Assoumoundele",
    "gn:cc2":"CG",
    "gn:country_code":"CG",
    "gn:dem":573,
    "gn:feature_class":"P",
    "gn:feature_code":"PPL",
    "gn:name":"Assoumound\u00e9l\u00e9",
    "gn:population":0,
    "gn:timezone":"Africa/Brazzaville",
    "iso:country":"CG",
    "name:und_x_variant":[
        "Assound\u00e9l\u00e9",
        "Assoumound\u00e9l\u00e9"
    ],
    "wof:name":"Assoumoundele",
    "wof:placetype":"locality"
},
  "geometry": {"coordinates":[14.53583,1.61972],"type":"Point"}
}