{
  "type": "Feature",
  "properties": {
    "gn:admin1_code":"07",
    "gn:asciiname":"Mayoko-Bakota",
    "gn:country_code":"CG",
    "gn:dem":652,
    "gn:feature_class":"P",
    "gn:feature_code":"PPL",
    "gn:name":"Mayoko-Bakota",
    "gn:population":0,
    "gn:timezone":"Africa/Brazzaville",
    "iso:country":"CG",
    "wof:name":"Mayoko-Bakota",
    "wof:placetype":"locality"
},
  "geometry": {"coordinates":[12.7975,-2.325],"type":"Point"}
}