{
  "type": "Feature",
  "properties": {
    "gn:admin1_code":"11",
    "gn:asciiname":"Mangola I",
    "gn:cc2":"CG",
    "gn:country_code":"CG",
    "gn:dem":282,
    "gn:feature_class":"P",
    "gn:feature_code":"PPL",
    "gn:name":"Mangola I",
    "gn:population":0,
    "gn:timezone":"Africa/Brazzaville",
    "iso:country":"CG",
    "name:und_x_variant":[
        "Mangola",
        "Mangola I"
    ],
    "wof:name":"Mangola I",
    "wof:placetype":"locality"
},
  "geometry": {"coordinates":[14.14,-4.28444],"type":"Point"}
}