{
  "type": "Feature",
  "properties": {
    "gn:admin1_code":"11",
    "gn:asciiname":"Matzouele",
    "gn:country_code":"CG",
    "gn:dem":474,
    "gn:feature_class":"P",
    "gn:feature_code":"PPL",
    "gn:name":"Matzou\u00e9l\u00e9",
    "gn:population":0,
    "gn:timezone":"Africa/Brazzaville",
    "iso:country":"CG",
    "wof:name":"Matzouele",
    "wof:placetype":"locality"
},
  "geometry": {"coordinates":[14.57111,-3.71472],"type":"Point"}
}