{
  "type": "Feature",
  "properties": {
    "gn:admin1_code":"01",
    "gn:asciiname":"Mousasi",
    "gn:country_code":"CG",
    "gn:dem":203,
    "gn:feature_class":"P",
    "gn:feature_code":"PPL",
    "gn:name":"Mousasi",
    "gn:population":0,
    "gn:timezone":"Africa/Brazzaville",
    "iso:country":"CG",
    "wof:name":"Mousasi",
    "wof:placetype":"locality"
},
  "geometry": {"coordinates":[13.83194,-4.25917],"type":"Point"}
}