{
  "type": "Feature",
  "properties": {
    "gn:admin1_code":"06",
    "gn:asciiname":"Bokale",
    "gn:country_code":"CG",
    "gn:dem":310,
    "gn:feature_class":"P",
    "gn:feature_code":"PPL",
    "gn:name":"Bokal\u00e9",
    "gn:population":0,
    "gn:timezone":"Africa/Brazzaville",
    "iso:country":"CG",
    "wof:name":"Bokale",
    "wof:placetype":"locality"
},
  "geometry": {"coordinates":[17.38778,1.1825],"type":"Point"}
}