{
  "type": "Feature",
  "properties": {
    "gn:admin1_code":"13",
    "gn:asciiname":"Okona",
    "gn:cc2":"CG",
    "gn:country_code":"CG",
    "gn:dem":341,
    "gn:feature_class":"P",
    "gn:feature_code":"PPL",
    "gn:name":"Okona",
    "gn:population":0,
    "gn:timezone":"Africa/Brazzaville",
    "iso:country":"CG",
    "name:und_x_variant":[
        "Okouna",
        "Okona"
    ],
    "wof:name":"Okona",
    "wof:placetype":"locality"
},
  "geometry": {"coordinates":[15.58361,-0.91139],"type":"Point"}
}