{
  "type": "Feature",
  "properties": {
    "gn:admin1_code":"05",
    "gn:asciiname":"Moudoumou",
    "gn:country_code":"CG",
    "gn:dem":471,
    "gn:feature_class":"P",
    "gn:feature_code":"PPL",
    "gn:name":"Moudoumou",
    "gn:population":0,
    "gn:timezone":"Africa/Brazzaville",
    "iso:country":"CG",
    "wof:name":"Moudoumou",
    "wof:placetype":"locality"
},
  "geometry": {"coordinates":[13.15,-3.01667],"type":"Point"}
}