{
  "type": "Feature",
  "properties": {
    "gn:admin1_code":"07",
    "gn:asciiname":"Mouvendze",
    "gn:country_code":"CG",
    "gn:dem":418,
    "gn:feature_class":"P",
    "gn:feature_code":"PPL",
    "gn:name":"Mouvendz\u00e9",
    "gn:population":0,
    "gn:timezone":"Africa/Brazzaville",
    "iso:country":"CG",
    "wof:name":"Mouvendze",
    "wof:placetype":"locality"
},
  "geometry": {"coordinates":[12.69417,-2.93417],"type":"Point"}
}