{
  "type": "Feature",
  "properties": {
    "gn:admin1_code":"13",
    "gn:asciiname":"Matoko",
    "gn:country_code":"CG",
    "gn:dem":294,
    "gn:feature_class":"P",
    "gn:feature_code":"PPL",
    "gn:name":"Matoko",
    "gn:population":0,
    "gn:timezone":"Africa/Brazzaville",
    "iso:country":"CG",
    "wof:name":"Matoko",
    "wof:placetype":"locality"
},
  "geometry": {"coordinates":[17.30972,-0.95167],"type":"Point"}
}