{
  "type": "Feature",
  "properties": {
    "gn:admin1_code":"08",
    "gn:asciiname":"Ongoye",
    "gn:country_code":"CG",
    "gn:dem":413,
    "gn:feature_class":"P",
    "gn:feature_code":"PPL",
    "gn:name":"Ongoye",
    "gn:population":0,
    "gn:timezone":"Africa/Brazzaville",
    "iso:country":"CG",
    "wof:name":"Ongoye",
    "wof:placetype":"locality"
},
  "geometry": {"coordinates":[15.54917,-1.60056],"type":"Point"}
}