{
  "type": "Feature",
  "properties": {
    "gn:admin1_code":"04",
    "gn:asciiname":"Tchimpila",
    "gn:country_code":"CG",
    "gn:dem":139,
    "gn:feature_class":"P",
    "gn:feature_code":"PPL",
    "gn:name":"Tchimpila",
    "gn:population":0,
    "gn:timezone":"Africa/Brazzaville",
    "iso:country":"CG",
    "wof:name":"Tchimpila",
    "wof:placetype":"locality"
},
  "geometry": {"coordinates":[11.86528,-4.6275],"type":"Point"}
}