{
  "type": "Feature",
  "properties": {
    "gn:admin1_code":"05",
    "gn:asciiname":"Lefoutou",
    "gn:country_code":"CG",
    "gn:dem":614,
    "gn:feature_class":"P",
    "gn:feature_code":"PPL",
    "gn:name":"L\u00e9foutou",
    "gn:population":0,
    "gn:timezone":"Africa/Brazzaville",
    "iso:country":"CG",
    "wof:name":"Lefoutou",
    "wof:placetype":"locality"
},
  "geometry": {"coordinates":[13.60194,-2.81917],"type":"Point"}
}