{
  "type": "Feature",
  "properties": {
    "gn:admin1_code":"10",
    "gn:asciiname":"Kelembele",
    "gn:country_code":"CG",
    "gn:dem":466,
    "gn:feature_class":"P",
    "gn:feature_code":"PPL",
    "gn:name":"Kelemb\u00e9l\u00e9",
    "gn:population":0,
    "gn:timezone":"Africa/Brazzaville",
    "iso:country":"CG",
    "wof:name":"Kelembele",
    "wof:placetype":"locality"
},
  "geometry": {"coordinates":[15.84556,1.52389],"type":"Point"}
}