{
  "type": "Feature",
  "properties": {
    "gn:admin1_code":"12",
    "gn:asciiname":"Samba",
    "gn:country_code":"CG",
    "gn:dem":284,
    "gn:feature_class":"P",
    "gn:feature_code":"PPL",
    "gn:name":"Samba",
    "gn:population":0,
    "gn:timezone":"Africa/Brazzaville",
    "iso:country":"CG",
    "wof:name":"Samba",
    "wof:placetype":"locality"
},
  "geometry": {"coordinates":[15.19778,-4.26],"type":"Point"}
}