{
  "type": "Feature",
  "properties": {
    "gn:admin1_code":"11",
    "gn:asciiname":"Miango",
    "gn:cc2":"CG",
    "gn:country_code":"CG",
    "gn:dem":470,
    "gn:feature_class":"P",
    "gn:feature_code":"PPL",
    "gn:name":"Miango",
    "gn:population":0,
    "gn:timezone":"Africa/Brazzaville",
    "iso:country":"CG",
    "name:und_x_variant":[
        "M\u00e9ango",
        "Moango",
        "Miango"
    ],
    "wof:name":"Miango",
    "wof:placetype":"locality"
},
  "geometry": {"coordinates":[14.59917,-3.01694],"type":"Point"}
}