{
  "type": "Feature",
  "properties": {
    "gn:admin1_code":"11",
    "gn:asciiname":"Kouaka",
    "gn:country_code":"CG",
    "gn:dem":331,
    "gn:feature_class":"P",
    "gn:feature_code":"PPL",
    "gn:name":"Kouaka",
    "gn:population":0,
    "gn:timezone":"Africa/Brazzaville",
    "iso:country":"CG",
    "wof:name":"Kouaka",
    "wof:placetype":"locality"
},
  "geometry": {"coordinates":[14.2925,-4.22917],"type":"Point"}
}