{
  "type": "Feature",
  "properties": {
    "gn:admin1_code":"14",
    "gn:asciiname":"Boulou",
    "gn:country_code":"CG",
    "gn:dem":492,
    "gn:feature_class":"P",
    "gn:feature_code":"PPL",
    "gn:name":"Boulou",
    "gn:population":0,
    "gn:timezone":"Africa/Brazzaville",
    "iso:country":"CG",
    "wof:name":"Boulou",
    "wof:placetype":"locality"
},
  "geometry": {"coordinates":[14.53,-0.90472],"type":"Point"}
}