{
  "type": "Feature",
  "properties": {
    "gn:admin1_code":"05",
    "gn:asciiname":"Ondama",
    "gn:country_code":"CG",
    "gn:dem":598,
    "gn:feature_class":"P",
    "gn:feature_code":"PPL",
    "gn:name":"Ondama",
    "gn:population":0,
    "gn:timezone":"Africa/Brazzaville",
    "iso:country":"CG",
    "wof:name":"Ondama",
    "wof:placetype":"locality"
},
  "geometry": {"coordinates":[13.86583,-2.94694],"type":"Point"}
}