{
  "type": "Feature",
  "properties": {
    "gn:admin1_code":"04",
    "gn:asciiname":"Boukagni Dilou",
    "gn:country_code":"CG",
    "gn:dem":211,
    "gn:feature_class":"P",
    "gn:feature_code":"PPL",
    "gn:name":"Boukagni Dilou",
    "gn:population":0,
    "gn:timezone":"Africa/Brazzaville",
    "iso:country":"CG",
    "wof:name":"Boukagni Dilou",
    "wof:placetype":"locality"
},
  "geometry": {"coordinates":[12.04833,-4.03472],"type":"Point"}
}