{
  "type": "Feature",
  "properties": {
    "gn:admin1_code":"11",
    "gn:asciiname":"Kinkousou II",
    "gn:country_code":"CG",
    "gn:dem":454,
    "gn:feature_class":"P",
    "gn:feature_code":"PPL",
    "gn:name":"Kinkousou II",
    "gn:population":0,
    "gn:timezone":"Africa/Brazzaville",
    "iso:country":"CG",
    "wof:name":"Kinkousou II",
    "wof:placetype":"locality"
},
  "geometry": {"coordinates":[14.71639,-3.99778],"type":"Point"}
}