{
  "type": "Feature",
  "properties": {
    "gn:admin1_code":"14",
    "gn:asciiname":"Okondo",
    "gn:country_code":"CG",
    "gn:dem":396,
    "gn:feature_class":"P",
    "gn:feature_code":"PPL",
    "gn:name":"Okondo",
    "gn:population":0,
    "gn:timezone":"Africa/Brazzaville",
    "iso:country":"CG",
    "wof:name":"Okondo",
    "wof:placetype":"locality"
},
  "geometry": {"coordinates":[15.11333,-0.83361],"type":"Point"}
}