{
  "type": "Feature",
  "properties": {
    "gn:admin1_code":"01",
    "gn:asciiname":"Kinga",
    "gn:country_code":"CG",
    "gn:dem":544,
    "gn:feature_class":"P",
    "gn:feature_code":"PPL",
    "gn:name":"Kinga",
    "gn:population":0,
    "gn:timezone":"Africa/Brazzaville",
    "iso:country":"CG",
    "name:ceb_x_preferred":[
        "Kinga"
    ],
    "name:deu_x_preferred":[
        "Kinga"
    ],
    "name:fra_x_preferred":[
        "Kinga"
    ],
    "name:swe_x_preferred":[
        "Kinga"
    ],
    "wof:name":"Kinga",
    "wof:placetype":"locality"
},
  "geometry": {"coordinates":[14.11111,-3.52167],"type":"Point"}
}