{
  "type": "Feature",
  "properties": {
    "gn:admin1_code":"07",
    "gn:asciiname":"Doumanga",
    "gn:country_code":"CG",
    "gn:dem":563,
    "gn:feature_class":"P",
    "gn:feature_code":"PPL",
    "gn:name":"Doumanga",
    "gn:population":0,
    "gn:timezone":"Africa/Brazzaville",
    "iso:country":"CG",
    "wof:name":"Doumanga",
    "wof:placetype":"locality"
},
  "geometry": {"coordinates":[12.67111,-2.68194],"type":"Point"}
}