{
  "type": "Feature",
  "properties": {
    "gn:admin1_code":"07",
    "gn:asciiname":"Nianga",
    "gn:cc2":"CG",
    "gn:country_code":"CG",
    "gn:dem":446,
    "gn:feature_class":"P",
    "gn:feature_code":"PPL",
    "gn:name":"Nianga",
    "gn:population":0,
    "gn:timezone":"Africa/Brazzaville",
    "iso:country":"CG",
    "name:und_x_variant":[
        "Nyanga",
        "Nianga"
    ],
    "wof:name":"Nianga",
    "wof:placetype":"locality"
},
  "geometry": {"coordinates":[12.93472,-3.16583],"type":"Point"}
}