{
  "type": "Feature",
  "properties": {
    "gn:admin1_code":"11",
    "gn:asciiname":"Pie",
    "gn:country_code":"CG",
    "gn:dem":667,
    "gn:feature_class":"P",
    "gn:feature_code":"PPL",
    "gn:name":"Pi\u00e9",
    "gn:population":0,
    "gn:timezone":"Africa/Brazzaville",
    "iso:country":"CG",
    "name:ara_x_preferred":[
        "\u0641\u0637\u064a\u0631\u0629"
    ],
    "name:bak_x_preferred":[
        "\u0411\u04d9\u043b\u0435\u0448"
    ],
    "name:bel_x_preferred":[
        "\u041f\u0456\u0440\u043e\u0433"
    ],
    "name:cym_x_preferred":[
        "Pei"
    ],
    "name:dan_x_preferred":[
        "Pie"
    ],
    "name:est_x_preferred":[
        "Pirukas"
    ],
    "name:fas_x_preferred":[
        "\u067e\u0627\u06cc"
    ],
    "name:fin_x_preferred":[
        "Piirakka"
    ],
    "name:fra_x_preferred":[
        "Tourte"
    ],
    "name:gla_x_preferred":[
        "P\u00e0idh"
    ],
    "name:gle_x_preferred":[
        "Pi\u00f3g"
    ],
    "name:heb_x_preferred":[
        "\u05e4\u05d0\u05d9"
    ],
    "name:hrv_x_preferred":[
        "Pita"
    ],
    "name:ido_x_preferred":[
        "Torto"
    ],
    "name:ind_x_preferred":[
        "Pastei"
    ],
    "name:isl_x_preferred":[
        "Baka"
    ],
    "name:kan_x_preferred":[
        "\u0caa\u0cc8"
    ],
    "name:lat_x_preferred":[
        "Crustum"
    ],
    "name:mkd_x_preferred":[
        "\u041f\u0438\u0442\u0430"
    ],
    "name:nld_x_preferred":[
        "Pastei"
    ],
    "name:nno_x_preferred":[
        "Pai"
    ],
    "name:nor_x_preferred":[
        "Pai"
    ],
    "name:nrm_x_preferred":[
        "P\u00e2t\u00e9"
    ],
    "name:oci_x_preferred":[
        "Torta"
    ],
    "name:pan_x_preferred":[
        "\u0a2a\u0a3e\u0a08"
    ],
    "name:por_x_preferred":[
        "Torta"
    ],
    "name:rus_x_preferred":[
        "\u041f\u0438\u0440\u043e\u0433"
    ],
    "name:sco_x_preferred":[
        "Pie"
    ],
    "name:srp_x_preferred":[
        "\u041f\u0438\u0442\u0430"
    ],
    "name:swe_x_preferred":[
        "Paj"
    ],
    "name:tat_x_preferred":[
        "\u0411\u04d9\u043b\u0435\u0448"
    ],
    "name:tha_x_preferred":[
        "\u0e1e\u0e32\u0e22"
    ],
    "name:tur_x_preferred":[
        "Turta"
    ],
    "name:ukr_x_preferred":[
        "\u041f\u0438\u0440\u0456\u0433"
    ],
    "name:vie_x_preferred":[
        "Pie"
    ],
    "name:zho_x_preferred":[
        "\u897f\u5f0f\u9921\u9905"
    ],
    "wof:name":"Pie",
    "wof:placetype":"locality"
},
  "geometry": {"coordinates":[15.66028,-3.07528],"type":"Point"}
}