{
  "type": "Feature",
  "properties": {
    "gn:admin1_code":"11",
    "gn:asciiname":"Pie",
    "gn:country_code":"CG",
    "gn:dem":667,
    "gn:feature_class":"P",
    "gn:feature_code":"PPL",
    "gn:name":"Pi\u00e9",
    "gn:population":0,
    "gn:timezone":"Africa/Brazzaville",
    "iso:country":"CG",
    "wof:name":"Pie",
    "wof:placetype":"locality"
},
  "geometry": {"coordinates":[15.66028,-3.07528],"type":"Point"}
}