{
  "type": "Feature",
  "properties": {
    "gn:admin1_code":"11",
    "gn:asciiname":"Bimbouloulou",
    "gn:country_code":"CG",
    "gn:dem":499,
    "gn:feature_class":"P",
    "gn:feature_code":"PPL",
    "gn:name":"Bimbouloulou",
    "gn:population":0,
    "gn:timezone":"Africa/Brazzaville",
    "iso:country":"CG",
    "wof:name":"Bimbouloulou",
    "wof:placetype":"locality"
},
  "geometry": {"coordinates":[14.57944,-4.5125],"type":"Point"}
}