{
  "type": "Feature",
  "properties": {
    "gn:admin1_code":"11",
    "gn:asciiname":"Seleke",
    "gn:country_code":"CG",
    "gn:dem":589,
    "gn:feature_class":"P",
    "gn:feature_code":"PPL",
    "gn:name":"S\u00e9l\u00e9k\u00e9",
    "gn:population":0,
    "gn:timezone":"Africa/Brazzaville",
    "iso:country":"CG",
    "wof:name":"Seleke",
    "wof:placetype":"locality"
},
  "geometry": {"coordinates":[14.58833,-3.2325],"type":"Point"}
}