{
  "type": "Feature",
  "properties": {
    "gn:admin1_code":"12",
    "gn:asciiname":"Goma J.B.",
    "gn:country_code":"CG",
    "gn:dem":309,
    "gn:feature_class":"P",
    "gn:feature_code":"PPL",
    "gn:name":"Goma J.B.",
    "gn:population":0,
    "gn:timezone":"Africa/Brazzaville",
    "iso:country":"CG",
    "wof:name":"Goma J.B.",
    "wof:placetype":"locality"
},
  "geometry": {"coordinates":[15.23444,-4.03278],"type":"Point"}
}