{
  "type": "Feature",
  "properties": {
    "gn:admin1_code":"08",
    "gn:asciiname":"Gania",
    "gn:country_code":"CG",
    "gn:dem":346,
    "gn:feature_class":"P",
    "gn:feature_code":"PPL",
    "gn:name":"Gania",
    "gn:population":0,
    "gn:timezone":"Africa/Brazzaville",
    "iso:country":"CG",
    "wof:name":"Gania",
    "wof:placetype":"locality"
},
  "geometry": {"coordinates":[15.89528,-1.33278],"type":"Point"}
}