{
  "type": "Feature",
  "properties": {
    "gn:admin1_code":"01",
    "gn:asciiname":"Kinanga-Londe",
    "gn:country_code":"CG",
    "gn:dem":776,
    "gn:feature_class":"P",
    "gn:feature_code":"PPL",
    "gn:name":"Kinanga-Londe",
    "gn:population":0,
    "gn:timezone":"Africa/Brazzaville",
    "iso:country":"CG",
    "wof:name":"Kinanga-Londe",
    "wof:placetype":"locality"
},
  "geometry": {"coordinates":[13.72306,-4.46361],"type":"Point"}
}