{
  "type": "Feature",
  "properties": {
    "gn:admin1_code":"13",
    "gn:asciiname":"Ossambou",
    "gn:country_code":"CG",
    "gn:dem":317,
    "gn:feature_class":"P",
    "gn:feature_code":"PPL",
    "gn:name":"Ossambou",
    "gn:population":0,
    "gn:timezone":"Africa/Brazzaville",
    "iso:country":"CG",
    "wof:name":"Ossambou",
    "wof:placetype":"locality"
},
  "geometry": {"coordinates":[15.97278,-0.51389],"type":"Point"}
}