{
  "type": "Feature",
  "properties": {
    "gn:admin1_code":"13",
    "gn:asciiname":"Kentsele",
    "gn:country_code":"CG",
    "gn:dem":391,
    "gn:feature_class":"P",
    "gn:feature_code":"PPL",
    "gn:name":"Kents\u00e9l\u00e9",
    "gn:population":0,
    "gn:timezone":"Africa/Brazzaville",
    "iso:country":"CG",
    "name:und_x_variant":[
        "Kensts\u00e9le",
        "Kents\u00e9l\u00e9"
    ],
    "wof:name":"Kentsele",
    "wof:placetype":"locality"
},
  "geometry": {"coordinates":[15.08611,-1.35806],"type":"Point"}
}