{
  "type": "Feature",
  "properties": {
    "gn:admin1_code":"08",
    "gn:asciiname":"Ebouie",
    "gn:country_code":"CG",
    "gn:dem":364,
    "gn:feature_class":"P",
    "gn:feature_code":"PPL",
    "gn:name":"Ebouie",
    "gn:population":0,
    "gn:timezone":"Africa/Brazzaville",
    "iso:country":"CG",
    "wof:name":"Ebouie",
    "wof:placetype":"locality"
},
  "geometry": {"coordinates":[16.03333,-1.86667],"type":"Point"}
}