{
  "type": "Feature",
  "properties": {
    "gn:admin1_code":"11",
    "gn:asciiname":"Mbounda IV",
    "gn:country_code":"CG",
    "gn:dem":534,
    "gn:feature_class":"P",
    "gn:feature_code":"PPL",
    "gn:name":"Mbounda IV",
    "gn:population":0,
    "gn:timezone":"Africa/Brazzaville",
    "iso:country":"CG",
    "wof:name":"Mbounda IV",
    "wof:placetype":"locality"
},
  "geometry": {"coordinates":[14.74917,-4.67444],"type":"Point"}
}