{
  "type": "Feature",
  "properties": {
    "gn:admin1_code":"08",
    "gn:asciiname":"Kadjouni",
    "gn:country_code":"CG",
    "gn:dem":394,
    "gn:feature_class":"P",
    "gn:feature_code":"PPL",
    "gn:name":"Kadjouni",
    "gn:population":0,
    "gn:timezone":"Africa/Brazzaville",
    "iso:country":"CG",
    "wof:name":"Kadjouni",
    "wof:placetype":"locality"
},
  "geometry": {"coordinates":[15.00333,-1.65917],"type":"Point"}
}