{
  "type": "Feature",
  "properties": {
    "gn:admin1_code":"11",
    "gn:asciiname":"Mbamou",
    "gn:country_code":"CG",
    "gn:dem":412,
    "gn:feature_class":"P",
    "gn:feature_code":"PPL",
    "gn:name":"Mbamou",
    "gn:population":0,
    "gn:timezone":"Africa/Brazzaville",
    "iso:country":"CG",
    "wof:name":"Mbamou",
    "wof:placetype":"locality"
},
  "geometry": {"coordinates":[14.87972,-4.27861],"type":"Point"}
}