{
  "type": "Feature",
  "properties": {
    "gn:admin1_code":"11",
    "gn:asciiname":"Banianda",
    "gn:country_code":"CG",
    "gn:dem":347,
    "gn:feature_class":"P",
    "gn:feature_code":"PPL",
    "gn:name":"Banianda",
    "gn:population":0,
    "gn:timezone":"Africa/Brazzaville",
    "iso:country":"CG",
    "wof:name":"Banianda",
    "wof:placetype":"locality"
},
  "geometry": {"coordinates":[14.41528,-4.08222],"type":"Point"}
}