{
  "type": "Feature",
  "properties": {
    "gn:admin1_code":"07",
    "gn:asciiname":"Maboudou",
    "gn:country_code":"CG",
    "gn:dem":138,
    "gn:feature_class":"P",
    "gn:feature_code":"PPL",
    "gn:name":"Maboudou",
    "gn:population":0,
    "gn:timezone":"Africa/Brazzaville",
    "iso:country":"CG",
    "wof:name":"Maboudou",
    "wof:placetype":"locality"
},
  "geometry": {"coordinates":[12.15944,-3.34028],"type":"Point"}
}