{
  "type": "Feature",
  "properties": {
    "gn:admin1_code":"01",
    "gn:asciiname":"Kibounda",
    "gn:country_code":"CG",
    "gn:dem":198,
    "gn:feature_class":"P",
    "gn:feature_code":"PPL",
    "gn:name":"Kibounda",
    "gn:population":0,
    "gn:timezone":"Africa/Brazzaville",
    "iso:country":"CG",
    "wof:name":"Kibounda",
    "wof:placetype":"locality"
},
  "geometry": {"coordinates":[13.49222,-4.16944],"type":"Point"}
}