{
  "type": "Feature",
  "properties": {
    "gn:admin1_code":"11",
    "gn:asciiname":"Massembo-Loubaki",
    "gn:cc2":"CG",
    "gn:country_code":"CG",
    "gn:dem":451,
    "gn:feature_class":"P",
    "gn:feature_code":"PPL",
    "gn:name":"Massembo-Loubaki",
    "gn:population":0,
    "gn:timezone":"Africa/Brazzaville",
    "iso:country":"CG",
    "name:und_x_variant":[
        "Brusseauz",
        "Brusseaux",
        "Massembo-Loubaki"
    ],
    "wof:name":"Massembo-Loubaki",
    "wof:placetype":"locality"
},
  "geometry": {"coordinates":[14.59444,-4.25306],"type":"Point"}
}