{
  "type": "Feature",
  "properties": {
    "gn:admin1_code":"11",
    "gn:asciiname":"Kinnkakassa",
    "gn:cc2":"CG",
    "gn:country_code":"CG",
    "gn:dem":459,
    "gn:feature_class":"P",
    "gn:feature_code":"PPL",
    "gn:name":"Kinnkakassa",
    "gn:population":0,
    "gn:timezone":"Africa/Brazzaville",
    "iso:country":"CG",
    "name:und_x_variant":[
        "Kinkakasa",
        "Kinnkakassa"
    ],
    "wof:name":"Kinnkakassa",
    "wof:placetype":"locality"
},
  "geometry": {"coordinates":[14.66222,-4.26833],"type":"Point"}
}