{
  "type": "Feature",
  "properties": {
    "gn:admin1_code":"07",
    "gn:asciiname":"Londela-Mpoukou",
    "gn:country_code":"CG",
    "gn:dem":421,
    "gn:feature_class":"P",
    "gn:feature_code":"PPL",
    "gn:name":"Londela-Mpoukou",
    "gn:population":0,
    "gn:timezone":"Africa/Brazzaville",
    "iso:country":"CG",
    "wof:name":"Londela-Mpoukou",
    "wof:placetype":"locality"
},
  "geometry": {"coordinates":[13.34972,-4.7675],"type":"Point"}
}