{
  "type": "Feature",
  "properties": {
    "gn:admin1_code":"14",
    "gn:asciiname":"Olouma",
    "gn:country_code":"CG",
    "gn:dem":440,
    "gn:feature_class":"P",
    "gn:feature_code":"PPL",
    "gn:name":"Olouma",
    "gn:population":0,
    "gn:timezone":"Africa/Brazzaville",
    "iso:country":"CG",
    "wof:name":"Olouma",
    "wof:placetype":"locality"
},
  "geometry": {"coordinates":[14.85167,-0.01917],"type":"Point"}
}