{
  "type": "Feature",
  "properties": {
    "gn:admin1_code":"11",
    "gn:asciiname":"Makana I",
    "gn:country_code":"CG",
    "gn:dem":494,
    "gn:feature_class":"P",
    "gn:feature_code":"PPL",
    "gn:name":"Makana I",
    "gn:population":0,
    "gn:timezone":"Africa/Brazzaville",
    "iso:country":"CG",
    "wof:name":"Makana I",
    "wof:placetype":"locality"
},
  "geometry": {"coordinates":[14.63806,-3.6425],"type":"Point"}
}