{
  "type": "Feature",
  "properties": {
    "gn:admin1_code":"11",
    "gn:asciiname":"Mafoussi",
    "gn:cc2":"CG",
    "gn:country_code":"CG",
    "gn:dem":494,
    "gn:feature_class":"P",
    "gn:feature_code":"PPL",
    "gn:name":"Mafoussi",
    "gn:population":0,
    "gn:timezone":"Africa/Brazzaville",
    "iso:country":"CG",
    "name:und_x_variant":[
        "Mafousi",
        "Mafoussi"
    ],
    "wof:name":"Mafoussi",
    "wof:placetype":"locality"
},
  "geometry": {"coordinates":[14.54167,-4.54472],"type":"Point"}
}