{
  "type": "Feature",
  "properties": {
    "gn:admin1_code":"11",
    "gn:asciiname":"Salabiakou",
    "gn:country_code":"CG",
    "gn:dem":505,
    "gn:feature_class":"P",
    "gn:feature_code":"PPL",
    "gn:name":"Salabiakou",
    "gn:population":0,
    "gn:timezone":"Africa/Brazzaville",
    "iso:country":"CG",
    "wof:name":"Salabiakou",
    "wof:placetype":"locality"
},
  "geometry": {"coordinates":[14.60917,-3.60833],"type":"Point"}
}