{
  "type": "Feature",
  "properties": {
    "gn:admin1_code":"04",
    "gn:asciiname":"Souangui",
    "gn:country_code":"CG",
    "gn:dem":88,
    "gn:feature_class":"P",
    "gn:feature_code":"PPL",
    "gn:name":"Souangui",
    "gn:population":0,
    "gn:timezone":"Africa/Brazzaville",
    "iso:country":"CG",
    "wof:name":"Souangui",
    "wof:placetype":"locality"
},
  "geometry": {"coordinates":[11.65889,-3.96194],"type":"Point"}
}