{
  "type": "Feature",
  "properties": {
    "gn:admin1_code":"04",
    "gn:asciiname":"Midoumba",
    "gn:country_code":"CG",
    "gn:dem":204,
    "gn:feature_class":"P",
    "gn:feature_code":"PPL",
    "gn:name":"Midoumba",
    "gn:population":0,
    "gn:timezone":"Africa/Brazzaville",
    "iso:country":"CG",
    "wof:name":"Midoumba",
    "wof:placetype":"locality"
},
  "geometry": {"coordinates":[11.98528,-4.09667],"type":"Point"}
}