{
  "type": "Feature",
  "properties": {
    "gn:admin1_code":"14",
    "gn:asciiname":"Ilembou",
    "gn:country_code":"CG",
    "gn:dem":406,
    "gn:feature_class":"P",
    "gn:feature_code":"PPL",
    "gn:name":"Il\u00e8mbou",
    "gn:population":0,
    "gn:timezone":"Africa/Brazzaville",
    "iso:country":"CG",
    "wof:name":"Ilembou",
    "wof:placetype":"locality"
},
  "geometry": {"coordinates":[14.65833,0.5675],"type":"Point"}
}