{
  "type": "Feature",
  "properties": {
    "gn:admin1_code":"11",
    "gn:asciiname":"Mituomi",
    "gn:cc2":"CG",
    "gn:country_code":"CG",
    "gn:dem":557,
    "gn:feature_class":"P",
    "gn:feature_code":"PPL",
    "gn:name":"Mituomi",
    "gn:population":0,
    "gn:timezone":"Africa/Brazzaville",
    "iso:country":"CG",
    "name:und_x_variant":[
        "Mitouomi",
        "Mituomi"
    ],
    "wof:name":"Mituomi",
    "wof:placetype":"locality"
},
  "geometry": {"coordinates":[14.28917,-3.24194],"type":"Point"}
}