{
  "type": "Feature",
  "properties": {
    "gn:admin1_code":"11",
    "gn:asciiname":"Maipili",
    "gn:country_code":"CG",
    "gn:dem":272,
    "gn:feature_class":"P",
    "gn:feature_code":"PPL",
    "gn:name":"Ma\u00efpili",
    "gn:population":0,
    "gn:timezone":"Africa/Brazzaville",
    "iso:country":"CG",
    "wof:name":"Maipili",
    "wof:placetype":"locality"
},
  "geometry": {"coordinates":[15.9825,-3.74694],"type":"Point"}
}