{
  "type": "Feature",
  "properties": {
    "gn:admin1_code":"06",
    "gn:asciiname":"Ebila",
    "gn:country_code":"CG",
    "gn:dem":321,
    "gn:feature_class":"P",
    "gn:feature_code":"PPL",
    "gn:name":"Ebila",
    "gn:population":0,
    "gn:timezone":"Africa/Brazzaville",
    "iso:country":"CG",
    "wof:name":"Ebila",
    "wof:placetype":"locality"
},
  "geometry": {"coordinates":[17.845,1.01056],"type":"Point"}
}