{
  "type": "Feature",
  "properties": {
    "gn:admin1_code":"07",
    "gn:asciiname":"Milamila",
    "gn:country_code":"CG",
    "gn:dem":121,
    "gn:feature_class":"P",
    "gn:feature_code":"PPL",
    "gn:name":"Milamila",
    "gn:population":0,
    "gn:timezone":"Africa/Brazzaville",
    "iso:country":"CG",
    "wof:name":"Milamila",
    "wof:placetype":"locality"
},
  "geometry": {"coordinates":[12.45389,-3.72],"type":"Point"}
}