{
  "type": "Feature",
  "properties": {
    "gn:admin1_code":"11",
    "gn:asciiname":"Malaba",
    "gn:country_code":"CG",
    "gn:dem":387,
    "gn:feature_class":"P",
    "gn:feature_code":"PPL",
    "gn:name":"Malaba",
    "gn:population":0,
    "gn:timezone":"Africa/Brazzaville",
    "iso:country":"CG",
    "wof:name":"Malaba",
    "wof:placetype":"locality"
},
  "geometry": {"coordinates":[14.84278,-4.51861],"type":"Point"}
}