{
  "type": "Feature",
  "properties": {
    "gn:admin1_code":"11",
    "gn:asciiname":"Nkodia",
    "gn:country_code":"CG",
    "gn:dem":440,
    "gn:feature_class":"P",
    "gn:feature_code":"PPL",
    "gn:name":"Nkodia",
    "gn:population":0,
    "gn:timezone":"Africa/Brazzaville",
    "iso:country":"CG",
    "wof:name":"Nkodia",
    "wof:placetype":"locality"
},
  "geometry": {"coordinates":[14.44972,-3.77028],"type":"Point"}
}