{
  "type": "Feature",
  "properties": {
    "gn:admin1_code":"10",
    "gn:asciiname":"Bamegod",
    "gn:cc2":"CG",
    "gn:country_code":"CG",
    "gn:dem":531,
    "gn:feature_class":"P",
    "gn:feature_code":"PPL",
    "gn:name":"Bam\u00e9god",
    "gn:population":0,
    "gn:timezone":"Africa/Brazzaville",
    "iso:country":"CG",
    "name:und_x_variant":[
        "Bamagod I",
        "Bamagode I",
        "Bam\u00e9god"
    ],
    "wof:name":"Bamegod",
    "wof:placetype":"locality"
},
  "geometry": {"coordinates":[14.21194,1.85694],"type":"Point"}
}