{
  "type": "Feature",
  "properties": {
    "gn:admin1_code":"07",
    "gn:asciiname":"Tsouengi",
    "gn:country_code":"CG",
    "gn:dem":422,
    "gn:feature_class":"P",
    "gn:feature_code":"PPL",
    "gn:name":"Tsouengi",
    "gn:population":0,
    "gn:timezone":"Africa/Brazzaville",
    "iso:country":"CG",
    "wof:name":"Tsouengi",
    "wof:placetype":"locality"
},
  "geometry": {"coordinates":[12.05833,-2.48111],"type":"Point"}
}