{
  "type": "Feature",
  "properties": {
    "gn:admin1_code":"14",
    "gn:asciiname":"Lebango",
    "gn:country_code":"CG",
    "gn:dem":541,
    "gn:feature_class":"P",
    "gn:feature_code":"PPL",
    "gn:name":"L\u00e9bango",
    "gn:population":0,
    "gn:timezone":"Africa/Brazzaville",
    "iso:country":"CG",
    "name:und_x_variant":[
        "Lebanga",
        "L\u00e9bango"
    ],
    "wof:name":"Lebango",
    "wof:placetype":"locality"
},
  "geometry": {"coordinates":[14.78583,0.38889],"type":"Point"}
}