{
  "type": "Feature",
  "properties": {
    "gn:admin1_code":"08",
    "gn:asciiname":"Mpana",
    "gn:cc2":"CG",
    "gn:country_code":"CG",
    "gn:dem":370,
    "gn:feature_class":"P",
    "gn:feature_code":"PPL",
    "gn:name":"Mpana",
    "gn:population":0,
    "gn:timezone":"Africa/Brazzaville",
    "iso:country":"CG",
    "name:und_x_variant":[
        "M\u2019Pana",
        "Mpana"
    ],
    "wof:name":"Mpana",
    "wof:placetype":"locality"
},
  "geometry": {"coordinates":[15.21694,-1.59972],"type":"Point"}
}