{
  "type": "Feature",
  "properties": {
    "gn:admin1_code":"11",
    "gn:asciiname":"Ingolo",
    "gn:country_code":"CG",
    "gn:dem":720,
    "gn:feature_class":"P",
    "gn:feature_code":"PPL",
    "gn:name":"Ingolo",
    "gn:population":0,
    "gn:timezone":"Africa/Brazzaville",
    "iso:country":"CG",
    "wof:name":"Ingolo",
    "wof:placetype":"locality"
},
  "geometry": {"coordinates":[15.43028,-3.42333],"type":"Point"}
}