{
  "type": "Feature",
  "properties": {
    "gn:admin1_code":"11",
    "gn:asciiname":"Gamawolo",
    "gn:country_code":"CG",
    "gn:dem":456,
    "gn:feature_class":"P",
    "gn:feature_code":"PPL",
    "gn:name":"Gamawolo",
    "gn:population":0,
    "gn:timezone":"Africa/Brazzaville",
    "iso:country":"CG",
    "wof:name":"Gamawolo",
    "wof:placetype":"locality"
},
  "geometry": {"coordinates":[14.57583,-4.20778],"type":"Point"}
}