{
  "type": "Feature",
  "properties": {
    "gn:admin1_code":"06",
    "gn:asciiname":"Isongo",
    "gn:country_code":"CG",
    "gn:dem":347,
    "gn:feature_class":"P",
    "gn:feature_code":"PPL",
    "gn:name":"Isongo",
    "gn:population":0,
    "gn:timezone":"Africa/Brazzaville",
    "iso:country":"CG",
    "wof:name":"Isongo",
    "wof:placetype":"locality"
},
  "geometry": {"coordinates":[18.11056,2.65722],"type":"Point"}
}