{
  "type": "Feature",
  "properties": {
    "gn:admin1_code":"04",
    "gn:asciiname":"Loulema",
    "gn:country_code":"CG",
    "gn:dem":74,
    "gn:feature_class":"P",
    "gn:feature_code":"PPL",
    "gn:name":"Loulema",
    "gn:population":0,
    "gn:timezone":"Africa/Brazzaville",
    "iso:country":"CG",
    "wof:name":"Loulema",
    "wof:placetype":"locality"
},
  "geometry": {"coordinates":[11.55694,-4.2875],"type":"Point"}
}