{
  "type": "Feature",
  "properties": {
    "gn:admin1_code":"05",
    "gn:asciiname":"Onkouma",
    "gn:country_code":"CG",
    "gn:dem":578,
    "gn:feature_class":"P",
    "gn:feature_code":"PPL",
    "gn:name":"Onkouma",
    "gn:population":0,
    "gn:timezone":"Africa/Brazzaville",
    "iso:country":"CG",
    "wof:name":"Onkouma",
    "wof:placetype":"locality"
},
  "geometry": {"coordinates":[13.89556,-2.91611],"type":"Point"}
}