{
  "type": "Feature",
  "properties": {
    "gn:admin1_code":"08",
    "gn:asciiname":"Mban",
    "gn:cc2":"CG",
    "gn:country_code":"CG",
    "gn:dem":374,
    "gn:feature_class":"P",
    "gn:feature_code":"PPL",
    "gn:name":"Mban",
    "gn:population":0,
    "gn:timezone":"Africa/Brazzaville",
    "iso:country":"CG",
    "name:und_x_variant":[
        "M\u2019Ban",
        "Mban"
    ],
    "wof:name":"Mban",
    "wof:placetype":"locality"
},
  "geometry": {"coordinates":[15.94806,-1.74306],"type":"Point"}
}