{
  "type": "Feature",
  "properties": {
    "gn:admin1_code":"13",
    "gn:asciiname":"Ounza",
    "gn:cc2":"CG",
    "gn:country_code":"CG",
    "gn:dem":336,
    "gn:feature_class":"P",
    "gn:feature_code":"PPL",
    "gn:name":"Ounza",
    "gn:population":0,
    "gn:timezone":"Africa/Brazzaville",
    "iso:country":"CG",
    "name:und_x_variant":[
        "Ondza",
        "Ounza"
    ],
    "wof:name":"Ounza",
    "wof:placetype":"locality"
},
  "geometry": {"coordinates":[15.6875,-0.01778],"type":"Point"}
}