{
  "type": "Feature",
  "properties": {
    "gn:admin1_code":"07",
    "gn:asciiname":"Youlandziami",
    "gn:country_code":"CG",
    "gn:dem":474,
    "gn:feature_class":"P",
    "gn:feature_code":"PPL",
    "gn:name":"Youlandziami",
    "gn:population":0,
    "gn:timezone":"Africa/Brazzaville",
    "iso:country":"CG",
    "wof:name":"Youlandziami",
    "wof:placetype":"locality"
},
  "geometry": {"coordinates":[12.86667,-3.01667],"type":"Point"}
}