{
  "type": "Feature",
  "properties": {
    "gn:admin1_code":"13",
    "gn:asciiname":"Pango",
    "gn:country_code":"CG",
    "gn:dem":327,
    "gn:feature_class":"P",
    "gn:feature_code":"PPL",
    "gn:name":"Pango",
    "gn:population":0,
    "gn:timezone":"Africa/Brazzaville",
    "iso:country":"CG",
    "wof:name":"Pango",
    "wof:placetype":"locality"
},
  "geometry": {"coordinates":[16.05694,0.15028],"type":"Point"}
}