{
  "type": "Feature",
  "properties": {
    "gn:admin1_code":"04",
    "gn:asciiname":"Vandji",
    "gn:country_code":"CG",
    "gn:dem":65,
    "gn:feature_class":"P",
    "gn:feature_code":"PPL",
    "gn:name":"Vandji",
    "gn:population":0,
    "gn:timezone":"Africa/Brazzaville",
    "iso:country":"CG",
    "wof:name":"Vandji",
    "wof:placetype":"locality"
},
  "geometry": {"coordinates":[11.32667,-4.06417],"type":"Point"}
}