{
  "type": "Feature",
  "properties": {
    "gn:admin1_code":"07",
    "gn:asciiname":"Mougoudi",
    "gn:country_code":"CG",
    "gn:dem":208,
    "gn:feature_class":"P",
    "gn:feature_code":"PPL",
    "gn:name":"Mougoudi",
    "gn:population":0,
    "gn:timezone":"Africa/Brazzaville",
    "iso:country":"CG",
    "wof:name":"Mougoudi",
    "wof:placetype":"locality"
},
  "geometry": {"coordinates":[12.02167,-2.84556],"type":"Point"}
}