{
  "type": "Feature",
  "properties": {
    "gn:admin1_code":"07",
    "gn:asciiname":"Tembe",
    "gn:country_code":"CG",
    "gn:dem":337,
    "gn:feature_class":"P",
    "gn:feature_code":"PPL",
    "gn:name":"Temb\u00e9",
    "gn:population":0,
    "gn:timezone":"Africa/Brazzaville",
    "iso:country":"CG",
    "wof:name":"Tembe",
    "wof:placetype":"locality"
},
  "geometry": {"coordinates":[12.63722,-4.15028],"type":"Point"}
}