{
  "type": "Feature",
  "properties": {
    "gn:admin1_code":"14",
    "gn:asciiname":"Mboma",
    "gn:country_code":"CG",
    "gn:dem":389,
    "gn:feature_class":"P",
    "gn:feature_code":"PPL",
    "gn:name":"Mboma",
    "gn:population":0,
    "gn:timezone":"Africa/Brazzaville",
    "iso:country":"CG",
    "name:und_x_variant":[
        "M\u2019Bomo",
        "Mboma"
    ],
    "wof:name":"Mboma",
    "wof:placetype":"locality"
},
  "geometry": {"coordinates":[14.8375,-0.66472],"type":"Point"}
}