{
  "type": "Feature",
  "properties": {
    "gn:admin1_code":"11",
    "gn:asciiname":"Kinnsele",
    "gn:country_code":"CG",
    "gn:dem":481,
    "gn:feature_class":"P",
    "gn:feature_code":"PPL",
    "gn:name":"Kinns\u00e9l\u00e9",
    "gn:population":0,
    "gn:timezone":"Africa/Brazzaville",
    "iso:country":"CG",
    "wof:name":"Kinnsele",
    "wof:placetype":"locality"
},
  "geometry": {"coordinates":[14.66861,-4.47694],"type":"Point"}
}