{
  "type": "Feature",
  "properties": {
    "gn:admin1_code":"14",
    "gn:asciiname":"Omboye",
    "gn:country_code":"CG",
    "gn:dem":532,
    "gn:feature_class":"P",
    "gn:feature_code":"PPL",
    "gn:name":"Omboy\u00e9",
    "gn:population":0,
    "gn:timezone":"Africa/Brazzaville",
    "iso:country":"CG",
    "name:und_x_variant":[
        "Omboyi",
        "Omboy\u00e9"
    ],
    "wof:name":"Omboye",
    "wof:placetype":"locality"
},
  "geometry": {"coordinates":[14.45278,-0.47972],"type":"Point"}
}