{
  "type": "Feature",
  "properties": {
    "gn:admin1_code":"01",
    "gn:asciiname":"Kenge",
    "gn:country_code":"CG",
    "gn:dem":515,
    "gn:feature_class":"P",
    "gn:feature_code":"PPL",
    "gn:name":"Kenge",
    "gn:population":0,
    "gn:timezone":"Africa/Brazzaville",
    "iso:country":"CG",
    "name:ceb_x_preferred":[
        "Kenge"
    ],
    "name:swe_x_preferred":[
        "Kenge"
    ],
    "wof:name":"Kenge",
    "wof:placetype":"locality"
},
  "geometry": {"coordinates":[13.85167,-4.00111],"type":"Point"}
}