{
  "type": "Feature",
  "properties": {
    "gn:admin1_code":"12",
    "gn:asciiname":"Bouaki",
    "gn:country_code":"CG",
    "gn:dem":273,
    "gn:feature_class":"P",
    "gn:feature_code":"PPL",
    "gn:name":"Bouaki",
    "gn:population":0,
    "gn:timezone":"Africa/Brazzaville",
    "iso:country":"CG",
    "wof:name":"Bouaki",
    "wof:placetype":"locality"
},
  "geometry": {"coordinates":[15.67472,-3.98944],"type":"Point"}
}