{
  "type": "Feature",
  "properties": {
    "gn:admin1_code":"07",
    "gn:asciiname":"Inga Dihika",
    "gn:cc2":"CG",
    "gn:country_code":"CG",
    "gn:dem":380,
    "gn:feature_class":"P",
    "gn:feature_code":"PPL",
    "gn:name":"Inga Dihika",
    "gn:population":0,
    "gn:timezone":"Africa/Brazzaville",
    "iso:country":"CG",
    "name:und_x_variant":[
        "Manga-Dihika",
        "Hinga Dinika",
        "Inga Dihika"
    ],
    "wof:name":"Inga Dihika",
    "wof:placetype":"locality"
},
  "geometry": {"coordinates":[12.73944,-4.24944],"type":"Point"}
}