{
  "type": "Feature",
  "properties": {
    "gn:admin1_code":"01",
    "gn:asciiname":"Kinsimba",
    "gn:country_code":"CG",
    "gn:dem":530,
    "gn:feature_class":"P",
    "gn:feature_code":"PPL",
    "gn:name":"Kinsimba",
    "gn:population":0,
    "gn:timezone":"Africa/Brazzaville",
    "iso:country":"CG",
    "wof:name":"Kinsimba",
    "wof:placetype":"locality"
},
  "geometry": {"coordinates":[13.73694,-4.38444],"type":"Point"}
}