{
  "type": "Feature",
  "properties": {
    "gn:admin1_code":"14",
    "gn:asciiname":"Adinga",
    "gn:country_code":"CG",
    "gn:dem":387,
    "gn:feature_class":"P",
    "gn:feature_code":"PPL",
    "gn:name":"Adinga",
    "gn:population":0,
    "gn:timezone":"Africa/Brazzaville",
    "iso:country":"CG",
    "wof:name":"Adinga",
    "wof:placetype":"locality"
},
  "geometry": {"coordinates":[14.79889,-0.04222],"type":"Point"}
}