{
  "type": "Feature",
  "properties": {
    "gn:admin1_code":"04",
    "gn:asciiname":"Mavambou",
    "gn:country_code":"CG",
    "gn:dem":57,
    "gn:feature_class":"P",
    "gn:feature_code":"PPL",
    "gn:name":"Mavambou",
    "gn:population":0,
    "gn:timezone":"Africa/Brazzaville",
    "iso:country":"CG",
    "wof:name":"Mavambou",
    "wof:placetype":"locality"
},
  "geometry": {"coordinates":[12.08861,-4.50722],"type":"Point"}
}