{
  "type": "Feature",
  "properties": {
    "gn:admin1_code":"08",
    "gn:asciiname":"Ingou",
    "gn:country_code":"CG",
    "gn:dem":327,
    "gn:feature_class":"P",
    "gn:feature_code":"PPL",
    "gn:name":"Ingou",
    "gn:population":0,
    "gn:timezone":"Africa/Brazzaville",
    "iso:country":"CG",
    "wof:name":"Ingou",
    "wof:placetype":"locality"
},
  "geometry": {"coordinates":[16.12611,-1.88833],"type":"Point"}
}