{
  "type": "Feature",
  "properties": {
    "gn:admin1_code":"08",
    "gn:asciiname":"Etolo",
    "gn:country_code":"CG",
    "gn:dem":318,
    "gn:feature_class":"P",
    "gn:feature_code":"PPL",
    "gn:name":"Etolo",
    "gn:population":0,
    "gn:timezone":"Africa/Brazzaville",
    "iso:country":"CG",
    "wof:name":"Etolo",
    "wof:placetype":"locality"
},
  "geometry": {"coordinates":[16.17389,-2.01861],"type":"Point"}
}