{
  "type": "Feature",
  "properties": {
    "gn:admin1_code":"13",
    "gn:asciiname":"Abeya",
    "gn:country_code":"CG",
    "gn:dem":336,
    "gn:feature_class":"P",
    "gn:feature_code":"PPL",
    "gn:name":"Ab\u00e9ya",
    "gn:population":0,
    "gn:timezone":"Africa/Brazzaville",
    "iso:country":"CG",
    "wof:name":"Abeya",
    "wof:placetype":"locality"
},
  "geometry": {"coordinates":[15.91167,-0.63972],"type":"Point"}
}