{
  "type": "Feature",
  "properties": {
    "gn:admin1_code":"05",
    "gn:asciiname":"Kimbouni",
    "gn:cc2":"CG",
    "gn:country_code":"CG",
    "gn:dem":479,
    "gn:feature_class":"P",
    "gn:feature_code":"PPL",
    "gn:name":"Kimbouni",
    "gn:population":0,
    "gn:timezone":"Africa/Brazzaville",
    "iso:country":"CG",
    "name:und_x_variant":[
        "Kimbounou",
        "Kimbouni"
    ],
    "wof:name":"Kimbouni",
    "wof:placetype":"locality"
},
  "geometry": {"coordinates":[13.5475,-3.09611],"type":"Point"}
}