{
  "type": "Feature",
  "properties": {
    "gn:admin1_code":"13",
    "gn:asciiname":"Oboumi",
    "gn:cc2":"CG",
    "gn:country_code":"CG",
    "gn:dem":325,
    "gn:feature_class":"P",
    "gn:feature_code":"PPL",
    "gn:name":"Oboumi",
    "gn:population":0,
    "gn:timezone":"Africa/Brazzaville",
    "iso:country":"CG",
    "name:und_x_variant":[
        "Obomi",
        "Oboumi"
    ],
    "wof:name":"Oboumi",
    "wof:placetype":"locality"
},
  "geometry": {"coordinates":[15.855,-1.03111],"type":"Point"}
}