{
  "type": "Feature",
  "properties": {
    "gn:admin1_code":"01",
    "gn:asciiname":"Moubiri",
    "gn:country_code":"CG",
    "gn:dem":418,
    "gn:feature_class":"P",
    "gn:feature_code":"PPL",
    "gn:name":"Moubiri",
    "gn:population":0,
    "gn:timezone":"Africa/Brazzaville",
    "iso:country":"CG",
    "wof:name":"Moubiri",
    "wof:placetype":"locality"
},
  "geometry": {"coordinates":[13.74972,-3.87278],"type":"Point"}
}