{
  "type": "Feature",
  "properties": {
    "gn:admin1_code":"10",
    "gn:asciiname":"Ombebo",
    "gn:country_code":"CG",
    "gn:dem":330,
    "gn:feature_class":"P",
    "gn:feature_code":"PPL",
    "gn:name":"Omb\u00e9bo",
    "gn:population":0,
    "gn:timezone":"Africa/Brazzaville",
    "iso:country":"CG",
    "wof:name":"Ombebo",
    "wof:placetype":"locality"
},
  "geometry": {"coordinates":[16.16444,0.11556],"type":"Point"}
}