{
  "type": "Feature",
  "properties": {
    "gn:admin1_code":"04",
    "gn:asciiname":"Djeno",
    "gn:cc2":"CG",
    "gn:country_code":"CG",
    "gn:dem":17,
    "gn:feature_class":"P",
    "gn:feature_code":"PPL",
    "gn:name":"Dj\u00e9no",
    "gn:population":0,
    "gn:timezone":"Africa/Brazzaville",
    "iso:country":"CG",
    "name:und_x_variant":[
        "Djano",
        "Dj\u00e9no"
    ],
    "wof:name":"Djeno",
    "wof:placetype":"locality"
},
  "geometry": {"coordinates":[11.9475,-4.91972],"type":"Point"}
}