{
  "type": "Feature",
  "properties": {
    "gn:admin1_code":"01",
    "gn:asciiname":"Ngouele",
    "gn:country_code":"CG",
    "gn:dem":228,
    "gn:feature_class":"P",
    "gn:feature_code":"PPL",
    "gn:name":"Ngou\u00e9l\u00e9",
    "gn:population":0,
    "gn:timezone":"Africa/Brazzaville",
    "iso:country":"CG",
    "wof:name":"Ngouele",
    "wof:placetype":"locality"
},
  "geometry": {"coordinates":[13.10583,-4.02278],"type":"Point"}
}