{
  "type": "Feature",
  "properties": {
    "gn:admin1_code":"07",
    "gn:asciiname":"Gongo",
    "gn:country_code":"CG",
    "gn:dem":394,
    "gn:feature_class":"P",
    "gn:feature_code":"PPL",
    "gn:name":"Gongo",
    "gn:population":0,
    "gn:timezone":"Africa/Brazzaville",
    "iso:country":"CG",
    "wof:name":"Gongo",
    "wof:placetype":"locality"
},
  "geometry": {"coordinates":[12.98444,-4.38556],"type":"Point"}
}