{
  "type": "Feature",
  "properties": {
    "gn:admin1_code":"13",
    "gn:asciiname":"Angomo",
    "gn:country_code":"CG",
    "gn:dem":438,
    "gn:feature_class":"P",
    "gn:feature_code":"PPL",
    "gn:name":"Angomo",
    "gn:population":0,
    "gn:timezone":"Africa/Brazzaville",
    "iso:country":"CG",
    "wof:name":"Angomo",
    "wof:placetype":"locality"
},
  "geometry": {"coordinates":[15.03333,-0.01667],"type":"Point"}
}