{
  "type": "Feature",
  "properties": {
    "gn:admin1_code":"11",
    "gn:asciiname":"Bouende Nkombo",
    "gn:country_code":"CG",
    "gn:dem":417,
    "gn:feature_class":"P",
    "gn:feature_code":"PPL",
    "gn:name":"Bouend\u00e9 Nkombo",
    "gn:population":0,
    "gn:timezone":"Africa/Brazzaville",
    "iso:country":"CG",
    "wof:name":"Bouende Nkombo",
    "wof:placetype":"locality"
},
  "geometry": {"coordinates":[14.97806,-4.25167],"type":"Point"}
}