{
  "type": "Feature",
  "properties": {
    "gn:admin1_code":"13",
    "gn:asciiname":"Abouma",
    "gn:country_code":"CG",
    "gn:dem":365,
    "gn:feature_class":"P",
    "gn:feature_code":"PPL",
    "gn:name":"Abouma",
    "gn:population":0,
    "gn:timezone":"Africa/Brazzaville",
    "iso:country":"CG",
    "wof:name":"Abouma",
    "wof:placetype":"locality"
},
  "geometry": {"coordinates":[15.79694,-0.30111],"type":"Point"}
}