{
  "type": "Feature",
  "properties": {
    "gn:admin1_code":"04",
    "gn:asciiname":"Nionzi",
    "gn:country_code":"CG",
    "gn:dem":171,
    "gn:feature_class":"P",
    "gn:feature_code":"PPL",
    "gn:name":"Nionzi",
    "gn:population":0,
    "gn:timezone":"Africa/Brazzaville",
    "iso:country":"CG",
    "wof:name":"Nionzi",
    "wof:placetype":"locality"
},
  "geometry": {"coordinates":[12.07444,-4.11917],"type":"Point"}
}