{
  "type": "Feature",
  "properties": {
    "gn:admin1_code":"08",
    "gn:asciiname":"Vono",
    "gn:country_code":"CG",
    "gn:dem":280,
    "gn:feature_class":"P",
    "gn:feature_code":"PPL",
    "gn:name":"Vono",
    "gn:population":0,
    "gn:timezone":"Africa/Brazzaville",
    "iso:country":"CG",
    "wof:name":"Vono",
    "wof:placetype":"locality"
},
  "geometry": {"coordinates":[16.16832999999999,-2.51583],"type":"Point"}
}