{
  "type": "Feature",
  "properties": {
    "gn:admin1_code":"05",
    "gn:asciiname":"Malima",
    "gn:country_code":"CG",
    "gn:dem":573,
    "gn:feature_class":"P",
    "gn:feature_code":"PPL",
    "gn:name":"Malima",
    "gn:population":0,
    "gn:timezone":"Africa/Brazzaville",
    "iso:country":"CG",
    "wof:name":"Malima",
    "wof:placetype":"locality"
},
  "geometry": {"coordinates":[13.79,-2.85806],"type":"Point"}
}