{
  "type": "Feature",
  "properties": {
    "gn:admin1_code":"13",
    "gn:asciiname":"Botonou",
    "gn:country_code":"CG",
    "gn:dem":300,
    "gn:feature_class":"P",
    "gn:feature_code":"PPL",
    "gn:name":"Botonou",
    "gn:population":0,
    "gn:timezone":"Africa/Brazzaville",
    "iso:country":"CG",
    "wof:name":"Botonou",
    "wof:placetype":"locality"
},
  "geometry": {"coordinates":[17.37222,-0.8975],"type":"Point"}
}