{
  "type": "Feature",
  "properties": {
    "gn:admin1_code":"01",
    "gn:asciiname":"Mpalou",
    "gn:country_code":"CG",
    "gn:dem":180,
    "gn:feature_class":"P",
    "gn:feature_code":"PPL",
    "gn:name":"Mpalou",
    "gn:population":0,
    "gn:timezone":"Africa/Brazzaville",
    "iso:country":"CG",
    "wof:name":"Mpalou",
    "wof:placetype":"locality"
},
  "geometry": {"coordinates":[13.44417,-4.1775],"type":"Point"}
}