{
  "type": "Feature",
  "properties": {
    "gn:admin1_code":"11",
    "gn:asciiname":"Kokabikoulou",
    "gn:country_code":"CG",
    "gn:dem":427,
    "gn:feature_class":"P",
    "gn:feature_code":"PPL",
    "gn:name":"Kokabikoulou",
    "gn:population":0,
    "gn:timezone":"Africa/Brazzaville",
    "iso:country":"CG",
    "wof:name":"Kokabikoulou",
    "wof:placetype":"locality"
},
  "geometry": {"coordinates":[14.74833,-4.19306],"type":"Point"}
}