{
  "type": "Feature",
  "properties": {
    "gn:admin1_code":"11",
    "gn:asciiname":"Kibendo",
    "gn:country_code":"CG",
    "gn:dem":445,
    "gn:feature_class":"P",
    "gn:feature_code":"PPL",
    "gn:name":"Kibendo",
    "gn:population":0,
    "gn:timezone":"Africa/Brazzaville",
    "iso:country":"CG",
    "wof:name":"Kibendo",
    "wof:placetype":"locality"
},
  "geometry": {"coordinates":[14.67083,-3.92333],"type":"Point"}
}