{
  "type": "Feature",
  "properties": {
    "gn:admin1_code":"01",
    "gn:asciiname":"Kimbonga",
    "gn:country_code":"CG",
    "gn:dem":496,
    "gn:feature_class":"P",
    "gn:feature_code":"PPL",
    "gn:name":"Kimbonga",
    "gn:population":0,
    "gn:timezone":"Africa/Brazzaville",
    "iso:country":"CG",
    "wof:name":"Kimbonga",
    "wof:placetype":"locality"
},
  "geometry": {"coordinates":[13.39917,-4.32139],"type":"Point"}
}