{
  "type": "Feature",
  "properties": {
    "gn:admin1_code":"01",
    "gn:asciiname":"Kibiti",
    "gn:country_code":"CG",
    "gn:dem":483,
    "gn:feature_class":"P",
    "gn:feature_code":"PPL",
    "gn:name":"Kibiti",
    "gn:population":0,
    "gn:timezone":"Africa/Brazzaville",
    "iso:country":"CG",
    "name:ara_x_preferred":[
        "\u0643\u064a\u0628\u064a\u062a\u064a"
    ],
    "name:ben_x_preferred":[
        "\u0995\u09bf\u09ac\u09bf\u09a4\u09bf"
    ],
    "name:deu_x_preferred":[
        "Kibiti"
    ],
    "name:ell_x_preferred":[
        "\u039a\u03b9\u03bc\u03c0\u03af\u03c4\u03b9"
    ],
    "name:eng_x_preferred":[
        "Kibiti"
    ],
    "name:fas_x_preferred":[
        "\u06a9\u06cc\u0628\u06cc\u062a\u06cc"
    ],
    "name:fra_x_preferred":[
        "Mikumi"
    ],
    "name:heb_x_preferred":[
        "\u05e7\u05d9\u05d1\u05d9\u05d8\u05d9"
    ],
    "name:hin_x_preferred":[
        "\u0915\u0940\u092c\u0940\u091f\u0940"
    ],
    "name:hun_x_preferred":[
        "Kibiti"
    ],
    "name:ind_x_preferred":[
        "Kibiti"
    ],
    "name:ita_x_preferred":[
        "Kibiti"
    ],
    "name:jpn_x_preferred":[
        "\u30ad\u30d3\u30c6\u30a3"
    ],
    "name:kor_x_preferred":[
        "\ud0a4\ube44\ud2f0"
    ],
    "name:nld_x_preferred":[
        "Kibiti"
    ],
    "name:pol_x_preferred":[
        "Kibiti"
    ],
    "name:por_x_preferred":[
        "Kibiti"
    ],
    "name:rus_x_preferred":[
        "\u041a\u0438\u0431\u0438\u0442\u0438"
    ],
    "name:spa_x_preferred":[
        "Kibiti"
    ],
    "name:swe_x_preferred":[
        "Kibiti"
    ],
    "name:tur_x_preferred":[
        "Kibiti"
    ],
    "name:ukr_x_preferred":[
        "\u041a\u0456\u0431\u0456\u0442\u0456"
    ],
    "name:urd_x_preferred":[
        "\u06a9\u06cc\u0628\u06cc\u062a\u06cc"
    ],
    "name:vie_x_preferred":[
        "Kibiti"
    ],
    "name:zho_cn_x_preferred":[
        "\u57fa\u6bd4\u8482"
    ],
    "name:zho_tw_x_preferred":[
        "\u57fa\u6bd4\u8482"
    ],
    "wof:name":"Kibiti",
    "wof:placetype":"locality"
},
  "geometry": {"coordinates":[14.06222,-3.83528],"type":"Point"}
}