{
  "type": "Feature",
  "properties": {
    "gn:admin1_code":"08",
    "gn:asciiname":"Odzandongo",
    "gn:cc2":"CG",
    "gn:country_code":"CG",
    "gn:dem":311,
    "gn:feature_class":"P",
    "gn:feature_code":"PPL",
    "gn:name":"Odzandongo",
    "gn:population":0,
    "gn:timezone":"Africa/Brazzaville",
    "iso:country":"CG",
    "name:und_x_variant":[
        "Odzendongo",
        "Odzandongo"
    ],
    "wof:name":"Odzandongo",
    "wof:placetype":"locality"
},
  "geometry": {"coordinates":[16.06056,-1.25778],"type":"Point"}
}