{
  "type": "Feature",
  "properties": {
    "gn:admin1_code":"07",
    "gn:asciiname":"Koumina",
    "gn:country_code":"CG",
    "gn:dem":369,
    "gn:feature_class":"P",
    "gn:feature_code":"PPL",
    "gn:name":"Koumina",
    "gn:population":0,
    "gn:timezone":"Africa/Brazzaville",
    "iso:country":"CG",
    "wof:name":"Koumina",
    "wof:placetype":"locality"
},
  "geometry": {"coordinates":[13.14917,-4.59389],"type":"Point"}
}