{
  "type": "Feature",
  "properties": {
    "gn:admin1_code":"13",
    "gn:asciiname":"Mbouma",
    "gn:country_code":"CG",
    "gn:dem":360,
    "gn:feature_class":"P",
    "gn:feature_code":"PPL",
    "gn:name":"Mbouma",
    "gn:population":0,
    "gn:timezone":"Africa/Brazzaville",
    "iso:country":"CG",
    "name:und_x_variant":[
        "M\u2019Bouma",
        "Mbouma"
    ],
    "wof:name":"Mbouma",
    "wof:placetype":"locality"
},
  "geometry": {"coordinates":[15.06167,-1.40556],"type":"Point"}
}