{
  "type": "Feature",
  "properties": {
    "gn:admin1_code":"14",
    "gn:asciiname":"Oboko II",
    "gn:country_code":"CG",
    "gn:dem":505,
    "gn:feature_class":"P",
    "gn:feature_code":"PPL",
    "gn:name":"Oboko II",
    "gn:population":0,
    "gn:timezone":"Africa/Brazzaville",
    "iso:country":"CG",
    "name:und_x_variant":[
        "Obougou",
        "Oboko II"
    ],
    "wof:name":"Oboko II",
    "wof:placetype":"locality"
},
  "geometry": {"coordinates":[14.43167,-0.425],"type":"Point"}
}