{
  "type": "Feature",
  "properties": {
    "gn:admin1_code":"04",
    "gn:asciiname":"Tchizondi",
    "gn:cc2":"CG",
    "gn:country_code":"CG",
    "gn:dem":50,
    "gn:feature_class":"P",
    "gn:feature_code":"PPL",
    "gn:name":"Tchizondi",
    "gn:population":0,
    "gn:timezone":"Africa/Brazzaville",
    "iso:country":"CG",
    "name:und_x_variant":[
        "Tchizonzi",
        "Tchizondi"
    ],
    "wof:name":"Tchizondi",
    "wof:placetype":"locality"
},
  "geometry": {"coordinates":[11.695,-4.38167],"type":"Point"}
}