{
  "type": "Feature",
  "properties": {
    "gn:admin1_code":"05",
    "gn:asciiname":"Omoy-Gadzita",
    "gn:cc2":"CG",
    "gn:country_code":"CG",
    "gn:dem":587,
    "gn:feature_class":"P",
    "gn:feature_code":"PPL",
    "gn:name":"Omoy-Gadzita",
    "gn:population":0,
    "gn:timezone":"Africa/Brazzaville",
    "iso:country":"CG",
    "name:und_x_variant":[
        "Omoyi Ngadzita",
        "Omoy-Gadzita"
    ],
    "wof:name":"Omoy-Gadzita",
    "wof:placetype":"locality"
},
  "geometry": {"coordinates":[13.615,-2.61778],"type":"Point"}
}