{
  "type": "Feature",
  "properties": {
    "gn:admin1_code":"07",
    "gn:asciiname":"Ngoua II",
    "gn:country_code":"CG",
    "gn:dem":379,
    "gn:feature_class":"P",
    "gn:feature_code":"PPL",
    "gn:name":"Ngoua II",
    "gn:population":0,
    "gn:timezone":"Africa/Brazzaville",
    "iso:country":"CG",
    "wof:name":"Ngoua II",
    "wof:placetype":"locality"
},
  "geometry": {"coordinates":[12.39417,-2.90083],"type":"Point"}
}