{
  "type": "Feature",
  "properties": {
    "gn:admin1_code":"04",
    "gn:asciiname":"Milimba",
    "gn:country_code":"CG",
    "gn:dem":94,
    "gn:feature_class":"P",
    "gn:feature_code":"PPL",
    "gn:name":"Milimba",
    "gn:population":0,
    "gn:timezone":"Africa/Brazzaville",
    "iso:country":"CG",
    "wof:name":"Milimba",
    "wof:placetype":"locality"
},
  "geometry": {"coordinates":[12.31667,-4.75],"type":"Point"}
}