{
  "type": "Feature",
  "properties": {
    "gn:admin1_code":"07",
    "gn:asciiname":"Bango",
    "gn:country_code":"CG",
    "gn:dem":493,
    "gn:feature_class":"P",
    "gn:feature_code":"PPL",
    "gn:name":"Bango",
    "gn:population":0,
    "gn:timezone":"Africa/Brazzaville",
    "iso:country":"CG",
    "wof:name":"Bango",
    "wof:placetype":"locality"
},
  "geometry": {"coordinates":[12.65,-2.74889],"type":"Point"}
}