{
  "type": "Feature",
  "properties": {
    "gn:admin1_code":"11",
    "gn:asciiname":"Kinndouta",
    "gn:cc2":"CG",
    "gn:country_code":"CG",
    "gn:dem":489,
    "gn:feature_class":"P",
    "gn:feature_code":"PPL",
    "gn:name":"Kinndouta",
    "gn:population":0,
    "gn:timezone":"Africa/Brazzaville",
    "iso:country":"CG",
    "name:und_x_variant":[
        "Kindouta",
        "Kinndouta"
    ],
    "wof:name":"Kinndouta",
    "wof:placetype":"locality"
},
  "geometry": {"coordinates":[14.82917,-4.61194],"type":"Point"}
}