{
  "type": "Feature",
  "properties": {
    "gn:admin1_code":"07",
    "gn:asciiname":"Movisi",
    "gn:cc2":"CG",
    "gn:country_code":"CG",
    "gn:dem":388,
    "gn:feature_class":"P",
    "gn:feature_code":"PPL",
    "gn:name":"Movisi",
    "gn:population":0,
    "gn:timezone":"Africa/Brazzaville",
    "iso:country":"CG",
    "name:und_x_variant":[
        "Mouvissi",
        "Movisi"
    ],
    "wof:name":"Movisi",
    "wof:placetype":"locality"
},
  "geometry": {"coordinates":[12.70583,-3.035],"type":"Point"}
}