{
  "type": "Feature",
  "properties": {
    "gn:admin1_code":"01",
    "gn:asciiname":"Kingondala",
    "gn:country_code":"CG",
    "gn:dem":464,
    "gn:feature_class":"P",
    "gn:feature_code":"PPL",
    "gn:name":"Kingondala",
    "gn:population":0,
    "gn:timezone":"Africa/Brazzaville",
    "iso:country":"CG",
    "wof:name":"Kingondala",
    "wof:placetype":"locality"
},
  "geometry": {"coordinates":[13.64306,-4.45944],"type":"Point"}
}