{
  "type": "Feature",
  "properties": {
    "gn:admin1_code":"11",
    "gn:asciiname":"Kinnkoumba",
    "gn:country_code":"CG",
    "gn:dem":282,
    "gn:feature_class":"P",
    "gn:feature_code":"PPL",
    "gn:name":"Kinnkoumba",
    "gn:population":0,
    "gn:timezone":"Africa/Brazzaville",
    "iso:country":"CG",
    "wof:name":"Kinnkoumba",
    "wof:placetype":"locality"
},
  "geometry": {"coordinates":[14.13917,-4.28667],"type":"Point"}
}