{
  "type": "Feature",
  "properties": {
    "gn:admin1_code":"13",
    "gn:asciiname":"Vaga",
    "gn:country_code":"CG",
    "gn:dem":583,
    "gn:feature_class":"P",
    "gn:feature_code":"PPL",
    "gn:name":"Vaga",
    "gn:population":0,
    "gn:timezone":"Africa/Brazzaville",
    "iso:country":"CG",
    "wof:name":"Vaga",
    "wof:placetype":"locality"
},
  "geometry": {"coordinates":[14.59111,-1.19778],"type":"Point"}
}