{
  "type": "Feature",
  "properties": {
    "gn:admin1_code":"06",
    "gn:asciiname":"Mobaka",
    "gn:country_code":"CG",
    "gn:dem":323,
    "gn:feature_class":"P",
    "gn:feature_code":"PPL",
    "gn:name":"Mobaka",
    "gn:population":0,
    "gn:timezone":"Africa/Brazzaville",
    "iso:country":"CG",
    "wof:name":"Mobaka",
    "wof:placetype":"locality"
},
  "geometry": {"coordinates":[17.13889,-0.36278],"type":"Point"}
}