{
  "type": "Feature",
  "properties": {
    "gn:admin1_code":"14",
    "gn:asciiname":"Ovounigui",
    "gn:country_code":"CG",
    "gn:dem":387,
    "gn:feature_class":"P",
    "gn:feature_code":"PPL",
    "gn:name":"Ovounigui",
    "gn:population":0,
    "gn:timezone":"Africa/Brazzaville",
    "iso:country":"CG",
    "wof:name":"Ovounigui",
    "wof:placetype":"locality"
},
  "geometry": {"coordinates":[14.84,-0.82139],"type":"Point"}
}