{
  "type": "Feature",
  "properties": {
    "gn:admin1_code":"11",
    "gn:asciiname":"Zouno Pena",
    "gn:country_code":"CG",
    "gn:dem":275,
    "gn:feature_class":"P",
    "gn:feature_code":"PPL",
    "gn:name":"Zouno P\u00e9na",
    "gn:population":0,
    "gn:timezone":"Africa/Brazzaville",
    "iso:country":"CG",
    "wof:name":"Zouno Pena",
    "wof:placetype":"locality"
},
  "geometry": {"coordinates":[16.18222,-3.00194],"type":"Point"}
}