{
  "type": "Feature",
  "properties": {
    "gn:admin1_code":"10",
    "gn:asciiname":"Bomassa",
    "gn:cc2":"CG",
    "gn:country_code":"CG",
    "gn:dem":351,
    "gn:feature_class":"P",
    "gn:feature_code":"PPL",
    "gn:name":"Bomassa",
    "gn:population":0,
    "gn:timezone":"Africa/Brazzaville",
    "iso:country":"CG",
    "name:fin_x_preferred":[
        "Bomassa"
    ],
    "name:pol_x_preferred":[
        "Bomassa"
    ],
    "name:por_x_preferred":[
        "Bomassa"
    ],
    "name:ron_x_preferred":[
        "Bomassa"
    ],
    "name:und_x_variant":[
        "Bomasse",
        "Bomassa"
    ],
    "name:urd_x_preferred":[
        "\u0628\u0648\u0645\u0627\u0633\u0627"
    ],
    "name:zho_x_preferred":[
        "\u535a\u99ac\u85a9"
    ],
    "wof:name":"Bomassa",
    "wof:placetype":"locality"
},
  "geometry": {"coordinates":[16.18552,2.20372],"type":"Point"}
}