{
  "type": "Feature",
  "properties": {
    "gn:admin1_code":"10",
    "gn:asciiname":"Gandicolo",
    "gn:country_code":"CG",
    "gn:dem":372,
    "gn:feature_class":"P",
    "gn:feature_code":"PPL",
    "gn:name":"Gandicolo",
    "gn:population":0,
    "gn:timezone":"Africa/Brazzaville",
    "iso:country":"CG",
    "name:und_x_variant":[
        "Gandzicole",
        "Ganzikolo"
    ],
    "wof:name":"Gandicolo",
    "wof:placetype":"locality"
},
  "geometry": {"coordinates":[16.15467,1.68277],"type":"Point"}
}