{
  "type": "Feature",
  "properties": {
    "gn:admin1_code":"11",
    "gn:asciiname":"Mansiedi",
    "gn:country_code":"CG",
    "gn:dem":460,
    "gn:feature_class":"P",
    "gn:feature_code":"PPL",
    "gn:name":"Mansi\u00e9di",
    "gn:population":0,
    "gn:timezone":"Africa/Brazzaville",
    "iso:country":"CG",
    "wof:name":"Mansiedi",
    "wof:placetype":"locality"
},
  "geometry": {"coordinates":[14.6725,-4.37389],"type":"Point"}
}