{
  "type": "Feature",
  "properties": {
    "gn:admin1_code":"07",
    "gn:asciiname":"Nianga",
    "gn:country_code":"CG",
    "gn:dem":362,
    "gn:feature_class":"P",
    "gn:feature_code":"PPL",
    "gn:name":"Nianga",
    "gn:population":0,
    "gn:timezone":"Africa/Brazzaville",
    "iso:country":"CG",
    "wof:name":"Nianga",
    "wof:placetype":"locality"
},
  "geometry": {"coordinates":[12.20861,-2.78833],"type":"Point"}
}