{
  "type": "Feature",
  "properties": {
    "gn:admin1_code":"08",
    "gn:asciiname":"Bobanda",
    "gn:country_code":"CG",
    "gn:dem":282,
    "gn:feature_class":"P",
    "gn:feature_code":"PPL",
    "gn:name":"Bobanda",
    "gn:population":0,
    "gn:timezone":"Africa/Brazzaville",
    "iso:country":"CG",
    "wof:name":"Bobanda",
    "wof:placetype":"locality"
},
  "geometry": {"coordinates":[16.31361,-1.78944],"type":"Point"}
}