{
  "type": "Feature",
  "properties": {
    "gn:admin1_code":"11",
    "gn:asciiname":"Loukouta",
    "gn:country_code":"CG",
    "gn:dem":368,
    "gn:feature_class":"P",
    "gn:feature_code":"PPL",
    "gn:name":"Loukouta",
    "gn:population":0,
    "gn:timezone":"Africa/Brazzaville",
    "iso:country":"CG",
    "wof:name":"Loukouta",
    "wof:placetype":"locality"
},
  "geometry": {"coordinates":[15.03556,-4.1675],"type":"Point"}
}