{
  "type": "Feature",
  "properties": {
    "gn:admin1_code":"14",
    "gn:asciiname":"Tsama",
    "gn:country_code":"CG",
    "gn:dem":482,
    "gn:feature_class":"P",
    "gn:feature_code":"PPL",
    "gn:name":"Tsama",
    "gn:population":0,
    "gn:timezone":"Africa/Brazzaville",
    "iso:country":"CG",
    "wof:name":"Tsama",
    "wof:placetype":"locality"
},
  "geometry": {"coordinates":[14.67889,-1.07389],"type":"Point"}
}