{
  "type": "Feature",
  "properties": {
    "gn:admin1_code":"11",
    "gn:asciiname":"Gabanpakassa",
    "gn:cc2":"CG",
    "gn:country_code":"CG",
    "gn:dem":409,
    "gn:feature_class":"P",
    "gn:feature_code":"PPL",
    "gn:name":"Gabanpakassa",
    "gn:population":0,
    "gn:timezone":"Africa/Brazzaville",
    "iso:country":"CG",
    "name:und_x_variant":[
        "Ngaman",
        "Pakasa",
        "Pakassa",
        "Gabanpakassa"
    ],
    "wof:name":"Gabanpakassa",
    "wof:placetype":"locality"
},
  "geometry": {"coordinates":[14.84389,-4.37028],"type":"Point"}
}