{
  "type": "Feature",
  "properties": {
    "gn:admin1_code":"11",
    "gn:asciiname":"Kinganboma",
    "gn:country_code":"CG",
    "gn:dem":438,
    "gn:feature_class":"P",
    "gn:feature_code":"PPL",
    "gn:name":"Kinganboma",
    "gn:population":0,
    "gn:timezone":"Africa/Brazzaville",
    "iso:country":"CG",
    "wof:name":"Kinganboma",
    "wof:placetype":"locality"
},
  "geometry": {"coordinates":[14.42417,-3.86389],"type":"Point"}
}