{
  "type": "Feature",
  "properties": {
    "gn:admin1_code":"04",
    "gn:asciiname":"Koubou",
    "gn:country_code":"CG",
    "gn:dem":68,
    "gn:feature_class":"P",
    "gn:feature_code":"PPL",
    "gn:name":"Koubou",
    "gn:population":0,
    "gn:timezone":"Africa/Brazzaville",
    "iso:country":"CG",
    "wof:name":"Koubou",
    "wof:placetype":"locality"
},
  "geometry": {"coordinates":[11.32944,-4.0125],"type":"Point"}
}