{
  "type": "Feature",
  "properties": {
    "gn:admin1_code":"11",
    "gn:asciiname":"Loukonga",
    "gn:country_code":"CG",
    "gn:dem":499,
    "gn:feature_class":"P",
    "gn:feature_code":"PPL",
    "gn:name":"Loukonga",
    "gn:population":0,
    "gn:timezone":"Africa/Brazzaville",
    "iso:country":"CG",
    "wof:name":"Loukonga",
    "wof:placetype":"locality"
},
  "geometry": {"coordinates":[14.53222,-4.01722],"type":"Point"}
}