{
  "type": "Feature",
  "properties": {
    "gn:admin1_code":"12",
    "gn:asciiname":"Bemba",
    "gn:country_code":"CG",
    "gn:dem":350,
    "gn:feature_class":"P",
    "gn:feature_code":"PPL",
    "gn:name":"Bemba",
    "gn:population":0,
    "gn:timezone":"Africa/Brazzaville",
    "iso:country":"CG",
    "name:ceb_x_preferred":[
        "Bemba"
    ],
    "name:deu_x_preferred":[
        "Bemba"
    ],
    "name:fra_x_preferred":[
        "Bemba"
    ],
    "name:ita_x_preferred":[
        "Bemba"
    ],
    "name:nld_x_preferred":[
        "Bemba"
    ],
    "name:swe_x_preferred":[
        "Bemba"
    ],
    "wof:name":"Bemba",
    "wof:placetype":"locality"
},
  "geometry": {"coordinates":[15.29639,-4.04944],"type":"Point"}
}