{
  "type": "Feature",
  "properties": {
    "gn:admin1_code":"07",
    "gn:asciiname":"Petit Kimoele",
    "gn:country_code":"CG",
    "gn:dem":370,
    "gn:feature_class":"P",
    "gn:feature_code":"PPL",
    "gn:name":"Petit Kimoele",
    "gn:population":0,
    "gn:timezone":"Africa/Brazzaville",
    "iso:country":"CG",
    "wof:name":"Petit Kimoele",
    "wof:placetype":"locality"
},
  "geometry": {"coordinates":[12.95,-4.46667],"type":"Point"}
}