{
  "type": "Feature",
  "properties": {
    "gn:admin1_code":"05",
    "gn:asciiname":"Kouali",
    "gn:country_code":"CG",
    "gn:dem":590,
    "gn:feature_class":"P",
    "gn:feature_code":"PPL",
    "gn:name":"Kouali",
    "gn:population":0,
    "gn:timezone":"Africa/Brazzaville",
    "iso:country":"CG",
    "wof:name":"Kouali",
    "wof:placetype":"locality"
},
  "geometry": {"coordinates":[13.75389,-2.86389],"type":"Point"}
}