{
  "type": "Feature",
  "properties": {
    "gn:admin1_code":"11",
    "gn:asciiname":"Mingali",
    "gn:country_code":"CG",
    "gn:dem":580,
    "gn:feature_class":"P",
    "gn:feature_code":"PPL",
    "gn:name":"Mingali",
    "gn:population":0,
    "gn:timezone":"Africa/Brazzaville",
    "iso:country":"CG",
    "wof:name":"Mingali",
    "wof:placetype":"locality"
},
  "geometry": {"coordinates":[14.22806,-3.19556],"type":"Point"}
}