{
  "type": "Feature",
  "properties": {
    "gn:admin1_code":"10",
    "gn:asciiname":"Enieme",
    "gn:country_code":"CG",
    "gn:dem":333,
    "gn:feature_class":"P",
    "gn:feature_code":"PPL",
    "gn:name":"Eni\u00e9m\u00e9",
    "gn:population":0,
    "gn:timezone":"Africa/Brazzaville",
    "iso:country":"CG",
    "wof:name":"Enieme",
    "wof:placetype":"locality"
},
  "geometry": {"coordinates":[16.53333,0.16667],"type":"Point"}
}