{
  "type": "Feature",
  "properties": {
    "gn:admin1_code":"11",
    "gn:asciiname":"Moanga Moungoro",
    "gn:cc2":"CG",
    "gn:country_code":"CG",
    "gn:dem":426,
    "gn:feature_class":"P",
    "gn:feature_code":"PPL",
    "gn:name":"Moanga Moungoro",
    "gn:population":0,
    "gn:timezone":"Africa/Brazzaville",
    "iso:country":"CG",
    "name:und_x_variant":[
        "Moungoro",
        "Moanga Moungoro"
    ],
    "wof:name":"Moanga Moungoro",
    "wof:placetype":"locality"
},
  "geometry": {"coordinates":[14.45167,-3.78306],"type":"Point"}
}