{
  "type": "Feature",
  "properties": {
    "gn:admin1_code":"11",
    "gn:asciiname":"Matouridi",
    "gn:country_code":"CG",
    "gn:dem":418,
    "gn:feature_class":"P",
    "gn:feature_code":"PPL",
    "gn:name":"Matouridi",
    "gn:population":0,
    "gn:timezone":"Africa/Brazzaville",
    "iso:country":"CG",
    "wof:name":"Matouridi",
    "wof:placetype":"locality"
},
  "geometry": {"coordinates":[14.4725,-3.79222],"type":"Point"}
}