{
  "type": "Feature",
  "properties": {
    "gn:admin1_code":"11",
    "gn:asciiname":"Mayela",
    "gn:country_code":"CG",
    "gn:dem":353,
    "gn:feature_class":"P",
    "gn:feature_code":"PPL",
    "gn:name":"May\u00e9la",
    "gn:population":0,
    "gn:timezone":"Africa/Brazzaville",
    "iso:country":"CG",
    "wof:name":"Mayela",
    "wof:placetype":"locality"
},
  "geometry": {"coordinates":[15.06667,-4.18333],"type":"Point"}
}