{
  "type": "Feature",
  "properties": {
    "gn:admin1_code":"01",
    "gn:asciiname":"Pindi",
    "gn:country_code":"CG",
    "gn:dem":170,
    "gn:feature_class":"P",
    "gn:feature_code":"PPL",
    "gn:name":"Pindi",
    "gn:population":0,
    "gn:timezone":"Africa/Brazzaville",
    "iso:country":"CG",
    "name:ceb_x_preferred":[
        "Pindi"
    ],
    "name:fra_x_preferred":[
        "Pindi"
    ],
    "name:swe_x_preferred":[
        "Pindi"
    ],
    "name:vol_x_preferred":[
        "Pindi"
    ],
    "wof:name":"Pindi",
    "wof:placetype":"locality"
},
  "geometry": {"coordinates":[13.07111,-4.08111],"type":"Point"}
}