{
  "type": "Feature",
  "properties": {
    "gn:admin1_code":"05",
    "gn:asciiname":"Matangi",
    "gn:cc2":"CG",
    "gn:country_code":"CG",
    "gn:dem":615,
    "gn:feature_class":"P",
    "gn:feature_code":"PPL",
    "gn:name":"Matangi",
    "gn:population":0,
    "gn:timezone":"Africa/Brazzaville",
    "iso:country":"CG",
    "name:fin_x_preferred":[
        "Matangi"
    ],
    "name:fra_x_preferred":[
        "Matangi"
    ],
    "name:hin_x_preferred":[
        "\u092e\u093e\u0924\u0902\u0917\u0940"
    ],
    "name:hrv_x_preferred":[
        "Matangi"
    ],
    "name:nep_x_preferred":[
        "\u092e\u093e\u0924\u0919\u094d\u0917\u0940"
    ],
    "name:ori_x_preferred":[
        "\u0b2e\u0b3e\u0b24\u0b19\u0b4d\u0b17\u0b40"
    ],
    "name:pan_x_preferred":[
        "\u0a2e\u0a3e\u0a24\u0a70\u0a17\u0a40"
    ],
    "name:pol_x_preferred":[
        "Matangi"
    ],
    "name:por_x_preferred":[
        "Matangi"
    ],
    "name:sin_x_preferred":[
        "\u0db8\u0dcf\u0dad\u0d82\u0d9c\u0dd3"
    ],
    "name:slv_x_preferred":[
        "Matangi"
    ],
    "name:tam_x_preferred":[
        "\u0bae\u0bbe\u0ba4\u0b99\u0bcd\u0b95\u0bbf"
    ],
    "name:tha_x_preferred":[
        "\u0e1e\u0e23\u0e30\u0e41\u0e21\u0e48\u0e21\u0e32\u0e15\u0e31\u0e07\u0e04\u0e35"
    ],
    "name:und_x_variant":[
        "Matangui",
        "Matangi"
    ],
    "name:urd_x_preferred":[
        "\u0645\u0627\u062a\u0646\u06af\u06cc"
    ],
    "wof:name":"Matangi",
    "wof:placetype":"locality"
},
  "geometry": {"coordinates":[13.60306,-2.83222],"type":"Point"}
}