{
  "type": "Feature",
  "properties": {
    "gn:admin1_code":"05",
    "gn:asciiname":"Matangi",
    "gn:cc2":"CG",
    "gn:country_code":"CG",
    "gn:dem":615,
    "gn:feature_class":"P",
    "gn:feature_code":"PPL",
    "gn:name":"Matangi",
    "gn:population":0,
    "gn:timezone":"Africa/Brazzaville",
    "iso:country":"CG",
    "name:und_x_variant":[
        "Matangui",
        "Matangi"
    ],
    "wof:name":"Matangi",
    "wof:placetype":"locality"
},
  "geometry": {"coordinates":[13.60306,-2.83222],"type":"Point"}
}