{
  "type": "Feature",
  "properties": {
    "gn:admin1_code":"11",
    "gn:asciiname":"Boko",
    "gn:country_code":"CG",
    "gn:dem":371,
    "gn:feature_class":"P",
    "gn:feature_code":"PPL",
    "gn:name":"Boko",
    "gn:population":0,
    "gn:timezone":"Africa/Brazzaville",
    "iso:country":"CG",
    "name:ceb_x_preferred":[
        "Boko"
    ],
    "name:deu_x_preferred":[
        "Boko"
    ],
    "name:epo_x_preferred":[
        "Boko"
    ],
    "name:fra_x_preferred":[
        "Boko"
    ],
    "name:ido_x_preferred":[
        "Boko"
    ],
    "name:lin_x_preferred":[
        "Boko"
    ],
    "name:swe_x_preferred":[
        "Boko"
    ],
    "wof:name":"Boko",
    "wof:placetype":"locality"
},
  "geometry": {"coordinates":[14.88056,-4.14556],"type":"Point"}
}