{
  "type": "Feature",
  "properties": {
    "gn:admin1_code":"04",
    "gn:asciiname":"Dola",
    "gn:country_code":"CG",
    "gn:dem":161,
    "gn:feature_class":"P",
    "gn:feature_code":"PPL",
    "gn:name":"Dola",
    "gn:population":0,
    "gn:timezone":"Africa/Brazzaville",
    "iso:country":"CG",
    "wof:name":"Dola",
    "wof:placetype":"locality"
},
  "geometry": {"coordinates":[11.96667,-4.08333],"type":"Point"}
}