{
  "type": "Feature",
  "properties": {
    "gn:admin1_code":"04",
    "gn:asciiname":"Loufouyou",
    "gn:country_code":"CG",
    "gn:dem":150,
    "gn:feature_class":"P",
    "gn:feature_code":"PPL",
    "gn:name":"Loufouyou",
    "gn:population":0,
    "gn:timezone":"Africa/Brazzaville",
    "iso:country":"CG",
    "wof:name":"Loufouyou",
    "wof:placetype":"locality"
},
  "geometry": {"coordinates":[12.31972,-4.52333],"type":"Point"}
}