{
  "type": "Feature",
  "properties": {
    "gn:admin1_code":"07",
    "gn:asciiname":"Mbaya",
    "gn:country_code":"CG",
    "gn:dem":658,
    "gn:feature_class":"P",
    "gn:feature_code":"PPL",
    "gn:name":"Mbaya",
    "gn:population":0,
    "gn:timezone":"Africa/Brazzaville",
    "iso:country":"CG",
    "wof:name":"Mbaya",
    "wof:placetype":"locality"
},
  "geometry": {"coordinates":[12.73056,-2.465],"type":"Point"}
}