{
  "type": "Feature",
  "properties": {
    "gn:admin1_code":"07",
    "gn:asciiname":"Malambani",
    "gn:country_code":"CG",
    "gn:dem":689,
    "gn:feature_class":"P",
    "gn:feature_code":"PPL",
    "gn:name":"Malambani",
    "gn:population":0,
    "gn:timezone":"Africa/Brazzaville",
    "iso:country":"CG",
    "wof:name":"Malambani",
    "wof:placetype":"locality"
},
  "geometry": {"coordinates":[12.74556,-2.36444],"type":"Point"}
}