{
  "type": "Feature",
  "properties": {
    "gn:admin1_code":"11",
    "gn:asciiname":"Kinnssassa",
    "gn:country_code":"CG",
    "gn:dem":463,
    "gn:feature_class":"P",
    "gn:feature_code":"PPL",
    "gn:name":"Kinnssassa",
    "gn:population":0,
    "gn:timezone":"Africa/Brazzaville",
    "iso:country":"CG",
    "wof:name":"Kinnssassa",
    "wof:placetype":"locality"
},
  "geometry": {"coordinates":[14.59806,-4.04611],"type":"Point"}
}