{
  "type": "Feature",
  "properties": {
    "gn:admin1_code":"11",
    "gn:asciiname":"Dzio-Dzio",
    "gn:cc2":"CG",
    "gn:country_code":"CG",
    "gn:dem":740,
    "gn:feature_class":"P",
    "gn:feature_code":"PPL",
    "gn:name":"Dzio-Dzio",
    "gn:population":0,
    "gn:timezone":"Africa/Brazzaville",
    "iso:country":"CG",
    "name:und_x_variant":[
        "Nkala",
        "Dzio-Dzio"
    ],
    "wof:name":"Dzio-Dzio",
    "wof:placetype":"locality"
},
  "geometry": {"coordinates":[15.30917,-3.4925],"type":"Point"}
}