{
  "type": "Feature",
  "properties": {
    "gn:admin1_code":"07",
    "gn:asciiname":"Tchimossi",
    "gn:country_code":"CG",
    "gn:dem":139,
    "gn:feature_class":"P",
    "gn:feature_code":"PPL",
    "gn:name":"Tchimossi",
    "gn:population":0,
    "gn:timezone":"Africa/Brazzaville",
    "iso:country":"CG",
    "wof:name":"Tchimossi",
    "wof:placetype":"locality"
},
  "geometry": {"coordinates":[12.53333,-3.71667],"type":"Point"}
}