{
  "type": "Feature",
  "properties": {
    "gn:admin1_code":"11",
    "gn:asciiname":"Koura",
    "gn:country_code":"CG",
    "gn:dem":275,
    "gn:feature_class":"P",
    "gn:feature_code":"PPL",
    "gn:name":"Koura",
    "gn:population":0,
    "gn:timezone":"Africa/Brazzaville",
    "iso:country":"CG",
    "wof:name":"Koura",
    "wof:placetype":"locality"
},
  "geometry": {"coordinates":[16.17778,-3.04056],"type":"Point"}
}