{
  "type": "Feature",
  "properties": {
    "gn:admin1_code":"11",
    "gn:asciiname":"Mibouri Mountoubouna",
    "gn:country_code":"CG",
    "gn:dem":535,
    "gn:feature_class":"P",
    "gn:feature_code":"PPL",
    "gn:name":"Mibouri Mountoubouna",
    "gn:population":0,
    "gn:timezone":"Africa/Brazzaville",
    "iso:country":"CG",
    "wof:name":"Mibouri Mountoubouna",
    "wof:placetype":"locality"
},
  "geometry": {"coordinates":[14.68722,-3.63083],"type":"Point"}
}