{
  "type": "Feature",
  "properties": {
    "gn:admin1_code":"04",
    "gn:asciiname":"Boukoulibouali",
    "gn:country_code":"CG",
    "gn:dem":166,
    "gn:feature_class":"P",
    "gn:feature_code":"PPL",
    "gn:name":"Boukoulibouali",
    "gn:population":0,
    "gn:timezone":"Africa/Brazzaville",
    "iso:country":"CG",
    "wof:name":"Boukoulibouali",
    "wof:placetype":"locality"
},
  "geometry": {"coordinates":[11.93778,-4.66944],"type":"Point"}
}