{
  "type": "Feature",
  "properties": {
    "gn:admin1_code":"07",
    "gn:asciiname":"Manbanailou",
    "gn:cc2":"CG",
    "gn:country_code":"CG",
    "gn:dem":203,
    "gn:feature_class":"P",
    "gn:feature_code":"PPL",
    "gn:name":"Manbana\u00eflou",
    "gn:population":0,
    "gn:timezone":"Africa/Brazzaville",
    "iso:country":"CG",
    "name:und_x_variant":[
        "Mambana\u00eflou",
        "Manbana\u00eflou"
    ],
    "wof:name":"Manbanailou",
    "wof:placetype":"locality"
},
  "geometry": {"coordinates":[12.11556,-3.80861],"type":"Point"}
}