{
  "type": "Feature",
  "properties": {
    "gn:admin1_code":"07",
    "gn:asciiname":"Omoy",
    "gn:country_code":"CG",
    "gn:dem":423,
    "gn:feature_class":"P",
    "gn:feature_code":"PPL",
    "gn:name":"Omoy",
    "gn:population":0,
    "gn:timezone":"Africa/Brazzaville",
    "iso:country":"CG",
    "wof:name":"Omoy",
    "wof:placetype":"locality"
},
  "geometry": {"coordinates":[12.99167,-3.15361],"type":"Point"}
}