{
  "type": "Feature",
  "properties": {
    "gn:admin1_code":"08",
    "gn:asciiname":"Akou",
    "gn:country_code":"CG",
    "gn:dem":372,
    "gn:feature_class":"P",
    "gn:feature_code":"PPL",
    "gn:name":"Akou",
    "gn:population":0,
    "gn:timezone":"Africa/Brazzaville",
    "iso:country":"CG",
    "wof:name":"Akou",
    "wof:placetype":"locality"
},
  "geometry": {"coordinates":[15.96083,-1.65889],"type":"Point"}
}