{
  "type": "Feature",
  "properties": {
    "gn:admin1_code":"13",
    "gn:asciiname":"Oyomi",
    "gn:country_code":"CG",
    "gn:dem":346,
    "gn:feature_class":"P",
    "gn:feature_code":"PPL",
    "gn:name":"Oyomi",
    "gn:population":0,
    "gn:timezone":"Africa/Brazzaville",
    "iso:country":"CG",
    "wof:name":"Oyomi",
    "wof:placetype":"locality"
},
  "geometry": {"coordinates":[15.5025,-0.29222],"type":"Point"}
}