{
  "type": "Feature",
  "properties": {
    "gn:admin1_code":"04",
    "gn:asciiname":"Douvolo",
    "gn:country_code":"CG",
    "gn:dem":48,
    "gn:feature_class":"P",
    "gn:feature_code":"PPL",
    "gn:name":"Douvolo",
    "gn:population":0,
    "gn:timezone":"Africa/Brazzaville",
    "iso:country":"CG",
    "wof:name":"Douvolo",
    "wof:placetype":"locality"
},
  "geometry": {"coordinates":[12.04389,-4.11444],"type":"Point"}
}