{
  "type": "Feature",
  "properties": {
    "gn:admin1_code":"11",
    "gn:asciiname":"Mangola",
    "gn:country_code":"CG",
    "gn:dem":609,
    "gn:feature_class":"P",
    "gn:feature_code":"PPL",
    "gn:name":"Mangola",
    "gn:population":0,
    "gn:timezone":"Africa/Brazzaville",
    "iso:country":"CG",
    "name:ceb_x_preferred":[
        "Mangola"
    ],
    "name:swe_x_preferred":[
        "Mangola"
    ],
    "wof:name":"Mangola",
    "wof:placetype":"locality"
},
  "geometry": {"coordinates":[14.04917,-4.405],"type":"Point"}
}