{
  "type": "Feature",
  "properties": {
    "gn:admin1_code":"13",
    "gn:asciiname":"Botando",
    "gn:country_code":"CG",
    "gn:dem":293,
    "gn:feature_class":"P",
    "gn:feature_code":"PPL",
    "gn:name":"Botando",
    "gn:population":0,
    "gn:timezone":"Africa/Brazzaville",
    "iso:country":"CG",
    "wof:name":"Botando",
    "wof:placetype":"locality"
},
  "geometry": {"coordinates":[16.75889,-1.0275],"type":"Point"}
}