{
  "type": "Feature",
  "properties": {
    "gn:admin1_code":"11",
    "gn:asciiname":"Mayanou Kinndamba",
    "gn:cc2":"CG",
    "gn:country_code":"CG",
    "gn:dem":380,
    "gn:feature_class":"P",
    "gn:feature_code":"PPL",
    "gn:name":"Mayanou Kinndamba",
    "gn:population":0,
    "gn:timezone":"Africa/Brazzaville",
    "iso:country":"CG",
    "name:und_x_variant":[
        "Mayanou",
        "Mayanou Kinndamba"
    ],
    "wof:name":"Mayanou Kinndamba",
    "wof:placetype":"locality"
},
  "geometry": {"coordinates":[14.88333,-4.44694],"type":"Point"}
}