{
  "type": "Feature",
  "properties": {
    "gn:admin1_code":"04",
    "gn:asciiname":"Youbi",
    "gn:country_code":"CG",
    "gn:dem":28,
    "gn:feature_class":"P",
    "gn:feature_code":"PPL",
    "gn:name":"Youbi",
    "gn:population":0,
    "gn:timezone":"Africa/Brazzaville",
    "iso:country":"CG",
    "wof:name":"Youbi",
    "wof:placetype":"locality"
},
  "geometry": {"coordinates":[11.66778,-4.19],"type":"Point"}
}