{
  "type": "Feature",
  "properties": {
    "gn:admin1_code":"13",
    "gn:asciiname":"Bokoso",
    "gn:country_code":"CG",
    "gn:dem":291,
    "gn:feature_class":"P",
    "gn:feature_code":"PPL",
    "gn:name":"Bokoso",
    "gn:population":0,
    "gn:timezone":"Africa/Brazzaville",
    "iso:country":"CG",
    "wof:name":"Bokoso",
    "wof:placetype":"locality"
},
  "geometry": {"coordinates":[16.77,-1.1775],"type":"Point"}
}