{
  "type": "Feature",
  "properties": {
    "gn:admin1_code":"11",
    "gn:asciiname":"Mpombo",
    "gn:country_code":"CG",
    "gn:dem":590,
    "gn:feature_class":"P",
    "gn:feature_code":"PPL",
    "gn:name":"Mpombo",
    "gn:population":0,
    "gn:timezone":"Africa/Brazzaville",
    "iso:country":"CG",
    "name:swa_x_preferred":[
        "Mpombo"
    ],
    "wof:name":"Mpombo",
    "wof:placetype":"locality"
},
  "geometry": {"coordinates":[14.54278,-4.795],"type":"Point"}
}