{
  "type": "Feature",
  "properties": {
    "gn:admin1_code":"11",
    "gn:asciiname":"Kimbeti",
    "gn:country_code":"CG",
    "gn:dem":530,
    "gn:feature_class":"P",
    "gn:feature_code":"PPL",
    "gn:name":"Kimb\u00e9ti",
    "gn:population":0,
    "gn:timezone":"Africa/Brazzaville",
    "iso:country":"CG",
    "wof:name":"Kimbeti",
    "wof:placetype":"locality"
},
  "geometry": {"coordinates":[14.51694,-4.4725],"type":"Point"}
}