{
  "type": "Feature",
  "properties": {
    "gn:admin1_code":"12",
    "gn:asciiname":"Mandaka",
    "gn:country_code":"CG",
    "gn:dem":485,
    "gn:feature_class":"P",
    "gn:feature_code":"PPL",
    "gn:name":"Mandaka",
    "gn:population":0,
    "gn:timezone":"Africa/Brazzaville",
    "iso:country":"CG",
    "wof:name":"Mandaka",
    "wof:placetype":"locality"
},
  "geometry": {"coordinates":[15.34667,-3.92222],"type":"Point"}
}