{
  "type": "Feature",
  "properties": {
    "gn:admin1_code":"13",
    "gn:asciiname":"Mvoula",
    "gn:country_code":"CG",
    "gn:dem":364,
    "gn:feature_class":"P",
    "gn:feature_code":"PPL",
    "gn:name":"Mvoula",
    "gn:population":0,
    "gn:timezone":"Africa/Brazzaville",
    "iso:country":"CG",
    "wof:name":"Mvoula",
    "wof:placetype":"locality"
},
  "geometry": {"coordinates":[15.6025,0.19444],"type":"Point"}
}