{
  "type": "Feature",
  "properties": {
    "gn:admin1_code":"7280295",
    "gn:asciiname":"Tchilou",
    "gn:country_code":"CG",
    "gn:dem":20,
    "gn:feature_class":"P",
    "gn:feature_code":"PPL",
    "gn:name":"Tchilou",
    "gn:population":0,
    "gn:timezone":"Africa/Brazzaville",
    "iso:country":"CG",
    "wof:name":"Tchilou",
    "wof:placetype":"locality"
},
  "geometry": {"coordinates":[11.86667,-4.78333],"type":"Point"}
}