{
  "type": "Feature",
  "properties": {
    "gn:admin1_code":"13",
    "gn:asciiname":"Mboma-Ollembe",
    "gn:cc2":"CG",
    "gn:country_code":"CG",
    "gn:dem":331,
    "gn:feature_class":"P",
    "gn:feature_code":"PPL",
    "gn:name":"Mboma-Ollemb\u00e9",
    "gn:population":0,
    "gn:timezone":"Africa/Brazzaville",
    "iso:country":"CG",
    "name:und_x_variant":[
        "Bouma Ollemb\u00e9",
        "Mboma-Ollemb\u00e9"
    ],
    "wof:name":"Mboma-Ollembe",
    "wof:placetype":"locality"
},
  "geometry": {"coordinates":[15.75556,-0.78194],"type":"Point"}
}