{
  "type": "Feature",
  "properties": {
    "gn:admin1_code":"08",
    "gn:asciiname":"Asa",
    "gn:country_code":"CG",
    "gn:dem":685,
    "gn:feature_class":"P",
    "gn:feature_code":"PPL",
    "gn:name":"Asa",
    "gn:population":0,
    "gn:timezone":"Africa/Brazzaville",
    "iso:country":"CG",
    "name:cat_x_preferred":[
        "Asa"
    ],
    "name:ceb_x_preferred":[
        "Asa"
    ],
    "name:fin_x_preferred":[
        "Asa"
    ],
    "name:heb_x_preferred":[
        "\u05d0\u05e1\u05d0"
    ],
    "name:jpn_x_preferred":[
        "\u30a2\u30b5"
    ],
    "name:lmo_x_preferred":[
        "As\u00e0"
    ],
    "name:nld_x_preferred":[
        "Asa"
    ],
    "name:pol_x_preferred":[
        "Asa"
    ],
    "name:por_x_preferred":[
        "Asa"
    ],
    "name:spa_x_preferred":[
        "Asa"
    ],
    "name:swe_x_preferred":[
        "Asa"
    ],
    "wof:name":"Asa",
    "wof:placetype":"locality"
},
  "geometry": {"coordinates":[15.26861,-2.48944],"type":"Point"}
}