{
  "type": "Feature",
  "properties": {
    "gn:admin1_code":"14",
    "gn:asciiname":"Enkeya",
    "gn:country_code":"CG",
    "gn:dem":390,
    "gn:feature_class":"P",
    "gn:feature_code":"PPL",
    "gn:name":"Enk\u00e9ya",
    "gn:population":0,
    "gn:timezone":"Africa/Brazzaville",
    "iso:country":"CG",
    "name:und_x_variant":[
        "Ek\u00e9y\u00e9",
        "Enk\u00e9ya"
    ],
    "wof:name":"Enkeya",
    "wof:placetype":"locality"
},
  "geometry": {"coordinates":[14.82778,-0.72556],"type":"Point"}
}