{
  "type": "Feature",
  "properties": {
    "gn:admin1_code":"06",
    "gn:asciiname":"Bongombele",
    "gn:country_code":"CG",
    "gn:dem":320,
    "gn:feature_class":"P",
    "gn:feature_code":"PPL",
    "gn:name":"Bongomb\u00e9l\u00e9",
    "gn:population":0,
    "gn:timezone":"Africa/Brazzaville",
    "iso:country":"CG",
    "wof:name":"Bongombele",
    "wof:placetype":"locality"
},
  "geometry": {"coordinates":[17.68388999999999,-0.4375],"type":"Point"}
}