{
  "type": "Feature",
  "properties": {
    "gn:admin1_code":"08",
    "gn:asciiname":"Motendzi",
    "gn:country_code":"CG",
    "gn:dem":840,
    "gn:feature_class":"P",
    "gn:feature_code":"PPL",
    "gn:name":"Motendzi",
    "gn:population":0,
    "gn:timezone":"Africa/Brazzaville",
    "iso:country":"CG",
    "wof:name":"Motendzi",
    "wof:placetype":"locality"
},
  "geometry": {"coordinates":[14.45889,-2.43167],"type":"Point"}
}