{
  "type": "Feature",
  "properties": {
    "gn:admin1_code":"01",
    "gn:asciiname":"Mayoulou",
    "gn:country_code":"CG",
    "gn:dem":555,
    "gn:feature_class":"P",
    "gn:feature_code":"PPL",
    "gn:name":"Mayoulou",
    "gn:population":0,
    "gn:timezone":"Africa/Brazzaville",
    "iso:country":"CG",
    "wof:name":"Mayoulou",
    "wof:placetype":"locality"
},
  "geometry": {"coordinates":[13.8225,-3.73972],"type":"Point"}
}