{
  "type": "Feature",
  "properties": {
    "gn:admin1_code":"05",
    "gn:asciiname":"Boudouhou",
    "gn:cc2":"CG",
    "gn:country_code":"CG",
    "gn:dem":452,
    "gn:feature_class":"P",
    "gn:feature_code":"PPL",
    "gn:name":"Boudouhou",
    "gn:population":0,
    "gn:timezone":"Africa/Brazzaville",
    "iso:country":"CG",
    "name:und_x_variant":[
        "Mboudou",
        "Boudouhou"
    ],
    "wof:name":"Boudouhou",
    "wof:placetype":"locality"
},
  "geometry": {"coordinates":[13.46333,-3.61972],"type":"Point"}
}