{
  "type": "Feature",
  "properties": {
    "gn:admin1_code":"07",
    "gn:asciiname":"Matembo",
    "gn:country_code":"CG",
    "gn:dem":367,
    "gn:feature_class":"P",
    "gn:feature_code":"PPL",
    "gn:name":"Matembo",
    "gn:population":0,
    "gn:timezone":"Africa/Brazzaville",
    "iso:country":"CG",
    "wof:name":"Matembo",
    "wof:placetype":"locality"
},
  "geometry": {"coordinates":[13.075,-4.46472],"type":"Point"}
}