{
  "type": "Feature",
  "properties": {
    "gn:admin1_code":"13",
    "gn:asciiname":"Ossounga",
    "gn:country_code":"CG",
    "gn:dem":366,
    "gn:feature_class":"P",
    "gn:feature_code":"PPL",
    "gn:name":"Ossounga",
    "gn:population":0,
    "gn:timezone":"Africa/Brazzaville",
    "iso:country":"CG",
    "wof:name":"Ossounga",
    "wof:placetype":"locality"
},
  "geometry": {"coordinates":[15.82722,-0.3275],"type":"Point"}
}