{
  "type": "Feature",
  "properties": {
    "gn:admin1_code":"08",
    "gn:asciiname":"Eloundi",
    "gn:country_code":"CG",
    "gn:dem":304,
    "gn:feature_class":"P",
    "gn:feature_code":"PPL",
    "gn:name":"Eloundi",
    "gn:population":0,
    "gn:timezone":"Africa/Brazzaville",
    "iso:country":"CG",
    "wof:name":"Eloundi",
    "wof:placetype":"locality"
},
  "geometry": {"coordinates":[16.32722,-1.57694],"type":"Point"}
}