{
  "type": "Feature",
  "properties": {
    "gn:admin1_code":"14",
    "gn:asciiname":"Obala",
    "gn:country_code":"CG",
    "gn:dem":454,
    "gn:feature_class":"P",
    "gn:feature_code":"PPL",
    "gn:name":"Obala",
    "gn:population":0,
    "gn:timezone":"Africa/Brazzaville",
    "iso:country":"CG",
    "wof:name":"Obala",
    "wof:placetype":"locality"
},
  "geometry": {"coordinates":[14.51667,-0.41667],"type":"Point"}
}