{
  "type": "Feature",
  "properties": {
    "gn:admin1_code":"14",
    "gn:asciiname":"Obala",
    "gn:country_code":"CG",
    "gn:dem":454,
    "gn:feature_class":"P",
    "gn:feature_code":"PPL",
    "gn:name":"Obala",
    "gn:population":0,
    "gn:timezone":"Africa/Brazzaville",
    "iso:country":"CG",
    "name:ceb_x_preferred":[
        "Obala"
    ],
    "name:deu_x_preferred":[
        "Obala"
    ],
    "name:fra_x_preferred":[
        "Obala"
    ],
    "name:heb_x_preferred":[
        "\u05d0\u05d5\u05d1\u05d0\u05dc\u05d4"
    ],
    "name:ita_x_preferred":[
        "Obala"
    ],
    "name:msa_x_preferred":[
        "Obala"
    ],
    "name:pol_x_preferred":[
        "Obala"
    ],
    "name:por_x_preferred":[
        "Obala"
    ],
    "name:ron_x_preferred":[
        "Obala"
    ],
    "name:rus_x_preferred":[
        "\u041e\u0431\u0430\u043b\u0430"
    ],
    "name:slv_x_preferred":[
        "Obala"
    ],
    "name:spa_x_preferred":[
        "Obala"
    ],
    "name:swe_x_preferred":[
        "Obala"
    ],
    "name:zho_x_preferred":[
        "\u5967\u5df4\u62c9"
    ],
    "wof:name":"Obala",
    "wof:placetype":"locality"
},
  "geometry": {"coordinates":[14.51667,-0.41667],"type":"Point"}
}