{
  "type": "Feature",
  "properties": {
    "gn:admin1_code":"05",
    "gn:asciiname":"Pono",
    "gn:country_code":"CG",
    "gn:dem":547,
    "gn:feature_class":"P",
    "gn:feature_code":"PPL",
    "gn:name":"Pono",
    "gn:population":0,
    "gn:timezone":"Africa/Brazzaville",
    "iso:country":"CG",
    "name:spa_x_preferred":[
        "Pono"
    ],
    "wof:name":"Pono",
    "wof:placetype":"locality"
},
  "geometry": {"coordinates":[13.73361,-3.63611],"type":"Point"}
}