{
  "type": "Feature",
  "properties": {
    "gn:admin1_code":"04",
    "gn:asciiname":"Louessi",
    "gn:cc2":"CG",
    "gn:country_code":"CG",
    "gn:dem":55,
    "gn:feature_class":"P",
    "gn:feature_code":"PPL",
    "gn:name":"Lou\u00e9ssi",
    "gn:population":0,
    "gn:timezone":"Africa/Brazzaville",
    "iso:country":"CG",
    "name:und_x_variant":[
        "Louesi",
        "Lou\u00e9ssi"
    ],
    "wof:name":"Louessi",
    "wof:placetype":"locality"
},
  "geometry": {"coordinates":[11.93833,-4.81222],"type":"Point"}
}