{
  "type": "Feature",
  "properties": {
    "gn:admin1_code":"07",
    "gn:asciiname":"Passa",
    "gn:country_code":"CG",
    "gn:dem":666,
    "gn:feature_class":"P",
    "gn:feature_code":"PPL",
    "gn:name":"Passa",
    "gn:population":0,
    "gn:timezone":"Africa/Brazzaville",
    "iso:country":"CG",
    "name:arg_x_preferred":[
        "Pa\u00e7\u00e0"
    ],
    "name:cat_x_preferred":[
        "Pa\u00e7\u00e0"
    ],
    "name:ceb_x_preferred":[
        "Passa"
    ],
    "name:dan_x_preferred":[
        "Passa"
    ],
    "name:deu_x_preferred":[
        "Passa"
    ],
    "name:eus_x_preferred":[
        "Passa"
    ],
    "name:fra_x_preferred":[
        "Passa"
    ],
    "name:hun_x_preferred":[
        "Passa"
    ],
    "name:ita_x_preferred":[
        "Passa"
    ],
    "name:kaz_x_preferred":[
        "\u041f\u0430\u0441\u0441\u0430"
    ],
    "name:lat_x_preferred":[
        "Passa"
    ],
    "name:lmo_x_preferred":[
        "Passa"
    ],
    "name:msa_x_preferred":[
        "Passa"
    ],
    "name:nld_x_preferred":[
        "Passa"
    ],
    "name:oci_x_preferred":[
        "Pa\u00e7\u00e0"
    ],
    "name:pol_x_preferred":[
        "Passa"
    ],
    "name:ron_x_preferred":[
        "Passa"
    ],
    "name:slk_x_preferred":[
        "Passa"
    ],
    "name:spa_x_preferred":[
        "Passa"
    ],
    "name:swe_x_preferred":[
        "Passa"
    ],
    "name:ukr_x_preferred":[
        "\u041f\u0430\u0441\u0441\u0430"
    ],
    "name:vie_x_preferred":[
        "Passa"
    ],
    "name:vol_x_preferred":[
        "Passa"
    ],
    "name:war_x_preferred":[
        "Passa"
    ],
    "wof:name":"Passa",
    "wof:placetype":"locality"
},
  "geometry": {"coordinates":[12.77944,-2.19194],"type":"Point"}
}