{
  "type": "Feature",
  "properties": {
    "gn:admin1_code":"08",
    "gn:asciiname":"Onkala",
    "gn:country_code":"CG",
    "gn:dem":815,
    "gn:feature_class":"P",
    "gn:feature_code":"PPL",
    "gn:name":"Onkala",
    "gn:population":0,
    "gn:timezone":"Africa/Brazzaville",
    "iso:country":"CG",
    "wof:name":"Onkala",
    "wof:placetype":"locality"
},
  "geometry": {"coordinates":[14.54083,-2.32361],"type":"Point"}
}