{
  "type": "Feature",
  "properties": {
    "gn:admin1_code":"11",
    "gn:asciiname":"Talangai",
    "gn:country_code":"CG",
    "gn:dem":285,
    "gn:feature_class":"P",
    "gn:feature_code":"PPL",
    "gn:name":"Talangai",
    "gn:population":0,
    "gn:timezone":"Africa/Brazzaville",
    "iso:country":"CG",
    "wof:name":"Talangai",
    "wof:placetype":"locality"
},
  "geometry": {"coordinates":[15.28375,-4.21826],"type":"Point"}
}