{
  "type": "Feature",
  "properties": {
    "gn:admin1_code":"06",
    "gn:asciiname":"Ancien Bera Njoko",
    "gn:cc2":"CG",
    "gn:country_code":"CG",
    "gn:dem":456,
    "gn:feature_class":"P",
    "gn:feature_code":"PPL",
    "gn:name":"Ancien Bera Njoko",
    "gn:population":0,
    "gn:timezone":"Africa/Brazzaville",
    "iso:country":"CG",
    "name:und_x_variant":[
        "Bera-Ndjoko",
        "Bera Njoko",
        "Ancien Bera Njoko"
    ],
    "wof:name":"Ancien Bera Njoko",
    "wof:placetype":"locality"
},
  "geometry": {"coordinates":[16.96667,3.31667],"type":"Point"}
}