{
  "type": "Feature",
  "properties": {
    "gn:admin1_code":"04",
    "gn:asciiname":"Mangongo",
    "gn:country_code":"CG",
    "gn:dem":90,
    "gn:feature_class":"P",
    "gn:feature_code":"PPL",
    "gn:name":"Mangongo",
    "gn:population":0,
    "gn:timezone":"Africa/Brazzaville",
    "iso:country":"CG",
    "wof:name":"Mangongo",
    "wof:placetype":"locality"
},
  "geometry": {"coordinates":[11.93694,-4.13306],"type":"Point"}
}