{
  "type": "Feature",
  "properties": {
    "gn:admin1_code":"05",
    "gn:asciiname":"Otala",
    "gn:country_code":"CG",
    "gn:dem":597,
    "gn:feature_class":"P",
    "gn:feature_code":"PPL",
    "gn:name":"Otala",
    "gn:population":0,
    "gn:timezone":"Africa/Brazzaville",
    "iso:country":"CG",
    "name:nld_x_preferred":[
        "Otala"
    ],
    "wof:name":"Otala",
    "wof:placetype":"locality"
},
  "geometry": {"coordinates":[13.61028,-2.82167],"type":"Point"}
}