{
  "type": "Feature",
  "properties": {
    "gn:admin1_code":"11",
    "gn:asciiname":"Kinngouanga",
    "gn:cc2":"CG",
    "gn:country_code":"CG",
    "gn:dem":573,
    "gn:feature_class":"P",
    "gn:feature_code":"PPL",
    "gn:name":"Kinngouanga",
    "gn:population":0,
    "gn:timezone":"Africa/Brazzaville",
    "iso:country":"CG",
    "name:und_x_variant":[
        "Kingouanga",
        "Kinngouanga"
    ],
    "wof:name":"Kinngouanga",
    "wof:placetype":"locality"
},
  "geometry": {"coordinates":[14.00361,-4.37222],"type":"Point"}
}