{
  "type": "Feature",
  "properties": {
    "gn:admin1_code":"11",
    "gn:asciiname":"Nke II",
    "gn:country_code":"CG",
    "gn:dem":481,
    "gn:feature_class":"P",
    "gn:feature_code":"PPL",
    "gn:name":"Nk\u00e9 II",
    "gn:population":0,
    "gn:timezone":"Africa/Brazzaville",
    "iso:country":"CG",
    "wof:name":"Nke II",
    "wof:placetype":"locality"
},
  "geometry": {"coordinates":[14.58333,-3.47917],"type":"Point"}
}