{
  "type": "Feature",
  "properties": {
    "gn:admin1_code":"08",
    "gn:asciiname":"Okiele",
    "gn:country_code":"CG",
    "gn:dem":714,
    "gn:feature_class":"P",
    "gn:feature_code":"PPL",
    "gn:name":"Oki\u00e9l\u00e9",
    "gn:population":0,
    "gn:timezone":"Africa/Brazzaville",
    "iso:country":"CG",
    "wof:name":"Okiele",
    "wof:placetype":"locality"
},
  "geometry": {"coordinates":[15.29722,-2.68778],"type":"Point"}
}