{
  "type": "Feature",
  "properties": {
    "gn:admin1_code":"13",
    "gn:asciiname":"Mokoungou",
    "gn:country_code":"CG",
    "gn:dem":304,
    "gn:feature_class":"P",
    "gn:feature_code":"PPL",
    "gn:name":"Mokoungou",
    "gn:population":0,
    "gn:timezone":"Africa/Brazzaville",
    "iso:country":"CG",
    "wof:name":"Mokoungou",
    "wof:placetype":"locality"
},
  "geometry": {"coordinates":[17.11083,-0.28833],"type":"Point"}
}