{
  "type": "Feature",
  "properties": {
    "gn:admin1_code":"13",
    "gn:asciiname":"Iko",
    "gn:country_code":"CG",
    "gn:dem":315,
    "gn:feature_class":"P",
    "gn:feature_code":"PPL",
    "gn:name":"Iko",
    "gn:population":0,
    "gn:timezone":"Africa/Brazzaville",
    "iso:country":"CG",
    "wof:name":"Iko",
    "wof:placetype":"locality"
},
  "geometry": {"coordinates":[16.01472,-0.59722],"type":"Point"}
}