{
  "type": "Feature",
  "properties": {
    "gn:admin1_code":"11",
    "gn:asciiname":"Semo",
    "gn:country_code":"CG",
    "gn:dem":524,
    "gn:feature_class":"P",
    "gn:feature_code":"PPL",
    "gn:name":"S\u00e9mo",
    "gn:population":0,
    "gn:timezone":"Africa/Brazzaville",
    "iso:country":"CG",
    "wof:name":"Semo",
    "wof:placetype":"locality"
},
  "geometry": {"coordinates":[14.5025,-3.35139],"type":"Point"}
}