{
  "type": "Feature",
  "properties": {
    "gn:admin1_code":"01",
    "gn:asciiname":"Founvou",
    "gn:country_code":"CG",
    "gn:dem":175,
    "gn:feature_class":"P",
    "gn:feature_code":"PPL",
    "gn:name":"Founvou",
    "gn:population":0,
    "gn:timezone":"Africa/Brazzaville",
    "iso:country":"CG",
    "wof:name":"Founvou",
    "wof:placetype":"locality"
},
  "geometry": {"coordinates":[13.3275,-4.27361],"type":"Point"}
}