{
  "type": "Feature",
  "properties": {
    "gn:admin1_code":"01",
    "gn:asciiname":"Kindamba",
    "gn:country_code":"CG",
    "gn:dem":499,
    "gn:feature_class":"P",
    "gn:feature_code":"PPL",
    "gn:name":"Kindamba",
    "gn:population":0,
    "gn:timezone":"Africa/Brazzaville",
    "iso:country":"CG",
    "name:ceb_x_preferred":[
        "Kindamba"
    ],
    "name:fra_x_preferred":[
        "Kindamba"
    ],
    "name:ita_x_preferred":[
        "Kindamba"
    ],
    "name:pol_x_preferred":[
        "Kindamba"
    ],
    "name:spa_x_preferred":[
        "Kindamba"
    ],
    "name:swe_x_preferred":[
        "Kindamba"
    ],
    "name:urd_x_preferred":[
        "\u06a9\u0646\u0688\u0627\u0645\u0628\u0627"
    ],
    "wof:name":"Kindamba",
    "wof:placetype":"locality"
},
  "geometry": {"coordinates":[13.40972,-4.29917],"type":"Point"}
}