{
  "type": "Feature",
  "properties": {
    "gn:admin1_code":"01",
    "gn:asciiname":"Kindamba",
    "gn:country_code":"CG",
    "gn:dem":499,
    "gn:feature_class":"P",
    "gn:feature_code":"PPL",
    "gn:name":"Kindamba",
    "gn:population":0,
    "gn:timezone":"Africa/Brazzaville",
    "iso:country":"CG",
    "wof:name":"Kindamba",
    "wof:placetype":"locality"
},
  "geometry": {"coordinates":[13.40972,-4.29917],"type":"Point"}
}