{
  "type": "Feature",
  "properties": {
    "gn:admin1_code":"08",
    "gn:asciiname":"Tsampoko",
    "gn:country_code":"CG",
    "gn:dem":325,
    "gn:feature_class":"P",
    "gn:feature_code":"PPL",
    "gn:name":"Tsampoko",
    "gn:population":0,
    "gn:timezone":"Africa/Brazzaville",
    "iso:country":"CG",
    "wof:name":"Tsampoko",
    "wof:placetype":"locality"
},
  "geometry": {"coordinates":[16.14472,-1.80139],"type":"Point"}
}