{
  "type": "Feature",
  "properties": {
    "gn:admin1_code":"13",
    "gn:asciiname":"Ekiembe",
    "gn:country_code":"CG",
    "gn:dem":371,
    "gn:feature_class":"P",
    "gn:feature_code":"PPL",
    "gn:name":"Eki\u00e8mb\u00e9",
    "gn:population":0,
    "gn:timezone":"Africa/Brazzaville",
    "iso:country":"CG",
    "wof:name":"Ekiembe",
    "wof:placetype":"locality"
},
  "geometry": {"coordinates":[15.29139,-0.99806],"type":"Point"}
}