{
  "type": "Feature",
  "properties": {
    "gn:admin1_code":"06",
    "gn:asciiname":"Bodzendzo",
    "gn:country_code":"CG",
    "gn:dem":303,
    "gn:feature_class":"P",
    "gn:feature_code":"PPL",
    "gn:name":"Bodzendzo",
    "gn:population":0,
    "gn:timezone":"Africa/Brazzaville",
    "iso:country":"CG",
    "wof:name":"Bodzendzo",
    "wof:placetype":"locality"
},
  "geometry": {"coordinates":[17.42444,-0.07139],"type":"Point"}
}