{
  "type": "Feature",
  "properties": {
    "gn:admin1_code":"08",
    "gn:asciiname":"Asoumani",
    "gn:cc2":"CG",
    "gn:country_code":"CG",
    "gn:dem":296,
    "gn:feature_class":"P",
    "gn:feature_code":"PPL",
    "gn:name":"Asoumani",
    "gn:population":0,
    "gn:timezone":"Africa/Brazzaville",
    "iso:country":"CG",
    "name:und_x_variant":[
        "Assoumani",
        "Asoumani"
    ],
    "wof:name":"Asoumani",
    "wof:placetype":"locality"
},
  "geometry": {"coordinates":[16.26444,-1.58472],"type":"Point"}
}