{
  "type": "Feature",
  "properties": {
    "gn:admin1_code":"05",
    "gn:asciiname":"Mouyabi",
    "gn:country_code":"CG",
    "gn:dem":489,
    "gn:feature_class":"P",
    "gn:feature_code":"PPL",
    "gn:name":"Mouyabi",
    "gn:population":0,
    "gn:timezone":"Africa/Brazzaville",
    "iso:country":"CG",
    "wof:name":"Mouyabi",
    "wof:placetype":"locality"
},
  "geometry": {"coordinates":[13.51111,-3.11861],"type":"Point"}
}