{
  "type": "Feature",
  "properties": {
    "gn:admin1_code":"11",
    "gn:asciiname":"Mbama",
    "gn:country_code":"CG",
    "gn:dem":458,
    "gn:feature_class":"P",
    "gn:feature_code":"PPL",
    "gn:name":"Mbama",
    "gn:population":0,
    "gn:timezone":"Africa/Brazzaville",
    "iso:country":"CG",
    "name:ceb_x_preferred":[
        "Mbama"
    ],
    "name:swe_x_preferred":[
        "Mbama"
    ],
    "wof:name":"Mbama",
    "wof:placetype":"locality"
},
  "geometry": {"coordinates":[14.46639,-3.59389],"type":"Point"}
}