{
  "type": "Feature",
  "properties": {
    "gn:admin1_code":"05",
    "gn:asciiname":"Mawatena",
    "gn:country_code":"CG",
    "gn:dem":626,
    "gn:feature_class":"P",
    "gn:feature_code":"PPL",
    "gn:name":"Mawat\u00e9na",
    "gn:population":0,
    "gn:timezone":"Africa/Brazzaville",
    "iso:country":"CG",
    "wof:name":"Mawatena",
    "wof:placetype":"locality"
},
  "geometry": {"coordinates":[13.97167,-2.95],"type":"Point"}
}