{
  "type": "Feature",
  "properties": {
    "gn:admin1_code":"08",
    "gn:asciiname":"Kalanga",
    "gn:country_code":"CG",
    "gn:dem":323,
    "gn:feature_class":"P",
    "gn:feature_code":"PPL",
    "gn:name":"Kalanga",
    "gn:population":0,
    "gn:timezone":"Africa/Brazzaville",
    "iso:country":"CG",
    "name:ceb_x_preferred":[
        "Kalanga"
    ],
    "name:deu_x_preferred":[
        "Kalanga"
    ],
    "name:fra_x_preferred":[
        "Kalanga"
    ],
    "name:ita_x_preferred":[
        "Kalanga"
    ],
    "name:swe_x_preferred":[
        "Kalanga"
    ],
    "wof:name":"Kalanga",
    "wof:placetype":"locality"
},
  "geometry": {"coordinates":[16.16056,-1.48361],"type":"Point"}
}