{
  "type": "Feature",
  "properties": {
    "gn:admin1_code":"01",
    "gn:asciiname":"Kimanza",
    "gn:cc2":"CG",
    "gn:country_code":"CG",
    "gn:dem":155,
    "gn:feature_class":"P",
    "gn:feature_code":"PPL",
    "gn:name":"Kimanza",
    "gn:population":0,
    "gn:timezone":"Africa/Brazzaville",
    "iso:country":"CG",
    "name:und_x_variant":[
        "Kimandza",
        "Kimanza"
    ],
    "wof:name":"Kimanza",
    "wof:placetype":"locality"
},
  "geometry": {"coordinates":[12.93,-4.08528],"type":"Point"}
}