{
  "type": "Feature",
  "properties": {
    "gn:admin1_code":"05",
    "gn:asciiname":"Mitiene",
    "gn:country_code":"CG",
    "gn:dem":691,
    "gn:feature_class":"P",
    "gn:feature_code":"PPL",
    "gn:name":"Miti\u00e9n\u00e9",
    "gn:population":0,
    "gn:timezone":"Africa/Brazzaville",
    "iso:country":"CG",
    "wof:name":"Mitiene",
    "wof:placetype":"locality"
},
  "geometry": {"coordinates":[13.7075,-3.28167],"type":"Point"}
}