{
  "type": "Feature",
  "properties": {
    "gn:admin1_code":"14",
    "gn:asciiname":"Ossele",
    "gn:country_code":"CG",
    "gn:dem":512,
    "gn:feature_class":"P",
    "gn:feature_code":"PPL",
    "gn:name":"Oss\u00e9l\u00e9",
    "gn:population":0,
    "gn:timezone":"Africa/Brazzaville",
    "iso:country":"CG",
    "wof:name":"Ossele",
    "wof:placetype":"locality"
},
  "geometry": {"coordinates":[14.46667,-0.46667],"type":"Point"}
}