{
  "type": "Feature",
  "properties": {
    "gn:admin1_code":"04",
    "gn:asciiname":"Mengo",
    "gn:cc2":"CG",
    "gn:country_code":"CG",
    "gn:dem":177,
    "gn:feature_class":"P",
    "gn:feature_code":"PPL",
    "gn:name":"Mengo",
    "gn:population":0,
    "gn:timezone":"Africa/Brazzaville",
    "iso:country":"CG",
    "name:und_x_variant":[
        "Mingo",
        "Mengo"
    ],
    "wof:name":"Mengo",
    "wof:placetype":"locality"
},
  "geometry": {"coordinates":[11.94417,-4.6625],"type":"Point"}
}