{
  "type": "Feature",
  "properties": {
    "gn:admin1_code":"06",
    "gn:asciiname":"Anikou",
    "gn:cc2":"CG",
    "gn:country_code":"CG",
    "gn:dem":367,
    "gn:feature_class":"P",
    "gn:feature_code":"PPL",
    "gn:name":"Anikou",
    "gn:population":0,
    "gn:timezone":"Africa/Brazzaville",
    "iso:country":"CG",
    "name:und_x_variant":[
        "Libakoa",
        "Anikou"
    ],
    "wof:name":"Anikou",
    "wof:placetype":"locality"
},
  "geometry": {"coordinates":[17.17722,2.59139],"type":"Point"}
}