{
  "type": "Feature",
  "properties": {
    "gn:admin1_code":"11",
    "gn:asciiname":"Kissanga",
    "gn:country_code":"CG",
    "gn:dem":496,
    "gn:feature_class":"P",
    "gn:feature_code":"PPL",
    "gn:name":"Kissanga",
    "gn:population":0,
    "gn:timezone":"Africa/Brazzaville",
    "iso:country":"CG",
    "wof:name":"Kissanga",
    "wof:placetype":"locality"
},
  "geometry": {"coordinates":[14.43722,-4.34861],"type":"Point"}
}