{
  "type": "Feature",
  "properties": {
    "gn:admin1_code":"13",
    "gn:asciiname":"Mobenga",
    "gn:country_code":"CG",
    "gn:dem":291,
    "gn:feature_class":"P",
    "gn:feature_code":"PPL",
    "gn:name":"Mobenga",
    "gn:population":0,
    "gn:timezone":"Africa/Brazzaville",
    "iso:country":"CG",
    "wof:name":"Mobenga",
    "wof:placetype":"locality"
},
  "geometry": {"coordinates":[16.75639,-1.27972],"type":"Point"}
}