{
  "type": "Feature",
  "properties": {
    "gn:admin1_code":"11",
    "gn:asciiname":"Louguemo",
    "gn:cc2":"CG",
    "gn:country_code":"CG",
    "gn:dem":524,
    "gn:feature_class":"P",
    "gn:feature_code":"PPL",
    "gn:name":"Lougu\u00e9mo",
    "gn:population":0,
    "gn:timezone":"Africa/Brazzaville",
    "iso:country":"CG",
    "name:und_x_variant":[
        "Lou\u00e9mo",
        "Lougu\u00e9mo"
    ],
    "wof:name":"Louguemo",
    "wof:placetype":"locality"
},
  "geometry": {"coordinates":[14.67333,-4.61194],"type":"Point"}
}