{
  "type": "Feature",
  "properties": {
    "gn:admin1_code":"11",
    "gn:asciiname":"Ndembo",
    "gn:country_code":"CG",
    "gn:dem":611,
    "gn:feature_class":"P",
    "gn:feature_code":"PPL",
    "gn:name":"Ndembo",
    "gn:population":0,
    "gn:timezone":"Africa/Brazzaville",
    "iso:country":"CG",
    "wof:name":"Ndembo",
    "wof:placetype":"locality"
},
  "geometry": {"coordinates":[14.63972,-4.84889],"type":"Point"}
}