{
  "type": "Feature",
  "properties": {
    "gn:admin1_code":"04",
    "gn:asciiname":"Boulotombi",
    "gn:country_code":"CG",
    "gn:dem":11,
    "gn:feature_class":"P",
    "gn:feature_code":"PPL",
    "gn:name":"Boulotombi",
    "gn:population":0,
    "gn:timezone":"Africa/Brazzaville",
    "iso:country":"CG",
    "wof:name":"Boulotombi",
    "wof:placetype":"locality"
},
  "geometry": {"coordinates":[12.02806,-4.90972],"type":"Point"}
}