{
  "type": "Feature",
  "properties": {
    "gn:admin1_code":"13",
    "gn:asciiname":"Bobueta",
    "gn:country_code":"CG",
    "gn:dem":315,
    "gn:feature_class":"P",
    "gn:feature_code":"PPL",
    "gn:name":"Bobu\u00e9ta",
    "gn:population":0,
    "gn:timezone":"Africa/Brazzaville",
    "iso:country":"CG",
    "wof:name":"Bobueta",
    "wof:placetype":"locality"
},
  "geometry": {"coordinates":[16.54167,-0.42028],"type":"Point"}
}