{
  "type": "Feature",
  "properties": {
    "gn:admin1_code":"06",
    "gn:asciiname":"Ngbaka",
    "gn:cc2":"CG",
    "gn:country_code":"CG",
    "gn:dem":343,
    "gn:feature_class":"P",
    "gn:feature_code":"PPL",
    "gn:name":"Ngbaka",
    "gn:population":0,
    "gn:timezone":"Africa/Brazzaville",
    "iso:country":"CG",
    "name:deu_x_preferred":[
        "Ngbaka"
    ],
    "name:fra_x_preferred":[
        "Ngbaka"
    ],
    "name:und_x_variant":[
        "Mbaka",
        "Ngbaka"
    ],
    "wof:name":"Ngbaka",
    "wof:placetype":"locality"
},
  "geometry": {"coordinates":[18.50889,3.09944],"type":"Point"}
}