{
  "type": "Feature",
  "properties": {
    "gn:admin1_code":"11",
    "gn:asciiname":"Massesse",
    "gn:cc2":"CG",
    "gn:country_code":"CG",
    "gn:dem":518,
    "gn:feature_class":"P",
    "gn:feature_code":"PPL",
    "gn:name":"Mass\u00e9ss\u00e9",
    "gn:population":0,
    "gn:timezone":"Africa/Brazzaville",
    "iso:country":"CG",
    "name:und_x_variant":[
        "Mas\u00e9s\u00e9",
        "Mass\u00e9ss\u00e9"
    ],
    "wof:name":"Massesse",
    "wof:placetype":"locality"
},
  "geometry": {"coordinates":[14.67806,-4.61722],"type":"Point"}
}