{
  "type": "Feature",
  "properties": {
    "gn:admin1_code":"01",
    "gn:asciiname":"Koutina-Nzambi",
    "gn:country_code":"CG",
    "gn:dem":162,
    "gn:feature_class":"P",
    "gn:feature_code":"PPL",
    "gn:name":"Koutina-Nzambi",
    "gn:population":0,
    "gn:timezone":"Africa/Brazzaville",
    "iso:country":"CG",
    "wof:name":"Koutina-Nzambi",
    "wof:placetype":"locality"
},
  "geometry": {"coordinates":[12.76667,-3.95528],"type":"Point"}
}