{
  "type": "Feature",
  "properties": {
    "gn:admin1_code":"01",
    "gn:asciiname":"Kinanga",
    "gn:country_code":"CG",
    "gn:dem":608,
    "gn:feature_class":"P",
    "gn:feature_code":"PPL",
    "gn:name":"Kinanga",
    "gn:population":0,
    "gn:timezone":"Africa/Brazzaville",
    "iso:country":"CG",
    "name:por_x_preferred":[
        "Kinanga"
    ],
    "wof:name":"Kinanga",
    "wof:placetype":"locality"
},
  "geometry": {"coordinates":[13.72722,-4.38806],"type":"Point"}
}