{
  "type": "Feature",
  "properties": {
    "gn:admin1_code":"11",
    "gn:asciiname":"Lari",
    "gn:country_code":"CG",
    "gn:dem":445,
    "gn:feature_class":"P",
    "gn:feature_code":"PPL",
    "gn:name":"Lari",
    "gn:population":0,
    "gn:timezone":"Africa/Brazzaville",
    "iso:country":"CG",
    "name:ara_x_preferred":[
        "\u0646\u0648\u0631\u0633\u0627\u0648\u064a\u0627\u062a"
    ],
    "name:cat_x_preferred":[
        "Lari"
    ],
    "name:ces_x_preferred":[
        "Racci"
    ],
    "name:fas_x_preferred":[
        "\u0645\u0631\u063a\u0627\u0646 \u0646\u0648\u0631\u0648\u0632\u06cc"
    ],
    "name:fin_x_preferred":[
        "Lari"
    ],
    "name:heb_x_preferred":[
        "\u05e9\u05d7\u05e4\u05d0\u05d9\u05d9\u05dd"
    ],
    "name:isl_x_preferred":[
        "M\u00e1fuglar"
    ],
    "name:ita_x_preferred":[
        "Lari"
    ],
    "name:kat_x_preferred":[
        "\u10d7\u10dd\u10da\u10d8\u10d0\u10e1\u10dc\u10d0\u10d8\u10e0\u10dc\u10d8"
    ],
    "name:kor_x_preferred":[
        "\uac08\ub9e4\uae30\uc544\ubaa9"
    ],
    "name:lav_x_preferred":[
        "Kaijveid\u012bgie"
    ],
    "name:nor_x_preferred":[
        "M\u00e5kefugler"
    ],
    "name:pol_x_preferred":[
        "Mewowce"
    ],
    "name:por_x_preferred":[
        "Lari"
    ],
    "name:rus_x_preferred":[
        "Lari"
    ],
    "name:scn_x_preferred":[
        "Lari"
    ],
    "name:spa_x_preferred":[
        "Lari"
    ],
    "name:swe_x_preferred":[
        "Lari"
    ],
    "name:tam_x_preferred":[
        "\u0bb2\u0bc7\u0bb0\u0bbf"
    ],
    "wof:name":"Lari",
    "wof:placetype":"locality"
},
  "geometry": {"coordinates":[14.69861,-4.05417],"type":"Point"}
}