{
  "type": "Feature",
  "properties": {
    "gn:admin1_code":"11",
    "gn:asciiname":"Lari",
    "gn:country_code":"CG",
    "gn:dem":445,
    "gn:feature_class":"P",
    "gn:feature_code":"PPL",
    "gn:name":"Lari",
    "gn:population":0,
    "gn:timezone":"Africa/Brazzaville",
    "iso:country":"CG",
    "wof:name":"Lari",
    "wof:placetype":"locality"
},
  "geometry": {"coordinates":[14.69861,-4.05417],"type":"Point"}
}