{
  "type": "Feature",
  "properties": {
    "gn:admin1_code":"13",
    "gn:asciiname":"Yombe",
    "gn:cc2":"CG",
    "gn:country_code":"CG",
    "gn:dem":345,
    "gn:feature_class":"P",
    "gn:feature_code":"PPL",
    "gn:name":"Yomb\u00e9",
    "gn:population":0,
    "gn:timezone":"Africa/Brazzaville",
    "iso:country":"CG",
    "name:ceb_x_preferred":[
        "Yombe"
    ],
    "name:fra_x_preferred":[
        "Yombe"
    ],
    "name:swe_x_preferred":[
        "Yombe"
    ],
    "name:und_x_variant":[
        "Oyomb\u00e9",
        "Yomb\u00e9"
    ],
    "wof:name":"Yombe",
    "wof:placetype":"locality"
},
  "geometry": {"coordinates":[15.92361,0.0075],"type":"Point"}
}