{
  "type": "Feature",
  "properties": {
    "gn:admin1_code":"01",
    "gn:asciiname":"Mboma",
    "gn:cc2":"CG",
    "gn:country_code":"CG",
    "gn:dem":374,
    "gn:feature_class":"P",
    "gn:feature_code":"PPL",
    "gn:name":"Mboma",
    "gn:population":0,
    "gn:timezone":"Africa/Brazzaville",
    "iso:country":"CG",
    "name:und_x_variant":[
        "Boma",
        "Mboma"
    ],
    "wof:name":"Mboma",
    "wof:placetype":"locality"
},
  "geometry": {"coordinates":[13.54972,-4.27222],"type":"Point"}
}