{
  "type": "Feature",
  "properties": {
    "gn:admin1_code":"08",
    "gn:asciiname":"Odzatoni",
    "gn:cc2":"CG",
    "gn:country_code":"CG",
    "gn:dem":359,
    "gn:feature_class":"P",
    "gn:feature_code":"PPL",
    "gn:name":"Odzatoni",
    "gn:population":0,
    "gn:timezone":"Africa/Brazzaville",
    "iso:country":"CG",
    "name:und_x_variant":[
        "Ondzatounou",
        "Otzatounou",
        "Odzatoni"
    ],
    "wof:name":"Odzatoni",
    "wof:placetype":"locality"
},
  "geometry": {"coordinates":[16.01361,-1.54639],"type":"Point"}
}