{
  "type": "Feature",
  "properties": {
    "gn:admin1_code":"12",
    "gn:asciiname":"Case Barnier",
    "gn:country_code":"CG",
    "gn:dem":526,
    "gn:feature_class":"P",
    "gn:feature_code":"PPL",
    "gn:name":"Case Barnier",
    "gn:population":0,
    "gn:timezone":"Africa/Brazzaville",
    "iso:country":"CG",
    "wof:name":"Case Barnier",
    "wof:placetype":"locality"
},
  "geometry": {"coordinates":[15.20028,-4.18639],"type":"Point"}
}