{
  "type": "Feature",
  "properties": {
    "gn:admin1_code":"10",
    "gn:asciiname":"Ngali",
    "gn:cc2":"CG",
    "gn:country_code":"CG",
    "gn:dem":383,
    "gn:feature_class":"P",
    "gn:feature_code":"PPL",
    "gn:name":"Ngali",
    "gn:population":0,
    "gn:timezone":"Africa/Brazzaville",
    "iso:country":"CG",
    "name:und_x_variant":[
        "N\u2019Cali",
        "Ngali"
    ],
    "wof:name":"Ngali",
    "wof:placetype":"locality"
},
  "geometry": {"coordinates":[15.88333,1.78333],"type":"Point"}
}