{
  "type": "Feature",
  "properties": {
    "gn:admin1_code":"07",
    "gn:asciiname":"Bouma",
    "gn:country_code":"CG",
    "gn:dem":221,
    "gn:feature_class":"P",
    "gn:feature_code":"PPL",
    "gn:name":"Bouma",
    "gn:population":0,
    "gn:timezone":"Africa/Brazzaville",
    "iso:country":"CG",
    "name:nld_x_preferred":[
        "Bouma"
    ],
    "name:pol_x_preferred":[
        "Bouma"
    ],
    "name:swe_x_preferred":[
        "Ordbild"
    ],
    "wof:name":"Bouma",
    "wof:placetype":"locality"
},
  "geometry": {"coordinates":[12.61667,-3.98333],"type":"Point"}
}