{
  "type": "Feature",
  "properties": {
    "gn:admin1_code":"10",
    "gn:asciiname":"Ndoumba",
    "gn:cc2":"CG",
    "gn:country_code":"CG",
    "gn:dem":355,
    "gn:feature_class":"P",
    "gn:feature_code":"PPL",
    "gn:name":"Ndoumba",
    "gn:population":0,
    "gn:timezone":"Africa/Brazzaville",
    "iso:country":"CG",
    "name:und_x_variant":[
        "Doumba",
        "Ndoumba"
    ],
    "wof:name":"Ndoumba",
    "wof:placetype":"locality"
},
  "geometry": {"coordinates":[15.88139,1.78028],"type":"Point"}
}