{
  "type": "Feature",
  "properties": {
    "gn:admin1_code":"14",
    "gn:asciiname":"Lengui-Lengui",
    "gn:country_code":"CG",
    "gn:dem":479,
    "gn:feature_class":"P",
    "gn:feature_code":"PPL",
    "gn:name":"L\u00e8ngui-L\u00e8ngui",
    "gn:population":0,
    "gn:timezone":"Africa/Brazzaville",
    "iso:country":"CG",
    "name:und_x_variant":[
        "Lengue-lengu\u00e9",
        "L\u00e8ngui-L\u00e8ngui"
    ],
    "wof:name":"Lengui-Lengui",
    "wof:placetype":"locality"
},
  "geometry": {"coordinates":[14.63472,0.63194],"type":"Point"}
}