{
  "type": "Feature",
  "properties": {
    "gn:admin1_code":"13",
    "gn:asciiname":"Adzie",
    "gn:country_code":"CG",
    "gn:dem":451,
    "gn:feature_class":"P",
    "gn:feature_code":"PPL",
    "gn:name":"Adzi\u00e9",
    "gn:population":0,
    "gn:timezone":"Africa/Brazzaville",
    "iso:country":"CG",
    "name:und_x_variant":[
        "Adzi\u00e9 I",
        "Adzi\u00e9"
    ],
    "wof:name":"Adzie",
    "wof:placetype":"locality"
},
  "geometry": {"coordinates":[14.97528,-1.22083],"type":"Point"}
}