{
  "type": "Feature",
  "properties": {
    "gn:admin1_code":"11",
    "gn:asciiname":"Makelekele",
    "gn:country_code":"CG",
    "gn:dem":303,
    "gn:feature_class":"P",
    "gn:feature_code":"PPL",
    "gn:name":"Makelekele",
    "gn:population":0,
    "gn:timezone":"Africa/Brazzaville",
    "iso:country":"CG",
    "wof:name":"Makelekele",
    "wof:placetype":"locality"
},
  "geometry": {"coordinates":[15.22888,-4.29833],"type":"Point"}
}