{
  "type": "Feature",
  "properties": {
    "gn:admin1_code":"08",
    "gn:asciiname":"Ebi",
    "gn:country_code":"CG",
    "gn:dem":280,
    "gn:feature_class":"P",
    "gn:feature_code":"PPL",
    "gn:name":"Ebi",
    "gn:population":0,
    "gn:timezone":"Africa/Brazzaville",
    "iso:country":"CG",
    "wof:name":"Ebi",
    "wof:placetype":"locality"
},
  "geometry": {"coordinates":[16.17583,-2.54528],"type":"Point"}
}