{
  "type": "Feature",
  "properties": {
    "gn:admin1_code":"08",
    "gn:asciiname":"Ebi",
    "gn:country_code":"CG",
    "gn:dem":280,
    "gn:feature_class":"P",
    "gn:feature_code":"PPL",
    "gn:name":"Ebi",
    "gn:population":0,
    "gn:timezone":"Africa/Brazzaville",
    "iso:country":"CG",
    "name:afr_x_preferred":[
        "Ebi"
    ],
    "name:deu_x_preferred":[
        "Ebi"
    ],
    "name:diq_x_preferred":[
        "Ebi"
    ],
    "name:fas_x_preferred":[
        "\u0627\u0628\u06cc"
    ],
    "name:fra_x_preferred":[
        "Ebi"
    ],
    "name:glg_x_preferred":[
        "Ebi"
    ],
    "name:sco_x_preferred":[
        "Ebi"
    ],
    "name:spa_x_preferred":[
        "Ebi Hamedi"
    ],
    "name:swe_x_preferred":[
        "Ebi"
    ],
    "name:tur_x_preferred":[
        "Ebi"
    ],
    "name:urd_x_preferred":[
        "\u0627\u0628\u06cc"
    ],
    "wof:name":"Ebi",
    "wof:placetype":"locality"
},
  "geometry": {"coordinates":[16.17583,-2.54528],"type":"Point"}
}