{
  "type": "Feature",
  "properties": {
    "gn:admin1_code":"01",
    "gn:asciiname":"Kingouala",
    "gn:country_code":"CG",
    "gn:dem":411,
    "gn:feature_class":"P",
    "gn:feature_code":"PPL",
    "gn:name":"Kingouala",
    "gn:population":0,
    "gn:timezone":"Africa/Brazzaville",
    "iso:country":"CG",
    "wof:name":"Kingouala",
    "wof:placetype":"locality"
},
  "geometry": {"coordinates":[13.80472,-3.915],"type":"Point"}
}