{
  "type": "Feature",
  "properties": {
    "gn:admin1_code":"11",
    "gn:asciiname":"Mousele",
    "gn:country_code":"CG",
    "gn:dem":495,
    "gn:feature_class":"P",
    "gn:feature_code":"PPL",
    "gn:name":"Mous\u00e9l\u00e9",
    "gn:population":0,
    "gn:timezone":"Africa/Brazzaville",
    "iso:country":"CG",
    "wof:name":"Mousele",
    "wof:placetype":"locality"
},
  "geometry": {"coordinates":[14.49972,-3.43389],"type":"Point"}
}