{
  "type": "Feature",
  "properties": {
    "gn:admin1_code":"05",
    "gn:asciiname":"Mimpousa",
    "gn:cc2":"CG",
    "gn:country_code":"CG",
    "gn:dem":595,
    "gn:feature_class":"P",
    "gn:feature_code":"PPL",
    "gn:name":"Mimpousa",
    "gn:population":0,
    "gn:timezone":"Africa/Brazzaville",
    "iso:country":"CG",
    "name:und_x_variant":[
        "Yogo",
        "Mimpoussa",
        "Mimpousa"
    ],
    "wof:name":"Mimpousa",
    "wof:placetype":"locality"
},
  "geometry": {"coordinates":[14.08972,-2.94972],"type":"Point"}
}