{
  "type": "Feature",
  "properties": {
    "gn:admin1_code":"13",
    "gn:asciiname":"Ollebi",
    "gn:country_code":"CG",
    "gn:dem":369,
    "gn:feature_class":"P",
    "gn:feature_code":"PPL",
    "gn:name":"Oll\u00e9bi",
    "gn:population":0,
    "gn:timezone":"Africa/Brazzaville",
    "iso:country":"CG",
    "name:und_x_variant":[
        "Ol\u00e9bi",
        "Ollibi",
        "Oll\u00e9bi"
    ],
    "wof:name":"Ollebi",
    "wof:placetype":"locality"
},
  "geometry": {"coordinates":[15.10639,-1.30583],"type":"Point"}
}