{
  "type": "Feature",
  "properties": {
    "gn:admin1_code":"07",
    "gn:asciiname":"Mavounogo",
    "gn:cc2":"CG",
    "gn:country_code":"CG",
    "gn:dem":452,
    "gn:feature_class":"P",
    "gn:feature_code":"PPL",
    "gn:name":"Mavounogo",
    "gn:population":0,
    "gn:timezone":"Africa/Brazzaville",
    "iso:country":"CG",
    "name:und_x_variant":[
        "Mavounougou",
        "Mavounogo"
    ],
    "wof:name":"Mavounogo",
    "wof:placetype":"locality"
},
  "geometry": {"coordinates":[12.89056,-3.11639],"type":"Point"}
}