{
  "type": "Feature",
  "properties": {
    "gn:admin1_code":"11",
    "gn:asciiname":"Moutele",
    "gn:country_code":"CG",
    "gn:dem":485,
    "gn:feature_class":"P",
    "gn:feature_code":"PPL",
    "gn:name":"Mout\u00e9l\u00e9",
    "gn:population":0,
    "gn:timezone":"Africa/Brazzaville",
    "iso:country":"CG",
    "wof:name":"Moutele",
    "wof:placetype":"locality"
},
  "geometry": {"coordinates":[14.59167,-3.69472],"type":"Point"}
}