{
  "type": "Feature",
  "properties": {
    "gn:admin1_code":"11",
    "gn:asciiname":"Mbamba",
    "gn:country_code":"CG",
    "gn:dem":303,
    "gn:feature_class":"P",
    "gn:feature_code":"PPL",
    "gn:name":"Mbamba",
    "gn:population":0,
    "gn:timezone":"Africa/Brazzaville",
    "iso:country":"CG",
    "wof:name":"Mbamba",
    "wof:placetype":"locality"
},
  "geometry": {"coordinates":[14.08667,-4.31083],"type":"Point"}
}