{
  "type": "Feature",
  "properties": {
    "gn:admin1_code":"05",
    "gn:asciiname":"Moutoumou",
    "gn:country_code":"CG",
    "gn:dem":559,
    "gn:feature_class":"P",
    "gn:feature_code":"PPL",
    "gn:name":"Moutoumou",
    "gn:population":0,
    "gn:timezone":"Africa/Brazzaville",
    "iso:country":"CG",
    "wof:name":"Moutoumou",
    "wof:placetype":"locality"
},
  "geometry": {"coordinates":[13.78639,-2.86333],"type":"Point"}
}