{
  "type": "Feature",
  "properties": {
    "gn:admin1_code":"11",
    "gn:asciiname":"Makana",
    "gn:country_code":"CG",
    "gn:dem":355,
    "gn:feature_class":"P",
    "gn:feature_code":"PPL",
    "gn:name":"Makana",
    "gn:population":0,
    "gn:timezone":"Africa/Brazzaville",
    "iso:country":"CG",
    "wof:name":"Makana",
    "wof:placetype":"locality"
},
  "geometry": {"coordinates":[14.94639,-4.01833],"type":"Point"}
}