{
  "type": "Feature",
  "properties": {
    "gn:admin1_code":"11",
    "gn:asciiname":"Kingouala Mbola",
    "gn:country_code":"CG",
    "gn:dem":363,
    "gn:feature_class":"P",
    "gn:feature_code":"PPL",
    "gn:name":"Kingouala Mb\u00f4la",
    "gn:population":0,
    "gn:timezone":"Africa/Brazzaville",
    "iso:country":"CG",
    "wof:name":"Kingouala Mbola",
    "wof:placetype":"locality"
},
  "geometry": {"coordinates":[14.9175,-3.73667],"type":"Point"}
}