{
  "type": "Feature",
  "properties": {
    "gn:admin1_code":"10",
    "gn:asciiname":"Poulani",
    "gn:country_code":"CG",
    "gn:dem":436,
    "gn:feature_class":"P",
    "gn:feature_code":"PPL",
    "gn:name":"Poulani",
    "gn:population":0,
    "gn:timezone":"Africa/Brazzaville",
    "iso:country":"CG",
    "wof:name":"Poulani",
    "wof:placetype":"locality"
},
  "geometry": {"coordinates":[15.83611,1.32694],"type":"Point"}
}