{
  "type": "Feature",
  "properties": {
    "gn:admin1_code":"11",
    "gn:asciiname":"Kimbele",
    "gn:country_code":"CG",
    "gn:dem":441,
    "gn:feature_class":"P",
    "gn:feature_code":"PPL",
    "gn:name":"Kimb\u00e9l\u00e9",
    "gn:population":0,
    "gn:timezone":"Africa/Brazzaville",
    "iso:country":"CG",
    "wof:name":"Kimbele",
    "wof:placetype":"locality"
},
  "geometry": {"coordinates":[14.76417,-4.06694],"type":"Point"}
}