{
  "type": "Feature",
  "properties": {
    "gn:admin1_code":"08",
    "gn:asciiname":"Etonton",
    "gn:cc2":"CG",
    "gn:country_code":"CG",
    "gn:dem":290,
    "gn:feature_class":"P",
    "gn:feature_code":"PPL",
    "gn:name":"Etonton",
    "gn:population":0,
    "gn:timezone":"Africa/Brazzaville",
    "iso:country":"CG",
    "name:und_x_variant":[
        "Ebonton",
        "Etonton"
    ],
    "wof:name":"Etonton",
    "wof:placetype":"locality"
},
  "geometry": {"coordinates":[16.27639,-1.70472],"type":"Point"}
}