{
  "type": "Feature",
  "properties": {
    "gn:admin1_code":"08",
    "gn:asciiname":"Masali",
    "gn:cc2":"CG",
    "gn:country_code":"CG",
    "gn:dem":293,
    "gn:feature_class":"P",
    "gn:feature_code":"PPL",
    "gn:name":"Masali",
    "gn:population":0,
    "gn:timezone":"Africa/Brazzaville",
    "iso:country":"CG",
    "name:und_x_variant":[
        "Massali",
        "Masali"
    ],
    "wof:name":"Masali",
    "wof:placetype":"locality"
},
  "geometry": {"coordinates":[16.20667000000001,-1.92611],"type":"Point"}
}