{
  "type": "Feature",
  "properties": {
    "gn:admin1_code":"05",
    "gn:asciiname":"Ingama",
    "gn:cc2":"CG",
    "gn:country_code":"CG",
    "gn:dem":610,
    "gn:feature_class":"P",
    "gn:feature_code":"PPL",
    "gn:name":"Ingama",
    "gn:population":0,
    "gn:timezone":"Africa/Brazzaville",
    "iso:country":"CG",
    "name:und_x_variant":[
        "Imgama",
        "Ingama"
    ],
    "wof:name":"Ingama",
    "wof:placetype":"locality"
},
  "geometry": {"coordinates":[13.86167,-2.99056],"type":"Point"}
}