{
  "type": "Feature",
  "properties": {
    "gn:admin1_code":"10",
    "gn:asciiname":"Bamagod II",
    "gn:cc2":"CG",
    "gn:country_code":"CG",
    "gn:dem":540,
    "gn:feature_class":"P",
    "gn:feature_code":"PPL",
    "gn:name":"Bamagod II",
    "gn:population":0,
    "gn:timezone":"Africa/Brazzaville",
    "iso:country":"CG",
    "name:und_x_variant":[
        "Bamagode II",
        "Bamagod II"
    ],
    "wof:name":"Bamagod II",
    "wof:placetype":"locality"
},
  "geometry": {"coordinates":[14.2225,1.825],"type":"Point"}
}