{
  "type": "Feature",
  "properties": {
    "gn:admin1_code":"10",
    "gn:asciiname":"Lopembe",
    "gn:country_code":"CG",
    "gn:dem":453,
    "gn:feature_class":"P",
    "gn:feature_code":"PPL",
    "gn:name":"Lopembe",
    "gn:population":0,
    "gn:timezone":"Africa/Brazzaville",
    "iso:country":"CG",
    "wof:name":"Lopembe",
    "wof:placetype":"locality"
},
  "geometry": {"coordinates":[15.83417,1.54194],"type":"Point"}
}