{
  "type": "Feature",
  "properties": {
    "gn:admin1_code":"14",
    "gn:asciiname":"Bandza",
    "gn:country_code":"CG",
    "gn:dem":608,
    "gn:feature_class":"P",
    "gn:feature_code":"PPL",
    "gn:name":"Bandza",
    "gn:population":0,
    "gn:timezone":"Africa/Brazzaville",
    "iso:country":"CG",
    "wof:name":"Bandza",
    "wof:placetype":"locality"
},
  "geometry": {"coordinates":[14.55194,0.66472],"type":"Point"}
}