{
  "type": "Feature",
  "properties": {
    "gn:admin1_code":"14",
    "gn:asciiname":"Bandza",
    "gn:country_code":"CG",
    "gn:dem":608,
    "gn:feature_class":"P",
    "gn:feature_code":"PPL",
    "gn:name":"Bandza",
    "gn:population":0,
    "gn:timezone":"Africa/Brazzaville",
    "iso:country":"CG",
    "name:fra_x_preferred":[
        "Bandza"
    ],
    "name:hye_x_preferred":[
        "\u0532\u0561\u0576\u0571\u0561"
    ],
    "name:kat_x_preferred":[
        "\u10d1\u10d0\u10dc\u10eb\u10d0"
    ],
    "name:xmf_x_preferred":[
        "\u10d1\u10d0\u10dc\u10eb\u10d0"
    ],
    "wof:name":"Bandza",
    "wof:placetype":"locality"
},
  "geometry": {"coordinates":[14.55194,0.66472],"type":"Point"}
}