{
  "type": "Feature",
  "properties": {
    "gn:admin1_code":"13",
    "gn:asciiname":"Konziolo",
    "gn:country_code":"CG",
    "gn:dem":287,
    "gn:feature_class":"P",
    "gn:feature_code":"PPL",
    "gn:name":"Konziolo",
    "gn:population":0,
    "gn:timezone":"Africa/Brazzaville",
    "iso:country":"CG",
    "wof:name":"Konziolo",
    "wof:placetype":"locality"
},
  "geometry": {"coordinates":[16.66528,-1.4575],"type":"Point"}
}