{
  "type": "Feature",
  "properties": {
    "gn:admin1_code":"08",
    "gn:asciiname":"Mosinde",
    "gn:cc2":"CG",
    "gn:country_code":"CG",
    "gn:dem":353,
    "gn:feature_class":"P",
    "gn:feature_code":"PPL",
    "gn:name":"Mosind\u00e9",
    "gn:population":0,
    "gn:timezone":"Africa/Brazzaville",
    "iso:country":"CG",
    "name:und_x_variant":[
        "Mossend\u00e9",
        "Mosind\u00e9"
    ],
    "wof:name":"Mosinde",
    "wof:placetype":"locality"
},
  "geometry": {"coordinates":[15.92861,-1.47833],"type":"Point"}
}