{
  "type": "Feature",
  "properties": {
    "gn:admin1_code":"04",
    "gn:asciiname":"Vela",
    "gn:country_code":"CG",
    "gn:dem":85,
    "gn:feature_class":"P",
    "gn:feature_code":"PPL",
    "gn:name":"V\u00e9la",
    "gn:population":0,
    "gn:timezone":"Africa/Brazzaville",
    "iso:country":"CG",
    "name:ara_x_preferred":[
        "\u0641\u064a\u0644\u0627"
    ],
    "name:arg_x_preferred":[
        "Vela"
    ],
    "name:ast_x_preferred":[
        "Vela"
    ],
    "name:bul_x_preferred":[
        "\u0412\u0435\u043b\u0430"
    ],
    "name:cat_x_preferred":[
        "Vela"
    ],
    "name:ceb_x_preferred":[
        "Vela"
    ],
    "name:ces_x_preferred":[
        "Vela"
    ],
    "name:deu_x_preferred":[
        "Vela"
    ],
    "name:fas_x_preferred":[
        "\u0628\u0627\u062f\u0628\u0627\u0646"
    ],
    "name:fin_x_preferred":[
        "Vela"
    ],
    "name:fra_x_preferred":[
        "Vela"
    ],
    "name:glg_x_preferred":[
        "Vela"
    ],
    "name:hrv_x_preferred":[
        "Vela"
    ],
    "name:hun_x_preferred":[
        "Vela"
    ],
    "name:ita_x_preferred":[
        "Vela"
    ],
    "name:nld_x_preferred":[
        "Vela"
    ],
    "name:nor_x_preferred":[
        "Vela"
    ],
    "name:pol_x_preferred":[
        "Vela"
    ],
    "name:por_x_preferred":[
        "Vela"
    ],
    "name:que_x_preferred":[
        "Vela"
    ],
    "name:rus_x_preferred":[
        "\u0412\u0435\u043b\u0430"
    ],
    "name:spa_x_preferred":[
        "Vela"
    ],
    "name:srp_x_preferred":[
        "Vela"
    ],
    "name:swe_x_preferred":[
        "Vela"
    ],
    "wof:name":"Vela",
    "wof:placetype":"locality"
},
  "geometry": {"coordinates":[11.62806,-4.36333],"type":"Point"}
}