{
  "type": "Feature",
  "properties": {
    "gn:admin1_code":"04",
    "gn:asciiname":"Vela",
    "gn:country_code":"CG",
    "gn:dem":85,
    "gn:feature_class":"P",
    "gn:feature_code":"PPL",
    "gn:name":"V\u00e9la",
    "gn:population":0,
    "gn:timezone":"Africa/Brazzaville",
    "iso:country":"CG",
    "wof:name":"Vela",
    "wof:placetype":"locality"
},
  "geometry": {"coordinates":[11.62806,-4.36333],"type":"Point"}
}