{
  "type": "Feature",
  "properties": {
    "gn:admin1_code":"11",
    "gn:asciiname":"Adjipo",
    "gn:country_code":"CG",
    "gn:dem":272,
    "gn:feature_class":"P",
    "gn:feature_code":"PPL",
    "gn:name":"Adjipo",
    "gn:population":0,
    "gn:timezone":"Africa/Brazzaville",
    "iso:country":"CG",
    "wof:name":"Adjipo",
    "wof:placetype":"locality"
},
  "geometry": {"coordinates":[16.17389,-3.18278],"type":"Point"}
}