{
  "type": "Feature",
  "properties": {
    "gn:admin1_code":"13",
    "gn:asciiname":"Nkori",
    "gn:country_code":"CG",
    "gn:dem":409,
    "gn:feature_class":"P",
    "gn:feature_code":"PPL",
    "gn:name":"Nkori",
    "gn:population":0,
    "gn:timezone":"Africa/Brazzaville",
    "iso:country":"CG",
    "wof:name":"Nkori",
    "wof:placetype":"locality"
},
  "geometry": {"coordinates":[14.77472,-1.58611],"type":"Point"}
}