{
  "type": "Feature",
  "properties": {
    "gn:admin1_code":"08",
    "gn:asciiname":"Inga",
    "gn:country_code":"CG",
    "gn:dem":731,
    "gn:feature_class":"P",
    "gn:feature_code":"PPL",
    "gn:name":"Inga",
    "gn:population":0,
    "gn:timezone":"Africa/Brazzaville",
    "iso:country":"CG",
    "wof:name":"Inga",
    "wof:placetype":"locality"
},
  "geometry": {"coordinates":[14.95278,-2.30667],"type":"Point"}
}