{
  "type": "Feature",
  "properties": {
    "gn:admin1_code":"06",
    "gn:asciiname":"Mokendo",
    "gn:country_code":"CG",
    "gn:dem":388,
    "gn:feature_class":"P",
    "gn:feature_code":"PPL",
    "gn:name":"Mokendo",
    "gn:population":0,
    "gn:timezone":"Africa/Brazzaville",
    "iso:country":"CG",
    "wof:name":"Mokendo",
    "wof:placetype":"locality"
},
  "geometry": {"coordinates":[17.67111000000001,2.84611],"type":"Point"}
}