{
  "type": "Feature",
  "properties": {
    "gn:admin1_code":"08",
    "gn:asciiname":"Goulanganpini",
    "gn:cc2":"CG",
    "gn:country_code":"CG",
    "gn:dem":379,
    "gn:feature_class":"P",
    "gn:feature_code":"PPL",
    "gn:name":"Goulanganpini",
    "gn:population":0,
    "gn:timezone":"Africa/Brazzaville",
    "iso:country":"CG",
    "name:und_x_variant":[
        "Goulangampina",
        "Goulanganpini"
    ],
    "wof:name":"Goulanganpini",
    "wof:placetype":"locality"
},
  "geometry": {"coordinates":[16.02472,-1.81889],"type":"Point"}
}