{
  "type": "Feature",
  "properties": {
    "gn:admin1_code":"13",
    "gn:asciiname":"Ossounga",
    "gn:cc2":"CG",
    "gn:country_code":"CG",
    "gn:dem":361,
    "gn:feature_class":"P",
    "gn:feature_code":"PPL",
    "gn:name":"Ossounga",
    "gn:population":0,
    "gn:timezone":"Africa/Brazzaville",
    "iso:country":"CG",
    "name:und_x_variant":[
        "Ossangui",
        "Ossounga"
    ],
    "wof:name":"Ossounga",
    "wof:placetype":"locality"
},
  "geometry": {"coordinates":[15.90111,-0.54583],"type":"Point"}
}