{
  "type": "Feature",
  "properties": {
    "gn:admin1_code":"13",
    "gn:asciiname":"Makenenge",
    "gn:country_code":"CG",
    "gn:dem":301,
    "gn:feature_class":"P",
    "gn:feature_code":"PPL",
    "gn:name":"Mak\u00e9neng\u00e9",
    "gn:population":0,
    "gn:timezone":"Africa/Brazzaville",
    "iso:country":"CG",
    "wof:name":"Makenenge",
    "wof:placetype":"locality"
},
  "geometry": {"coordinates":[16.48667,-1.06389],"type":"Point"}
}