{
  "type": "Feature",
  "properties": {
    "gn:admin1_code":"13",
    "gn:asciiname":"Maboko",
    "gn:country_code":"CG",
    "gn:dem":298,
    "gn:feature_class":"P",
    "gn:feature_code":"PPL",
    "gn:name":"Maboko",
    "gn:population":0,
    "gn:timezone":"Africa/Brazzaville",
    "iso:country":"CG",
    "wof:name":"Maboko",
    "wof:placetype":"locality"
},
  "geometry": {"coordinates":[16.76222000000001,-0.95278],"type":"Point"}
}