{
  "type": "Feature",
  "properties": {
    "gn:admin1_code":"11",
    "gn:asciiname":"Kibouende",
    "gn:country_code":"CG",
    "gn:dem":450,
    "gn:feature_class":"P",
    "gn:feature_code":"PPL",
    "gn:name":"Kibouend\u00e9",
    "gn:population":0,
    "gn:timezone":"Africa/Brazzaville",
    "iso:country":"CG",
    "wof:name":"Kibouende",
    "wof:placetype":"locality"
},
  "geometry": {"coordinates":[14.65417,-4.41944],"type":"Point"}
}