{
  "type": "Feature",
  "properties": {
    "gn:admin1_code":"05",
    "gn:asciiname":"Moukouma",
    "gn:country_code":"CG",
    "gn:dem":595,
    "gn:feature_class":"P",
    "gn:feature_code":"PPL",
    "gn:name":"Moukouma",
    "gn:population":0,
    "gn:timezone":"Africa/Brazzaville",
    "iso:country":"CG",
    "wof:name":"Moukouma",
    "wof:placetype":"locality"
},
  "geometry": {"coordinates":[13.62389,-2.76278],"type":"Point"}
}