{
  "type": "Feature",
  "properties": {
    "gn:admin1_code":"11",
    "gn:asciiname":"Makokossa",
    "gn:cc2":"CG",
    "gn:country_code":"CG",
    "gn:dem":459,
    "gn:feature_class":"P",
    "gn:feature_code":"PPL",
    "gn:name":"Makokossa",
    "gn:population":0,
    "gn:timezone":"Africa/Brazzaville",
    "iso:country":"CG",
    "name:und_x_variant":[
        "Makokosa",
        "Makokossa"
    ],
    "wof:name":"Makokossa",
    "wof:placetype":"locality"
},
  "geometry": {"coordinates":[14.69,-4.31833],"type":"Point"}
}