{
  "type": "Feature",
  "properties": {
    "gn:admin1_code":"12",
    "gn:asciiname":"Inkieno",
    "gn:country_code":"CG",
    "gn:dem":726,
    "gn:feature_class":"P",
    "gn:feature_code":"PPL",
    "gn:name":"Inki\u00e9no",
    "gn:population":0,
    "gn:timezone":"Africa/Brazzaville",
    "iso:country":"CG",
    "wof:name":"Inkieno",
    "wof:placetype":"locality"
},
  "geometry": {"coordinates":[15.36556,-3.65889],"type":"Point"}
}