{
  "type": "Feature",
  "properties": {
    "gn:admin1_code":"05",
    "gn:asciiname":"Bama",
    "gn:country_code":"CG",
    "gn:dem":450,
    "gn:feature_class":"P",
    "gn:feature_code":"PPL",
    "gn:name":"Bama",
    "gn:population":0,
    "gn:timezone":"Africa/Brazzaville",
    "iso:country":"CG",
    "name:cat_x_preferred":[
        "Bama"
    ],
    "name:ceb_x_preferred":[
        "Bama"
    ],
    "name:deu_x_preferred":[
        "Bama"
    ],
    "name:fra_x_preferred":[
        "Bama"
    ],
    "name:glg_x_preferred":[
        "Bama"
    ],
    "name:ita_x_preferred":[
        "Bama"
    ],
    "name:nld_x_preferred":[
        "Bama"
    ],
    "name:nor_x_preferred":[
        "Bama"
    ],
    "name:swe_x_preferred":[
        "Bama"
    ],
    "wof:name":"Bama",
    "wof:placetype":"locality"
},
  "geometry": {"coordinates":[13.17194,-3.26778],"type":"Point"}
}