{
  "type": "Feature",
  "properties": {
    "gn:admin1_code":"11",
    "gn:asciiname":"Tombi",
    "gn:cc2":"CG",
    "gn:country_code":"CG",
    "gn:dem":545,
    "gn:feature_class":"P",
    "gn:feature_code":"PPL",
    "gn:name":"Tombi",
    "gn:population":0,
    "gn:timezone":"Africa/Brazzaville",
    "iso:country":"CG",
    "name:und_x_variant":[
        "Tomba",
        "Tombi"
    ],
    "wof:name":"Tombi",
    "wof:placetype":"locality"
},
  "geometry": {"coordinates":[14.57944,-4.76806],"type":"Point"}
}