{
  "type": "Feature",
  "properties": {
    "gn:admin1_code":"05",
    "gn:asciiname":"Mouyabi",
    "gn:country_code":"CG",
    "gn:dem":437,
    "gn:feature_class":"P",
    "gn:feature_code":"PPL",
    "gn:name":"Mouyabi",
    "gn:population":0,
    "gn:timezone":"Africa/Brazzaville",
    "iso:country":"CG",
    "wof:name":"Mouyabi",
    "wof:placetype":"locality"
},
  "geometry": {"coordinates":[13.27306,-3.2675],"type":"Point"}
}