{
  "type": "Feature",
  "properties": {
    "gn:admin1_code":"11",
    "gn:asciiname":"Missafou",
    "gn:country_code":"CG",
    "gn:dem":472,
    "gn:feature_class":"P",
    "gn:feature_code":"PPL",
    "gn:name":"Missafou",
    "gn:population":0,
    "gn:timezone":"Africa/Brazzaville",
    "iso:country":"CG",
    "wof:name":"Missafou",
    "wof:placetype":"locality"
},
  "geometry": {"coordinates":[14.48833,-4.275],"type":"Point"}
}