{
  "type": "Feature",
  "properties": {
    "gn:admin1_code":"10",
    "gn:asciiname":"Alangon",
    "gn:country_code":"CG",
    "gn:dem":426,
    "gn:feature_class":"P",
    "gn:feature_code":"PPL",
    "gn:name":"Alangon",
    "gn:population":0,
    "gn:timezone":"Africa/Brazzaville",
    "iso:country":"CG",
    "wof:name":"Alangon",
    "wof:placetype":"locality"
},
  "geometry": {"coordinates":[14.63861,1.66306],"type":"Point"}
}