{
  "type": "Feature",
  "properties": {
    "gn:admin1_code":"13",
    "gn:asciiname":"Yombe",
    "gn:cc2":"CG",
    "gn:country_code":"CG",
    "gn:dem":340,
    "gn:feature_class":"P",
    "gn:feature_code":"PPL",
    "gn:name":"Yomb\u00e9",
    "gn:population":0,
    "gn:timezone":"Africa/Brazzaville",
    "iso:country":"CG",
    "name:und_x_variant":[
        "Youmbi",
        "Yomb\u00e9"
    ],
    "wof:name":"Yombe",
    "wof:placetype":"locality"
},
  "geometry": {"coordinates":[15.57778,-0.085],"type":"Point"}
}