{
  "type": "Feature",
  "properties": {
    "gn:admin1_code":"06",
    "gn:asciiname":"Malala",
    "gn:country_code":"CG",
    "gn:dem":332,
    "gn:feature_class":"P",
    "gn:feature_code":"PPL",
    "gn:name":"Malala",
    "gn:population":0,
    "gn:timezone":"Africa/Brazzaville",
    "iso:country":"CG",
    "wof:name":"Malala",
    "wof:placetype":"locality"
},
  "geometry": {"coordinates":[18.05111,1.77611],"type":"Point"}
}