{
  "type": "Feature",
  "properties": {
    "gn:admin1_code":"06",
    "gn:asciiname":"Gandou",
    "gn:country_code":"CG",
    "gn:dem":372,
    "gn:feature_class":"P",
    "gn:feature_code":"PPL",
    "gn:name":"Gandou",
    "gn:population":0,
    "gn:timezone":"Africa/Brazzaville",
    "iso:country":"CG",
    "wof:name":"Gandou",
    "wof:placetype":"locality"
},
  "geometry": {"coordinates":[17.35528,2.4325],"type":"Point"}
}