{
  "type": "Feature",
  "properties": {
    "gn:admin1_code":"11",
    "gn:asciiname":"Kitounga",
    "gn:country_code":"CG",
    "gn:dem":458,
    "gn:feature_class":"P",
    "gn:feature_code":"PPL",
    "gn:name":"Kitounga",
    "gn:population":0,
    "gn:timezone":"Africa/Brazzaville",
    "iso:country":"CG",
    "wof:name":"Kitounga",
    "wof:placetype":"locality"
},
  "geometry": {"coordinates":[14.57389,-4.26],"type":"Point"}
}