{
  "type": "Feature",
  "properties": {
    "gn:admin1_code":"04",
    "gn:asciiname":"Youngou-Zassi",
    "gn:country_code":"CG",
    "gn:dem":57,
    "gn:feature_class":"P",
    "gn:feature_code":"PPL",
    "gn:name":"Youngou-Zassi",
    "gn:population":0,
    "gn:timezone":"Africa/Brazzaville",
    "iso:country":"CG",
    "wof:name":"Youngou-Zassi",
    "wof:placetype":"locality"
},
  "geometry": {"coordinates":[12.21639,-4.63861],"type":"Point"}
}