{
  "type": "Feature",
  "properties": {
    "gn:admin1_code":"07",
    "gn:asciiname":"Magabiga",
    "gn:country_code":"CG",
    "gn:dem":465,
    "gn:feature_class":"P",
    "gn:feature_code":"PPL",
    "gn:name":"Magabiga",
    "gn:population":0,
    "gn:timezone":"Africa/Brazzaville",
    "iso:country":"CG",
    "wof:name":"Magabiga",
    "wof:placetype":"locality"
},
  "geometry": {"coordinates":[12.24861,-2.61361],"type":"Point"}
}